Workbook

Sheet Introduction
B1: Annual GDP and GDPR
B3: Quarterly GDP and GDPR | F3: SUMMARY PAGE
B5: Seasonally adjusted and annualised quarterly GDP and GDPR | F5: SUMMARY PAGE
B7: Year-on-Year Growth Rates per Sector | F7: Sector Ratings
B9: Seasonally adjusted and annualised quarterly Rates per Sector
B11: Yearly Provincial Contribution Rates per Sector
B13: Yearly Provincial Sector as a % of National Sector GDP
B15: Ethekwini Municipal Area GDP
B17: Msunduzi Municipal Area GDP
B19: Mthlatuze Municipal Area GDP
B21: Hibiscus Coast Municipal GDP
B23: Newcastle Municipal GDP | D23: Model Assumptions
B25: Comparitive Growth Rates | D25: Stable structural relationship between SA and KZN economy
B27: Comparitive Contribution Rates | D27: Stable relationship between GDP and Fuel Consumption
B29: KZN GDP and Provincial Government Budget | D29: Fuel Consumption per R1 GDP are location insensitive
B31: KZN Socio Economic Analysis
B32: KZN Economic Analysis

Sheet Summary
A1: SUMMARY PAGE
A3: Annual GDP and GDPR
A35: Quarterly GDP and GDPR
A103: Seasonally adjusted and annualised quarterly GDP and GDPR
A163: Ethekwini Municipal Area
A196: Msunduzi Municipal Area
A230: Mthlatuze Municipal Area
A266: Hibiscus Coast Municipal Area
A302: Newcastle Municipal Area

Sheet Sector Summary
A1: SUMMARY PAGE
A3: PLEASE TAKE NOTE
A4: BLACK = NON-SEASONAL ANNUAL RATE
A5: RED = SEASONAL ANNUAL RATE

Sheet Annual
A1: Annual GDP and GDPR
A3: SA – GDP by activity
A4: Constant 2005 prices - Rand million
A5: National Industry | B5: 1995 | C5: 1996 | D5: 1997 | E5: 1998 | F5: 1999 | G5: 2000 | H5: 2001 | I5: 2002 | J5: 2003 | K5: 2004 | L5: 2005 | M5: 2006 | N5: 2007 | O5: 2008 | P5: 2009 | Q5: 2010 | R5: 2011 | S5: 2012 | T5: 2013
A6: Primary Industries | B6: =SUM(B7:B8) -> 127206.68 | C6: =SUM(C7:C8) -> 132737.49 | D6: =SUM(D7:D8) -> 134732.09 | E6: =SUM(E7:E8) -> 132879.43 | F6: =SUM(F7:F8) -> 133396.86 | G6: =SUM(G7:G8) -> 133856.6 | H6: =SUM(H7:H8) -> 132609.54 | I6: =SUM(I7:I8) -> 135785.81 | ... T6: =SUM(T7:T8) -> 142490.08
A7: Agriculture, forestry and fishing | B7: 26405.124 | C7: 32742.354 | D7: 33037.035 | E7: 31286.072 | F7: 33225.809 | G7: 34787.422 | H7: 33639.437 | I7: 35826 | J7: 36070 | K7: 36380 | L7: 37402.2 | M7: 35359 | N7: 36301 | O7: 42143.138 | P7: 41454.14 | Q7: 41613.903 | R7: 41586.853 | S7: 42433.445 | T7: 43414.14
A8: Mining and quarrying | B8: 100801.55 | C8: 99995.14 | D8: 101695.06 | E8: 101593.36 | F8: 100171.06 | G8: 99069.174 | H8: 98970.105 | I8: 99959.806 | J8: 103354.82 | K8: 104915.26 | L8: 105991.9 | M8: 105364.26 | N8: 105335.68 | O8: 99395.847 | P8: 94057.359 | Q8: 99383.17 | R8: 99687.222 | S8: 96082.321 | T8: 99075.942
A9: Secondary Industries | B9: =SUM(B10:B12) -> 248296.2 | C9: =SUM(C10:C12) -> 254358.8 | D9: =SUM(D10:D12) -> 261763.46 | E9: =SUM(E10:E12) -> 257891.65 | F9: =SUM(F10:F12) -> 258636.33 | G9: =SUM(G10:G12) -> 277586.36 | H9: =SUM(H10:H12) -> 284951.66 | I9: =SUM(I10:I12) -> 293957 | ... T9: =SUM(T10:T12) -> 395262.28
A10: Manufacturing | B10: 196934.25 | C10: 199691.33 | D10: 205083 | E10: 204672.83 | F10: 205900.87 | G10: 222578.84 | H10: 229701.36 | I10: 236133 | J10: 232581 | K10: 243965 | L10: 259101 | M10: 275782.4 | N10: 290246 | O10: 297888.57 | P10: 267722.57 | Q10: 282508.71 | R10: 291785.14 | S10: 297808.31 | T10: 300050.43
A11: Electricity, gas and water | B11: 25843.26 | C11: 28634.332 | D11: 29751.071 | E11: 27876.753 | F11: 27737.369 | G11: 28597.228 | H11: 27539.13 | I11: 28503 | J11: 29344 | K11: 31335 | L11: 33010.2 | M11: 34139 | N11: 35294 | O11: 34195.636 | P11: 33711.906 | Q11: 34538.154 | R11: 35049.055 | S11: 34476.319 | T11: 34332.855
A12: Construction | B12: 25518.69 | C12: 26033.14 | D12: 26929.389 | E12: 25342.07 | F12: 24998.088 | G12: 26410.289 | H12: 27711.166 | I12: 29321 | J12: 31575 | K12: 34451 | L12: 38558 | M12: 42582 | N12: 48971 | O12: 53145.384 | P12: 57278.524 | Q12: 57706.903 | R12: 57869.458 | S12: 59206.362 | T12: 60879
A13: Tertiary industries | B13: =SUM(B14:B18) -> 636192.82 | C13: =SUM(C14:C18) -> 662878.91 | D13: =SUM(D14:D18) -> 679765.27 | E13: =SUM(E14:E18) -> 693351.13 | F13: =SUM(F14:F18) -> 719841.56 | G13: =SUM(G14:G18) -> 748200.15 | H13: =SUM(H14:H18) -> 774956.39 | I13: =SUM(I14:I18) -> 806527.2 | ... T13: =SUM(T14:T18) -> 1240201.3
A14: Wholesale & retail trade; hotels & restaurants | B14: 131650.34 | C14: 136521.41 | D14: 137067.49 | E14: 138849.37 | F14: 149401.92 | G14: 161503.48 | H14: 164572.04 | I14: 168357.2 | J14: 172845.2 | K14: 182175 | L14: 195012.2 | M14: 206636 | N14: 217607 | O14: 219749.14 | P14: 217073.92 | Q14: 225337.56 | R14: 235294.55 | S14: 244278.14 | T14: 249606.79
A15: Transport , storage and communication | B15: 74969.254 | C15: 79542.379 | D15: 85587.6 | E15: 90294.918 | F15: 94990.253 | G15: 102874.44 | H15: 108944.04 | I15: 118749 | J15: 126287 | K15: 132459 | L15: 139471.8 | M15: 146607 | N15: 156289 | O15: 162522.04 | P15: 163999.44 | Q15: 167313.42 | R15: 172530.12 | S15: 176699.46 | T15: 180108.46
A16: Finance, real estate and business services | B16: 174720 | C16: 186575.4 | D16: 195355.8 | E16: 199853 | F16: 210066.6 | G16: 216747.2 | H16: 234450.1 | I16: 249165 | J16: 261123 | K16: 279544 | L16: 295503.5 | M16: 324002 | N16: 349500.92 | O16: 375240.47 | P16: 378986.81 | Q16: 387188.66 | R16: 405479.22 | S16: 420473.37 | T16: 430597
A17: Personal services | B17: 63819.642 | C17: 65516.096 | D17: 65494.661 | E17: 69562.679 | F17: 72254.154 | G17: 75735.383 | H17: 77438.116 | I17: 79346 | J17: 83756 | K17: 85219 | L17: 88454.7 | M17: 93073 | N17: 98247 | O17: 102105.56 | P17: 101233.11 | Q17: 101670.85 | R17: 104025.73 | S17: 106180.87 | T17: 108045.05
A18: General government services | B18: 191033.58 | C18: 194723.63 | D18: 196259.72 | E18: 194791.17 | F18: 193128.63 | G18: 191339.64 | H18: 189552.09 | I18: 190910 | J18: 196193 | K18: 199947 | L18: 208560.8 | M18: 214947 | N18: 223284 | O18: 233416 | P18: 242542 | Q18: 250014 | R18: 260494 | S18: 267714 | T18: 271844
A19: All industries at basic prices | B19: =B13+B9+B6 -> 1011695.7 | C19: =C13+C9+C6 -> 1049975.2 | D19: =D13+D9+D6 -> 1076260.8 | E19: =E13+E9+E6 -> 1084122.2 | F19: =F13+F9+F6 -> 1111874.7 | G19: =G13+G9+G6 -> 1159643.1 | H19: =H13+H9+H6 -> 1192517.6 | I19: =I13+I9+I6 -> 1236270 | ... T19: =T13+T9+T6 -> 1777953.7
A20: Taxes less subsidies on products | B20: 133676.76 | C20: 140208.86 | D20: 144304.78 | E20: 142661.12 | F20: 141889.98 | G20: 144129.16 | H20: 146201.17 | I20: 150165 | J20: 154193 | K20: 161940 | L20: 170015 | M20: 180630 | N20: 190089 | O20: 194792 | P20: 188839 | Q20: 195733 | R20: 205542 | S20: 211091 | T20: 215479
A21: SA - GDP at constant 2005 prices | B21: =B19+B20 -> 1145372.5 | C21: =C19+C20 -> 1190184.1 | D21: =D19+D20 -> 1220565.6 | E21: =E19+E20 -> 1226783.3 | F21: =F19+F20 -> 1253764.7 | G21: =G19+G20 -> 1303772.3 | H21: =H19+H20 -> 1338718.8 | I21: =I19+I20 -> 1386435 | ... T21: =T19+T20 -> 1993432.7
A23: KZN – GDPR by activity
A24: Constant 2005 prices - Rand million
A25: Provincial Industry | B25: 1995 | C25: 1996 | D25: 1997 | E25: 1998 | F25: 1999 | G25: 2000 | H25: 2001 | I25: 2002 | J25: 2003 | K25: 2004 | L25: 2005 | M25: 2006 | N25: 2007 | O25: 2008 | P25: 2009 | Q25: 2010 | R25: 2011 | S25: 2012 | T25: 2013
A26: Primary Industries | B26: =B27+B28 -> 12647.433 | C26: =C27+C28 -> 15724.196 | D26: =D27+D28 -> 15757.65 | E26: =E27+E28 -> 15760.501 | F26: =F27+F28 -> 13821.738 | G26: 14059.846 | H26: 13804.539 | I26: 13819.258 | J26: 14560.827 | K26: 14670.86 | L26: 13796.857 | M26: 13726.996 | N26: 14230.05 | O26: 15530.125 | P26: 15243.988 | Q26: =SUM(Q27:Q28) -> 15537.976 | R26: =SUM(R27:R28) -> 15614.797 | S26: =SUM(S27:S28) -> 15988.264 | T26: =SUM(T27:T28) -> 16466.299
A27: Agriculture, forestry and fishing | B27: 8243.6494 | C27: 9590.1168 | D27: 9555.8073 | E27: 9642.4591 | F27: 9388.88 | G27: 9741.35 | H27: 9706.76 | I27: 10158.474 | J27: 10684.788 | K27: 10717 | L27: 10091.489 | M27: 10144.925 | N27: 10559.454 | O27: 12095.033 | P27: 11746.697 | Q27: 12023.463 | R27: 12148.83 | S27: 12455.255 | T27: =SUM(Quarterly!BV27:BY27) -> 12882.147
A28: Mining and quarrying | B28: 4403.7833 | C28: 6134.0795 | D28: 6201.8427 | E28: 6118.0414 | F28: 4432.8582 | G28: 4318.4962 | H28: 4097.7793 | I28: 3660.7832 | J28: 3875.7421 | K28: 3953.3719 | L28: 3705.9903 | M28: 3582.1283 | N28: 3671.407 | O28: 3431.4323 | P28: 3211.9769 | Q28: 3514.5131 | R28: 3465.9669 | S28: 3533.0086 | T28: =SUM(Quarterly!BV28:BY28) -> 3584.1511
A29: Secondary Industries | B29: =B30+B31+B32 -> 50300.616 | C29: =C30+C31+C32 -> 51439.133 | D29: =D30+D31+D32 -> 52980.98 | E29: =E30+E31+E32 -> 51933.881 | F29: =F30+F31+F32 -> 52382.09 | G29: 56563.711 | H29: 59380.107 | I29: 59989.937 | J29: 59093.765 | K29: 62217.716 | L29: 66446.722 | M29: 70391.388 | N29: 74568.824 | O29: 76572.692 | P29: 70148.665 | Q29: =SUM(Q30:Q32) -> 74297.62 | R29: =SUM(R30:R32) -> 76373.065 | S29: =SUM(S30:S32) -> 77717.658 | T29: =SUM(T30:T32) -> 78410.042
A30: Manufacturing | B30: 41206.6 | C30: 41926.886 | D30: 43038.36 | E30: 42844.617 | F30: 43531.509 | G30: 47270.843 | H30: 48677.683 | I30: 49960.634 | J30: 49502.968 | K30: 51829.694 | L30: 55026.96 | M30: 58348.48 | N30: 61440.731 | O30: 63013.372 | P30: 56740.803 | Q30: 60192.776 | R30: 62165.176 | S30: 63485.736 | T30: =SUM(Quarterly!BV30:BY30) -> 63959.502
A31: Electricity, gas and water | B31: 4495.2863 | C31: 4993.0969 | D31: 5165.0171 | E31: 4849.3541 | F31: 4852.2025 | G31: 5136.9116 | H31: 5128.9257 | I31: 5626.6256 | J31: 4979.0051 | K31: 5343.3901 | L31: 5691.2969 | M31: 5879.2136 | N31: 6075.1904 | O31: 5830.7275 | P31: 5602.3111 | Q31: 5669.0461 | R31: 5736.8007 | S31: 5547.3043 | T31: =SUM(Quarterly!BV31:BY31) -> 5508.4458
A32: Construction | B32: 4598.7298 | C32: 4519.1498 | D32: 4777.6035 | E32: 4239.9102 | F32: 3998.3783 | G32: 4155.9562 | H32: 5573.498 | I32: 4402.6768 | J32: 4611.7926 | K32: 5044.6319 | L32: 5728.5484 | M32: 6163.7935 | N32: 7052.9033 | O32: 7656.3255 | P32: 8298.9292 | Q32: 8435.798 | R32: 8471.0883 | S32: 8684.6185 | T32: =SUM(Quarterly!BV32:BY32) -> 8942.0946
A33: Tertiary industries | B33: =SUM(B34:B38) -> 99772.901 | C33: =SUM(C34:C38) -> 103962.56 | D33: =SUM(D34:D38) -> 105537.09 | E33: =SUM(E34:E38) -> 108436.23 | F33: =SUM(F34:F38) -> 111911.67 | G33: 116046.82 | H33: 121244.05 | I33: 126098.8 | J33: 132006.66 | K33: 137951.47 | L33: 147296.36 | M33: 155772.09 | N33: 165536.18 | O33: 172740.71 | P33: 174996.29 | Q33: =SUM(Q34:Q38) -> 180722.53 | R33: =SUM(R34:R38) -> 188235.78 | S33: =SUM(S34:S38) -> 193978.65 | T33: =SUM(T34:T38) -> 198221.68
A34: Wholesale & retail trade; hotels & restaurants | B34: 21355.843 | C34: 21835.713 | D34: 21956.732 | E34: 22150.158 | F34: 23734.656 | G34: 25691.399 | H34: 27698.397 | I34: 28376.888 | J34: 29361.146 | K34: 30957.43 | L34: 32959.681 | M34: 35070.016 | N34: 37031.186 | O34: 37423.088 | P34: 37446.864 | Q34: 39008.245 | R34: 40992.229 | S34: 42524.566 | T34: =SUM(Quarterly!BV34:BY34) -> 43728.354
A35: Transport , storage and communication | B35: 17467.023 | C35: 18247.31 | D35: 19261.839 | E35: 20134.14 | F35: 20849.208 | G35: 22194.91 | H35: 23152.354 | I35: 25318.289 | J35: 27088.303 | K35: 28301.562 | L35: 29975.763 | M35: 31534.57 | N35: 33783.704 | O35: 35198.833 | P35: 35759.306 | Q35: 36715.879 | R35: 37781.343 | S35: 38749.746 | T35: =SUM(Quarterly!BV35:BY35) -> 39414.538
A36: Finance, real estate and business services | B36: 24397.324 | C36: 26067.429 | D36: 27172.628 | E36: 27832.073 | F36: 29524.634 | G36: 29876.96 | H36: 31579.969 | I36: 33176.274 | J36: 35030.692 | K36: 37561.687 | L36: 41534.132 | M36: 44730.09 | N36: 48201.169 | O36: 51760.699 | P36: 52599.709 | Q36: 53885.893 | R36: 56479.573 | S36: 58367.887 | T36: =SUM(Quarterly!BV36:BY36) -> 59824.321
A37: Personal services | B37: 10462.035 | C37: 10733.983 | D37: 10723.031 | E37: 11390.053 | F37: 11811.006 | G37: 12366.988 | H37: 12655.308 | I37: 12960.485 | J37: 13682.568 | K37: 13924.515 | L37: 14394.744 | M37: 15158.467 | N37: 15993.348 | O37: 16596.258 | P37: 16592.493 | Q37: 16703.006 | R37: 17129.72 | S37: 17516.427 | T37: =SUM(Quarterly!BV37:BY37) -> 17865.338
A38: General government services | B38: 26090.676 | C38: 27078.126 | D38: 26422.865 | E38: 26929.808 | F38: 25992.162 | G38: 25916.567 | H38: 26158.024 | I38: 26266.861 | J38: 26844.074 | K38: 27206.323 | L38: 28431.677 | M38: 29278.956 | N38: 30470.367 | O38: 31970.944 | P38: 33217.019 | Q38: 34409.511 | R38: 35852.917 | S38: 36820.026 | T38: =SUM(Quarterly!BV38:BY38) -> 37389.131
A39: All industries at basic prices | B39: =B33+B29+B26 -> 162720.95 | C39: =C33+C29+C26 -> 171125.89 | D39: =D33+D29+D26 -> 174275.72 | E39: =E33+E29+E26 -> 176130.61 | F39: =F33+F29+F26 -> 178115.49 | G39: 186451.17 | H39: 194342.91 | I39: 199907.99 | J39: 205661.25 | K39: 214840.04 | L39: 227539.94 | M39: 239890.48 | N39: 254335.06 | O39: 264843.53 | P39: 260388.94 | Q39: =Q26+Q29+Q33 -> 270558.13 | R39: =R26+R29+R33 -> 280223.64 | S39: =S26+S29+S33 -> 287684.57 | T39: =T26+T29+T33 -> 293098.02
A40: Taxes less subsidies on products | B40: 21530.728 | C40: 22661.717 | D40: 23287.012 | E40: 23156.565 | F40: 22702.228 | G40: 23280.712 | H40: 24730.666 | I40: 24615.022 | J40: 25021.001 | K40: 26215.374 | L40: 27399.009 | M40: 29154.713 | N40: 30569.553 | O40: 31373.999 | P40: 30500.475 | Q40: 32059.683 | R40: 33164.225 | S40: 34497.679 | T40: =SUM(Quarterly!BV40:BY40) -> 34688.413
A41: KZN - GDPR at constant 2005 prices | B41: =B40+B39 -> 184251.68 | C41: =C40+C39 -> 193787.61 | D41: =D40+D39 -> 197562.74 | E41: =E40+E39 -> 199287.18 | F41: =F40+F39 -> 200817.72 | G41: 209731.89 | H41: 219073.58 | I41: 224523.01 | J41: 230682.27 | K41: 241055.47 | L41: 254938.58 | M41: 269045.17 | N41: 284904.87 | O41: 296224.5 | P41: 290947.35 | Q41: =Q39+Q40 -> 302617.81 | R41: =R39+R40 -> 313387.87 | S41: =S39+S40 -> 322182.25 | T41: =T39+T40 -> 327786.44
A43: Structure Relationship
A44: National - Provincial Structure | B44: 1995 | C44: 1996 | D44: 1997 | E44: 1998 | F44: 1999 | G44: 2000 | H44: 2001 | I44: 2002 | J44: 2003 | K44: 2004 | L44: 2005 | M44: 2006 | N44: 2007 | O44: 2008 | P44: 2009 | Q44: 2010 | R44: 2011 | S44: 2012 | T44: 2013
A45: Primary Industries | B45: =B26/B6*100 -> 9.9424284 | C45: =C26/C6*100 -> 11.846085 | D45: =D26/D6*100 -> 11.695543 | E45: =E26/E6*100 -> 11.860752 | F45: =F26/F6*100 -> 10.361367 | G45: =G26/G6*100 -> 10.503663 | H45: =H26/H6*100 -> 10.409914 | I45: =I26/I6*100 -> 10.177248 | ... R45: =R26/R6*100 -> 11.05284 | S45: =R45+($R45-$Q45) -> 11.085609 | T45: =S45+($R45-$Q45) -> 11.118378 | U45: =T45 -> 11.118378 | V45: =U45 -> 11.118378 | W45: =V45 -> 11.118378 | X45: =W45 -> 11.118378
A46: Agriculture, forestry and fishing | B46: =B27/B7*100 -> 31.219885 | C46: =C27/C7*100 -> 29.289638 | D46: =D27/D7*100 -> 28.924531 | E46: =E27/E7*100 -> 30.820293 | F46: =F27/F7*100 -> 28.257792 | G46: =G27/G7*100 -> 28.002507 | H46: =H27/H7*100 -> 28.855299 | I46: =I27/I7*100 -> 28.355032 | ... S46: =S27/S7*100 -> 29.352449 | T46: =S46+($R46-$Q46) -> 29.6727 | U46: =T46 -> 29.6727 | V46: =U46 -> 29.6727 | W46: =V46 -> 29.6727 | X46: =W46 -> 29.6727
A47: Mining and quarrying | B47: =B28/B8*100 -> 4.3687653 | C47: =C28/C8*100 -> 6.1343776 | D47: =D28/D8*100 -> 6.0984701 | E47: =E28/E8*100 -> 6.0220877 | F47: =F28/F8*100 -> 4.4252885 | G47: =G28/G8*100 -> 4.3590716 | H47: =H28/H8*100 -> 4.1404213 | I47: =I28/I8*100 -> 3.6622552 | ... S47: =S28/S8*100 -> 3.6770642 | T47: =S47+($R47-$Q47) -> 3.6175797 | U47: =T47 -> 3.6175797 | V47: =U47 -> 3.6175797 | W47: =V47 -> 3.6175797 | X47: =W47 -> 3.6175797
A48: Secondary Industries | B48: =B29/B9*100 -> 20.258311 | C48: =C29/C9*100 -> 20.22306 | D48: =D29/D9*100 -> 20.240022 | E48: =E29/E9*100 -> 20.137868 | F48: =F29/F9*100 -> 20.253183 | G48: =G29/G9*100 -> 20.376978 | H48: =H29/H9*100 -> 20.83866 | I48: =I29/I9*100 -> 20.407725 | ... R48: =R29/R9*100 -> 19.852441 | S48: =R48+($R48-$Q48) -> 19.879165 | T48: =S48+($R48-$Q48) -> 19.905889 | U48: =T48 -> 19.905889 | V48: =U48 -> 19.905889 | W48: =V48 -> 19.905889 | X48: =W48 -> 19.905889
A49: Manufacturing | B49: =B30/B10*100 -> 20.924039 | C49: =C30/C10*100 -> 20.995847 | D49: =D30/D10*100 -> 20.985825 | E49: =E30/E10*100 -> 20.933221 | F49: =F30/F10*100 -> 21.141974 | G49: =G30/G10*100 -> 21.237798 | H49: =H30/H10*100 -> 21.191726 | I49: =I30/I10*100 -> 21.157837 | ... S49: =S30/S10*100 -> 21.317651 | T49: =S49+($R49-$Q49) -> 21.316251 | U49: =T49 -> 21.316251 | V49: =U49 -> 21.316251 | W49: =V49 -> 21.316251 | X49: =W49 -> 21.316251
A50: Electricity, gas and water | B50: =B31/B11*100 -> 17.394424 | C50: =C31/C11*100 -> 17.437449 | D50: =D31/D11*100 -> 17.360777 | E50: =E31/E11*100 -> 17.395692 | F50: =F31/F11*100 -> 17.493377 | G50: =G31/G11*100 -> 17.962971 | H50: =H31/H11*100 -> 18.624138 | I50: =I31/I11*100 -> 19.740468 | ... S50: =S31/S11*100 -> 16.090187 | T50: =S50+($R50-$Q50) -> 16.04424 | U50: =T50 -> 16.04424 | V50: =U50 -> 16.04424 | W50: =V50 -> 16.04424 | X50: =W50 -> 16.04424
A51: Construction | B51: =B32/B12*100 -> 18.021026 | C51: =C32/C12*100 -> 17.359219 | D51: =D32/D12*100 -> 17.741225 | E51: =E32/E12*100 -> 16.730718 | F51: =F32/F12*100 -> 15.994737 | G51: =G32/G12*100 -> 15.736125 | H51: =H32/H12*100 -> 20.112824 | I51: =I32/I12*100 -> 15.015439 | ... S51: =S32/S12*100 -> 14.668387 | T51: =S51+($R51-$Q51) -> 14.688307 | U51: =T51 -> 14.688307 | V51: =U51 -> 14.688307 | W51: =V51 -> 14.688307 | X51: =W51 -> 14.688307
A52: Tertiary industries | B52: =B33/B13*100 -> 15.682809 | C52: =C33/C13*100 -> 15.683492 | D52: =D33/D13*100 -> 15.52552 | E52: =E33/E13*100 -> 15.63944 | F52: =F33/F13*100 -> 15.546708 | G52: =G33/G13*100 -> 15.510131 | H52: =H33/H13*100 -> 15.645274 | I52: =I33/I13*100 -> 15.634785 | ... R52: =R33/R13*100 -> 15.981661 | S52: =R52+($R52-$Q52) -> 15.991725 | T52: =S52+($R52-$Q52) -> 16.001789 | U52: =T52 -> 16.001789 | V52: =U52 -> 16.001789 | W52: =V52 -> 16.001789 | X52: =W52 -> 16.001789
A53: Wholesale & retail trade; hotels & restaurants | B53: =B34/B14*100 -> 16.221638 | C53: =C34/C14*100 -> 15.994351 | D53: =D34/D14*100 -> 16.01892 | E53: =E34/E14*100 -> 15.952653 | F53: =F34/F14*100 -> 15.886446 | G53: =G34/G14*100 -> 15.907644 | H53: =H34/H14*100 -> 16.83056 | I53: =I34/I14*100 -> 16.855168 | ... S53: =S34/S14*100 -> 17.408257 | T53: =S53+($R53-$Q53) -> 17.518896 | U53: =T53 -> 17.518896 | V53: =U53 -> 17.518896 | W53: =V53 -> 17.518896 | X53: =W53 -> 17.518896
A54: Transport , storage and communication | B54: =B35/B15*100 -> 23.298916 | C54: =C35/C15*100 -> 22.940362 | D54: =D35/D15*100 -> 22.505408 | E54: =E35/E15*100 -> 22.298198 | F54: =F35/F15*100 -> 21.948787 | G54: =G35/G15*100 -> 21.574756 | H54: =H35/H15*100 -> 21.251603 | I54: =I35/I15*100 -> 21.320844 | ... S54: =S35/S15*100 -> 21.929748 | T54: =S54+($R54-$Q54) -> 21.883779 | U54: =T54 -> 21.883779 | V54: =U54 -> 21.883779 | W54: =V54 -> 21.883779 | X54: =W54 -> 21.883779
A55: Finance, real estate and business services | B55: =B36/B16*100 -> 13.96367 | C55: =C36/C16*100 -> 13.971525 | D55: =D36/D16*100 -> 13.909302 | E55: =E36/E16*100 -> 13.926272 | F55: =F36/F16*100 -> 14.054892 | G55: =G36/G16*100 -> 13.784243 | H55: =H36/H16*100 -> 13.469804 | I55: =I36/I16*100 -> 13.314982 | ... S55: =S36/S16*100 -> 13.881471 | T55: =S55+($R55-$Q55) -> 13.893344 | U55: =T55 -> 13.893344 | V55: =U55 -> 13.893344 | W55: =V55 -> 13.893344 | X55: =W55 -> 13.893344
A56: Personal services | B56: =B37/B17*100 -> 16.393128 | C56: =C37/C17*100 -> 16.383734 | D56: =D37/D17*100 -> 16.372374 | E56: =E37/E17*100 -> 16.373799 | F56: =F37/F17*100 -> 16.346474 | G56: =G37/G17*100 -> 16.329207 | H56: =H37/H17*100 -> 16.342479 | I56: =I37/I17*100 -> 16.334138 | ... S56: =S37/S17*100 -> 16.496783 | T56: =S56+($R56-$Q56) -> 16.535083 | U56: =T56 -> 16.535083 | V56: =U56 -> 16.535083 | W56: =V56 -> 16.535083 | X56: =W56 -> 16.535083
A57: General government services | B57: =B38/B18*100 -> 13.657639 | C57: =C38/C18*100 -> 13.905927 | D57: =D38/D18*100 -> 13.463214 | E57: =E38/E18*100 -> 13.824964 | F57: =F38/F18*100 -> 13.458472 | G57: =G38/G18*100 -> 13.544797 | H57: =H38/H18*100 -> 13.799913 | I57: =I38/I18*100 -> 13.758766 | ... S57: =S38/S18*100 -> 13.753493 | T57: =S57+($R57-$Q57) -> 13.753892 | U57: =T57 -> 13.753892 | V57: =U57 -> 13.753892 | W57: =V57 -> 13.753892 | X57: =W57 -> 13.753892
A58: All industries at basic prices | B58: =B39/B19*100 -> 16.083982 | C58: =C39/C19*100 -> 16.298089 | D58: =D39/D19*100 -> 16.192704 | E58: =E39/E19*100 -> 16.24638 | F58: =F39/F19*100 -> 16.019385 | G58: =G39/G19*100 -> 16.078324 | H58: =H39/H19*100 -> 16.296859 | I58: =I39/I19*100 -> 16.170253 | ... R58: =R39/R19*100 -> 16.446967 | S58: =R58+($R58-$Q58) -> 16.469349 | T58: =S58+($R58-$Q58) -> 16.491731 | U58: =T58 -> 16.491731 | V58: =U58 -> 16.491731 | W58: =V58 -> 16.491731 | X58: =W58 -> 16.491731
A59: Taxes less subsidies on products | B59: =B40/B20*100 -> 16.10656 | C59: =C40/C20*100 -> 16.162828 | D59: =D40/D20*100 -> 16.137381 | E59: =E40/E20*100 -> 16.231868 | F59: =F40/F20*100 -> 15.999882 | G59: =G40/G20*100 -> 16.152674 | H59: =H40/H20*100 -> 16.915504 | I59: =I40/I20*100 -> 16.391983 | ... S59: =S40/S20*100 -> 16.342563 | T59: =S59+($R59-$Q59) -> 16.09828 | U59: =T59 -> 16.09828 | V59: =U59 -> 16.09828 | W59: =V59 -> 16.09828 | X59: =W59 -> 16.09828
A60: KZN - GDPR at constant 2005 prices | B60: =B41/B21*100 -> 16.086617 | C60: =C41/C21*100 -> 16.282154 | D60: =D41/D21*100 -> 16.186163 | E60: =E41/E21*100 -> 16.244692 | F60: =F41/F21*100 -> 16.017178 | G60: =G41/G21*100 -> 16.086543 | H60: =H41/H21*100 -> 16.364421 | I60: =I41/I21*100 -> 16.194269 | ... R60: =R41/R21*100 -> 16.413385 | S60: =R60+($R60-$Q60) -> 16.406995 | T60: =S60+($R60-$Q60) -> 16.400605 | U60: =T60 -> 16.400605 | V60: =U60 -> 16.400605 | W60: =V60 -> 16.400605 | X60: =W60 -> 16.400605
A62: SA – GDP by activity
A63: PA Change
A64: National Industry | C64: 1996 | D64: 1997 | E64: 1998 | F64: 1999 | G64: 2000 | H64: 2001 | I64: 2002 | J64: 2003 | K64: 2004 | L64: 2005 | M64: 2006 | N64: 2007 | O64: 2008 | P64: 2009 | Q64: 2010 | R64: 2011 | S64: 2012 | T64: 2013
A65: Primary Industries | C65: =(C6-B6)/B6*100 -> 4.3478986 | D65: =(D6-C6)/C6*100 -> 1.502664 | E65: =(E6-D6)/D6*100 -> -1.375068 | F65: =(F6-E6)/E6*100 -> 0.38939765 | G65: =(G6-F6)/F6*100 -> 0.34463433 | H65: =(H6-G6)/G6*100 -> -0.9316344 | I65: =(I6-H6)/H6*100 -> 2.3952005 | J65: =(J6-I6)/I6*100 -> 2.6799669 | ... T65: =(T6-S6)/S6*100 -> 2.8692152
A66: Agriculture, forestry and fishing | C66: =(C7-B7)/B7*100 -> 24 | D66: =(D7-C7)/C7*100 -> 0.9 | E66: =(E7-D7)/D7*100 -> -5.3 | F66: =(F7-E7)/E7*100 -> 6.2 | G66: =(G7-F7)/F7*100 -> 4.7 | H66: =(H7-G7)/G7*100 -> -3.3 | I66: =(I7-H7)/H7*100 -> 6.5 | J66: =(J7-I7)/I7*100 -> 0.68106961 | ... T66: =(T7-S7)/S7*100 -> 2.3111365
A67: Mining and quarrying | C67: =(C8-B8)/B8*100 -> -0.8 | D67: =(D8-C8)/C8*100 -> 1.7 | E67: =(E8-D8)/D8*100 -> -0.1 | F67: =(F8-E8)/E8*100 -> -1.4 | G67: =(G8-F8)/F8*100 -> -1.1 | H67: =(H8-G8)/G8*100 -> -0.1 | I67: =(I8-H8)/H8*100 -> 1 | J67: =(J8-I8)/I8*100 -> 3.3963798 | ... T67: =(T8-S8)/S8*100 -> 3.115683
A68: Secondary Industries | C68: =(C9-B9)/B9*100 -> 2.4416812 | D68: =(D9-C9)/C9*100 -> 2.9111058 | E68: =(E9-D9)/D9*100 -> -1.4791227 | F68: =(F9-E9)/E9*100 -> 0.28875363 | G68: =(G9-F9)/F9*100 -> 7.326902 | H68: =(H9-G9)/G9*100 -> 2.6533371 | I68: =(I9-H9)/H9*100 -> 3.1603052 | J68: =(J9-I9)/I9*100 -> -0.15546491 | ... T68: =(T9-S9)/S9*100 -> 0.96331589
A69: Manufacturing | C69: =(C10-B10)/B10*100 -> 1.4 | D69: =(D10-C10)/C10*100 -> 2.7 | E69: =(E10-D10)/D10*100 -> -0.2 | F69: =(F10-E10)/E10*100 -> 0.6 | G69: =(G10-F10)/F10*100 -> 8.1 | H69: =(H10-G10)/G10*100 -> 3.2 | I69: =(I10-H10)/H10*100 -> 2.8 | J69: =(J10-I10)/I10*100 -> -1.504237 | ... T69: =(T10-S10)/S10*100 -> 0.75287363
A70: Electricity, gas and water | C70: =(C11-B11)/B11*100 -> 10.8 | D70: =(D11-C11)/C11*100 -> 3.9 | E70: =(E11-D11)/D11*100 -> -6.3 | F70: =(F11-E11)/E11*100 -> -0.5 | G70: =(G11-F11)/F11*100 -> 3.1 | H70: =(H11-G11)/G11*100 -> -3.7 | I70: =(I11-H11)/H11*100 -> 3.5 | J70: =(J11-I11)/I11*100 -> 2.9505666 | ... T70: =(T11-S11)/S11*100 -> -0.41612157
A71: Construction | C71: =(C12-B12)/B12*100 -> 2.0159734 | D71: =(D12-C12)/C12*100 -> 3.4427236 | E71: =(E12-D12)/D12*100 -> -5.894375 | F71: =(F12-E12)/E12*100 -> -1.3573544 | G71: =(G12-F12)/F12*100 -> 5.6492369 | H71: =(H12-G12)/G12*100 -> 4.9256418 | I71: =(I12-H12)/H12*100 -> 5.8093347 | J71: =(J12-I12)/I12*100 -> 7.6873231 | ... T71: =(T12-S12)/S12*100 -> 2.8250986
A72: Tertiary industries | C72: =(C13-B13)/B13*100 -> 4.1946552 | D72: =(D13-C13)/C13*100 -> 2.547427 | E72: =(E13-D13)/D13*100 -> 1.9986111 | F72: =(F13-E13)/E13*100 -> 3.8206365 | G72: =(G13-F13)/F13*100 -> 3.9395599 | H72: =(H13-G13)/G13*100 -> 3.5760809 | I72: =(I13-H13)/H13*100 -> 4.073882 | J72: =(J13-I13)/I13*100 -> 4.1755566 | ... T72: =(T13-S13)/S13*100 -> 2.0451353
A73: Wholesale & retail trade; hotels & restaurants | C73: =(C14-B14)/B14*100 -> 3.7 | D73: =(D14-C14)/C14*100 -> 0.4 | E73: =(E14-D14)/D14*100 -> 1.3 | F73: =(F14-E14)/E14*100 -> 7.6 | G73: =(G14-F14)/F14*100 -> 8.1 | H73: =(H14-G14)/G14*100 -> 1.9 | I73: =(I14-H14)/H14*100 -> 2.3 | J73: =(J14-I14)/I14*100 -> 2.6657607 | ... T73: =(T14-S14)/S14*100 -> 2.1813884
A74: Transport , storage and communication | C74: =(C15-B15)/B15*100 -> 6.1 | D74: =(D15-C15)/C15*100 -> 7.6 | E74: =(E15-D15)/D15*100 -> 5.5 | F74: =(F15-E15)/E15*100 -> 5.2 | G74: =(G15-F15)/F15*100 -> 8.3 | H74: =(H15-G15)/G15*100 -> 5.9 | I74: =(I15-H15)/H15*100 -> 9 | J74: =(J15-I15)/I15*100 -> 6.3478429 | ... T74: =(T15-S15)/S15*100 -> 1.9292629
A75: Finance, real estate and business services | C75: =(C16-B16)/B16*100 -> 6.7853709 | D75: =(D16-C16)/C16*100 -> 4.7060867 | E75: =(E16-D16)/D16*100 -> 2.302056 | F75: =(F16-E16)/E16*100 -> 5.1105563 | G75: =(G16-F16)/F16*100 -> 3.1802295 | H75: =(H16-G16)/G16*100 -> 8.1675334 | I75: =(I16-H16)/H16*100 -> 6.2763462 | J75: =(J16-I16)/I16*100 -> 4.7992294 | ... T75: =(T16-S16)/S16*100 -> 2.4076754
A76: Personal services | C76: =(C17-B17)/B17*100 -> 2.6582004 | D76: =(D17-C17)/C17*100 -> -0.032717766 | E76: =(E17-D17)/D17*100 -> 6.2112207 | F76: =(F17-E17)/E17*100 -> 3.8691359 | G76: =(G17-F17)/F17*100 -> 4.8180335 | H76: =(H17-G17)/G17*100 -> 2.2482669 | I76: =(I17-H17)/H17*100 -> 2.4637526 | J76: =(J17-I17)/I17*100 -> 5.5579361 | ... T76: =(T17-S17)/S17*100 -> 1.7556655
... A80: SA - GDP at constant 2005 prices | C80: =(C21-B21)/B21*100 -> 3.9124055 | D80: =(D21-C21)/C21*100 -> 2.5526741 | E80: =(E21-D21)/D21*100 -> 0.50941484 | F80: =(F21-E21)/E21*100 -> 2.1993604 | G80: =(G21-F21)/F21*100 -> 3.9885898 | H80: =(H21-G21)/G21*100 -> 2.680415 | I80: =(I21-H21)/H21*100 -> 3.5643216 | J80: =(J21-I21)/I21*100 -> 2.9490755 | ... T80: =(T21-S21)/S21*100 -> 1.8906283
A82: KZN – GDPR by activity
A83: PA Change
A84: Provincial Industry | C84: 1996 | D84: 1997 | E84: 1998 | F84: 1999 | G84: 2000 | H84: 2001 | I84: 2002 | J84: 2003 | K84: 2004 | L84: 2005 | M84: 2006 | N84: 2007 | O84: 2008 | P84: 2009 | Q84: 2010 | R84: 2011 | S84: 2012 | T84: 2013
A85: Primary Industries | C85: =(C26-B26)/B26*100 -> 24.327179 | D85: =(D26-C26)/C26*100 -> 0.21275363 | E85: =(E26-D26)/D26*100 -> 0.018089306 | F85: =(F26-E26)/E26*100 -> -12.3014 | G85: =(G26-F26)/F26*100 -> 1.7227067 | H85: =(H26-G26)/G26*100 -> -1.8158587 | I85: =(I26-H26)/H26*100 -> 0.10661873 | J85: =(J26-I26)/I26*100 -> 5.3662048 | ... T85: =(T26-S26)/S26*100 -> 2.9899082
A86: Agriculture, forestry and fishing | C86: =(C27-B27)/B27*100 -> 16.33339 | D86: =(D27-C27)/C27*100 -> -0.35775829 | E86: =(E27-D27)/D27*100 -> 0.90679689 | F86: =(F27-E27)/E27*100 -> -2.6298178 | G86: =(G27-F27)/F27*100 -> 3.7541219 | H86: =(H27-G27)/G27*100 -> -0.35508425 | I86: =(I27-H27)/H27*100 -> 4.6535995 | J86: =(J27-I27)/I27*100 -> 5.1810406 | ... T86: =(T27-S27)/S27*100 -> 3.4274041
A87: Mining and quarrying | C87: =(C28-B28)/B28*100 -> 39.291129 | D87: =(D28-C28)/C28*100 -> 1.104701 | E87: =(E28-D28)/D28*100 -> -1.3512325 | F87: =(F28-E28)/E28*100 -> -27.544488 | G87: =(G28-F28)/F28*100 -> -2.5798703 | H87: =(H28-G28)/G28*100 -> -5.1109674 | I87: =(I28-H28)/H28*100 -> -10.664217 | J87: =(J28-I28)/I28*100 -> 5.871938 | ... T87: =(T28-S28)/S28*100 -> 1.4475615
A88: Secondary Industries | C88: =(C29-B29)/B29*100 -> 2.2634245 | D88: =(D29-C29)/C29*100 -> 2.9974217 | E88: =(E29-D29)/D29*100 -> -1.9763677 | F88: =(F29-E29)/E29*100 -> 0.86303659 | G88: =(G29-F29)/F29*100 -> 7.9829223 | H88: =(H29-G29)/G29*100 -> 4.9791564 | I88: =(I29-H29)/H29*100 -> 1.0269937 | J88: =(J29-I29)/I29*100 -> -1.4938695 | ... T88: =(T29-S29)/S29*100 -> 0.89089646
A89: Manufacturing | C89: =(C30-B30)/B30*100 -> 1.7479865 | D89: =(D30-C30)/C30*100 -> 2.6509811 | E89: =(E30-D30)/D30*100 -> -0.45016265 | F89: =(F30-E30)/E30*100 -> 1.6032162 | G89: =(G30-F30)/F30*100 -> 8.5899493 | H89: =(H30-G30)/G30*100 -> 2.9761257 | I89: =(I30-H30)/H30*100 -> 2.6356048 | J89: =(J30-I30)/I30*100 -> -0.91605472 | ... T89: =(T30-S30)/S30*100 -> 0.74625617
A90: Electricity, gas and water | C90: =(C31-B31)/B31*100 -> 11.07406 | D90: =(D31-C31)/C31*100 -> 3.4431571 | E90: =(E31-D31)/D31*100 -> -6.1115589 | F90: =(F31-E31)/E31*100 -> 0.05873819 | G90: =(G31-F31)/F31*100 -> 5.8676268 | H90: =(H31-G31)/G31*100 -> -0.1554615 | I90: =(I31-H31)/H31*100 -> 9.7037841 | J90: =(J31-I31)/I31*100 -> -11.509926 | ... T90: =(T31-S31)/S31*100 -> -0.70049306
A91: Construction | C91: =(C32-B32)/B32*100 -> -1.7304781 | D91: =(D32-C32)/C32*100 -> 5.7190779 | E91: =(E32-D32)/D32*100 -> -11.254457 | F91: =(F32-E32)/E32*100 -> -5.6966269 | G91: =(G32-F32)/F32*100 -> 3.9410442 | H91: =(H32-G32)/G32*100 -> 34.108681 | I91: =(I32-H32)/H32*100 -> -21.006938 | J91: =(J32-I32)/I32*100 -> 4.7497429 | ... T91: =(T32-S32)/S32*100 -> 2.9647373
A92: Tertiary industries | C92: =(C33-B33)/B33*100 -> 4.1991954 | D92: =(D33-C33)/C33*100 -> 1.51452 | E92: =(E33-D33)/D33*100 -> 2.7470317 | F92: =(F33-E33)/E33*100 -> 3.2050495 | G92: =(G33-F33)/F33*100 -> 3.6950185 | H92: =(H33-G33)/G33*100 -> 4.4785614 | I92: =(I33-H33)/H33*100 -> 4.0041102 | J92: =(J33-I33)/I33*100 -> 4.6851053 | ... T92: =(T33-S33)/S33*100 -> 2.1873694
A93: Wholesale & retail trade; hotels & restaurants | C93: =(C34-B34)/B34*100 -> 2.2470205 | D93: =(D34-C34)/C34*100 -> 0.55422679 | E93: =(E34-D34)/D34*100 -> 0.88094179 | F93: =(F34-E34)/E34*100 -> 7.1534381 | G93: =(G34-F34)/F34*100 -> 8.2442431 | H93: =(H34-G34)/G34*100 -> 7.8119454 | I93: =(I34-H34)/H34*100 -> 2.4495688 | J93: =(J34-I34)/I34*100 -> 3.4685182 | ... T93: =(T34-S34)/S34*100 -> 2.8308062
A94: Transport , storage and communication | C94: =(C35-B35)/B35*100 -> 4.4671965 | D94: =(D35-C35)/C35*100 -> 5.5598838 | E94: =(E35-D35)/D35*100 -> 4.5286472 | F94: =(F35-E35)/E35*100 -> 3.5515228 | G94: =(G35-F35)/F35*100 -> 6.4544517 | H94: =(H35-G35)/G35*100 -> 4.3137984 | I94: =(I35-H35)/H35*100 -> 9.3551418 | J94: =(J35-I35)/I35*100 -> 6.9910453 | ... T94: =(T35-S35)/S35*100 -> 1.7156018
A95: Finance, real estate and business services | C95: =(C36-B36)/B36*100 -> 6.8454418 | D95: =(D36-C36)/C36*100 -> 4.2397691 | E95: =(E36-D36)/D36*100 -> 2.4268725 | F95: =(F36-E36)/E36*100 -> 6.0813332 | G95: =(G36-F36)/F36*100 -> 1.1933288 | H95: =(H36-G36)/G36*100 -> 5.7000744 | I95: =(I36-H36)/H36*100 -> 5.0548031 | J95: =(J36-I36)/I36*100 -> 5.5895925 | ... T95: =(T36-S36)/S36*100 -> 2.4952662
A96: Personal services | C96: =(C37-B37)/B37*100 -> 2.5993757 | D96: =(D37-C37)/C37*100 -> -0.10203571 | E96: =(E37-D37)/D37*100 -> 6.220466 | F96: =(F37-E37)/E37*100 -> 3.6957968 | G96: =(G37-F37)/F37*100 -> 4.707316 | H96: =(H37-G37)/G37*100 -> 2.3313695 | I96: =(I37-H37)/H37*100 -> 2.4114593 | J96: =(J37-I37)/I37*100 -> 5.5714174 | ... T96: =(T37-S37)/S37*100 -> 1.9919066
... A99: Taxes less subsidies on products | C99: =(C40-B40)/B40*100 -> 5.2529069 | D99: =(D40-C40)/C40*100 -> 2.759255 | E99: =(E40-D40)/D40*100 -> -0.56017126 | F99: =(F40-E40)/E40*100 -> -1.9620212 | G99: =(G40-F40)/F40*100 -> 2.5481394 | H99: =(H40-G40)/G40*100 -> 6.2281327 | I99: =(I40-H40)/H40*100 -> -0.46761515 | J99: =(J40-I40)/I40*100 -> 1.649316 | ... T99: =(T40-S40)/S40*100 -> 0.55289001
A100: KZN - GDPR at constant 2005 prices | C100: =(C41-B41)/B41*100 -> 5.1754906 | D100: =(D41-C41)/C41*100 -> 1.948076 | E100: =(E41-D41)/D41*100 -> 0.87285779 | F100: =(F41-E41)/E41*100 -> 0.76800943 | G100: =G98 -> 4.6799297 | H100: =(H41-G41)/G41*100 -> 4.45411 | I100: =(I41-H41)/H41*100 -> 2.4874919 | J100: =(J41-I41)/I41*100 -> 2.743264 | K100: =(K41-J41)/J41*100 -> 4.4967465 | L100: =(L41-K41)/K41*100 -> 5.7593019 | M100: =(M41-L41)/L41*100 -> 5.5333279 | N100: =(N41-M41)/M41*100 -> 5.8948085 | O100: =(O41-N41)/N41*100 -> 3.9731293 | ... T100: =(T41-S41)/S41*100 -> 1.7394447
A102: Targeted GDP | C102: 5 | D102: 5 | E102: 5 | F102: 5 | G102: 5 | H102: 5 | I102: 5 | J102: 5 | K102: 5 | L102: 5 | M102: 5 | N102: 5 | O102: 5 | P102: 5 | Q102: 5 | R102: 5 | S102: 5 | T102: 5
A103: Potential GDP | C103: 3.5 | D103: 3.5 | E103: 3.5 | F103: 3.5 | G103: 3.5 | H103: 3.5 | I103: 3.5 | J103: 3.5 | K103: 3.5 | L103: 3.5 | M103: 3.5 | N103: 3.5 | O103: 3.5 | P103: 3.5 | Q103: 3.5 | R103: 3.5 | S103: 3.5 | T103: 3.5
A134: Primary Industries | B134: =B26/B$39*100 -> 7.7724673 | C134: =C26/C$39*100 -> 9.1886718 | D134: =D26/D$39*100 -> 9.0417929 | E134: =E26/E$39*100 -> 8.9481892 | F134: =F26/F$39*100 -> 7.7599864 | G134: =G26/G$39*100 -> 7.5407657 | H134: =H26/H$39*100 -> 7.1031865 | I134: =I26/I$39*100 -> 6.912809 | ... P134: =P26/P$39*100 -> 5.8543145
A135: Agriculture, forestry and fishing | B135: =B27/B$39*100 -> 5.0661266 | C135: =C27/C$39*100 -> 5.6041297 | D135: =D27/D$39*100 -> 5.4831546 | E135: =E27/E$39*100 -> 5.4746071 | F135: =F27/F$39*100 -> 5.2712315 | G135: =G27/G$39*100 -> 5.2246118 | H135: =H27/H$39*100 -> 4.9946561 | I135: =I27/I$39*100 -> 5.0815746 | ... P135: =P27/P$39*100 -> 4.5112119
A136: Mining and quarrying | B136: =B28/B$39*100 -> 2.7063407 | C136: =C28/C$39*100 -> 3.5845421 | D136: =D28/D$39*100 -> 3.5586383 | E136: =E28/E$39*100 -> 3.4735821 | F136: =F28/F$39*100 -> 2.488755 | G136: =G28/G$39*100 -> 2.3161539 | H136: =H28/H$39*100 -> 2.1085304 | I136: =I28/I$39*100 -> 1.8312341 | ... P136: =P28/P$39*100 -> 1.2335305
A137: Secondary Industries | B137: =B29/B$39*100 -> 30.912194 | C137: =C29/C$39*100 -> 30.059235 | D137: =D29/D$39*100 -> 30.400666 | E137: =E29/E$39*100 -> 29.486005 | F137: =F29/F$39*100 -> 29.409058 | G137: =G29/G$39*100 -> 30.33701 | H137: =H29/H$39*100 -> 30.554295 | I137: =I29/I$39*100 -> 30.008774 | ... P137: =P29/P$39*100 -> 26.939956
A138: Manufacturing | B138: =B30/B$39*100 -> 25.323476 | C138: =C30/C$39*100 -> 24.500609 | D138: =D30/D$39*100 -> 24.695556 | E138: =E30/E$39*100 -> 24.32548 | F138: =F30/F$39*100 -> 24.440046 | G138: =G30/G$39*100 -> 25.352934 | H138: =H30/H$39*100 -> 25.047316 | I138: =I30/I$39*100 -> 24.991815 | ... P138: =P30/P$39*100 -> 21.790788
A139: Electricity, gas and water | B139: =B31/B$39*100 -> 2.7625738 | C139: =C31/C$39*100 -> 2.9177917 | D139: =D31/D$39*100 -> 2.9637043 | E139: =E31/E$39*100 -> 2.7532715 | F139: =F31/F$39*100 -> 2.7241889 | G139: =G31/G$39*100 -> 2.7550975 | H139: =H31/H$39*100 -> 2.6391113 | I139: =I31/I$39*100 -> 2.8146076 | ... P139: =P31/P$39*100 -> 2.1515165
A140: Construction | B140: =B32/B$39*100 -> 2.8261449 | C140: =C32/C$39*100 -> 2.6408335 | D140: =D32/D$39*100 -> 2.741405 | E140: =E32/E$39*100 -> 2.4072534 | F140: =F32/F$39*100 -> 2.2448234 | G140: =G32/G$39*100 -> 2.2289783 | H140: =H32/H$39*100 -> 2.867868 | I140: =I32/I$39*100 -> 2.2023516 | ... P140: =P32/P$39*100 -> 3.1871281
A141: Tertiary industries | B141: =B33/B$39*100 -> 61.315338 | C141: =C33/C$39*100 -> 60.752094 | D141: =D33/D$39*100 -> 60.557542 | E141: =E33/E$39*100 -> 61.565806 | F141: =F33/F$39*100 -> 62.830955 | G141: =G33/G$39*100 -> 62.239792 | H141: =H33/H$39*100 -> 62.386661 | I141: =I33/I$39*100 -> 63.078417 | ... P141: =P33/P$39*100 -> 67.20573
...

Sheet Quarterly
A1: Quarterly GDP and GDPR
A3: SA – GDP by activity
A4: Constant 2005 prices - Rand million
A5: National Industry | B5: 1995q1 | C5: 1995q2 | D5: 1995q3 | E5: 1995q4 | F5: 1996q1 | G5: 1996q2 | H5: 1996q3 | I5: 1996q4 | J5: 1997q1 | K5: 1997q2 | L5: 1997q3 | M5: 1997q4 | N5: 1998q1 | O5: 1998q2 | P5: 1998q3 | Q5: 1998q4 | R5: 1999q1 | S5: 1999q2 | T5: 1999q3 | U5: 1999q4 | V5: 2000q1 | W5: 2000q2 | X5: 2000q3 | Y5: 2000q4 | Z5: 2001q1 | AA5: 2001q2 | AB5: 2001q3 | AC5: 2001q4 | AD5: 2002q1 | AE5: 2002q2 | AF5: 2002q3 | AG5: 2002q4 | AH5: 2003q1 | AI5: 2003q2 | AJ5: 2003q3 | AK5: 2003q4 | AL5: 2004q1 | AM5: 2004q2 | AN5: 2004q3 | AO5: 2004q4 | AP5: 2005q1 | AQ5: 2005q2 | AR5: 2005q3 | AS5: 2005q4 | AT5: 2006q1 | AU5: 2006q2 | AV5: 2006q3 | AW5: 2006q4 | AX5: 2007q1 | AY5: 2007q2 | AZ5: 2007q3 | BA5: 2007q4 | BB5: 2008q1 | BC5: 2008q2 | BD5: 2008q3 | BE5: 2008q4 | BF5: 2009q1 | BG5: 2009q2 | BH5: 2009q3 | BI5: 2009q4 | BJ5: 2010q1 | BK5: 2010q2 | BL5: 2010q3 | BM5: 2010q4 | BN5: 2011q1 | BO5: 2011q2 | BP5: 2011q3 | BQ5: 2011q4 | BR5: 2012q1 | BS5: 2012q2 | BT5: 2012q3 | BU5: 2012q4 | BV5: 2013q1 | BW5: 2013q2 | BX5: 2013q3 | BY5: 2013q4
A6: Primary Industries | B6: =SUM(B7:B8) -> 30258.8 | C6: =SUM(C7:C8) -> 32377.82 | D6: =SUM(D7:D8) -> 33293.89 | E6: =SUM(E7:E8) -> 31276.16 | F6: =SUM(F7:F8) -> 30465.08 | G6: =SUM(G7:G8) -> 37121.12 | H6: =SUM(H7:H8) -> 34049.1 | I6: =SUM(I7:I8) -> 31102.19 | ... BY6: =SUM(BY7:BY8) -> 32721.635
A7: Agriculture, forestry and fishing | B7: 5062.1 | C7: 7356.02 | D7: 7888 | E7: 6099 | F7: 5558.1 | G7: 12384.12 | H7: 8868.1 | I7: 5932.03 | J7: 6137.03 | K7: 12139 | L7: 8805 | M7: 5956 | N7: 5940 | O7: 11721.07 | P7: 8501 | Q7: 5124 | R7: 6517.96 | S7: 12954.96 | T7: 9061.22 | U7: 4691.67 | V7: 5537.12 | W7: 11101.1 | X7: 12376.1 | Y7: 5773.1 | Z7: 6153.1 | AA7: 12832.12 | AB7: 9836.12 | AC7: 4818.1 | AD7: 6730 | AE7: 14095 | AF7: 9261 | AG7: 5740 | AH7: 6181 | AI7: 15590 | AJ7: 9732 | AK7: 4567 | AL7: 6217 | AM7: 14145 | AN7: 10694 | AO7: 5324 | AP7: 7163.8 | AQ7: 13125.8 | AR7: 11715.8 | AS7: 5396.8 | AT7: 7085.25 | AU7: 11987.2 | AV7: 10591.3 | AW7: 5695.25 | AX7: 7315.25 | AY7: 12354.25 | AZ7: 10809.25 | BA7: 5822.25 | BB7: 8703.25 | BC7: 14401.25 | BD7: 12449.25 | BE7: 6589.39 | BF7: 8535.425 | BG7: 13896.321 | BH7: 12114.781 | BI7: 6907.613 | BJ7: 8686.153 | BK7: 14243.173 | BL7: 11909.646 | BM7: 6774.928 | BN7: 8524.77 | BO7: 14163.233 | BP7: 12022.434 | BQ7: 6876.413 | BR7: 8978.103 | BS7: 15041.18 | BT7: 11691.576 | BU7: 6722.582 | BV7: 9415 | BW7: 16059.28 | BX7: 11347 | BY7: 6592.86
A8: Mining and quarrying | B8: 25196.7 | C8: 25021.8 | D8: 25405.89 | E8: 25177.16 | F8: 24906.98 | G8: 24737 | H8: 25181 | I8: 25170.16 | J8: 24808.9 | K8: 25306 | L8: 25838 | M8: 25742.16 | N8: 25391.1 | O8: 25393.1 | P8: 25469 | Q8: 25340.16 | R8: 24818.9 | S8: 24945 | T8: 25190 | U8: 25217.16 | V8: 24545.02 | W8: 24844 | X8: 24830 | Y8: 24850.15 | Z8: 24393.95 | AA8: 24949 | AB8: 24964 | AC8: 24663.15 | AD8: 24272.1 | AE8: 24939.2 | AF8: 25304.2 | AG8: 25444.31 | AH8: 24976.66 | AI8: 25819 | AJ8: 26341 | AK8: 26218.16 | AL8: 26218.07 | AM8: 26148 | AN8: 26941 | AO8: 25608.19 | AP8: 27314.2 | AQ8: 26780.05 | AR8: 26435.75 | AS8: 25461.9 | AT8: 25829.3 | AU8: 26141.25 | AV8: 26338.25 | AW8: 27055.46 | AX8: 26386.46 | AY8: 26250 | AZ8: 26459 | BA8: 26240.22 | BB8: 24067.695 | BC8: 25313.695 | BD8: 24890.765 | BE8: 25123.695 | BF8: 22503.124 | BG8: 23592.386 | BH8: 23799.131 | BI8: 24162.719 | BJ8: 24643.346 | BK8: 23521.241 | BL8: 25355.421 | BM8: 25863.163 | BN8: 25030.861 | BO8: 25608.498 | BP8: 24409.997 | BQ8: 24637.864 | BR8: 22684.654 | BS8: 25284.901 | BT8: 24231.372 | BU8: 23881.392 | BV8: 23480.768 | BW8: 24586.21 | BX8: 24880.189 | BY8: 26128.775
A9: Secondary Industries | B9: =SUM(B10:B12) -> 59838.294 | C9: =SUM(C10:C12) -> 60951.914 | D9: =SUM(D10:D12) -> 64373.854 | E9: =SUM(E10:E12) -> 63132.141 | F9: =SUM(F10:F12) -> 61155.882 | G9: =SUM(G10:G12) -> 62054.545 | H9: =SUM(H10:H12) -> 65627.743 | I9: =SUM(I10:I12) -> 65520.633 | ... BY9: =SUM(BY10:BY12) -> 103470.04
A10: Manufacturing | B10: 47012.75 | C10: 47913.75 | D10: 51302.75 | E10: 50705 | F10: 48082.77 | G10: 48476.78 | H10: 51529 | I10: 51602.78 | J10: 48886 | K10: 50565 | L10: 53014 | M10: 52618 | N10: 49839.83 | O10: 50694 | P10: 52238 | Q10: 51901 | R10: 48787.87 | S10: 50065 | T10: 52918 | U10: 54130 | V10: 52235.84 | W10: 54092 | X10: 57401 | Y10: 58850 | Z10: 55589.68 | AA10: 56707.68 | AB10: 58319 | AC10: 59085 | AD10: 55853 | AE10: 57999 | AF10: 61089.4 | AG10: 61191.6 | AH10: 56905 | AI10: 57095 | AJ10: 59577 | AK10: 59004 | AL10: 57990 | AM10: 59585 | AN10: 63263 | AO10: 63127 | AP10: 60082.8 | AQ10: 63866.1 | AR10: 67716.1 | AS10: 67436 | AT10: 64270.2 | AU10: 67358.2 | AV10: 71460 | AW10: 72694 | AX10: 68753 | AY10: 71153 | AZ10: 74004 | BA10: 76336 | BB10: 70732.4 | BC10: 75966.4 | BD10: 77526.438 | BE10: 73663.33 | BF10: 63676.25 | BG10: 64777.98 | BH10: 69106.157 | BI10: 70162.182 | BJ10: 66216.616 | BK10: 70464.499 | BL10: 72845.894 | BM10: 72981.701 | BN10: 70096.904 | BO10: 71797.959 | BP10: 74585.281 | BQ10: 75304.996 | BR10: 70547.963 | BS10: 73218.038 | BT10: 76219.576 | BU10: 77822.734 | BV10: 70339.52 | BW10: 75088.639 | BX10: 75946.736 | BY10: 78675.531
A11: Electricity, gas and water | B11: 6403 | C11: 6528.26 | D11: 6634 | E11: 6278 | F11: 6526 | G11: 6953 | H11: 7530.6 | I11: 7624.73 | J11: 7238 | K11: 7506.07 | L11: 7602 | M11: 7405 | N11: 6851.4 | O11: 7016.75 | P11: 7067.6 | Q11: 6941 | R11: 6573.8 | S11: 6922.6 | T11: 7126.97 | U11: 7114 | V11: 6839.6 | W11: 7181.63 | X11: 7423 | Y11: 7153 | Z11: 6694 | AA11: 6876 | AB11: 7089.13 | AC11: 6880 | AD11: 6798 | AE11: 7124.4 | AF11: 7366.4 | AG11: 7214.2 | AH11: 7042 | AI11: 7319 | AJ11: 7563 | AK11: 7420 | AL11: 7468.4 | AM11: 7812.6 | AN11: 8128 | AO11: 7926 | AP11: 7862.2 | AQ11: 8221 | AR11: 8445 | AS11: 8482 | AT11: 8082.4 | AU11: 8492.4 | AV11: 8775.2 | AW11: 8789 | AX11: 8373.25 | AY11: 8739.25 | AZ11: 9126.25 | BA11: 9055.25 | BB11: 8136.5 | BC11: 8396.5 | BD11: 9045.5 | BE11: 8617.14 | BF11: 7969.214 | BG11: 8305.971 | BH11: 8754.956 | BI11: 8681.769 | BJ11: 8204.278 | BK11: 8525.336 | BL11: 8909.241 | BM11: 8899.296 | BN11: 8377.685 | BO11: 8714.789 | BP11: 9011.287 | BQ11: 8945.299 | BR11: 8339.539 | BS11: 8539.729 | BT11: 8874.6 | BU11: 8722.451 | BV11: 8112.638 | BW11: 8544.068 | BX11: 8954.6454 | BY11: 8721.504
A12: Construction | B12: 6422.544 | C12: 6509.904 | D12: 6437.104 | E12: 6149.141 | F12: 6547.112 | G12: 6624.765 | H12: 6568.143 | I12: 6293.123 | J12: 6674.916 | K12: 6715.36 | L12: 6636.09 | M12: 6903.022 | N12: 6480.615 | O12: 6318.006 | P12: 6142.888 | Q12: 6400.561 | R12: 6226.694 | S12: 6219.189 | T12: 6121.623 | U12: 6430.582 | V12: 6333.016 | W12: 6478.114 | X12: 6553.164 | Y12: 7045.996 | Z12: 6835.854 | AA12: 6892.142 | AB12: 6790.824 | AC12: 7192.345 | AD12: 7135 | AE12: 7142 | AF12: 7285 | AG12: 7759 | AH12: 7718 | AI12: 7719 | AJ12: 7860 | AK12: 8278 | AL12: 8203 | AM12: 8391 | AN12: 8709 | AO12: 9148 | AP12: 9169 | AQ12: 9427 | AR12: 9755 | AS12: 10207 | AT12: 10149 | AU12: 10403 | AV12: 10770 | AW12: 11260 | AX12: 11706 | AY12: 11835 | AZ12: 12111 | BA12: 13319 | BB12: 12860.1 | BC12: 13017.2 | BD12: 13344.08 | BE12: 13924 | BF12: 14024.88 | BG12: 14046.88 | BH12: 14299.88 | BI12: 14906.88 | BJ12: 14418 | BK12: 14261 | BL12: 14241 | BM12: 14786.9 | BN12: 14382.1 | BO12: 14314.1 | BP12: 14322.1 | BQ12: 14851.16 | BR12: 14567.1 | BS12: 14549.1 | BT12: 14708.1 | BU12: 15382.06 | BV12: 14865 | BW12: 14876 | BX12: 15065 | BY12: 16073
A13: Tertiary industries | B13: =SUM(B14:B18) -> 153604.77 | C13: =SUM(C14:C18) -> 155355.7 | D13: =SUM(D14:D18) -> 160579.76 | E13: =SUM(E14:E18) -> 166652.99 | F13: =SUM(F14:F18) -> 160373.11 | G13: =SUM(G14:G18) -> 162200.92 | H13: =SUM(H14:H18) -> 167002.95 | I13: =SUM(I14:I18) -> 173302.31 | ... BY13: =SUM(BY14:BY18) -> 321456.49
A14: Wholesale & retail trade; hotels & restaurants | B14: 30073.34 | C14: 30851 | D14: 32904 | E14: 37822 | F14: 31777.41 | G14: 32290 | H14: 33855 | I14: 38599 | J14: 32449.873 | K14: 32660.873 | L14: 33914.872 | M14: 38041.872 | N14: 32465.37 | O14: 33179 | P14: 34404 | Q14: 38801 | R14: 33899.92 | S14: 35209 | T14: 37235 | U14: 43058 | V14: 37121.14 | W14: 38512.14 | X14: 40140.2 | Y14: 45730 | Z14: 38628.26 | AA14: 39421.26 | AB14: 40506.26 | AC14: 46016.26 | AD14: 39112.8 | AE14: 40078.8 | AF14: 41609.8 | AG14: 47555.8 | AH14: 39758.1 | AI14: 40820.1 | AJ14: 43057 | AK14: 49210 | AL14: 41559 | AM14: 42792 | AN14: 44739 | AO14: 53085 | AP14: 44713.6 | AQ14: 45740.6 | AR14: 47897 | AS14: 56661 | AT14: 47122 | AU14: 48496 | AV14: 50913 | AW14: 60105 | AX14: 50059 | AY14: 51313 | AZ14: 53701 | BA14: 62534 | BB14: 52156.609 | BC14: 52318.119 | BD14: 53124.549 | BE14: 62149.863 | BF14: 51506.209 | BG14: 51223.484 | BH14: 53059.02 | BI14: 61285.207 | BJ14: 52037.182 | BK14: 53120.19 | BL14: 55521.891 | BM14: 64658.297 | BN14: 54224.274 | BO14: 55200.272 | BP14: 57967.38 | BQ14: 67902.624 | BR14: 56782.36 | BS14: 57493.337 | BT14: 59979.42 | BU14: 70023.023 | BV14: 58054.918 | BW14: 58890.277 | BX14: 61193.732 | BY14: 71467.867
A15: Transport , storage and communication | B15: 17874.6 | C15: 17916.65 | D15: 19388 | E15: 19790 | F15: 19268 | G15: 19181 | H15: 20490.38 | I15: 20603 | J15: 20408 | K15: 20599.6 | L15: 22022 | M15: 22558 | N15: 22050.8 | O15: 22140 | P15: 22920.12 | Q15: 23184 | R15: 22545 | S15: 23058.6 | T15: 24412.65 | U15: 24974 | V15: 24539 | W15: 25166.6 | X15: 26411.84 | Y15: 26757 | Z15: 25921.04 | AA15: 26414 | AB15: 27868 | AC15: 28741 | AD15: 28219 | AE15: 28976.6 | AF15: 30425.6 | AG15: 31127.8 | AH15: 30280 | AI15: 30872 | AJ15: 32080 | AK15: 33055 | AL15: 31536 | AM15: 32203 | AN15: 33963 | AO15: 34757 | AP15: 33324.9 | AQ15: 34034.9 | AR15: 35687 | AS15: 36425 | AT15: 34860 | AU15: 35709 | AV15: 37790 | AW15: 38248 | AX15: 37390 | AY15: 38228 | AZ15: 40002 | BA15: 40669 | BB15: 39017.254 | BC15: 39778.156 | BD15: 41545.39 | BE15: 42181.239 | BF15: 39881.66 | BG15: 40081.723 | BH15: 41692.247 | BI15: 42343.81 | BJ15: 40141.228 | BK15: 40893.445 | BL15: 42756.827 | BM15: 43521.92 | BN15: 41353.794 | BO15: 42233.84 | BP15: 44032.83 | BQ15: 44909.656 | BR15: 42585.497 | BS15: 43356.485 | BT15: 44995.333 | BU15: 45762.145 | BV15: 43369.448 | BW15: 44124.117 | BX15: 45926.782 | BY15: 46688.112
A16: Finance, real estate and business services | B16: 42556.1 | C16: 42973 | D16: 44240.3 | E16: 44950.6 | F16: 44425 | G16: 45833.1 | H16: 47500.3 | I16: 48817 | J16: 48114.8 | K16: 48886.8 | L16: 49171.8 | M16: 49182.4 | N16: 48536.6 | O16: 49922.3 | P16: 50635.3 | Q16: 50758.8 | R16: 51054.2 | S16: 52293 | T16: 53176.6 | U16: 53542.8 | V16: 52888.1 | W16: 53699.6 | X16: 54622 | Y16: 55537.5 | Z16: 56218.6 | AA16: 58088.5 | AB16: 59463.3 | AC16: 60679.7 | AD16: 62383 | AE16: 62225 | AF16: 61925 | AG16: 62632 | AH16: 65193 | AI16: 64824 | AJ16: 65121 | AK16: 65985 | AL16: 69261 | AM16: 69354 | AN16: 69721 | AO16: 71208 | AP16: 73169.1 | AQ16: 73288 | AR16: 73956 | AS16: 75091 | AT16: 79305 | AU16: 80254 | AV16: 81374 | AW16: 83069 | AX16: 86091 | AY16: 85714 | AZ16: 87185 | BA16: 90511 | BB16: 91562 | BC16: 92840 | BD16: 94186 | BE16: 96653 | BF16: 94300.9 | BG16: 94221.91 | BH16: 94319 | BI16: 96145 | BJ16: 95658.6 | BK16: 96321.06 | BL16: 96651 | BM16: 98558 | BN16: 99559.1 | BO16: 100356.1 | BP16: 101565.02 | BQ16: 103999 | BR16: 105061.1 | BS16: 104615.1 | BT16: 104333.1 | BU16: 106464.07 | BV16: 106799 | BW16: 108365 | BX16: 107820 | BY16: 107613
A17: Personal services | B17: 15489.027 | C17: 15927.348 | D17: 16210.662 | E17: 16192.586 | F17: 16382.948 | G17: 16318.07 | H17: 16403.519 | I17: 16411.555 | J17: 16232.787 | K17: 16416.974 | L17: 16551.23 | M17: 16293.67 | N17: 16752.634 | O17: 17240.631 | P17: 17763.096 | Q17: 17806.318 | R17: 17715.541 | S17: 17942.23 | T17: 18331.776 | U17: 18264.605 | V17: 18400 | W17: 18733 | X17: 19313.1 | Y17: 19289.287 | Z17: 19142.092 | AA17: 19234.897 | AB17: 19611.719 | AC17: 19449.408 | AD17: 19376.69 | AE17: 19614.329 | AF17: 20157.27 | AG17: 20197.711 | AH17: 20362 | AI17: 20836 | AJ17: 21469 | AK17: 21089 | AL17: 20771.6 | AM17: 21194.4 | AN17: 21649 | AO17: 21604 | AP17: 21793.2 | AQ17: 22005.2 | AR17: 22373.2 | AS17: 22283.1 | AT17: 23051 | AU17: 23178 | AV17: 23381 | AW17: 23463 | AX17: 24555 | AY17: 24843 | AZ17: 24839 | BA17: 24010 | BB17: 25606.5 | BC17: 26011.6 | BD17: 25841.6 | BE17: 24646.15 | BF17: 25224.428 | BG17: 25428.403 | BH17: 25450.317 | BI17: 25129.962 | BJ17: 25128.698 | BK17: 25503.328 | BL17: 25636.247 | BM17: 25402.577 | BN17: 26010.337 | BO17: 26168.561 | BP17: 26052.007 | BQ17: 25794.825 | BR17: 26428.081 | BS17: 26953.854 | BT17: 26792.118 | BU17: 26006.808 | BV17: 26937.594 | BW17: 27350.109 | BX17: 27264.835 | BY17: 26492.509
A18: General government services | B18: 47611.7 | C18: 47687.7 | D18: 47836.8 | E18: 47897.8 | F18: 48519.75 | G18: 48578.75 | H18: 48753.75 | I18: 48871.75 | J18: 48945 | K18: 48962 | L18: 49141 | M18: 49212 | N18: 48654.7 | O18: 48704.7 | P18: 48697.8 | Q18: 48733.8 | R18: 48267 | S18: 48347 | T18: 48320 | U18: 48195 | V18: 47824.25 | W18: 47893.3 | X18: 47873.3 | Y18: 47749.15 | Z18: 47533.75 | AA18: 47470.75 | AB18: 47303.75 | AC18: 47243.75 | AD18: 47144 | AE18: 47698 | AF18: 47955 | AG18: 48113 | AH18: 48264 | AI18: 48972 | AJ18: 49331 | AK18: 49626 | AL18: 49094 | AM18: 49848 | AN18: 50171 | AO18: 50834 | AP18: 51032 | AQ18: 52145 | AR18: 52604.9 | AS18: 52778.9 | AT18: 52881 | AU18: 53540 | AV18: 53892 | AW18: 54634 | AX18: 55106 | AY18: 55460 | AZ18: 56041 | BA18: 56677 | BB18: 57252 | BC18: 57900 | BD18: 58795 | BE18: 59469 | BF18: 59561 | BG18: 60608 | BH18: 60958 | BI18: 61415 | BJ18: 61217 | BK18: 62339 | BL18: 62802 | BM18: 63656 | BN18: 63511 | BO18: 64925 | BP18: 65495 | BQ18: 66563 | BR18: 65452 | BS18: 66643 | BT18: 67250 | BU18: 68369 | BV18: 66904 | BW18: 67806 | BX18: 67939 | BY18: 69195
A19: All industries at basic prices | B19: =B13+B9+B6 -> 243701.86 | C19: =C13+C9+C6 -> 248685.43 | D19: =D13+D9+D6 -> 258247.51 | E19: =E13+E9+E6 -> 261061.29 | F19: =F13+F9+F6 -> 251994.07 | G19: =G13+G9+G6 -> 261376.58 | H19: =H13+H9+H6 -> 266679.79 | I19: =I13+I9+I6 -> 269925.13 | ... BY19: =BY13+BY9+BY6 -> 457648.16
A20: Taxes less subsidies on products | B20: 33235.871 | C20: 33241.522 | D20: 33531.924 | E20: 33667.398 | F20: 34509.038 | G20: 34878.722 | H20: 35196.079 | I20: 35625.014 | J20: 35904.12 | K20: 36008.799 | L20: 36166.786 | M20: 36225.119 | N20: 35451.63 | O20: 35103.333 | P20: 35807.525 | Q20: 36298.649 | R20: 34779.415 | S20: 34720.163 | T20: 35829.062 | U20: 36561.295 | V20: 35228.343 | W20: 35286.01 | X20: 36444.759 | Y20: 37170.049 | Z20: 35800.585 | AA20: 35833.764 | AB20: 36888.876 | AC20: 37677.956 | AD20: 36282 | AE20: 37312 | AF20: 38018 | AG20: 38553 | AH20: 37315 | AI20: 38479 | AJ20: 38792 | AK20: 39607 | AL20: 38569 | AM20: 40241 | AN20: 41066 | AO20: 42064 | AP20: 40702 | AQ20: 42368 | AR20: 43136 | AS20: 43809 | AT20: 42815 | AU20: 44740 | AV20: 45411 | AW20: 47664 | AX20: 46050 | AY20: 47125 | AZ20: 47919 | BA20: 48995 | BB20: 47583 | BC20: 48943 | BD20: 48901 | BE20: 49365 | BF20: 46615 | BG20: 46591 | BH20: 46949 | BI20: 48684 | BJ20: 47586 | BK20: 48541 | BL20: 49189 | BM20: 50417 | BN20: 49792 | BO20: 50892 | BP20: 51570 | BQ20: 53288 | BR20: 51858 | BS20: 52599 | BT20: 52442 | BU20: 54192 | BV20: 52616 | BW20: 53795 | BX20: 53437 | BY20: 55631
A21: SA - GDP at constant 2005 prices | B21: =B19+B20 -> 276937.73 | C21: =C19+C20 -> 281926.95 | D21: =D19+D20 -> 291779.43 | E21: =E19+E20 -> 294728.69 | F21: =F19+F20 -> 286503.11 | G21: =G19+G20 -> 296255.31 | H21: =H19+H20 -> 301875.87 | I21: =I19+I20 -> 305550.14 | ... BY21: =BY19+BY20 -> 513279.16
A23: KZN – GDPR by activity
A24: Constant 2005 prices - Rand million
A25: Provincial Industry | B25: =B5 -> 1995q1 | C25: =C5 -> 1995q2 | D25: =D5 -> 1995q3 | E25: =E5 -> 1995q4 | F25: =F5 -> 1996q1 | G25: =G5 -> 1996q2 | H25: =H5 -> 1996q3 | I25: =I5 -> 1996q4 | ... BY25: =BY5 -> 2013q4
A26: Primary Industries | B26: =SUM(B27:B28) -> 2681.1665 | C26: =SUM(C27:C28) -> 3389.6847 | D26: =SUM(D27:D28) -> 3572.5483 | E26: =SUM(E27:E28) -> 3004.0318 | F26: =SUM(F27:F28) -> 3155.8356 | G26: =SUM(G27:G28) -> 5144.7249 | H26: =SUM(H27:H28) -> 4142.132 | I26: =SUM(I27:I28) -> 3281.5028 | ... BY26: =SUM(BY27:BY28) -> 2901.5088
A27: Agriculture, forestry and fishing | B27: =B7*Annual!$B46/100 -> 1580.3818 | C27: =C7*Annual!$B46/100 -> 2296.541 | D27: =D7*Annual!$B46/100 -> 2462.6245 | E27: =E7*Annual!$B46/100 -> 1904.1008 | F27: =F7*Annual!$C46/100 -> 1627.9474 | G27: =G7*Annual!$C46/100 -> 3627.2639 | H27: =H7*Annual!$C46/100 -> 2597.4344 | I27: =I7*Annual!$C46/100 -> 1737.4701 | J27: =J7*Annual!$D46/100 -> 1775.1071 | K27: =K7*Annual!$D46/100 -> 3511.1488 | L27: =L7*Annual!$D46/100 -> 2546.8049 | M27: =M7*Annual!$D46/100 -> 1722.7451 | N27: =N7*Annual!$E46/100 -> 1830.7254 | O27: =O7*Annual!$E46/100 -> 3612.4681 | P27: =P7*Annual!$E46/100 -> 2620.0331 | Q27: =Q7*Annual!$E46/100 -> 1579.2318 | R27: =R7*Annual!$F46/100 -> 1841.8316 | S27: =S7*Annual!$F46/100 -> 3660.7857 | T27: =T7*Annual!$F46/100 -> 2560.5007 | U27: =U7*Annual!$F46/100 -> 1325.7624 | V27: =V7*Annual!$G46/100 -> 1550.5324 | W27: =W7*Annual!$G46/100 -> 3108.5863 | X27: =X7*Annual!$G46/100 -> 3465.6182 | Y27: =Y7*Annual!$G46/100 -> 1616.6127 | Z27: =Z7*Annual!H46/100 -> 1775.4954 | AA27: =AA7*Annual!H46/100 -> 3702.7466 | AB27: =AB7*Annual!H46/100 -> 2838.2418 | AC27: =AC7*Annual!H46/100 -> 1390.2772 | AD27: =AD7*Annual!$I46/100 -> 1908.2936 | AE27: =AE7*Annual!$I46/100 -> 3996.6417 | AF27: =AF7*Annual!$I46/100 -> 2625.9595 | AG27: =AG7*Annual!$I46/100 -> 1627.5788 | AH27: =AH7*Annual!$J46/100 -> 1830.9586 | AI27: =AI7*Annual!$J46/100 -> 4618.1273 | AJ27: =AJ7*Annual!$J46/100 -> 2882.8489 | AK27: =AK7*Annual!$J46/100 -> 1352.8536 | AL27: =AL7*Annual!$K46/100 -> 1831.4345 | AM27: =AM7*Annual!$K46/100 -> 4166.9038 | AN27: =AN7*Annual!$K46/100 -> 3150.2912 | AO27: =AO7*Annual!$K46/100 -> 1568.3701 | AP27: =AP7*Annual!$L46/100 -> 1932.8652 | AQ27: =AQ7*Annual!$L46/100 -> 3541.4728 | AR27: =AR7*Annual!$L46/100 -> 3161.0406 | AS27: =AS7*Annual!$L46/100 -> 1456.1109 | AT27: =AT7*Annual!$M46/100 -> 2032.844 | AU27: =AU7*Annual!$M46/100 -> 3439.2728 | AV27: =AV7*Annual!$M46/100 -> 3038.7722 | AW27: =AW7*Annual!$M46/100 -> 1634.0362 | AX27: =AX7*Annual!$N46/100 -> 2127.9041 | AY27: =AY7*Annual!$N46/100 -> 3593.6789 | AZ27: =AZ7*Annual!$N46/100 -> 3144.2599 | BA27: =BA7*Annual!$N46/100 -> 1693.6112 | BB27: =BB7*Annual!$O46/100 -> 2497.823 | BC27: =BC7*Annual!$O46/100 -> 4133.1426 | BD27: =BD7*Annual!$O46/100 -> 3572.9208 | BE27: =BE7*Annual!$O46/100 -> 1891.1475 | BF27: =BF7*Annual!P46/100 -> 2418.6498 | BG27: =BG7*Annual!P46/100 -> 3937.7459 | BH27: =BH7*Annual!P46/100 -> 3432.9179 | BI27: =BI7*Annual!P46/100 -> 1957.3832 | BJ27: =BJ7*Annual!Q46/100 -> 2509.6815 | BK27: =BK7*Annual!Q46/100 -> 4115.2657 | BL27: =BL7*Annual!Q46/100 -> 3441.0421 | BM27: =BM7*Annual!Q46/100 -> 1957.4732 | BN27: =BN7*Annual!$R46/100 -> 2490.3539 | BO27: =BO7*Annual!$R46/100 -> 4137.5265 | BP27: =BP7*Annual!$R46/100 -> 3512.1317 | BQ27: =BQ7*Annual!$R46/100 -> 2008.8169 | BR27: =BR7*Annual!$S46/100 -> 2635.2931 | BS27: =BS7*Annual!$S46/100 -> 4414.9547 | BT27: =BT7*Annual!$S46/100 -> 3431.7639 | BU27: =BU7*Annual!$S46/100 -> 1973.2425 | BV27: =BV7*Annual!$T46/100 -> 2793.6847 | BW27: =BW7*Annual!$T46/100 -> 4765.2219 | BX27: =BX7*Annual!$T46/100 -> 3366.9612 | BY27: =BY7*Annual!$U46/100 -> 1956.2796
A28: Mining and quarrying | B28: =B8*Annual!$B47/100 -> 1100.7847 | C28: =C8*Annual!$B47/100 -> 1093.1437 | D28: =D8*Annual!$B47/100 -> 1109.9237 | E28: =E8*Annual!$B47/100 -> 1099.931 | F28: =F8*Annual!$C47/100 -> 1527.8882 | G28: =G8*Annual!$C47/100 -> 1517.461 | H28: =H8*Annual!$C47/100 -> 1544.6976 | I28: =I8*Annual!$C47/100 -> 1544.0327 | J28: =J8*Annual!$D47/100 -> 1512.9634 | K28: =K8*Annual!$D47/100 -> 1543.2789 | L28: =L8*Annual!$D47/100 -> 1575.7227 | M28: =M8*Annual!$D47/100 -> 1569.8779 | N28: =N8*Annual!$E47/100 -> 1529.0743 | O28: =O8*Annual!$E47/100 -> 1529.1948 | P28: =P8*Annual!$E47/100 -> 1533.7655 | Q28: =Q8*Annual!$E47/100 -> 1526.0067 | R28: =R8*Annual!$F47/100 -> 1098.3079 | S28: =S8*Annual!$F47/100 -> 1103.8882 | T28: =T8*Annual!$F47/100 -> 1114.7302 | U28: =U8*Annual!$F47/100 -> 1115.9321 | V28: =V8*Annual!$G47/100 -> 1069.935 | W28: =W8*Annual!$G47/100 -> 1082.9678 | X28: =X8*Annual!$G47/100 -> 1082.3575 | Y28: =Y8*Annual!$G47/100 -> 1083.2358 | Z28: =Z8*Annual!H47/100 -> 1010.0123 | AA28: =AA8*Annual!H47/100 -> 1032.9937 | AB28: =AB8*Annual!H47/100 -> 1033.6148 | AC28: =AC8*Annual!H47/100 -> 1021.1583 | AD28: =AD8*Annual!$I47/100 -> 888.90625 | AE28: =AE8*Annual!$I47/100 -> 913.33716 | AF28: =AF8*Annual!$I47/100 -> 926.70439 | AG28: =AG8*Annual!$I47/100 -> 931.83557 | AH28: =AH8*Annual!$J47/100 -> 936.60937 | AI28: =AI8*Annual!$J47/100 -> 968.19661 | AJ28: =AJ8*Annual!$J47/100 -> 987.77128 | AK28: =AK8*Annual!$J47/100 -> 983.16486 | AL28: =AL8*Annual!$K47/100 -> 987.93811 | AM28: =AM8*Annual!$K47/100 -> 985.29776 | AN28: =AN8*Annual!$K47/100 -> 1015.1792 | AO28: =AO8*Annual!$K47/100 -> 964.95687 | AP28: =AP8*Annual!$L47/100 -> 955.03676 | AQ28: =AQ8*Annual!$L47/100 -> 936.36028 | AR28: =AR8*Annual!$L47/100 -> 924.32189 | AS28: =AS8*Annual!$L47/100 -> 890.27137 | AT28: =AT8*Annual!$M47/100 -> 878.13335 | AU28: =AU8*Annual!$M47/100 -> 888.73889 | AV28: =AV8*Annual!$M47/100 -> 895.43641 | AW28: =AW8*Annual!$M47/100 -> 919.8198 | AX28: =AX8*Annual!$N47/100 -> 919.68298 | AY28: =AY8*Annual!$N47/100 -> 914.92676 | AZ28: =AZ8*Annual!$N47/100 -> 922.21132 | BA28: =BA8*Annual!$N47/100 -> 914.58588 | BB28: =BB8*Annual!$O47/100 -> 830.88649 | BC28: =BC8*Annual!$O47/100 -> 873.90201 | BD28: =BD8*Annual!$O47/100 -> 859.30125 | BE28: =BE8*Annual!$O47/100 -> 867.34266 | BF28: =BF8*Annual!P47/100 -> 768.46209 | BG28: =BG8*Annual!P47/100 -> 805.65944 | BH28: =BH8*Annual!P47/100 -> 812.7196 | BI28: =BI8*Annual!P47/100 -> 825.13581 | BJ28: =BJ8*Annual!Q47/100 -> 871.46912 | BK28: =BK8*Annual!Q47/100 -> 831.78782 | BL28: =BL8*Annual!Q47/100 -> 896.65041 | BM28: =BM8*Annual!Q47/100 -> 914.60583 | BN28: =BN8*Annual!$R47/100 -> 870.28342 | BO28: =BO8*Annual!$R47/100 -> 890.36694 | BP28: =BP8*Annual!$R47/100 -> 848.69696 | BQ28: =BQ8*Annual!$R47/100 -> 856.61953 | BR28: =BR8*Annual!$S47/100 -> 834.12929 | BS28: =BS8*Annual!$S47/100 -> 929.74204 | BT28: =BT8*Annual!$S47/100 -> 891.00311 | BU28: =BU8*Annual!$S47/100 -> 878.13412 | BV28: =BV8*Annual!$T47/100 -> 849.43549 | BW28: =BW8*Annual!$T47/100 -> 889.42573 | BX28: =BX8*Annual!$T47/100 -> 900.06066 | BY28: =BY8*Annual!$U47/100 -> 945.22923
A29: Secondary Industries | B29: =SUM(B30:B32) -> 12108.14 | C29: =SUM(C30:C32) -> 12334.197 | D29: =SUM(D30:D32) -> 13048.586 | E29: =SUM(E30:E32) -> 12809.694 | F29: =SUM(F30:F32) -> 12369.88 | G29: =SUM(G30:G32) -> 12540.544 | H29: =SUM(H30:H32) -> 13272.273 | I29: =SUM(I30:I32) -> 13256.436 | ... BY29: =SUM(BY30:BY32) -> 20530.824
A30: Manufacturing | B30: =B10*Annual!$B49/100 -> 9836.9662 | C30: =C10*Annual!$B49/100 -> 10025.492 | D30: =D10*Annual!$B49/100 -> 10734.607 | E30: =E10*Annual!$B49/100 -> 10609.534 | F30: =F10*Annual!$C49/100 -> 10095.385 | G30: =G10*Annual!$C49/100 -> 10178.11 | H30: =H10*Annual!$C49/100 -> 10818.95 | I30: =I10*Annual!$C49/100 -> 10834.441 | J30: =J10*Annual!$D49/100 -> 10259.131 | K30: =K10*Annual!$D49/100 -> 10611.483 | L30: =L10*Annual!$D49/100 -> 11125.425 | M30: =M10*Annual!$D49/100 -> 11042.322 | N30: =N10*Annual!$E49/100 -> 10433.082 | O30: =O10*Annual!$E49/100 -> 10611.887 | P30: =P10*Annual!$E49/100 -> 10935.096 | Q30: =Q10*Annual!$E49/100 -> 10864.551 | R30: =R10*Annual!$F49/100 -> 10314.719 | S30: =S10*Annual!$F49/100 -> 10584.729 | T30: =T10*Annual!$F49/100 -> 11187.91 | U30: =U10*Annual!$F49/100 -> 11444.151 | V30: =V10*Annual!$G49/100 -> 11093.742 | W30: =W10*Annual!$G49/100 -> 11487.949 | X30: =X10*Annual!$G49/100 -> 12190.708 | Y30: =Y10*Annual!$G49/100 -> 12498.444 | Z30: =Z10*Annual!H49/100 -> 11780.413 | AA30: =AA10*Annual!H49/100 -> 12017.336 | AB30: =AB10*Annual!H49/100 -> 12358.803 | AC30: =AC10*Annual!H49/100 -> 12521.131 | AD30: =AD10*Annual!$I49/100 -> 11817.287 | AE30: =AE10*Annual!$I49/100 -> 12271.334 | AF30: =AF10*Annual!$I49/100 -> 12925.195 | AG30: =AG10*Annual!$I49/100 -> 12946.819 | AH30: =AH10*Annual!$J49/100 -> 12111.765 | AI30: =AI10*Annual!$J49/100 -> 12152.205 | AJ30: =AJ10*Annual!$J49/100 -> 12680.478 | AK30: =AK10*Annual!$J49/100 -> 12558.52 | AL30: =AL10*Annual!$K49/100 -> 12319.816 | AM30: =AM10*Annual!$K49/100 -> 12658.67 | AN30: =AN10*Annual!$K49/100 -> 13440.051 | AO30: =AO10*Annual!$K49/100 -> 13411.158 | AP30: =AP10*Annual!$L49/100 -> 12760.174 | AQ30: =AQ10*Annual!$L49/100 -> 13563.658 | AR30: =AR10*Annual!$L49/100 -> 14381.307 | AS30: =AS10*Annual!$L49/100 -> 14321.821 | AT30: =AT10*Annual!$M49/100 -> 13597.925 | AU30: =AU10*Annual!$M49/100 -> 14251.267 | AV30: =AV10*Annual!$M49/100 -> 15119.103 | AW30: =AW10*Annual!$M49/100 -> 15380.185 | AX30: =AX10*Annual!$N49/100 -> 14553.98 | AY30: =AY10*Annual!$N49/100 -> 15062.024 | AZ30: =AZ10*Annual!$N49/100 -> 15665.538 | BA30: =BA10*Annual!$N49/100 -> 16159.188 | BB30: =BB10*Annual!$O49/100 -> 14962.263 | BC30: =BC10*Annual!$O49/100 -> 16069.428 | BD30: =BD10*Annual!$O49/100 -> 16399.428 | BE30: =BE10*Annual!$O49/100 -> 15582.252 | BF30: =BF10*Annual!P49/100 -> 13495.469 | BG30: =BG10*Annual!P49/100 -> 13728.968 | BH30: =BH10*Annual!P49/100 -> 14646.277 | BI30: =BI10*Annual!P49/100 -> 14870.089 | BJ30: =BJ10*Annual!Q49/100 -> 14108.457 | BK30: =BK10*Annual!Q49/100 -> 15013.533 | BL30: =BL10*Annual!Q49/100 -> 15520.926 | BM30: =BM10*Annual!Q49/100 -> 15549.861 | BN30: =BN10*Annual!$R49/100 -> 14934.23 | BO30: =BO10*Annual!$R49/100 -> 15296.642 | BP30: =BP10*Annual!$R49/100 -> 15890.484 | BQ30: =BQ10*Annual!$R49/100 -> 16043.82 | BR30: =BR10*Annual!$S49/100 -> 15039.169 | BS30: =BS10*Annual!$S49/100 -> 15608.366 | BT30: =BT10*Annual!$S49/100 -> 16248.223 | BU30: =BU10*Annual!$S49/100 -> 16589.979 | BV30: =BV10*Annual!$T49/100 -> 14993.749 | BW30: =BW10*Annual!$T49/100 -> 16006.083 | BX30: =BX10*Annual!$T49/100 -> 16188.997 | BY30: =BY10*Annual!$U49/100 -> 16770.674
A31: Electricity, gas and water | B31: =B11*Annual!$B50/100 -> 1113.765 | C31: =C11*Annual!$B50/100 -> 1135.5533 | D31: =D11*Annual!$B50/100 -> 1153.9461 | E31: =E11*Annual!$B50/100 -> 1092.022 | F31: =F11*Annual!$C50/100 -> 1137.9679 | G31: =G11*Annual!$C50/100 -> 1212.4258 | H31: =H11*Annual!$C50/100 -> 1313.1445 | I31: =I11*Annual!$C50/100 -> 1329.5584 | J31: =J11*Annual!$D50/100 -> 1256.5731 | K31: =K11*Annual!$D50/100 -> 1303.1121 | L31: =L11*Annual!$D50/100 -> 1319.7663 | M31: =M11*Annual!$D50/100 -> 1285.5656 | N31: =N11*Annual!$E50/100 -> 1191.8484 | O31: =O11*Annual!$E50/100 -> 1220.6122 | P31: =P11*Annual!$E50/100 -> 1229.4579 | Q31: =Q11*Annual!$E50/100 -> 1207.435 | R31: =R11*Annual!$F50/100 -> 1149.9796 | S31: =S11*Annual!$F50/100 -> 1210.9965 | T31: =T11*Annual!$F50/100 -> 1246.7477 | U31: =U11*Annual!$F50/100 -> 1244.4788 | V31: =V11*Annual!$G50/100 -> 1228.5953 | W31: =W11*Annual!$G50/100 -> 1290.0341 | X31: =X11*Annual!$G50/100 -> 1333.3913 | Y31: =Y11*Annual!$G50/100 -> 1284.8913 | Z31: =Z11*Annual!H50/100 -> 1246.6998 | AA31: =AA11*Annual!H50/100 -> 1280.5957 | AB31: =AB11*Annual!H50/100 -> 1320.2894 | AC31: =AC11*Annual!H50/100 -> 1281.3407 | AD31: =AD11*Annual!$I50/100 -> 1341.957 | AE31: =AE11*Annual!$I50/100 -> 1406.3899 | AF31: =AF11*Annual!$I50/100 -> 1454.1618 | AG31: =AG11*Annual!$I50/100 -> 1424.1168 | AH31: =AH11*Annual!$J50/100 -> 1194.8662 | AI31: =AI11*Annual!$J50/100 -> 1241.8668 | AJ31: =AJ11*Annual!$J50/100 -> 1283.268 | AK31: =AK11*Annual!$J50/100 -> 1259.0042 | AL31: =AL11*Annual!$K50/100 -> 1273.5463 | AM31: =AM11*Annual!$K50/100 -> 1332.2409 | AN31: =AN11*Annual!$K50/100 -> 1386.0244 | AO31: =AO11*Annual!$K50/100 -> 1351.5784 | AP31: =AP11*Annual!$L50/100 -> 1355.5239 | AQ31: =AQ11*Annual!$L50/100 -> 1417.3847 | AR31: =AR11*Annual!$L50/100 -> 1456.0046 | AS31: =AS11*Annual!$L50/100 -> 1462.3838 | AT31: =AT11*Annual!$M50/100 -> 1391.9024 | AU31: =AU11*Annual!$M50/100 -> 1462.5101 | AV31: =AV11*Annual!$M50/100 -> 1511.2123 | AW31: =AW11*Annual!$M50/100 -> 1513.5888 | AX31: =AX11*Annual!$N50/100 -> 1441.2956 | AY31: =AY11*Annual!$N50/100 -> 1504.2956 | AZ31: =AZ11*Annual!$N50/100 -> 1570.9103 | BA31: =BA11*Annual!$N50/100 -> 1558.689 | BB31: =BB11*Annual!$O50/100 -> 1387.3617 | BC31: =BC11*Annual!$O50/100 -> 1431.6945 | BD31: =BD11*Annual!$O50/100 -> 1542.356 | BE31: =BE11*Annual!$O50/100 -> 1469.316 | BF31: =BF11*Annual!P50/100 -> 1324.3397 | BG31: =BG11*Annual!P50/100 -> 1380.3027 | BH31: =BH11*Annual!P50/100 -> 1454.9159 | BI31: =BI11*Annual!P50/100 -> 1442.7535 | BJ31: =BJ11*Annual!Q50/100 -> 1346.6391 | BK31: =BK11*Annual!Q50/100 -> 1399.3372 | BL31: =BL11*Annual!Q50/100 -> 1462.3508 | BM31: =BM11*Annual!Q50/100 -> 1460.7185 | BN31: =BN11*Annual!$R50/100 -> 1371.2526 | BO31: =BO11*Annual!$R50/100 -> 1426.4295 | BP31: =BP11*Annual!$R50/100 -> 1474.9601 | BQ31: =BQ11*Annual!$R50/100 -> 1464.1592 | BR31: =BR11*Annual!$S50/100 -> 1341.8475 | BS31: =BS11*Annual!$S50/100 -> 1374.0584 | BT31: =BT11*Annual!$S50/100 -> 1427.9398 | BU31: =BU11*Annual!$S50/100 -> 1403.4587 | BV31: =BV11*Annual!$T50/100 -> 1301.6111 | BW31: =BW11*Annual!$T50/100 -> 1370.8308 | BX31: =BX11*Annual!$T50/100 -> 1436.7048 | BY31: =BY11*Annual!$U50/100 -> 1399.2991
A32: Construction | B32: =B12*Annual!$B51/100 -> 1157.4083 | C32: =C12*Annual!$B51/100 -> 1173.1515 | D32: =D12*Annual!$B51/100 -> 1160.0322 | E32: =E12*Annual!$B51/100 -> 1108.1383 | F32: =F12*Annual!$C51/100 -> 1136.5275 | G32: =G12*Annual!$C51/100 -> 1150.0075 | H32: =H12*Annual!$C51/100 -> 1140.1783 | I32: =I12*Annual!$C51/100 -> 1092.437 | J32: =J12*Annual!$D51/100 -> 1184.2119 | K32: =K12*Annual!$D51/100 -> 1191.3871 | L32: =L12*Annual!$D51/100 -> 1177.3237 | M32: =M12*Annual!$D51/100 -> 1224.6807 | N32: =N12*Annual!$E51/100 -> 1084.2534 | O32: =O12*Annual!$E51/100 -> 1057.0478 | P32: =P12*Annual!$E51/100 -> 1027.7493 | Q32: =Q12*Annual!$E51/100 -> 1070.8598 | R32: =R12*Annual!$F51/100 -> 995.9433 | S32: =S12*Annual!$F51/100 -> 994.74289 | T32: =T12*Annual!$F51/100 -> 979.13747 | U32: =U12*Annual!$F51/100 -> 1028.5546 | V32: =V12*Annual!$G51/100 -> 996.57132 | W32: =W12*Annual!$G51/100 -> 1019.4041 | X32: =X12*Annual!$G51/100 -> 1031.2141 | Y32: =Y12*Annual!$G51/100 -> 1108.7667 | Z32: =Z12*Annual!H51/100 -> 1374.8833 | AA32: =AA12*Annual!H51/100 -> 1386.2044 | AB32: =AB12*Annual!H51/100 -> 1365.8265 | AC32: =AC12*Annual!H51/100 -> 1446.5837 | AD32: =AD12*Annual!$I51/100 -> 1071.3516 | AE32: =AE12*Annual!$I51/100 -> 1072.4026 | AF32: =AF12*Annual!$I51/100 -> 1093.8747 | AG32: =AG12*Annual!$I51/100 -> 1165.0479 | AH32: =AH12*Annual!$J51/100 -> 1127.2784 | AI32: =AI12*Annual!$J51/100 -> 1127.4245 | AJ32: =AJ12*Annual!$J51/100 -> 1148.0187 | AK32: =AK12*Annual!$J51/100 -> 1209.0711 | AL32: =AL12*Annual!$K51/100 -> 1201.1586 | AM32: =AM12*Annual!$K51/100 -> 1228.6873 | AN32: =AN12*Annual!$K51/100 -> 1275.2518 | AO32: =AO12*Annual!$K51/100 -> 1339.5342 | AP32: =AP12*Annual!$L51/100 -> 1362.2351 | AQ32: =AQ12*Annual!$L51/100 -> 1400.566 | AR32: =AR12*Annual!$L51/100 -> 1449.2969 | AS32: =AS12*Annual!$L51/100 -> 1516.4504 | AT32: =AT12*Annual!$M51/100 -> 1469.0794 | AU32: =AU12*Annual!$M51/100 -> 1505.8462 | AV32: =AV12*Annual!$M51/100 -> 1558.9699 | AW32: =AW12*Annual!$M51/100 -> 1629.898 | AX32: =AX12*Annual!$N51/100 -> 1685.922 | AY32: =AY12*Annual!$N51/100 -> 1704.5008 | AZ32: =AZ12*Annual!$N51/100 -> 1744.2509 | BA32: =BA12*Annual!$N51/100 -> 1918.2295 | BB32: =BB12*Annual!$O51/100 -> 1852.6748 | BC32: =BC12*Annual!$O51/100 -> 1875.3072 | BD32: =BD12*Annual!$O51/100 -> 1922.3988 | BE32: =BE12*Annual!$O51/100 -> 2005.9442 | BF32: =BF12*Annual!P51/100 -> 2032.0266 | BG32: =BG12*Annual!P51/100 -> 2035.2142 | BH32: =BH12*Annual!P51/100 -> 2071.8706 | BI32: =BI12*Annual!P51/100 -> 2159.8172 | BJ32: =BJ12*Annual!Q51/100 -> 2107.6739 | BK32: =BK12*Annual!Q51/100 -> 2084.7231 | BL32: =BL12*Annual!Q51/100 -> 2081.7994 | BM32: =BM12*Annual!Q51/100 -> 2161.601 | BN32: =BN12*Annual!$R51/100 -> 2105.2908 | BO32: =BO12*Annual!$R51/100 -> 2095.3368 | BP32: =BP12*Annual!$R51/100 -> 2096.5079 | BQ32: =BQ12*Annual!$R51/100 -> 2173.9531 | BR32: =BR12*Annual!$S51/100 -> 2136.7587 | BS32: =BS12*Annual!$S51/100 -> 2134.1183 | BT32: =BT12*Annual!$S51/100 -> 2157.4411 | BU32: =BU12*Annual!$S51/100 -> 2256.3001 | BV32: =BV12*Annual!$T51/100 -> 2183.4169 | BW32: =BW12*Annual!$T51/100 -> 2185.0326 | BX32: =BX12*Annual!$T51/100 -> 2212.7935 | BY32: =BY12*Annual!$U51/100 -> 2360.8516
A33: Tertiary industries | B33: =SUM(B34:B38) -> 24027.14 | C33: =SUM(C34:C38) -> 24303.535 | D33: =SUM(D34:D38) -> 25223.143 | E33: =SUM(E34:E38) -> 26219.137 | F33: =SUM(F34:F38) -> 25140.849 | G33: =SUM(G34:G38) -> 25397.185 | H33: =SUM(H34:H38) -> 26219.141 | I33: =SUM(I34:I38) -> 27205.437 | ... BY33: =SUM(BY34:BY38) -> 51586.112
A34: Wholesale & retail trade; hotels & restaurants | B34: =B14*Annual!$B53/100 -> 4878.3885 | C34: =C14*Annual!$B53/100 -> 5004.5376 | D34: =D14*Annual!$B53/100 -> 5337.5679 | E34: =E14*Annual!$B53/100 -> 6135.3481 | F34: =F14*Annual!$C53/100 -> 5082.5905 | G34: =G14*Annual!$C53/100 -> 5164.5759 | H34: =H14*Annual!$C53/100 -> 5414.8875 | I34: =I14*Annual!$C53/100 -> 6173.6595 | J34: =J14*Annual!$D53/100 -> 5198.1192 | K34: =K14*Annual!$D53/100 -> 5231.9191 | L34: =L14*Annual!$D53/100 -> 5432.7964 | M34: =M14*Annual!$D53/100 -> 6093.8972 | N34: =N14*Annual!$E53/100 -> 5179.0878 | O34: =O14*Annual!$E53/100 -> 5292.9308 | P34: =P14*Annual!$E53/100 -> 5488.3508 | Q34: =Q14*Annual!$E53/100 -> 6189.7889 | R34: =R14*Annual!$F53/100 -> 5385.4926 | S34: =S14*Annual!$F53/100 -> 5593.4589 | T34: =T14*Annual!$F53/100 -> 5915.3183 | U34: =U14*Annual!$F53/100 -> 6840.3861 | V34: =V14*Annual!$G53/100 -> 5905.0989 | W34: =W14*Annual!$G53/100 -> 6126.3743 | X34: =X14*Annual!$G53/100 -> 6385.3603 | Y34: =Y14*Annual!$G53/100 -> 7274.5658 | Z34: =Z14*Annual!H53/100 -> 6501.3526 | AA34: =AA14*Annual!H53/100 -> 6634.8189 | AB34: =AB14*Annual!H53/100 -> 6817.4305 | AC34: =AC14*Annual!H53/100 -> 7744.7943 | AD34: =AD14*Annual!$I53/100 -> 6592.528 | AE34: =AE14*Annual!$I53/100 -> 6755.3489 | AF34: =AF14*Annual!$I53/100 -> 7013.4015 | AG34: =AG14*Annual!$I53/100 -> 8015.6098 | AH34: =AH14*Annual!$J53/100 -> 6753.6927 | AI34: =AI14*Annual!$J53/100 -> 6934.0942 | AJ34: =AJ14*Annual!$J53/100 -> 7314.0755 | AK34: =AK14*Annual!$J53/100 -> 8359.2832 | AL34: =AL14*Annual!$K53/100 -> 7062.2196 | AM34: =AM14*Annual!$K53/100 -> 7271.7462 | AN34: =AN14*Annual!$K53/100 -> 7602.6045 | AO34: =AO14*Annual!$K53/100 -> 9020.8601 | AP34: =AP14*Annual!$L53/100 -> 7557.199 | AQ34: =AQ14*Annual!$L53/100 -> 7730.7758 | AR34: =AR14*Annual!$L53/100 -> 8095.2364 | AS34: =AS14*Annual!$L53/100 -> 9576.4701 | AT34: =AT14*Annual!$M53/100 -> 7997.4898 | AU34: =AU14*Annual!$M53/100 -> 8230.6835 | AV34: =AV14*Annual!$M53/100 -> 8640.8938 | AW34: =AW14*Annual!$M53/100 -> 10200.949 | AX34: =AX14*Annual!$N53/100 -> 8518.7708 | AY34: =AY14*Annual!$N53/100 -> 8732.1698 | AZ34: =AZ14*Annual!$N53/100 -> 9138.5468 | BA34: =BA14*Annual!$N53/100 -> 10641.699 | BB34: =BB14*Annual!$O53/100 -> 8882.2255 | BC34: =BC14*Annual!$O53/100 -> 8909.7305 | BD34: =BD14*Annual!$O53/100 -> 9047.0648 | BE34: =BE14*Annual!$O53/100 -> 10584.068 | BF34: =BF14*Annual!P53/100 -> 8885.2035 | BG34: =BG14*Annual!P53/100 -> 8836.4314 | BH34: =BH14*Annual!P53/100 -> 9153.0749 | BI34: =BI14*Annual!P53/100 -> 10572.153 | BJ34: =BJ14*Annual!Q53/100 -> 9008.1704 | BK34: =BK14*Annual!Q53/100 -> 9195.6502 | BL34: =BL14*Annual!Q53/100 -> 9611.4093 | BM34: =BM14*Annual!Q53/100 -> 11193.015 | BN34: =BN14*Annual!$R53/100 -> 9446.7716 | BO34: =BO14*Annual!$R53/100 -> 9616.8067 | BP34: =BP14*Annual!$R53/100 -> 10098.883 | BQ34: =BQ14*Annual!$R53/100 -> 11829.768 | BR34: =BR14*Annual!$S53/100 -> 9884.819 | BS34: =BS14*Annual!$S53/100 -> 10008.588 | BT34: =BT14*Annual!$S53/100 -> 10441.371 | BU34: =BU14*Annual!$S53/100 -> 12189.788 | BV34: =BV14*Annual!$T53/100 -> 10170.581 | BW34: =BW14*Annual!$T53/100 -> 10316.926 | BX34: =BX14*Annual!$T53/100 -> 10720.466 | BY34: =BY14*Annual!$U53/100 -> 12520.381
A35: Transport , storage and communication | B35: =B15*Annual!$B54/100 -> 4164.588 | C35: =C15*Annual!$B54/100 -> 4174.3852 | D35: =D15*Annual!$B54/100 -> 4517.1938 | E35: =E15*Annual!$B54/100 -> 4610.8554 | F35: =F15*Annual!$C54/100 -> 4420.1489 | G35: =G15*Annual!$C54/100 -> 4400.1908 | H35: =H15*Annual!$C54/100 -> 4700.5673 | I35: =I15*Annual!$C54/100 -> 4726.4028 | J35: =J15*Annual!$D54/100 -> 4592.9037 | K35: =K15*Annual!$D54/100 -> 4636.0241 | L35: =L15*Annual!$D54/100 -> 4956.141 | M35: =M15*Annual!$D54/100 -> 5076.77 | N35: =N15*Annual!$E54/100 -> 4916.9311 | O35: =O15*Annual!$E54/100 -> 4936.8211 | P35: =P15*Annual!$E54/100 -> 5110.7738 | Q35: =Q15*Annual!$E54/100 -> 5169.6142 | R35: =R15*Annual!$F54/100 -> 4948.354 | S35: =S15*Annual!$F54/100 -> 5061.0829 | T35: =T15*Annual!$F54/100 -> 5358.2805 | U35: =U15*Annual!$F54/100 -> 5481.49 | V35: =V15*Annual!$G54/100 -> 5294.2293 | W35: =W15*Annual!$G54/100 -> 5429.6325 | X35: =X15*Annual!$G54/100 -> 5698.29 | Y35: =Y15*Annual!$G54/100 -> 5772.7574 | Z35: =Z15*Annual!H54/100 -> 5508.6365 | AA35: =AA15*Annual!H54/100 -> 5613.3984 | AB35: =AB15*Annual!H54/100 -> 5922.3967 | AC35: =AC15*Annual!H54/100 -> 6107.9231 | AD35: =AD15*Annual!$I54/100 -> 6016.5291 | AE35: =AE15*Annual!$I54/100 -> 6178.0558 | AF35: =AF15*Annual!$I54/100 -> 6486.9948 | AG35: =AG15*Annual!$I54/100 -> 6636.7098 | AH35: =AH15*Annual!$J54/100 -> 6494.9979 | AI35: =AI15*Annual!$J54/100 -> 6621.9807 | AJ35: =AJ15*Annual!$J54/100 -> 6881.0942 | AK35: =AK15*Annual!$J54/100 -> 7090.2297 | AL35: =AL15*Annual!$K54/100 -> 6738.0703 | AM35: =AM15*Annual!$K54/100 -> 6880.5834 | AN35: =AN15*Annual!$K54/100 -> 7256.6299 | AO35: =AO15*Annual!$K54/100 -> 7426.2782 | AP35: =AP15*Annual!$L54/100 -> 7162.3031 | AQ35: =AQ15*Annual!$L54/100 -> 7314.8988 | AR35: =AR15*Annual!$L54/100 -> 7669.9738 | AS35: =AS15*Annual!$L54/100 -> 7828.5874 | AT35: =AT15*Annual!$M54/100 -> 7498.2444 | AU35: =AU15*Annual!$M54/100 -> 7680.8609 | AV35: =AV15*Annual!$M54/100 -> 8128.4755 | AW35: =AW15*Annual!$M54/100 -> 8226.9895 | AX35: =AX15*Annual!$N54/100 -> 8082.2879 | AY35: =AY15*Annual!$N54/100 -> 8263.4315 | AZ35: =AZ15*Annual!$N54/100 -> 8646.9024 | BA35: =BA15*Annual!$N54/100 -> 8791.0823 | BB35: =BB15*Annual!$O54/100 -> 8450.3112 | BC35: =BC15*Annual!$O54/100 -> 8615.1064 | BD35: =BD15*Annual!$O54/100 -> 8997.8519 | BE35: =BE15*Annual!$O54/100 -> 9135.5633 | BF35: =BF15*Annual!P54/100 -> 8696.0081 | BG35: =BG15*Annual!P54/100 -> 8739.6309 | BH35: =BH15*Annual!P54/100 -> 9090.7981 | BI35: =BI15*Annual!P54/100 -> 9232.8683 | BJ35: =BJ15*Annual!Q54/100 -> 8808.7405 | BK35: =BK15*Annual!Q54/100 -> 8973.8098 | BL35: =BL15*Annual!Q54/100 -> 9382.7173 | BM35: =BM15*Annual!Q54/100 -> 9550.6122 | BN35: =BN15*Annual!$R54/100 -> 9055.8208 | BO35: =BO15*Annual!$R54/100 -> 9248.5368 | BP35: =BP15*Annual!$R54/100 -> 9642.4869 | BQ35: =BQ15*Annual!$R54/100 -> 9834.4978 | BR35: =BR15*Annual!$S54/100 -> 9338.8921 | BS35: =BS15*Annual!$S54/100 -> 9507.9678 | BT35: =BT15*Annual!$S54/100 -> 9867.3631 | BU35: =BU15*Annual!$S54/100 -> 10035.523 | BV35: =BV15*Annual!$T54/100 -> 9490.8743 | BW35: =BW15*Annual!$T54/100 -> 9656.0244 | BX35: =BX15*Annual!$T54/100 -> 10050.516 | BY35: =BY15*Annual!$U54/100 -> 10217.123
A36: Finance, real estate and business services | B36: =B16*Annual!$B55/100 -> 5942.3934 | C36: =C16*Annual!$B55/100 -> 6000.6079 | D36: =D16*Annual!$B55/100 -> 6177.5695 | E36: =E16*Annual!$B55/100 -> 6276.7534 | F36: =F16*Annual!$C55/100 -> 6206.85 | G36: =G16*Annual!$C55/100 -> 6403.5831 | H36: =H16*Annual!$C55/100 -> 6636.5163 | I36: =I16*Annual!$C55/100 -> 6820.4794 | J36: =J16*Annual!$D55/100 -> 6692.4327 | K36: =K16*Annual!$D55/100 -> 6799.8125 | L36: =L16*Annual!$D55/100 -> 6839.454 | M36: =M16*Annual!$D55/100 -> 6840.9284 | N36: =N16*Annual!$E55/100 -> 6759.339 | O36: =O16*Annual!$E55/100 -> 6952.3154 | P36: =P16*Annual!$E55/100 -> 7051.6097 | Q36: =Q16*Annual!$E55/100 -> 7068.8086 | R36: =R16*Annual!$F55/100 -> 7175.6127 | S36: =S16*Annual!$F55/100 -> 7349.7247 | T36: =T16*Annual!$F55/100 -> 7473.9137 | U36: =U16*Annual!$F55/100 -> 7525.3827 | V36: =V16*Annual!$G55/100 -> 7290.224 | W36: =W16*Annual!$G55/100 -> 7402.0831 | X36: =X16*Annual!$G55/100 -> 7529.2289 | Y36: =Y16*Annual!$G55/100 -> 7655.4237 | Z36: =Z16*Annual!H55/100 -> 7572.5351 | AA36: =AA16*Annual!H55/100 -> 7824.407 | AB36: =AB16*Annual!H55/100 -> 8009.5899 | AC36: =AC16*Annual!H55/100 -> 8173.4366 | AD36: =AD16*Annual!$I55/100 -> 8306.2849 | AE36: =AE16*Annual!$I55/100 -> 8285.2473 | AF36: =AF16*Annual!$I55/100 -> 8245.3023 | AG36: =AG16*Annual!$I55/100 -> 8339.4393 | AH36: =AH16*Annual!$J55/100 -> 8745.9011 | AI36: =AI16*Annual!$J55/100 -> 8696.3982 | AJ36: =AJ16*Annual!$J55/100 -> 8736.242 | AK36: =AK16*Annual!$J55/100 -> 8852.151 | AL36: =AL16*Annual!$K55/100 -> 9306.4419 | AM36: =AM16*Annual!$K55/100 -> 9318.9381 | AN36: =AN16*Annual!$K55/100 -> 9368.251 | AO36: =AO16*Annual!$K55/100 -> 9568.0558 | AP36: =AP16*Annual!$L55/100 -> 10284.193 | AQ36: =AQ16*Annual!$L55/100 -> 10300.905 | AR36: =AR16*Annual!$L55/100 -> 10394.795 | AS36: =AS16*Annual!$L55/100 -> 10554.323 | AT36: =AT16*Annual!$M55/100 -> 10948.45 | AU36: =AU16*Annual!$M55/100 -> 11079.465 | AV36: =AV16*Annual!$M55/100 -> 11234.086 | AW36: =AW16*Annual!$M55/100 -> 11468.089 | AX36: =AX16*Annual!$N55/100 -> 11873.179 | AY36: =AY16*Annual!$N55/100 -> 11821.185 | AZ36: =AZ16*Annual!$N55/100 -> 12024.057 | BA36: =BA16*Annual!$N55/100 -> 12482.76 | BB36: =BB16*Annual!$O55/100 -> 12630.069 | BC36: =BC16*Annual!$O55/100 -> 12806.357 | BD36: =BD16*Annual!$O55/100 -> 12992.024 | BE36: =BE16*Annual!$O55/100 -> 13332.322 | BF36: =BF16*Annual!P55/100 -> 13088.054 | BG36: =BG16*Annual!P55/100 -> 13077.091 | BH36: =BH16*Annual!P55/100 -> 13090.566 | BI36: =BI16*Annual!P55/100 -> 13343.997 | BJ36: =BJ16*Annual!Q55/100 -> 13313.017 | BK36: =BK16*Annual!Q55/100 -> 13405.213 | BL36: =BL16*Annual!Q55/100 -> 13451.131 | BM36: =BM16*Annual!Q55/100 -> 13716.533 | BN36: =BN16*Annual!$R55/100 -> 13867.679 | BO36: =BO16*Annual!$R55/100 -> 13978.693 | BP36: =BP16*Annual!$R55/100 -> 14147.085 | BQ36: =BQ16*Annual!$R55/100 -> 14486.116 | BR36: =BR16*Annual!$S55/100 -> 14584.026 | BS36: =BS16*Annual!$S55/100 -> 14522.114 | BT36: =BT16*Annual!$S55/100 -> 14482.969 | BU36: =BU16*Annual!$S55/100 -> 14778.779 | BV36: =BV16*Annual!$T55/100 -> 14837.952 | BW36: =BW16*Annual!$T55/100 -> 15055.522 | BX36: =BX16*Annual!$T55/100 -> 14979.803 | BY36: =BY16*Annual!$U55/100 -> 14951.044
A37: Personal services | B37: =B17*Annual!$B56/100 -> 2539.1359 | C37: =C17*Annual!$B56/100 -> 2610.9905 | D37: =D17*Annual!$B56/100 -> 2657.4344 | E37: =E17*Annual!$B56/100 -> 2654.4713 | F37: =F17*Annual!$C56/100 -> 2684.1387 | G37: =G17*Annual!$C56/100 -> 2673.5092 | H37: =H17*Annual!$C56/100 -> 2687.509 | I37: =I17*Annual!$C56/100 -> 2688.8256 | J37: =J17*Annual!$D56/100 -> 2657.6926 | K37: =K17*Annual!$D56/100 -> 2687.8482 | L37: =L17*Annual!$D56/100 -> 2709.8293 | M37: =M17*Annual!$D56/100 -> 2667.6605 | N37: =N17*Annual!$E56/100 -> 2743.0426 | O37: =O17*Annual!$E56/100 -> 2822.9462 | P37: =P17*Annual!$E56/100 -> 2908.4935 | Q37: =Q17*Annual!$E56/100 -> 2915.5707 | R37: =R17*Annual!$F56/100 -> 2895.8662 | S37: =S17*Annual!$F56/100 -> 2932.922 | T37: =T17*Annual!$F56/100 -> 2996.599 | U37: =U17*Annual!$F56/100 -> 2985.6188 | V37: =V17*Annual!$G56/100 -> 3004.5741 | W37: =W17*Annual!$G56/100 -> 3058.9504 | X37: =X17*Annual!$G56/100 -> 3153.6761 | Y37: =Y17*Annual!$G56/100 -> 3149.7876 | Z37: =Z17*Annual!H56/100 -> 3128.2923 | AA37: =AA17*Annual!H56/100 -> 3143.459 | AB37: =AB17*Annual!H56/100 -> 3205.041 | AC37: =AC17*Annual!H56/100 -> 3178.5153 | AD37: =AD17*Annual!$I56/100 -> 3165.0154 | AE37: =AE17*Annual!$I56/100 -> 3203.8317 | AF37: =AF17*Annual!$I56/100 -> 3292.5164 | AG37: =AG17*Annual!$I56/100 -> 3299.122 | AH37: =AH17*Annual!$J56/100 -> 3326.382 | AI37: =AI17*Annual!$J56/100 -> 3403.8157 | AJ37: =AJ17*Annual!$J56/100 -> 3507.224 | AK37: =AK17*Annual!$J56/100 -> 3445.1464 | AL37: =AL17*Annual!$K56/100 -> 3394.0137 | AM37: =AM17*Annual!$K56/100 -> 3463.0979 | AN37: =AN17*Annual!$K56/100 -> 3537.3781 | AO37: =AO17*Annual!$K56/100 -> 3530.0253 | AP37: =AP17*Annual!$L56/100 -> 3546.5333 | AQ37: =AQ17*Annual!$L56/100 -> 3581.0333 | AR37: =AR17*Annual!$L56/100 -> 3640.92 | AS37: =AS17*Annual!$L56/100 -> 3626.2575 | AT37: =AT17*Annual!$M56/100 -> 3754.2341 | AU37: =AU17*Annual!$M56/100 -> 3774.9181 | AV37: =AV17*Annual!$M56/100 -> 3807.98 | AW37: =AW17*Annual!$M56/100 -> 3821.3351 | AX37: =AX17*Annual!$N56/100 -> 3997.2381 | AY37: =AY17*Annual!$N56/100 -> 4044.1208 | AZ37: =AZ17*Annual!$N56/100 -> 4043.4696 | BA37: =BA17*Annual!$N56/100 -> 3908.5191 | BB37: =BB17*Annual!$O56/100 -> 4162.0857 | BC37: =BC17*Annual!$O56/100 -> 4227.9308 | BD37: =BD17*Annual!$O56/100 -> 4200.2989 | BE37: =BE17*Annual!$O56/100 -> 4005.9903 | BF37: =BF17*Annual!P56/100 -> 4134.3802 | BG37: =BG17*Annual!P56/100 -> 4167.8125 | BH37: =BH17*Annual!P56/100 -> 4171.4043 | BI37: =BI17*Annual!P56/100 -> 4118.8969 | BJ37: =BJ17*Annual!Q56/100 -> 4128.2709 | BK37: =BK17*Annual!Q56/100 -> 4189.817 | BL37: =BL17*Annual!Q56/100 -> 4211.6536 | BM37: =BM17*Annual!Q56/100 -> 4173.2651 | BN37: =BN17*Annual!$R56/100 -> 4283.0729 | BO37: =BO17*Annual!$R56/100 -> 4309.1274 | BP37: =BP17*Annual!$R56/100 -> 4289.9347 | BQ37: =BQ17*Annual!$R56/100 -> 4247.585 | BR37: =BR17*Annual!$S56/100 -> 4359.7831 | BS37: =BS17*Annual!$S56/100 -> 4446.5187 | BT37: =BT17*Annual!$S56/100 -> 4419.8375 | BU37: =BU17*Annual!$S56/100 -> 4290.2866 | BV37: =BV17*Annual!$T56/100 -> 4454.1534 | BW37: =BW17*Annual!$T56/100 -> 4522.3631 | BX37: =BX17*Annual!$T56/100 -> 4508.263 | BY37: =BY17*Annual!$U56/100 -> 4380.5582
A38: General government services | B38: =B18*Annual!$B57/100 -> 6502.634 | C38: =C18*Annual!$B57/100 -> 6513.0138 | D38: =D18*Annual!$B57/100 -> 6533.3773 | E38: =E18*Annual!$B57/100 -> 6541.7085 | F38: =F18*Annual!$C57/100 -> 6747.1211 | G38: =G18*Annual!$C57/100 -> 6755.3256 | H38: =H18*Annual!$C57/100 -> 6779.6609 | I38: =I18*Annual!$C57/100 -> 6796.0699 | J38: =J18*Annual!$D57/100 -> 6589.57 | K38: =K18*Annual!$D57/100 -> 6591.8587 | L38: =L18*Annual!$D57/100 -> 6615.9578 | M38: =M18*Annual!$D57/100 -> 6625.5167 | N38: =N18*Annual!$E57/100 -> 6726.4946 | O38: =O18*Annual!$E57/100 -> 6733.4071 | P38: =P18*Annual!$E57/100 -> 6732.4532 | Q38: =Q18*Annual!$E57/100 -> 6737.4302 | R38: =R18*Annual!$F57/100 -> 6496.0006 | S38: =S18*Annual!$F57/100 -> 6506.7674 | T38: =T18*Annual!$F57/100 -> 6503.1336 | U38: =U18*Annual!$F57/100 -> 6486.3105 | V38: =V18*Annual!$G57/100 -> 6477.6978 | W38: =W18*Annual!$G57/100 -> 6487.0504 | X38: =X18*Annual!$G57/100 -> 6484.3415 | Y38: =Y18*Annual!$G57/100 -> 6467.5256 | Z38: =Z18*Annual!H57/100 -> 6559.6162 | AA38: =AA18*Annual!H57/100 -> 6550.9223 | AB38: =AB18*Annual!H57/100 -> 6527.8764 | AC38: =AC18*Annual!H57/100 -> 6519.5965 | AD38: =AD18*Annual!$I57/100 -> 6486.4328 | AE38: =AE18*Annual!$I57/100 -> 6562.6564 | AF38: =AF18*Annual!$I57/100 -> 6598.0164 | AG38: =AG18*Annual!$I57/100 -> 6619.7553 | AH38: =AH18*Annual!$J57/100 -> 6603.7136 | AI38: =AI18*Annual!$J57/100 -> 6700.5856 | AJ38: =AJ18*Annual!$J57/100 -> 6749.7057 | AK38: =AK18*Annual!$J57/100 -> 6790.069 | AL38: =AL18*Annual!$K57/100 -> 6680.1064 | AM38: =AM18*Annual!$K57/100 -> 6782.7015 | AN38: =AN18*Annual!$K57/100 -> 6826.6513 | AO38: =AO18*Annual!$K57/100 -> 6916.8642 | AP38: =AP18*Annual!$L57/100 -> 6956.8458 | AQ38: =AQ18*Annual!$L57/100 -> 7108.5735 | AR38: =AR18*Annual!$L57/100 -> 7171.2686 | AS38: =AS18*Annual!$L57/100 -> 7194.9888 | AT38: =AT18*Annual!$M57/100 -> 7203.1733 | AU38: =AU18*Annual!$M57/100 -> 7292.9388 | AV38: =AV18*Annual!$M57/100 -> 7340.8864 | AW38: =AW18*Annual!$M57/100 -> 7441.9577 | AX38: =AX18*Annual!$N57/100 -> 7520.0194 | AY38: =AY18*Annual!$N57/100 -> 7568.3279 | AZ38: =AZ18*Annual!$N57/100 -> 7647.6139 | BA38: =BA18*Annual!$N57/100 -> 7734.4054 | BB38: =BB18*Annual!$O57/100 -> 7841.7952 | BC38: =BC18*Annual!$O57/100 -> 7930.5516 | BD38: =BD18*Annual!$O57/100 -> 8053.1396 | BE38: =BE18*Annual!$O57/100 -> 8145.4572 | BF38: =BF18*Annual!P57/100 -> 8157.098 | BG38: =BG18*Annual!P57/100 -> 8300.4885 | BH38: =BH18*Annual!P57/100 -> 8348.4223 | BI38: =BI18*Annual!P57/100 -> 8411.0101 | BJ38: =BJ18*Annual!Q57/100 -> 8425.3162 | BK38: =BK18*Annual!Q57/100 -> 8579.7375 | BL38: =BL18*Annual!Q57/100 -> 8643.4603 | BM38: =BM18*Annual!Q57/100 -> 8760.9966 | BN38: =BN18*Annual!$R57/100 -> 8741.2939 | BO38: =BO18*Annual!$R57/100 -> 8935.9089 | BP38: =BP18*Annual!$R57/100 -> 9014.3604 | BQ38: =BQ18*Annual!$R57/100 -> 9161.3539 | BR38: =BR18*Annual!$S57/100 -> 9001.9362 | BS38: =BS18*Annual!$S57/100 -> 9165.7403 | BT38: =BT18*Annual!$S57/100 -> 9249.224 | BU38: =BU18*Annual!$S57/100 -> 9403.1256 | BV38: =BV18*Annual!$T57/100 -> 9201.9042 | BW38: =BW18*Annual!$T57/100 -> 9325.9643 | BX38: =BX18*Annual!$T57/100 -> 9344.257 | BY38: =BY18*Annual!$U57/100 -> 9517.0059
A39: All industries at basic prices | B39: =B33+B29+B26 -> 38816.446 | C39: =C33+C29+C26 -> 40027.416 | D39: =D33+D29+D26 -> 41844.277 | E39: =E33+E29+E26 -> 42032.863 | F39: =F33+F29+F26 -> 40666.565 | G39: =G33+G29+G26 -> 43082.453 | H39: =H33+H29+H26 -> 43633.546 | I39: =I33+I29+I26 -> 43743.376 | ... BY39: =BY33+BY29+BY26 -> 75018.446
A40: Taxes less subsidies on products | B40: =B20*Annual!$B59/100 -> 5353.1555 | C40: =C20*Annual!$B59/100 -> 5354.0657 | D40: =D20*Annual!$B59/100 -> 5400.8395 | E40: =E20*Annual!$B59/100 -> 5422.6597 | F40: =F20*Annual!$C59/100 -> 5577.6364 | G40: =G20*Annual!$C59/100 -> 5637.3877 | H40: =H20*Annual!$C59/100 -> 5688.6816 | I40: =I20*Annual!$C59/100 -> 5758.0097 | J40: =J20*Annual!$D59/100 -> 5793.9847 | K40: =K20*Annual!$D59/100 -> 5810.8771 | L40: =L20*Annual!$D59/100 -> 5836.3721 | M40: =M20*Annual!$D59/100 -> 5845.7856 | N40: =N20*Annual!$E59/100 -> 5754.4619 | O40: =O20*Annual!$E59/100 -> 5697.9269 | P40: =P20*Annual!$E59/100 -> 5812.2303 | Q40: =Q20*Annual!$E59/100 -> 5891.949 | R40: =R20*Annual!$F59/100 -> 5564.6652 | S40: =S20*Annual!$F59/100 -> 5555.1849 | T40: =T20*Annual!$F59/100 -> 5732.6074 | U40: =U20*Annual!$F59/100 -> 5849.7638 | V40: =V20*Annual!$G59/100 -> 5690.3193 | W40: =W20*Annual!$G59/100 -> 5699.634 | X40: =X20*Annual!$G59/100 -> 5886.803 | Y40: =Y20*Annual!$G59/100 -> 6003.9568 | Z40: =Z20*Annual!H59/100 -> 6055.8495 | AA40: =AA20*Annual!H59/100 -> 6061.4619 | AB40: =AB20*Annual!H59/100 -> 6239.9395 | AC40: =AC20*Annual!H59/100 -> 6373.4163 | AD40: =AD20*Annual!$I59/100 -> 5947.3394 | AE40: =AE20*Annual!$I59/100 -> 6116.1768 | AF40: =AF20*Annual!$I59/100 -> 6231.9042 | AG40: =AG20*Annual!$I59/100 -> 6319.6013 | AH40: =AH20*Annual!$J59/100 -> 6055.13 | AI40: =AI20*Annual!$J59/100 -> 6244.0131 | AJ40: =AJ20*Annual!$J59/100 -> 6294.8038 | AK40: =AK20*Annual!$J59/100 -> 6427.0544 | AL40: =AL20*Annual!$K59/100 -> 6243.6752 | AM40: =AM20*Annual!$K59/100 -> 6514.344 | AN40: =AN20*Annual!$K59/100 -> 6647.8977 | AO40: =AO20*Annual!$K59/100 -> 6809.4572 | AP40: =AP20*Annual!$L59/100 -> 6559.3887 | AQ40: =AQ20*Annual!$L59/100 -> 6827.8753 | AR40: =AR20*Annual!$L59/100 -> 6951.6434 | AS40: =AS20*Annual!$L59/100 -> 7060.1017 | AT40: =AT20*Annual!$M59/100 -> 6910.5855 | AU40: =AU20*Annual!$M59/100 -> 7221.2915 | AV40: =AV20*Annual!$M59/100 -> 7329.5947 | AW40: =AW20*Annual!$M59/100 -> 7693.2418 | AX40: =AX20*Annual!$N59/100 -> 7405.6253 | AY40: =AY20*Annual!$N59/100 -> 7578.5037 | AZ40: =AZ20*Annual!$N59/100 -> 7706.1924 | BA40: =BA20*Annual!$N59/100 -> 7879.2316 | BB40: =BB20*Annual!$O59/100 -> 7663.9133 | BC40: =BC20*Annual!$O59/100 -> 7882.9605 | BD40: =BD20*Annual!$O59/100 -> 7876.1958 | BE40: =BE20*Annual!$O59/100 -> 7950.9295 | BF40: =BF20*Annual!P59/100 -> 7529.0572 | BG40: =BG20*Annual!P59/100 -> 7525.1808 | BH40: =BH20*Annual!P59/100 -> 7583.0035 | BI40: =BI20*Annual!P59/100 -> 7863.2333 | BJ40: =BJ20*Annual!Q59/100 -> 7794.2508 | BK40: =BK20*Annual!Q59/100 -> 7950.673 | BL40: =BL20*Annual!Q59/100 -> 8056.8109 | BM40: =BM20*Annual!Q59/100 -> 8257.9486 | BN40: =BN20*Annual!$R59/100 -> 8033.9449 | BO40: =BO20*Annual!$R59/100 -> 8211.43 | BP40: =BP20*Annual!$R59/100 -> 8320.8254 | BQ40: =BQ20*Annual!$R59/100 -> 8598.0249 | BR40: =BR20*Annual!$S59/100 -> 8474.9261 | BS40: =BS20*Annual!$S59/100 -> 8596.0245 | BT40: =BT20*Annual!$S59/100 -> 8570.3667 | BU40: =BU20*Annual!$S59/100 -> 8856.3615 | BV40: =BV20*Annual!$T59/100 -> 8470.2711 | BW40: =BW20*Annual!$T59/100 -> 8660.0698 | BX40: =BX20*Annual!$T59/100 -> 8602.438 | BY40: =BY20*Annual!$U59/100 -> 8955.6342
A41: KZN - GDPR at constant 2005 prices | B41: =B39+B40 -> 44169.601 | C41: =C39+C40 -> 45381.482 | D41: =D39+D40 -> 47245.116 | E41: =E39+E40 -> 47455.523 | F41: =F39+F40 -> 46244.201 | G41: =G39+G40 -> 48719.841 | H41: =H39+H40 -> 49322.227 | I41: =I39+I40 -> 49501.386 | ... BY41: =BY39+BY40 -> 83974.08
A43: SA – GDP by activity
A44: Quarterly Change
A45: National Industry | B45: =B25 -> 1995q1 | C45: =C25 -> 1995q2 | D45: =D25 -> 1995q3 | E45: =E25 -> 1995q4 | F45: =F25 -> 1996q1 | G45: =G25 -> 1996q2 | H45: =H25 -> 1996q3 | I45: =I25 -> 1996q4 | ... BY45: =BY25 -> 2013q4
A46: Primary Industries | C46: =(C6-B6)/B6*100 -> 7.0029876 | D46: =(D6-C6)/C6*100 -> 2.8293134 | E46: =(E6-D6)/D6*100 -> -6.0603612 | F46: =(F6-E6)/E6*100 -> -2.5932851 | G46: =(G6-F6)/F6*100 -> 21.848096 | H46: =(H6-G6)/G6*100 -> -8.2756663 | I46: =(I6-H6)/H6*100 -> -8.6548837 | J46: =(J6-I6)/I6*100 -> -0.50240835 | ... BY46: =(BY6-BX6)/BX6*100 -> -9.6765845
A47: Agriculture, forestry and fishing | C47: =(C7-B7)/B7*100 -> 45.31558 | D47: =(D7-C7)/C7*100 -> 7.2318999 | E47: =(E7-D7)/D7*100 -> -22.68002 | F47: =(F7-E7)/E7*100 -> -8.868667 | G47: =(G7-F7)/F7*100 -> 122.81211 | H47: =(H7-G7)/G7*100 -> -28.391359 | I47: =(I7-H7)/H7*100 -> -33.108219 | J47: =(J7-I7)/I7*100 -> 3.4558153 | ... BY47: =(BY7-BX7)/BX7*100 -> -41.89777
A48: Mining and quarrying | C48: =(C8-B8)/B8*100 -> -0.69413852 | D48: =(D8-C8)/C8*100 -> 1.5350215 | E48: =(E8-D8)/D8*100 -> -0.90030304 | F48: =(F8-E8)/E8*100 -> -1.0731155 | G48: =(G8-F8)/F8*100 -> -0.68245929 | H48: =(H8-G8)/G8*100 -> 1.7948822 | I48: =(I8-H8)/H8*100 -> -0.04304833 | J48: =(J8-I8)/I8*100 -> -1.435271 | ... BY48: =(BY8-BX8)/BX8*100 -> 5.018392
A49: Secondary Industries | C49: =(C9-B9)/B9*100 -> 1.861049 | D49: =(D9-C9)/C9*100 -> 5.6141633 | E49: =(E9-D9)/D9*100 -> -1.9289089 | F49: =(F9-E9)/E9*100 -> -3.1303532 | G49: =(G9-F9)/F9*100 -> 1.4694629 | H49: =(H9-G9)/G9*100 -> 5.7581568 | I49: =(I9-H9)/H9*100 -> -0.16320842 | J49: =(J9-I9)/I9*100 -> -4.1539846 | ... BY49: =(BY9-BX9)/BX9*100 -> 3.5048319
A50: Manufacturing | C50: =(C10-B10)/B10*100 -> 1.9165014 | D50: =(D10-C10)/C10*100 -> 7.0731262 | E50: =(E10-D10)/D10*100 -> -1.1651422 | F50: =(F10-E10)/E10*100 -> -5.1715413 | G50: =(G10-F10)/F10*100 -> 0.81944114 | H50: =(H10-G10)/G10*100 -> 6.2962515 | I50: =(I10-H10)/H10*100 -> 0.14318151 | J50: =(J10-I10)/I10*100 -> -5.2647939 | ... BY50: =(BY10-BX10)/BX10*100 -> 3.593038
A51: Electricity, gas and water | C51: =(C11-B11)/B11*100 -> 1.9562705 | D51: =(D11-C11)/C11*100 -> 1.6197272 | E51: =(E11-D11)/D11*100 -> -5.3662948 | F51: =(F11-E11)/E11*100 -> 3.9503026 | G51: =(G11-F11)/F11*100 -> 6.5430585 | H51: =(H11-G11)/G11*100 -> 8.3072055 | I51: =(I11-H11)/H11*100 -> 1.2499668 | J51: =(J11-I11)/I11*100 -> -5.0720485 | ... BY51: =(BY11-BX11)/BX11*100 -> -2.6035809
A52: Construction | C52: =(C12-B12)/B12*100 -> 1.3602087 | D52: =(D12-C12)/C12*100 -> -1.1182961 | E52: =(E12-D12)/D12*100 -> -4.4734868 | F52: =(F12-E12)/E12*100 -> 6.4719771 | G52: =(G12-F12)/F12*100 -> 1.1860649 | H52: =(H12-G12)/G12*100 -> -0.85470202 | I52: =(I12-H12)/H12*100 -> -4.1871805 | J52: =(J12-I12)/I12*100 -> 6.0668288 | ... BY52: =(BY12-BX12)/BX12*100 -> 6.6910056
A53: Tertiary industries | C53: =(C13-B13)/B13*100 -> 1.1398938 | D53: =(D13-C13)/C13*100 -> 3.3626471 | E53: =(E13-D13)/D13*100 -> 3.7820611 | F53: =(F13-E13)/E13*100 -> -3.768236 | G53: =(G13-F13)/F13*100 -> 1.1397245 | H53: =(H13-G13)/G13*100 -> 2.9605437 | I53: =(I13-H13)/H13*100 -> 3.7720029 | J53: =(J13-I13)/I13*100 -> -4.1268034 | ... BY53: =(BY13-BX13)/BX13*100 -> 3.6473784
A54: Wholesale & retail trade; hotels & restaurants | C54: =(C14-B14)/B14*100 -> 2.5858784 | D54: =(D14-C14)/C14*100 -> 6.6545655 | E54: =(E14-D14)/D14*100 -> 14.946511 | F54: =(F14-E14)/E14*100 -> -15.981677 | G54: =(G14-F14)/F14*100 -> 1.6130641 | H54: =(H14-G14)/G14*100 -> 4.8467018 | I54: =(I14-H14)/H14*100 -> 14.012701 | J54: =(J14-I14)/I14*100 -> -15.930795 | ... BY54: =(BY14-BX14)/BX14*100 -> 16.789522
A55: Transport , storage and communication | C55: =(C15-B15)/B15*100 -> 0.23525002 | D55: =(D15-C15)/C15*100 -> 8.2121937 | E55: =(E15-D15)/D15*100 -> 2.0734475 | F55: =(F15-E15)/E15*100 -> -2.6376958 | G55: =(G15-F15)/F15*100 -> -0.45152585 | H55: =(H15-G15)/G15*100 -> 6.8264428 | I55: =(I15-H15)/H15*100 -> 0.54962377 | J55: =(J15-I15)/I15*100 -> -0.94646411 | ... BY55: =(BY15-BX15)/BX15*100 -> 1.6577021
A56: Finance, real estate and business services | C56: =(C16-B16)/B16*100 -> 0.97964804 | D56: =(D16-C16)/C16*100 -> 2.949061 | E56: =(E16-D16)/D16*100 -> 1.6055497 | F56: =(F16-E16)/E16*100 -> -1.1692836 | G56: =(G16-F16)/F16*100 -> 3.1696117 | H56: =(H16-G16)/G16*100 -> 3.6375458 | I56: =(I16-H16)/H16*100 -> 2.7719825 | J56: =(J16-I16)/I16*100 -> -1.4384333 | ... BY56: =(BY16-BX16)/BX16*100 -> -0.19198664
A57: Personal services | C57: =(C17-B17)/B17*100 -> 2.8298824 | D57: =(D17-C17)/C17*100 -> 1.7787884 | E57: =(E17-D17)/D17*100 -> -0.11150273 | F57: =(F17-E17)/E17*100 -> 1.1756129 | G57: =(G17-F17)/F17*100 -> -0.3960117 | H57: =(H17-G17)/G17*100 -> 0.52364746 | I57: =(I17-H17)/H17*100 -> 0.0489901 | J57: =(J17-I17)/I17*100 -> -1.0892804 | ... BY57: =(BY17-BX17)/BX17*100 -> -2.8326825
... A61: SA - GDP at constant 2005 prices | C61: =(C21-B21)/B21*100 -> 1.8015685 | D61: =(D21-C21)/C21*100 -> 3.494691 | E61: =(E21-D21)/D21*100 -> 1.0107826 | F61: =(F21-E21)/E21*100 -> -2.790898 | G61: =(G21-F21)/F21*100 -> 3.4038717 | H61: =(H21-G21)/G21*100 -> 1.8972029 | I61: =(I21-H21)/H21*100 -> 1.2171464 | J61: =(J21-I21)/I21*100 -> -3.1912001 | ... BY61: =(BY21-BX21)/BX21*100 -> 2.7020638
A63: KZN – GDPR by activity
A64: Quarterly Change
A65: Provincial Industry | B65: =B45 -> 1995q1 | C65: =C45 -> 1995q2 | D65: =D45 -> 1995q3 | E65: =E45 -> 1995q4 | F65: =F45 -> 1996q1 | G65: =G45 -> 1996q2 | H65: =H45 -> 1996q3 | I65: =I45 -> 1996q4 | ... BY65: =BY45 -> 2013q4
A66: Primary Industries | C66: =(C26-B26)/B26*100 -> 26.425745 | D66: =(D26-C26)/C26*100 -> 5.3947063 | E66: =(E26-D26)/D26*100 -> -15.913471 | F66: =(F26-E26)/E26*100 -> 5.0533324 | G66: =(G26-F26)/F26*100 -> 63.02259 | H66: =(H26-G26)/G26*100 -> -19.487784 | I66: =(I26-H26)/H26*100 -> -20.777446 | J66: =(J26-I26)/I26*100 -> 0.20014425 | ... BY66: =(BY26-BX26)/BX26*100 -> -32.001549
A67: Agriculture, forestry and fishing | C67: =(C27-B27)/B27*100 -> 45.31558 | D67: =(D27-C27)/C27*100 -> 7.2318999 | E67: =(E27-D27)/D27*100 -> -22.68002 | F67: =(F27-E27)/E27*100 -> -14.50309 | G67: =(G27-F27)/F27*100 -> 122.81211 | H67: =(H27-G27)/G27*100 -> -28.391359 | I67: =(I27-H27)/H27*100 -> -33.108219 | J67: =(J27-I27)/I27*100 -> 2.1661978 | ... BY67: =(BY27-BX27)/BX27*100 -> -41.89777
A68: Mining and quarrying | C68: =(C28-B28)/B28*100 -> -0.69413852 | D68: =(D28-C28)/C28*100 -> 1.5350215 | E68: =(E28-D28)/D28*100 -> -0.90030304 | F68: =(F28-E28)/E28*100 -> 38.907636 | G68: =(G28-F28)/F28*100 -> -0.68245929 | H68: =(H28-G28)/G28*100 -> 1.7948822 | I68: =(I28-H28)/H28*100 -> -0.04304833 | J68: =(J28-I28)/I28*100 -> -2.0122177 | ... BY68: =(BY28-BX28)/BX28*100 -> 5.018392
A69: Secondary Industries | C69: =(C29-B29)/B29*100 -> 1.8669839 | D69: =(D29-C29)/C29*100 -> 5.7919398 | E69: =(E29-D29)/D29*100 -> -1.8307845 | F69: =(F29-E29)/E29*100 -> -3.4334483 | G69: =(G29-F29)/F29*100 -> 1.3796706 | H69: =(H29-G29)/G29*100 -> 5.8349065 | I69: =(I29-H29)/H29*100 -> -0.11932183 | J69: =(J29-I29)/I29*100 -> -4.1981154 | ... BY69: =(BY29-BX29)/BX29*100 -> 3.4898271
A70: Manufacturing | C70: =(C30-B30)/B30*100 -> 1.9165014 | D70: =(D30-C30)/C30*100 -> 7.0731262 | E70: =(E30-D30)/D30*100 -> -1.1651422 | F70: =(F30-E30)/E30*100 -> -4.8461071 | G70: =(G30-F30)/F30*100 -> 0.81944114 | H70: =(H30-G30)/G30*100 -> 6.2962515 | I70: =(I30-H30)/H30*100 -> 0.14318151 | J70: =(J30-I30)/I30*100 -> -5.3100111 | ... BY70: =(BY30-BX30)/BX30*100 -> 3.593038
A71: Electricity, gas and water | C71: =(C31-B31)/B31*100 -> 1.9562705 | D71: =(D31-C31)/C31*100 -> 1.6197272 | E71: =(E31-D31)/D31*100 -> -5.3662948 | F71: =(F31-E31)/E31*100 -> 4.2074198 | G71: =(G31-F31)/F31*100 -> 6.5430585 | H71: =(H31-G31)/G31*100 -> 8.3072055 | I71: =(I31-H31)/H31*100 -> 1.2499668 | J71: =(J31-I31)/I31*100 -> -5.4894417 | ... BY71: =(BY31-BX31)/BX31*100 -> -2.6035809
A72: Construction | C72: =(C32-B32)/B32*100 -> 1.3602087 | D72: =(D32-C32)/C32*100 -> -1.1182961 | E72: =(E32-D32)/D32*100 -> -4.4734868 | F72: =(F32-E32)/E32*100 -> 2.5618827 | G72: =(G32-F32)/F32*100 -> 1.1860649 | H72: =(H32-G32)/G32*100 -> -0.85470202 | I72: =(I32-H32)/H32*100 -> -4.1871805 | J72: =(J32-I32)/I32*100 -> 8.400929 | ... BY72: =(BY32-BX32)/BX32*100 -> 6.6910056
A73: Tertiary industries | C73: =(C33-B33)/B33*100 -> 1.1503462 | D73: =(D33-C33)/C33*100 -> 3.7838444 | E73: =(E33-D33)/D33*100 -> 3.94873 | F73: =(F33-E33)/E33*100 -> -4.1125973 | G73: =(G33-F33)/F33*100 -> 1.0195971 | H73: =(H33-G33)/G33*100 -> 3.236408 | I73: =(I33-H33)/H33*100 -> 3.7617408 | J73: =(J33-I33)/I33*100 -> -5.4206776 | ... BY73: =(BY33-BX33)/BX33*100 -> 3.9973294
A74: Wholesale & retail trade; hotels & restaurants | C74: =(C34-B34)/B34*100 -> 2.5858784 | D74: =(D34-C34)/C34*100 -> 6.6545655 | E74: =(E34-D34)/D34*100 -> 14.946511 | F74: =(F34-E34)/E34*100 -> -17.158889 | G74: =(G34-F34)/F34*100 -> 1.6130641 | H74: =(H34-G34)/G34*100 -> 4.8467018 | I74: =(I34-H34)/H34*100 -> 14.012701 | J74: =(J34-I34)/I34*100 -> -15.801654 | ... BY74: =(BY34-BX34)/BX34*100 -> 16.789522
A75: Transport , storage and communication | C75: =(C35-B35)/B35*100 -> 0.23525002 | D75: =(D35-C35)/C35*100 -> 8.2121937 | E75: =(E35-D35)/D35*100 -> 2.0734475 | F75: =(F35-E35)/E35*100 -> -4.1360324 | G75: =(G35-F35)/F35*100 -> -0.45152585 | H75: =(H35-G35)/G35*100 -> 6.8264428 | I75: =(I35-H35)/H35*100 -> 0.54962377 | J75: =(J35-I35)/I35*100 -> -2.8245378 | ... BY75: =(BY35-BX35)/BX35*100 -> 1.6577021
A76: Finance, real estate and business services | C76: =(C36-B36)/B36*100 -> 0.97964804 | D76: =(D36-C36)/C36*100 -> 2.949061 | E76: =(E36-D36)/D36*100 -> 1.6055497 | F76: =(F36-E36)/E36*100 -> -1.1136875 | G76: =(G36-F36)/F36*100 -> 3.1696117 | H76: =(H36-G36)/G36*100 -> 3.6375458 | I76: =(I36-H36)/H36*100 -> 2.7719825 | J76: =(J36-I36)/I36*100 -> -1.8773858 | ... BY76: =(BY36-BX36)/BX36*100 -> -0.19198664
A77: Personal services | C77: =(C37-B37)/B37*100 -> 2.8298824 | D77: =(D37-C37)/C37*100 -> 1.7787884 | E77: =(E37-D37)/D37*100 -> -0.11150273 | F77: =(F37-E37)/E37*100 -> 1.1176377 | G77: =(G37-F37)/F37*100 -> -0.3960117 | H77: =(H37-G37)/G37*100 -> 0.52364746 | I77: =(I37-H37)/H37*100 -> 0.0489901 | J77: =(J37-I37)/I37*100 -> -1.1578658 | ... BY77: =(BY37-BX37)/BX37*100 -> -2.8326825
... A81: KZN - GDPR at constant 2005 prices | C81: =(C41-B41)/B41*100 -> 2.7436988 | D81: =(D41-C41)/C41*100 -> 4.1065968 | E81: =(E41-D41)/D41*100 -> 0.44534992 | F81: =(F41-E41)/E41*100 -> -2.5525403 | G81: =(G41-F41)/F41*100 -> 5.3534055 | H81: =(H41-G41)/G41*100 -> 1.2364296 | I81: =(I41-H41)/H41*100 -> 0.36324038 | J81: =(J41-I41)/I41*100 -> -4.0174568 | ... BY81: =(BY41-BX41)/BX41*100 -> 2.0201608
A83: SA – GDP by activity
A84: Annual Change
A85: National Industry | B85: =B65 -> 1995q1 | C85: =C65 -> 1995q2 | D85: =D65 -> 1995q3 | E85: =E65 -> 1995q4 | F85: =F65 -> 1996q1 | G85: =G65 -> 1996q2 | H85: =H65 -> 1996q3 | I85: =I65 -> 1996q4 | ... BY85: =BY65 -> 2013q4
A86: Primary Industries | F86: =(F6-B6)/B6*100 -> 0.68171904 | G86: =(G6-C6)/C6*100 -> 14.649844 | H86: =(H6-D6)/D6*100 -> 2.2683141 | I86: =(I6-E6)/E6*100 -> -0.55623836 | J86: =(J6-F6)/F6*100 -> 1.5783645 | K86: =(K6-G6)/G6*100 -> 0.87249523 | L86: =(L6-H6)/H6*100 -> 1.7442458 | M86: =(M6-I6)/I6*100 -> 1.9161673 | ... BY86: =(BY6-BU6)/BU6*100 -> 6.9195608
A87: Agriculture, forestry and fishing | F87: =(F7-B7)/B7*100 -> 9.7983051 | G87: =(G7-C7)/C7*100 -> 68.353539 | H87: =(H7-D7)/D7*100 -> 12.425203 | I87: =(I7-E7)/E7*100 -> -2.7376619 | J87: =(J7-F7)/F7*100 -> 10.415969 | K87: =(K7-G7)/G7*100 -> -1.979309 | L87: =(L7-H7)/H7*100 -> -0.71153911 | M87: =(M7-I7)/I7*100 -> 0.40407752 | ... BY87: =(BY7-BU7)/BU7*100 -> -1.9296455
A88: Mining and quarrying | F88: =(F8-B8)/B8*100 -> -1.1498331 | G88: =(G8-C8)/C8*100 -> -1.1382075 | H88: =(H8-D8)/D8*100 -> -0.88518843 | I88: =(I8-E8)/E8*100 -> -0.027802977 | J88: =(J8-F8)/F8*100 -> -0.3937852 | K88: =(K8-G8)/G8*100 -> 2.3001981 | L88: =(L8-H8)/H8*100 -> 2.60911 | M88: =(M8-I8)/I8*100 -> 2.2725322 | ... BY88: =(BY8-BU8)/BU8*100 -> 9.4106013
A89: Secondary Industries | F89: =(F9-B9)/B9*100 -> 2.2019144 | G89: =(G9-C9)/C9*100 -> 1.8090178 | H89: =(H9-D9)/D9*100 -> 1.9478234 | I89: =(I9-E9)/E9*100 -> 3.7833217 | J89: =(J9-F9)/F9*100 -> 2.6866328 | K89: =(K9-G9)/G9*100 -> 4.4023931 | L89: =(L9-H9)/H9*100 -> 2.475092 | M89: =(M9-I9)/I9*100 -> 2.1449564 | ... BY89: =(BY9-BU9)/BU9*100 -> 1.5136193
A90: Manufacturing | F90: =(F10-B10)/B10*100 -> 2.2760209 | G90: =(G10-C10)/C10*100 -> 1.1750907 | H90: =(H10-D10)/D10*100 -> 0.4410095 | I90: =(I10-E10)/E10*100 -> 1.7705946 | J90: =(J10-F10)/F10*100 -> 1.6705152 | K90: =(K10-G10)/G10*100 -> 4.3076706 | L90: =(L10-H10)/H10*100 -> 2.8818723 | M90: =(M10-I10)/I10*100 -> 1.9673746 | ... BY90: =(BY10-BU10)/BU10*100 -> 1.0958205
A91: Electricity, gas and water | F91: =(F11-B11)/B11*100 -> 1.9209745 | G91: =(G11-C11)/C11*100 -> 6.5061747 | H91: =(H11-D11)/D11*100 -> 13.515225 | I91: =(I11-E11)/E11*100 -> 21.451577 | J91: =(J11-F11)/F11*100 -> 10.910205 | K91: =(K11-G11)/G11*100 -> 7.9544082 | L91: =(L11-H11)/H11*100 -> 0.94813162 | M91: =(M11-I11)/I11*100 -> -2.881807 | ... BY91: =(BY11-BU11)/BU11*100 -> -0.010857468
A92: Construction | F92: =(F12-B12)/B12*100 -> 1.939543 | G92: =(G12-C12)/C12*100 -> 1.7644039 | H92: =(H12-D12)/D12*100 -> 2.0356825 | I92: =(I12-E12)/E12*100 -> 2.3414978 | J92: =(J12-F12)/F12*100 -> 1.9520668 | K92: =(K12-G12)/G12*100 -> 1.3675202 | L92: =(L12-H12)/H12*100 -> 1.0344933 | M92: =(M12-I12)/I12*100 -> 9.6915156 | ... BY92: =(BY12-BU12)/BU12*100 -> 4.4918561
A93: Tertiary industries | F93: =(F13-B13)/B13*100 -> 4.4063358 | G93: =(G13-C13)/C13*100 -> 4.406161 | H93: =(H13-D13)/D13*100 -> 3.9999982 | I93: =(I13-E13)/E13*100 -> 3.9899189 | J93: =(J13-F13)/F13*100 -> 3.6024441 | K93: =(K13-G13)/G13*100 -> 3.2831664 | L93: =(L13-H13)/H13*100 -> 2.2741836 | M93: =(M13-I13)/I13*100 -> 1.145765 | ... BY93: =(BY13-BU13)/BU13*100 -> 1.525919
A94: Wholesale & retail trade; hotels & restaurants | F94: =(F14-B14)/B14*100 -> 5.6663809 | G94: =(G14-C14)/C14*100 -> 4.6643545 | H94: =(H14-D14)/D14*100 -> 2.8902261 | I94: =(I14-E14)/E14*100 -> 2.0543599 | J94: =(J14-F14)/F14*100 -> 2.1161652 | K94: =(K14-G14)/G14*100 -> 1.1485677 | L94: =(L14-H14)/H14*100 -> 0.1768498 | M94: =(M14-I14)/I14*100 -> -1.4433729 | ... BY94: =(BY14-BU14)/BU14*100 -> 2.0633844
A95: Transport , storage and communication | F95: =(F15-B15)/B15*100 -> 7.7954192 | G95: =(G15-C15)/C15*100 -> 7.0568438 | H95: =(H15-D15)/D15*100 -> 5.6858882 | I95: =(I15-E15)/E15*100 -> 4.1081354 | J95: =(J15-F15)/F15*100 -> 5.9165456 | K95: =(K15-G15)/G15*100 -> 7.3958605 | L95: =(L15-H15)/H15*100 -> 7.4748248 | M95: =(M15-I15)/I15*100 -> 9.4889094 | ... BY95: =(BY15-BU15)/BU15*100 -> 2.0234338
A96: Finance, real estate and business services | F96: =(F16-B16)/B16*100 -> 4.3916148 | G96: =(G16-C16)/C16*100 -> 6.6555744 | H96: =(H16-D16)/D16*100 -> 7.368847 | I96: =(I16-E16)/E16*100 -> 8.6014425 | J96: =(J16-F16)/F16*100 -> 8.3056837 | K96: =(K16-G16)/G16*100 -> 6.6626521 | L96: =(L16-H16)/H16*100 -> 3.5189251 | M96: =(M16-I16)/I16*100 -> 0.74850974 | ... BY96: =(BY16-BU16)/BU16*100 -> 1.0791716
A97: Personal services | F97: =(F17-B17)/B17*100 -> 5.7713236 | G97: =(G17-C17)/C17*100 -> 2.4531531 | H97: =(H17-D17)/D17*100 -> 1.1896958 | I97: =(I17-E17)/E17*100 -> 1.3522793 | J97: =(J17-F17)/F17*100 -> -0.9165688 | K97: =(K17-G17)/G17*100 -> 0.60609854 | L97: =(L17-H17)/H17*100 -> 0.90048513 | M97: =(M17-I17)/I17*100 -> -0.71830735 | ... BY97: =(BY17-BU17)/BU17*100 -> 1.8675909
... A101: SA - GDP at constant 2005 prices | F101: =(F21-B21)/B21*100 -> 3.4539812 | G101: =(G21-C21)/C21*100 -> 5.0822925 | H101: =(H21-D21)/D21*100 -> 3.4602991 | I101: =(I21-E21)/E21*100 -> 3.6716673 | J101: =(J21-F21)/F21*100 -> 3.2447527 | K101: =(K21-G21)/G21*100 -> 3.2104634 | L101: =(L21-H21)/H21*100 -> 2.3144971 | M101: =(M21-I21)/I21*100 -> 1.5012597 | ... BY101: =(BY21-BU21)/BU21*100 -> 1.9729665
A103: KZN – GDPR by activity
A104: Annual Change
A105: Provincial Industry | B105: =B85 -> 1995q1 | C105: =C85 -> 1995q2 | D105: =D85 -> 1995q3 | E105: =E85 -> 1995q4 | F105: =F85 -> 1996q1 | G105: =G85 -> 1996q2 | H105: =H85 -> 1996q3 | I105: =I85 -> 1996q4 | ... BY105: =BY85 -> 2013q4
A106: Primary Industries | F106: =(F26-B26)/B26*100 -> 17.703826 | G106: =(G26-C26)/C26*100 -> 51.775911 | H106: =(H26-D26)/D26*100 -> 15.943346 | I106: =(I26-E26)/E26*100 -> 9.2366169 | J106: =(J26-F26)/F26*100 -> 4.190172 | K106: =(K26-G26)/G26*100 -> -1.7551418 | L106: =(L26-H26)/H26*100 -> -0.47329086 | M106: =(M26-I26)/I26*100 -> 0.33887655 | ... BY106: =(BY26-BU26)/BU26*100 -> 1.7581752
A107: Agriculture, forestry and fishing | F107: =(F27-B27)/B27*100 -> 3.00975 | G107: =(G27-C27)/C27*100 -> 57.94466 | H107: =(H27-D27)/D27*100 -> 5.4742333 | I107: =(I27-E27)/E27*100 -> -8.7511494 | J107: =(J27-F27)/F27*100 -> 9.0395909 | K107: =(K27-G27)/G27*100 -> -3.2011756 | L107: =(L27-H27)/H27*100 -> -1.9492089 | M107: =(M27-I27)/I27*100 -> -0.8474989 | ... BY107: =(BY27-BU27)/BU27*100 -> -0.85964701
A108: Mining and quarrying | F108: =(F28-B28)/B28*100 -> 38.799913 | G108: =(G28-C28)/C28*100 -> 38.816237 | H108: =(H28-D28)/D28*100 -> 39.171512 | I108: =(I28-E28)/E28*100 -> 40.375406 | J108: =(J28-F28)/F28*100 -> -0.97682828 | K108: =(K28-G28)/G28*100 -> 1.7013858 | L108: =(L28-H28)/H28*100 -> 2.0084896 | M108: =(M28-I28)/I28*100 -> 1.6738819 | ... BY108: =(BY28-BU28)/BU28*100 -> 7.6406457
A109: Secondary Industries | F109: =(F29-B29)/B29*100 -> 2.1616909 | G109: =(G29-C29)/C29*100 -> 1.6729677 | H109: =(H29-D29)/D29*100 -> 1.7142615 | I109: =(I29-E29)/E29*100 -> 3.4875278 | J109: =(J29-F29)/F29*100 -> 2.6680566 | K109: =(K29-G29)/G29*100 -> 4.5088803 | L109: =(L29-H29)/H29*100 -> 2.6389052 | M109: =(M29-I29)/I29*100 -> 2.2338721 | ... BY109: =(BY29-BU29)/BU29*100 -> 1.3881002
A110: Manufacturing | F110: =(F30-B30)/B30*100 -> 2.6270137 | G110: =(G30-C30)/C30*100 -> 1.5223053 | H110: =(H30-D30)/D30*100 -> 0.78570493 | I110: =(I30-E30)/E30*100 -> 2.1198529 | J110: =(J30-F30)/F30*100 -> 1.6219877 | K110: =(K30-G30)/G30*100 -> 4.2578844 | L110: =(L30-H30)/H30*100 -> 2.8327667 | M110: =(M30-I30)/I30*100 -> 1.9187054 | ... BY110: =(BY30-BU30)/BU30*100 -> 1.0891805
A111: Electricity, gas and water | F111: =(F31-B31)/B31*100 -> 2.1730722 | G111: =(G31-C31)/C31*100 -> 6.7696137 | H111: =(H31-D31)/D31*100 -> 13.796 | I111: =(I31-E31)/E31*100 -> 21.751983 | J111: =(J31-F31)/F31*100 -> 10.422539 | K111: =(K31-G31)/G31*100 -> 7.4797382 | L111: =(L31-H31)/H31*100 -> 0.50426793 | M111: =(M31-I31)/I31*100 -> -3.3088306 | ... BY111: =(BY31-BU31)/BU31*100 -> -0.29638623
A112: Construction | F112: =(F32-B32)/B32*100 -> -1.8041017 | G112: =(G32-C32)/C32*100 -> -1.9728089 | H112: =(H32-D32)/D32*100 -> -1.7114928 | I112: =(I32-E32)/E32*100 -> -1.4169083 | J112: =(J32-F32)/F32*100 -> 4.1956178 | K112: =(K32-G32)/G32*100 -> 3.5982077 | L112: =(L32-H32)/H32*100 -> 3.2578522 | M112: =(M32-I32)/I32*100 -> 12.10538 | ... BY112: =(BY32-BU32)/BU32*100 -> 4.6337583
A113: Tertiary industries | F113: =(F33-B33)/B33*100 -> 4.6352149 | G113: =(G33-C33)/C33*100 -> 4.4999611 | H113: =(H33-D33)/D33*100 -> 3.9487473 | I113: =(I33-E33)/E33*100 -> 3.761758 | J113: =(J33-F33)/F33*100 -> 2.3462571 | K113: =(K33-G33)/G33*100 -> 2.1666893 | L113: =(L33-H33)/H33*100 -> 1.2778353 | M113: =(M33-I33)/I33*100 -> 0.36513159 | ... BY113: =(BY33-BU33)/BU33*100 -> 1.7527707
A114: Wholesale & retail trade; hotels & restaurants | F114: =(F34-B34)/B34*100 -> 4.1858497 | G114: =(G34-C34)/C34*100 -> 3.1978631 | H114: =(H34-D34)/D34*100 -> 1.4485927 | I114: =(I34-E34)/E34*100 -> 0.62443809 | J114: =(J34-F34)/F34*100 -> 2.2730283 | K114: =(K34-G34)/G34*100 -> 1.3039444 | L114: =(L34-H34)/H34*100 -> 0.33073381 | M114: =(M34-I34)/I34*100 -> -1.2919777 | ... BY114: =(BY34-BU34)/BU34*100 -> 2.7120523
A115: Transport , storage and communication | F115: =(F35-B35)/B35*100 -> 6.1365244 | G115: =(G35-C35)/C35*100 -> 5.4093152 | H115: =(H35-D35)/D35*100 -> 4.0594576 | I115: =(I35-E35)/E35*100 -> 2.5059853 | J115: =(J35-F35)/F35*100 -> 3.908348 | K115: =(K35-G35)/G35*100 -> 5.3596148 | L115: =(L35-H35)/H35*100 -> 5.4370819 | M115: =(M35-I35)/I35*100 -> 7.4129791 | ... BY115: =(BY35-BU35)/BU35*100 -> 1.8095753
...

Sheet Seasonal
A1: Seasonally adjusted and annualised quarterly GDP and GDPR
A3: SA – GDP by activity
A4: Seasonally adjusted and annualised quarterly - Rand million
A5: National Industry | B5: 1995q1 | C5: 1995q2 | D5: 1995q3 | E5: 1995q4 | F5: 1996q1 | G5: 1996q2 | H5: 1996q3 | I5: 1996q4 | J5: 1997q1 | K5: 1997q2 | L5: 1997q3 | M5: 1997q4 | N5: 1998q1 | O5: 1998q2 | P5: 1998q3 | Q5: 1998q4 | R5: 1999q1 | S5: 1999q2 | T5: 1999q3 | U5: 1999q4 | V5: 2000q1 | W5: 2000q2 | X5: 2000q3 | Y5: 2000q4 | Z5: 2001q1 | AA5: 2001q2 | AB5: 2001q3 | AC5: 2001q4 | AD5: 2002q1 | AE5: 2002q2 | AF5: 2002q3 | AG5: 2002q4 | AH5: 2003q1 | AI5: 2003q2 | AJ5: 2003q3 | AK5: 2003q4 | AL5: 2004q1 | AM5: 2004q2 | AN5: 2004q3 | AO5: 2004q4 | AP5: 2005q1 | AQ5: 2005q2 | AR5: 2005q3 | AS5: 2005q4 | AT5: 2006q1 | AU5: 2006q2 | AV5: 2006q3 | AW5: 2006q4 | AX5: 2007q1 | AY5: 2007q2 | AZ5: 2007q3 | BA5: 2007q4 | BB5: 2008q1 | BC5: 2008q2 | BD5: 2008q3 | BE5: 2008q4 | BF5: 2009q1 | BG5: 2009q2 | BH5: 2009q3 | BI5: 2009q4 | BJ5: 2010q1 | BK5: 2010q2 | BL5: 2010q3 | BM5: 2010q4 | BN5: 2011q1 | BO5: 2011q2 | BP5: 2011q3 | BQ5: 2011q4 | BR5: 2012q1 | BS5: 2012q2 | BT5: 2012q3 | BU5: 2012q4 | BV5: 2013q1 | BW5: 2013q2 | BX5: 2013q3 | BY5: 2013q4
A6: Primary Industries | B6: =SUM(B7:B8) -> 133373 | C6: =SUM(C7:C8) -> 127184.8 | D6: =SUM(D7:D8) -> 124442.8 | E6: =SUM(E7:E8) -> 123826.1 | F6: =SUM(F7:F8) -> 129139.6 | G6: =SUM(G7:G8) -> 132327.8 | H6: =SUM(H7:H8) -> 134413.75 | I6: =SUM(I7:I8) -> 135068.8 | ... BY6: =SUM(BY7:BY8) -> 146847.62
A7: Agriculture, forestry and fishing | B7: 31290.9 | C7: 26457.8 | D7: 23928.8 | E7: 23943 | F7: 28270 | G7: 32804.8 | H7: 34746.8 | I7: 35147.8 | J7: 33071 | K7: 33177.09 | L7: 33089 | M7: 32811.03 | N7: 31718.09 | O7: 30974.1 | P7: 30885.06 | Q7: 31567.02 | R7: 32402 | S7: 32830.06 | T7: 33404.08 | U7: 34267.08 | V7: 34704 | W7: 34951.85 | X7: 34998 | Y7: 34495.85 | Z7: 33843.18 | AA7: 33637.18 | AB7: 33547.2 | AC7: 33530.18 | AD7: 34474.24 | AE7: 35617.24 | AF7: 36368.25 | AG7: 36844.26 | AH7: 36885 | AI7: 36566 | AJ7: 35527 | AK7: 35302 | AL7: 35495 | AM7: 35830 | AN7: 36614 | AO7: 37581 | AP7: 37373.26 | AQ7: 37308.26 | AR7: 37397.2 | AS7: 37529.26 | AT7: 36601.25 | AU7: 35381.25 | AV7: 34765.25 | AW7: 34688.25 | AX7: 35214.75 | AY7: 36013.75 | AZ7: 36397.75 | BA7: 37577.75 | BB7: 39666 | BC7: 40889 | BD7: 43507.56 | BE7: 44510 | BF7: 43807.381 | BG7: 41943.561 | BH7: 40526.107 | BI7: 39539.515 | BJ7: 39896.66 | BK7: 40934.132 | BL7: 42351.42 | BM7: 43273.388 | BN7: 42772.756 | BO7: 41754.204 | BP7: 41118.86 | BQ7: 40701.584 | BR7: 41140.968 | BS7: 42036.284 | BT7: 42767.704 | BU7: 43788.808 | BV7: 43303.4 | BW7: 42973.5 | BX7: 43352 | BY7: 44027.66
A8: Mining and quarrying | B8: 102082.1 | C8: 100727 | D8: 100514 | E8: 99883.1 | F8: 100869.6 | G8: 99523 | H8: 99666.95 | I8: 99921 | J8: 100331.64 | K8: 101582.75 | L8: 102367.86 | M8: 102498 | N8: 102851.9 | O8: 101868.9 | P8: 100962.9 | Q8: 100689.75 | R8: 100610.76 | S8: 99885.47 | T8: 99930 | U8: 100258 | V8: 99627.29 | W8: 99309.29 | X8: 98476.28 | Y8: 98863.84 | Z8: 99136.6 | AA8: 99612 | AB8: 98944 | AC8: 98187.8 | AD8: 98767.35 | AE8: 99500.99 | AF8: 100420.99 | AG8: 101149.9 | AH8: 101736.77 | AI8: 102869.16 | AJ8: 104166.16 | AK8: 104647.18 | AL8: 105177.85 | AM8: 103888.03 | AN8: 106665.1 | AO8: 103930.07 | AP8: 107173.44 | AQ8: 106321.44 | AR8: 105532.44 | AS8: 104940.28 | AT8: 102888.74 | AU8: 104578.75 | AV8: 106098.7 | AW8: 107890.84 | AX8: 107892.49 | AY8: 105130.41 | AZ8: 104953.41 | BA8: 103366.41 | BB8: 98885.23 | BC8: 101296.49 | BD8: 98738.35 | BE8: 98663.35 | BF8: 92248.226 | BG8: 95085.82 | BH8: 93790.161 | BI8: 95105.229 | BJ8: 99373.384 | BK8: 93684.964 | BL8: 100371.68 | BM8: 104102.65 | BN8: 102510.02 | BO8: 102042.35 | BP8: 97288.533 | BQ8: 96907.978 | BR8: 93654.089 | BS8: 99097.919 | BT8: 96750.803 | BU8: 94826.466 | BV8: 97848.617 | BW8: 96499.067 | BX8: 99136.127 | BY8: 102819.96
A9: Secondary Industries | B9: =SUM(B10:B12) -> 246007.39 | C9: =SUM(C10:C12) -> 248517.85 | D9: =SUM(D10:D12) -> 250162.46 | E9: =SUM(E10:E12) -> 248497.1 | F9: =SUM(F10:F12) -> 251410.85 | G9: =SUM(G10:G12) -> 252330.73 | H9: =SUM(H10:H12) -> 255361.34 | I9: =SUM(I10:I12) -> 258332.3 | ... BY9: =SUM(BY10:BY12) -> 401824.97
A10: Manufacturing | B10: 194628.11 | C10: 197102.32 | D10: 198721.54 | E10: 197285.03 | F10: 199071.15 | G10: 198606.88 | H10: 199813.99 | I10: 201273.3 | J10: 202534.33 | K10: 206314.16 | L10: 205990.74 | M10: 205492.76 | N10: 206382.92 | O10: 206222.12 | P10: 203584.56 | Q10: 202501.73 | R10: 202099.98 | S10: 203577.69 | T10: 206838.46 | U10: 211087.34 | V10: 216503.16 | W10: 220045.4 | X10: 224646.4 | Y10: 229120.4 | Z10: 230455 | AA10: 230456.6 | AB10: 227993.84 | AC10: 229900 | AD10: 231756.8 | AE10: 235806.6 | AF10: 238454.6 | AG10: 238514 | AH10: 236290.6 | AI10: 233308.6 | AJ10: 231010.8 | AK10: 229714 | AL10: 236527 | AM10: 242273 | AN10: 248060 | AO10: 249000 | AP10: 248956.8 | AQ10: 258604.5 | AR10: 264530.9 | AS10: 264313 | AT10: 267966.4 | AU10: 273087.4 | AV10: 278429.4 | AW10: 283646.4 | AX10: 287789.69 | AY10: 289015.44 | AZ10: 288930.44 | BA10: 295248.44 | BB10: 295084 | BC10: 307058 | BD10: 301849.1 | BE10: 287563.18 | BF10: 268495.88 | BG10: 261288.96 | BH10: 266955.66 | BI10: 274149.79 | BJ10: 278597.44 | BK10: 283831.44 | BL10: 282132.45 | BM10: 285473.5 | BN10: 293990 | BO10: 290367.48 | BP10: 289892.9 | BQ10: 292890.19 | BR10: 297291.66 | BS10: 296490.91 | BT10: 297126.3 | BU10: 300324.39 | BV10: 294242.69 | BW10: 302494.88 | BX10: 297341.06 | BY10: 306123.08
A11: Electricity, gas and water | B11: 25998.096 | C11: 26008.454 | D11: 25849.434 | E11: 25517.041 | F11: 26601 | G11: 27716.587 | H11: 29386.4 | I11: 30833.343 | J11: 30179.521 | K11: 30258.817 | L11: 29646.58 | M11: 28919.365 | N11: 28371.857 | O11: 27991.318 | P11: 27582.45 | Q11: 27561.393 | R11: 27349.545 | S11: 27625.688 | T11: 27761.07 | U11: 28213.174 | V11: 28500.23 | W11: 28707.45 | X11: 28817.98 | Y11: 28363.25 | Z11: 27897 | AA11: 27506.28 | AB11: 27457.12 | AC11: 27296.12 | AD11: 27721.23 | AE11: 28366.25 | AF11: 28720.29 | AG11: 29204.23 | AH11: 29190 | AI11: 29199 | AJ11: 29329 | AK11: 29658 | AL11: 30218 | AM11: 30804 | AN11: 31849 | AO11: 32469 | AP11: 32480.45 | AQ11: 32784.45 | AR11: 33039.45 | AS11: 33736.45 | AT11: 33979 | AU11: 34075 | AV11: 34140 | AW11: 34362 | AX11: 34883.75 | AY11: 35189.75 | AZ11: 35536.75 | BA11: 35565.75 | BB11: 34073.668 | BC11: 33912.846 | BD11: 35015.705 | BE11: 33780.341 | BF11: 33410.481 | BG11: 33584.379 | BH11: 33874.71 | BI11: 33978.07 | BJ11: 34486.265 | BK11: 34445.587 | BL11: 34362.974 | BM11: 34857.779 | BN11: 35055.263 | BO11: 35135.822 | BP11: 34969.275 | BQ11: 35035.865 | BR11: 34853.046 | BS11: 34394.197 | BT11: 34442.524 | BU11: 34215.5 | BV11: 33977.22 | BW11: 34400.228 | BX11: 34726.088 | BY11: 34227.886
A12: Construction | B12: 25381.18 | C12: 25407.07 | D12: 25591.49 | E12: 25695.03 | F12: 25738.7 | G12: 26007.26 | H12: 26160.95 | I12: 26225.66 | J12: 26521.71 | K12: 26853.35 | L12: 27091.17 | M12: 27251.32 | N12: 25858.67 | O12: 25258.26 | P12: 25028.11 | Q12: 25223.24 | R12: 24943.05 | S12: 24921.79 | T12: 25000.59 | U12: 25126.92 | V12: 25417.12 | W12: 25995.01 | X12: 26781.79 | Y12: 27447.24 | Z12: 27428.48 | AA12: 27661.13 | AB12: 27746.19 | AC12: 28008.87 | AD12: 28432 | AE12: 28865 | AF12: 29568 | AG12: 30419 | AH12: 30917 | AI12: 31329 | AJ12: 31723 | AK12: 32331 | AL12: 33044 | AM12: 33967 | AN12: 34899 | AO12: 35894 | AP12: 36871 | AQ12: 37955 | AR12: 39155 | AS12: 40251 | AT12: 40916 | AU12: 42027 | AV12: 43170 | AW12: 44215 | AX12: 46588 | AY12: 48251 | AZ12: 49269 | BA12: 51776 | BB12: 51779.38 | BC12: 52536.38 | BD12: 53987.38 | BE12: 54278.38 | BF12: 56398.5 | BG12: 56669.5 | BH12: 57787.5 | BI12: 58258.58 | BJ12: 58013.9 | BK12: 57646.9 | BL12: 57516.8 | BM12: 57650 | BN12: 57816.48 | BO12: 57845.48 | BP12: 57858.45 | BQ12: 57957.42 | BR12: 58765.4 | BS12: 58803.4 | BT12: 59293.4 | BU12: 59963.24 | BV12: 60340 | BW12: 60690 | BX12: 61012 | BY12: 61474
A13: Tertiary industries | B13: =SUM(B14:B18) -> 626563.28 | C13: =SUM(C14:C18) -> 633262.94 | D13: =SUM(D14:D18) -> 639944.44 | E13: =SUM(E14:E18) -> 645002.21 | F13: =SUM(F14:F18) -> 652193.74 | G13: =SUM(G14:G18) -> 658834.58 | H13: =SUM(H14:H18) -> 666483.1 | I13: =SUM(I14:I18) -> 674005.7 | ... BY13: =SUM(BY14:BY18) -> 1247453.1
A14: Wholesale & retail trade; hotels & restaurants | B14: 127925.84 | C14: 130390.84 | D14: 133118.84 | E14: 135165.84 | F14: 134951.16 | G14: 135795.16 | H14: 136927.16 | I14: 138412.16 | J14: 138807.24 | K14: 137901.24 | L14: 137075.24 | M14: 134486.24 | N14: 137693.48 | O14: 138871 | P14: 139397 | Q14: 139436 | R14: 144092.68 | S14: 147438 | T14: 151255 | U14: 154822 | V14: 157962.49 | W14: 160959.49 | X14: 163044.49 | Y14: 164047.44 | Z14: 164354.47 | AA14: 164526.49 | AB14: 164505.82 | AC14: 164901.39 | AD14: 166141.99 | AE14: 167516.49 | AF14: 168516.59 | AG14: 171253.7 | AH14: 171482 | AI14: 172200 | AJ14: 173345 | AK14: 174353.8 | AL14: 176707 | AM14: 180030 | AN14: 183779 | AO14: 188184 | AP14: 190502.45 | AQ14: 193389.45 | AR14: 196153.45 | AS14: 200003.45 | AT14: 202191.25 | AU14: 205171.25 | AV14: 208124.25 | AW14: 211057.25 | AX14: 213894 | AY14: 216487 | AZ14: 218970 | BA14: 221077 | BB14: 222921.05 | BC14: 220888.23 | BD14: 217708.26 | BE14: 217479.02 | BF14: 217162.87 | BG14: 216071.67 | BH14: 217024.42 | BI14: 218036.72 | BJ14: 220587.7 | BK14: 224300.19 | BL14: 226849.19 | BM14: 229613.14 | BN14: 230877.2 | BO14: 233729.95 | BP14: 236870.7 | BQ14: 239700.35 | BR14: 242051.89 | BS14: 243802 | BT14: 245094.9 | BU14: 246163.79 | BV14: 247424.24 | BW14: 249301.81 | BX14: 250127.7 | BY14: 251573.42
A15: Transport , storage and communication | B15: 72174.485 | C15: 74125.88 | D15: 75980.39 | E15: 77596.263 | F15: 78010.558 | G15: 79051.094 | H15: 80304.86 | I15: 80802.993 | J15: 82833.938 | K15: 84562.078 | L15: 86469.599 | M15: 88484.784 | N15: 89744.46 | O15: 90491.869 | P15: 90065.27 | Q15: 90878.071 | R15: 91956.843 | S15: 94032.948 | T15: 96060.26 | U15: 97910.963 | V15: 100224.75 | W15: 102457.21 | X15: 103965.87 | Y15: 104849.95 | Z15: 105914.75 | AA15: 107509.02 | AB15: 109787.36 | AC15: 112565 | AD15: 115300.4 | AE15: 117932.4 | AF15: 119950.2 | AG15: 121813 | AH15: 124004 | AI15: 125437 | AJ15: 126765 | AK15: 128942 | AL15: 130153 | AM15: 131416 | AN15: 133261 | AO15: 135006 | AP15: 136575.36 | AQ15: 138587.2 | AR15: 140461.83 | AS15: 142262.79 | AT15: 144262 | AU15: 146065 | AV15: 147504 | AW15: 148597 | AX15: 151988 | AY15: 155591 | AZ15: 157925 | BA15: 159652 | BB15: 160749.81 | BC15: 161990 | BD15: 163314.79 | BE15: 164033.55 | BF15: 163356.08 | BG15: 163204.26 | BH15: 164140.46 | BI15: 165296.96 | BJ15: 165661.1 | BK15: 166838.78 | BL15: 167795.58 | BM15: 168958.14 | BN15: 170530.59 | BO15: 172240.09 | BP15: 173098.97 | BQ15: 174250.75 | BR15: 175400.73 | BS15: 176438.58 | BT15: 177034.93 | BU15: 177923.36 | BV15: 178856.2 | BW15: 179524.82 | BX15: 180675.71 | BY15: 181377.1
A16: Finance, real estate and business services | B16: 172965.6 | C16: 174028.9 | D16: 175457.9 | E16: 176427.6 | F16: 180089.5 | G16: 184353.1 | H16: 188753 | I16: 193106 | J16: 194069.1 | K16: 195117.7 | L16: 195721.6 | M16: 196514.8 | N16: 197019 | O16: 199794.7 | P16: 201259.6 | Q16: 201338.7 | R16: 206855.4 | S16: 209138.6 | T16: 211456.6 | U16: 212815.8 | V16: 213916.05 | W16: 214717.81 | X16: 217314.52 | Y16: 221040.41 | Z16: 227158 | AA16: 232269 | AB16: 236841.9 | AC16: 241531.5 | AD16: 247019 | AE16: 250251 | AF16: 249344 | AG16: 250046 | AH16: 255989 | AI16: 259461 | AJ16: 263376 | AK16: 265666 | AL16: 273173 | AM16: 278446 | AN16: 281244 | AO16: 285313 | AP16: 288187.1 | AQ16: 293692.1 | AR16: 299077.1 | AS16: 301060.1 | AT16: 312688 | AU16: 320797 | AV16: 328856 | AW16: 333667 | AX16: 339870 | AY16: 344026 | AZ16: 353202 | BA16: 360906 | BB16: 368838 | BC16: 370801 | BD16: 377891 | BE16: 383434 | BF16: 381408.7 | BG16: 377162.8 | BH16: 377752.9 | BI16: 379622.84 | BJ16: 382799.84 | BK16: 386437.6 | BL16: 388333.6 | BM16: 391183.6 | BN16: 397688.4 | BO16: 402431.4 | BP16: 408477.04 | BQ16: 413320.04 | BR16: 417753.39 | BS16: 419790.36 | BT16: 420981.36 | BU16: 423368.36 | BV16: 426778 | BW16: 430491 | BX16: 431746 | BY16: 433373
A17: Personal services | B17: 62694.603 | C17: 63742.571 | D17: 64275.56 | E17: 64565.754 | F17: 66380.219 | G17: 65352.93 | H17: 65005.676 | I17: 65325.546 | J17: 65215.241 | K17: 65391.765 | L17: 65655.314 | M17: 65721.63 | N17: 67643.138 | O17: 69056.157 | P17: 70324.735 | Q17: 71226.686 | R17: 71498.258 | S17: 71947.778 | T17: 72510.787 | U17: 73059.786 | V17: 74272.374 | W17: 75206.633 | X17: 76303.342 | Y17: 77160.368 | Z17: 77237.077 | AA17: 77268.208 | AB17: 77466.021 | AC17: 77781.154 | AD17: 78152.786 | AE17: 78818.682 | AF17: 79641.229 | AG17: 80771.303 | AH17: 82271 | AI17: 83534 | AJ17: 84453 | AK17: 84766 | AL17: 84952 | AM17: 84758 | AN17: 85264 | AO17: 85902 | AP17: 86750.45 | AQ17: 87984.45 | AR17: 89076.44 | AS17: 90007.44 | AT17: 91625 | AU17: 92686 | AV17: 93648 | AW17: 94333 | AX17: 95873 | AY17: 97348.16 | AZ17: 98981.4 | BA17: 100785.44 | BB17: 101291.85 | BC17: 101678.85 | BD17: 102477.85 | BE17: 102974.85 | BF17: 102295.87 | BG17: 101939.98 | BH17: 100890.23 | BI17: 99806.35 | BJ17: 100390.47 | BK17: 101418.26 | BL17: 102147.1 | BM17: 102727.58 | BN17: 103190 | BO17: 103795.02 | BP17: 104268.29 | BQ17: 104849.59 | BR17: 105289.82 | BS17: 105856.41 | BT17: 106472.99 | BU17: 107104.2 | BV17: 107428.97 | BW17: 107854.06 | BX17: 108272.6 | BY17: 108624.56
A18: General government services | B18: 190802.75 | C18: 190974.75 | D18: 191111.75 | E18: 191246.75 | F18: 192762.3 | G18: 194282.3 | H18: 195492.4 | I18: 196359 | J18: 196706.5 | K18: 196425.5 | L18: 196059.5 | M18: 195848.5 | N18: 195565.75 | O18: 195073.75 | P18: 194441.75 | Q18: 194082.75 | R18: 193953.25 | S18: 193609.25 | T18: 192938.25 | U18: 192015.25 | V18: 192116.35 | W18: 191769.33 | X18: 191140.33 | Y18: 190334 | Z18: 190881 | AA18: 190058 | AB18: 188887 | AC18: 188382 | AD18: 189812 | AE18: 190650 | AF18: 191372 | AG18: 191806 | AH18: 194417 | AI18: 195608 | AJ18: 196837 | AK18: 197910 | AL18: 197807 | AM18: 199194 | AN18: 200172 | AO18: 202615 | AP18: 206152.8 | AQ18: 208556.8 | AR18: 209758.8 | AS18: 209774.8 | AT18: 212675 | AU18: 214060 | AV18: 215131 | AW18: 217922 | AX18: 221741 | AY18: 221740 | AZ18: 223747 | BA18: 225908 | BB18: 230291 | BC18: 231514 | BD18: 234992 | BE18: 236867 | BF18: 239679 | BG18: 242634 | BH18: 243332 | BI18: 244523 | BJ18: 246435 | BK18: 248896 | BL18: 250950 | BM18: 253775 | BN18: 256790 | BO18: 259378 | BP18: 261338 | BQ18: 264470 | BR18: 265096 | BS18: 266046 | BT18: 268340 | BU18: 271374 | BV18: 271420 | BW18: 271578 | BX18: 271873 | BY18: 272505
A19: All industries at basic prices | B19: =B13+B9+B6 -> 1005943.7 | C19: =C13+C9+C6 -> 1008965.6 | D19: =D13+D9+D6 -> 1014549.7 | E19: =E13+E9+E6 -> 1017325.4 | F19: =F13+F9+F6 -> 1032744.2 | G19: =G13+G9+G6 -> 1043493.1 | H19: =H13+H9+H6 -> 1056258.2 | I19: =I13+I9+I6 -> 1067406.8 | ... BY19: =BY13+BY9+BY6 -> 1796125.7
A20: Taxes less subsidies on products | B20: 132946.05 | C20: 132962.85 | D20: 134127.7 | E20: 134670.27 | F20: 135976.8 | G20: 140029.49 | H20: 141550.41 | I20: 143278.71 | J20: 143769.84 | K20: 144223.13 | L20: 144500.14 | M20: 144726.18 | N20: 143956.7 | O20: 142659.39 | P20: 142000.07 | Q20: 142028.39 | R20: 141255.71 | S20: 141135.4 | T20: 142113.33 | U20: 143055.3 | V20: 143078.31 | W20: 143435.57 | X20: 144561.09 | Y20: 145441.67 | Z20: 145401.66 | AA20: 145671.85 | AB20: 146315.31 | AC20: 147415.9 | AD20: 148453 | AE20: 149248 | AF20: 151557 | AG20: 151402 | AH20: 153027 | AI20: 153614 | AJ20: 154317 | AK20: 155814 | AL20: 157635 | AM20: 160698 | AN20: 163718 | AO20: 165709 | AP20: 166049.2 | AQ20: 169472.27 | AR20: 171809.27 | AS20: 172729.27 | AT20: 175089 | AU20: 179620 | AV20: 181162 | AW20: 186649 | AX20: 188243 | AY20: 188504 | AZ20: 190892 | BA20: 192717 | BB20: 194190 | BC20: 194841 | BD20: 195972 | BE20: 194165 | BF20: 190323 | BG20: 186658 | BH20: 187667 | BI20: 190708 | BJ20: 193146 | BK20: 194448 | BL20: 196740 | BM20: 198598 | BN20: 202308 | BO20: 204294 | BP20: 206285 | BQ20: 209281 | BR20: 209692 | BS20: 210861 | BT20: 211582 | BU20: 212229 | BV20: 213453 | BW20: 215093 | BX20: 216192 | BY20: 217178
A21: SA - GDP at constant 2005 prices | B21: =B19+B20 -> 1138889.7 | C21: =C19+C20 -> 1141928.4 | D21: =D19+D20 -> 1148677.4 | E21: =E19+E20 -> 1151995.7 | F21: =F19+F20 -> 1168721 | G21: =G19+G20 -> 1183522.6 | H21: =H19+H20 -> 1197808.6 | I21: =I19+I20 -> 1210685.5 | ... BY21: =BY19+BY20 -> 2013303.7
A23: KZN – GDPR by activity
A24: Seasonally adjusted and annualised quarterly - Rand million
A25: Provincial Industry | B25: 1995q1 | C25: 1995q2 | D25: 1995q3 | E25: 1995q4 | F25: 1996q1 | G25: 1996q2 | H25: 1996q3 | I25: 1996q4 | J25: 1997q1 | K25: 1997q2 | L25: 1997q3 | M25: 1997q4 | N25: 1998q1 | O25: 1998q2 | P25: 1998q3 | Q25: 1998q4 | R25: 1999q1 | S25: 1999q2 | T25: 1999q3 | U25: 1999q4 | V25: 2000q1 | W25: 2000q2 | X25: 2000q3 | Y25: 2000q4 | Z25: 2001q1 | AA25: 2001q2 | AB25: 2001q3 | AC25: 2001q4 | AD25: 2002q1 | AE25: 2002q2 | AF25: 2002q3 | AG25: 2002q4 | AH25: 2003q1 | AI25: 2003q2 | AJ25: 2003q3 | AK25: 2003q4 | AL25: 2004q1 | AM25: 2004q2 | AN25: 2004q3 | AO25: 2004q4 | AP25: 2005q1 | AQ25: 2005q2 | AR25: 2005q3 | AS25: 2005q4 | AT25: 2006q1 | AU25: 2006q2 | AV25: 2006q3 | AW25: 2006q4 | AX25: 2007q1 | AY25: 2007q2 | AZ25: 2007q3 | BA25: 2007q4 | BB25: 2008q1 | BC25: 2008q2 | BD25: 2008q3 | BE25: 2008q4 | BF25: 2009q1 | BG25: 2009q2 | BH25: 2009q3 | BI25: 2009q4 | BJ25: =BJ5 -> 2010q1 | BK25: =BK5 -> 2010q2 | BL25: =BL5 -> 2010q3 | BM25: =BM5 -> 2010q4 | BN25: =BN5 -> 2011q1 | BO25: =BO5 -> 2011q2 | BP25: =BP5 -> 2011q3 | BQ25: =BQ5 -> 2011q4 | ... BY25: =BY5 -> 2013q4
A26: Primary Industries | B26: =SUM(B27:B28) -> 14228.71 | C26: =SUM(C27:C28) -> 12660.621 | D26: =SUM(D27:D28) -> 11861.765 | E26: =SUM(E27:E28) -> 11838.635 | F26: =SUM(F27:F28) -> 14467.903 | G26: =SUM(G27:G28) -> 15713.524 | H26: =SUM(H27:H28) -> 16291.159 | I26: =SUM(I27:I28) -> 16424.195 | ... BY26: =SUM(BY27:BY28) -> 16783.789
A27: Agriculture, forestry and fishing | B27: =B7/Quarterly!B7*Quarterly!B27 -> 9768.9831 | C27: =C7/Quarterly!C7*Quarterly!C27 -> 8260.0948 | D27: =D7/Quarterly!D7*Quarterly!D27 -> 7470.5439 | E27: =E7/Quarterly!E7*Quarterly!E27 -> 7474.9771 | F27: =F7/Quarterly!F7*Quarterly!F27 -> 8280.1806 | G27: =G7/Quarterly!G7*Quarterly!G27 -> 9608.4071 | H27: =H7/Quarterly!H7*Quarterly!H27 -> 10177.212 | I27: =I7/Quarterly!I7*Quarterly!I27 -> 10294.663 | ... BY27: =BY7/Quarterly!BY7*Quarterly!BY27 -> 13064.195
A28: Mining and quarrying | B28: =B8/Quarterly!B8*Quarterly!B28 -> 4459.7274 | C28: =C8/Quarterly!C8*Quarterly!C28 -> 4400.5263 | D28: =D8/Quarterly!D8*Quarterly!D28 -> 4391.2208 | E28: =E8/Quarterly!E8*Quarterly!E28 -> 4363.6583 | F28: =F8/Quarterly!F8*Quarterly!F28 -> 6187.7221 | G28: =G8/Quarterly!G8*Quarterly!G28 -> 6105.1166 | H28: =H8/Quarterly!H8*Quarterly!H28 -> 6113.9471 | I28: =I8/Quarterly!I8*Quarterly!I28 -> 6129.5314 | ... BY28: =BY8/Quarterly!BY8*Quarterly!BY28 -> 3719.5938
A29: Secondary Industries | B29: =SUM(B30:B32) -> 49820.231 | C29: =SUM(C30:C32) -> 50344.403 | D29: =SUM(D30:D32) -> 50688.782 | E29: =SUM(E30:E32) -> 50349.048 | F29: =SUM(F30:F32) -> 50903.247 | G29: =SUM(G30:G32) -> 51046.92 | H29: =SUM(H30:H32) -> 51618.214 | I29: =SUM(I30:I32) -> 52188.151 | ... BY29: =SUM(BY30:BY32) -> 79775.058
A30: Manufacturing | B30: =B10/Quarterly!B10*Quarterly!B30 -> 40724.063 | C30: =C10/Quarterly!C10*Quarterly!C30 -> 41241.767 | D30: =D10/Quarterly!D10*Quarterly!D30 -> 41580.573 | E30: =E10/Quarterly!E10*Quarterly!E30 -> 41279.998 | F30: =F10/Quarterly!F10*Quarterly!F30 -> 41796.674 | G30: =G10/Quarterly!G10*Quarterly!G30 -> 41699.197 | H30: =H10/Quarterly!H10*Quarterly!H30 -> 41952.639 | I30: =I10/Quarterly!I10*Quarterly!I30 -> 42259.033 | ... BY30: =BY10/Quarterly!BY10*Quarterly!BY30 -> 65253.964
A31: Electricity, gas and water | B31: =B11/Quarterly!B11*Quarterly!B31 -> 4522.2191 | C31: =C11/Quarterly!C11*Quarterly!C31 -> 4524.0208 | D31: =D11/Quarterly!D11*Quarterly!D31 -> 4496.3603 | E31: =E11/Quarterly!E11*Quarterly!E31 -> 4438.5424 | F31: =F11/Quarterly!F11*Quarterly!F31 -> 4638.5358 | G31: =G11/Quarterly!G11*Quarterly!G31 -> 4833.0657 | H31: =H11/Quarterly!H11*Quarterly!H31 -> 5124.2385 | I31: =I11/Quarterly!I11*Quarterly!I31 -> 5376.5484 | ... BY31: =BY11/Quarterly!BY11*Quarterly!BY31 -> 5491.6042
A32: Construction | B32: =B12/Quarterly!B12*Quarterly!B32 -> 4573.9491 | C32: =C12/Quarterly!C12*Quarterly!C32 -> 4578.6148 | D32: =D12/Quarterly!D12*Quarterly!D32 -> 4611.8491 | E32: =E12/Quarterly!E12*Quarterly!E32 -> 4630.5081 | F32: =F12/Quarterly!F12*Quarterly!F32 -> 4468.0373 | G32: =G12/Quarterly!G12*Quarterly!G32 -> 4514.6572 | H32: =H12/Quarterly!H12*Quarterly!H32 -> 4541.3366 | I32: =I12/Quarterly!I12*Quarterly!I32 -> 4552.5698 | ... BY32: =BY12/Quarterly!BY12*Quarterly!BY32 -> 9029.4901
A33: Tertiary industries | B33: =SUM(B34:B38) -> 98056.642 | C33: =SUM(C34:C38) -> 99254.92 | D33: =SUM(D34:D38) -> 100435.15 | E33: =SUM(E34:E38) -> 101345.11 | F33: =SUM(F34:F38) -> 102322.66 | G33: =SUM(G34:G38) -> 103335.11 | H33: =SUM(H34:H38) -> 104529.9 | I33: =SUM(I34:I38) -> 105662.78 | ... BY33: =SUM(BY34:BY38) -> 199416.26
A34: Wholesale & retail trade; hotels & restaurants | B34: =B14/Quarterly!B14*Quarterly!B34 -> 20751.667 | C34: =C14/Quarterly!C14*Quarterly!C34 -> 21151.53 | D34: =D14/Quarterly!D14*Quarterly!D34 -> 21594.057 | E34: =E14/Quarterly!E14*Quarterly!E34 -> 21926.114 | F34: =F14/Quarterly!F14*Quarterly!F34 -> 21584.562 | G34: =G14/Quarterly!G14*Quarterly!G34 -> 21719.554 | H34: =H14/Quarterly!H14*Quarterly!H34 -> 21900.61 | I34: =I14/Quarterly!I14*Quarterly!I34 -> 22138.127 | ... BY34: =BY14/Quarterly!BY14*Quarterly!BY34 -> 44072.885
A35: Transport , storage and communication | B35: =B15/Quarterly!B15*Quarterly!B35 -> 16815.873 | C35: =C15/Quarterly!C15*Quarterly!C35 -> 17270.526 | D35: =D15/Quarterly!D15*Quarterly!D35 -> 17702.607 | E35: =E15/Quarterly!E15*Quarterly!E35 -> 18079.088 | F35: =F15/Quarterly!F15*Quarterly!F35 -> 17895.904 | G35: =G15/Quarterly!G15*Quarterly!G35 -> 18134.607 | H35: =H15/Quarterly!H15*Quarterly!H35 -> 18422.226 | I35: =I15/Quarterly!I15*Quarterly!I35 -> 18536.499 | ... BY35: =BY15/Quarterly!BY15*Quarterly!BY35 -> 39692.165
A36: Finance, real estate and business services | B36: =B16/Quarterly!B16*Quarterly!B36 -> 24152.346 | C36: =C16/Quarterly!C16*Quarterly!C36 -> 24300.821 | D36: =D16/Quarterly!D16*Quarterly!D36 -> 24500.362 | E36: =E16/Quarterly!E16*Quarterly!E36 -> 24635.768 | F36: =F16/Quarterly!F16*Quarterly!F36 -> 25161.25 | G36: =G16/Quarterly!G16*Quarterly!G36 -> 25756.94 | H36: =H16/Quarterly!H16*Quarterly!H36 -> 26371.673 | I36: =I16/Quarterly!I16*Quarterly!I36 -> 26979.853 | ... BY36: =BY16/Quarterly!BY16*Quarterly!BY36 -> 60210.001
A37: Personal services | B37: =B17/Quarterly!B17*Quarterly!B37 -> 10277.606 | C37: =C17/Quarterly!C17*Quarterly!C37 -> 10449.401 | D37: =D17/Quarterly!D17*Quarterly!D37 -> 10536.775 | E37: =E17/Quarterly!E17*Quarterly!E37 -> 10584.346 | F37: =F17/Quarterly!F17*Quarterly!F37 -> 10875.559 | G37: =G17/Quarterly!G17*Quarterly!G37 -> 10707.25 | H37: =H17/Quarterly!H17*Quarterly!H37 -> 10650.357 | I37: =I17/Quarterly!I17*Quarterly!I37 -> 10702.764 | ... BY37: =BY17/Quarterly!BY17*Quarterly!BY37 -> 17961.161
A38: General government services | B38: =B18/Quarterly!B18*Quarterly!B38 -> 26059.15 | C38: =C18/Quarterly!C18*Quarterly!C38 -> 26082.641 | D38: =D18/Quarterly!D18*Quarterly!D38 -> 26101.352 | E38: =E18/Quarterly!E18*Quarterly!E38 -> 26119.79 | F38: =F18/Quarterly!F18*Quarterly!F38 -> 26805.385 | G38: =G18/Quarterly!G18*Quarterly!G38 -> 27016.755 | H38: =H18/Quarterly!H18*Quarterly!H38 -> 27185.031 | I38: =I18/Quarterly!I18*Quarterly!I38 -> 27305.539 | ... BY38: =BY18/Quarterly!BY18*Quarterly!BY38 -> 37480.045
A39: All industries at basic prices | B39: =B33+B29+B26 -> 162105.58 | C39: =C33+C29+C26 -> 162259.94 | D39: =D33+D29+D26 -> 162985.7 | E39: =E33+E29+E26 -> 163532.79 | F39: =F33+F29+F26 -> 167693.81 | G39: =G33+G29+G26 -> 170095.55 | H39: =H33+H29+H26 -> 172439.27 | I39: =I33+I29+I26 -> 174275.13 | ... BY39: =BY33+BY29+BY26 -> 295975.1
A40: Taxes less subsidies on products | B40: =B20/Quarterly!B20*Quarterly!B40 -> 21413.035 | C40: =C20/Quarterly!C20*Quarterly!C40 -> 21415.741 | D40: =D20/Quarterly!D20*Quarterly!D40 -> 21603.358 | E40: =E20/Quarterly!E20*Quarterly!E40 -> 21690.748 | F40: =F20/Quarterly!F20*Quarterly!F40 -> 21977.695 | G40: =G20/Quarterly!G20*Quarterly!G40 -> 22632.725 | H40: =H20/Quarterly!H20*Quarterly!H40 -> 22878.549 | I40: =I20/Quarterly!I20*Quarterly!I40 -> 23157.891 | ... BY40: =BY20/Quarterly!BY20*Quarterly!BY40 -> 34961.923
A41: KZN - GDPR at constant 2005 prices | B41: =B39+B40 -> 183518.62 | C41: =C39+C40 -> 183675.68 | D41: =D39+D40 -> 184589.06 | E41: =E39+E40 -> 185223.54 | F41: =F39+F40 -> 189671.51 | G41: =G39+G40 -> 192728.28 | H41: =H39+H40 -> 195317.82 | I41: =I39+I40 -> 197433.02 | ... BY41: =BY39+BY40 -> 330937.03
BD42: =BD41-BD27 -> 285988.08 | BE42: =BE41-BE27 -> 283722.61 | BF42: =BF41-BF27 -> 280127.38 | BG42: =BG41-BG27 -> 277708.8 | BH42: =BH41-BH27 -> 279612.67 | BI42: =(BH42-BD42)/BD42*100 -> -2.2292551 | BJ42: =(BH42-BD42)/BD42*100 -> -2.2292551 | BK42: =(BI42-BE42)/BE42*100 -> -100.00079 | BL42: =(BJ42-BF42)/BF42*100 -> -100.0008 | BM42: =(BK42-BG42)/BG42*100 -> -100.03601 | BN42: =(BK42-BG42)/BG42*100 -> -100.03601 | BO42: =(BL42-BH42)/BH42*100 -> -100.03576 | BP42: =(BM42-BI42)/BI42*100 -> 4387.4187 | BQ42: =(BM42-BI42)/BI42*100 -> 4387.4187 | BR42: =(BM42-BI42)/BI42*100 -> 4387.4187 | BS42: =(BN42-BJ42)/BJ42*100 -> 4387.4187 | BT42: =(BN42-BJ42)/BJ42*100 -> 4387.4187 | BV42: =(BN42-BJ42)/BJ42*100 -> 4387.4187 | BX42: =(BO42-BK42)/BK42*100 -> 0.034978051 | BY42: =(BP42-BL42)/BL42*100 -> -4487.3838
A43: SA – GDP by activity
A44: Quarterly Change
A45: National Industry | B45: 1995q1 | C45: 1995q2 | D45: 1995q3 | E45: 1995q4 | F45: 1996q1 | G45: 1996q2 | H45: 1996q3 | I45: 1996q4 | J45: 1997q1 | K45: 1997q2 | L45: 1997q3 | M45: 1997q4 | N45: 1998q1 | O45: 1998q2 | P45: 1998q3 | Q45: 1998q4 | R45: 1999q1 | S45: 1999q2 | T45: 1999q3 | U45: 1999q4 | V45: 2000q1 | W45: 2000q2 | X45: 2000q3 | Y45: 2000q4 | Z45: 2001q1 | AA45: 2001q2 | AB45: 2001q3 | AC45: 2001q4 | AD45: 2002q1 | AE45: 2002q2 | AF45: 2002q3 | AG45: 2002q4 | AH45: 2003q1 | AI45: 2003q2 | AJ45: 2003q3 | AK45: 2003q4 | AL45: 2004q1 | AM45: 2004q2 | AN45: 2004q3 | AO45: 2004q4 | AP45: 2005q1 | AQ45: 2005q2 | AR45: 2005q3 | AS45: 2005q4 | AT45: 2006q1 | AU45: 2006q2 | AV45: 2006q3 | AW45: 2006q4 | AX45: 2007q1 | AY45: 2007q2 | AZ45: 2007q3 | BA45: 2007q4 | BB45: 2008q1 | BC45: 2008q2 | BD45: 2008q3 | BE45: 2008q4 | BF45: 2009q1 | BG45: 2009q2 | BH45: 2009q3 | BI45: 2009q4 | BJ45: =BJ25 -> 2010q1 | BK45: =BK25 -> 2010q2 | BL45: =BL25 -> 2010q3 | BM45: =BM25 -> 2010q4 | BN45: =BN25 -> 2011q1 | BO45: =BO25 -> 2011q2 | BP45: =BP25 -> 2011q3 | BQ45: =BQ25 -> 2011q4 | ... BY45: =BY25 -> 2013q4
A46: Primary Industries | C46: =(C6-B6)/B6*100 -> -4.6397697 | D46: =(D6-C6)/C6*100 -> -2.155918 | E46: =(E6-D6)/D6*100 -> -0.49556905 | F46: =(F6-E6)/E6*100 -> 4.2910986 | G46: =(G6-F6)/F6*100 -> 2.4688012 | H46: =(H6-G6)/G6*100 -> 1.5763505 | I46: =(I6-H6)/H6*100 -> 0.48733853 | J46: =(J6-I6)/I6*100 -> -1.2335639 | ... BY46: =(BY6-BX6)/BX6*100 -> 3.0595455
A47: Agriculture, forestry and fishing | C47: =(C7-B7)/B7*100 -> -15.445705 | D47: =(D7-C7)/C7*100 -> -9.5586179 | E47: =(E7-D7)/D7*100 -> 0.059342717 | F47: =(F7-E7)/E7*100 -> 18.072088 | G47: =(G7-F7)/F7*100 -> 16.041033 | H47: =(H7-G7)/G7*100 -> 5.9198654 | I47: =(I7-H7)/H7*100 -> 1.1540631 | J47: =(J7-I7)/I7*100 -> -5.9087624 | ... BY47: =(BY7-BX7)/BX7*100 -> 1.558544
A48: Mining and quarrying | C48: =(C8-B8)/B8*100 -> -1.3274609 | D48: =(D8-C8)/C8*100 -> -0.21146267 | E48: =(E8-D8)/D8*100 -> -0.62767376 | F48: =(F8-E8)/E8*100 -> 0.98765457 | G48: =(G8-F8)/F8*100 -> -1.3349909 | H48: =(H8-G8)/G8*100 -> 0.14463993 | I48: =(I8-H8)/H8*100 -> 0.25489894 | J48: =(J8-I8)/I8*100 -> 0.41096466 | ... BY48: =(BY8-BX8)/BX8*100 -> 3.7159301
A49: Secondary Industries | C49: =(C9-B9)/B9*100 -> 1.0204802 | D49: =(D9-C9)/C9*100 -> 0.66177088 | E49: =(E9-D9)/D9*100 -> -0.66571124 | F49: =(F9-E9)/E9*100 -> 1.1725481 | G49: =(G9-F9)/F9*100 -> 0.36588689 | H49: =(H9-G9)/G9*100 -> 1.2010461 | I49: =(I9-H9)/H9*100 -> 1.1634341 | J49: =(J9-I9)/I9*100 -> 0.3496507 | ... BY49: =(BY9-BX9)/BX9*100 -> 2.224952
A50: Manufacturing | C50: =(C10-B10)/B10*100 -> 1.2712492 | D50: =(D10-C10)/C10*100 -> 0.82151156 | E50: =(E10-D10)/D10*100 -> -0.72287405 | F50: =(F10-E10)/E10*100 -> 0.90534956 | G50: =(G10-F10)/F10*100 -> -0.23321712 | H50: =(H10-G10)/G10*100 -> 0.60778652 | I50: =(I10-H10)/H10*100 -> 0.73033319 | J50: =(J10-I10)/I10*100 -> 0.6265274 | ... BY50: =(BY10-BX10)/BX10*100 -> 2.9535191
A51: Electricity, gas and water | C51: =(C11-B11)/B11*100 -> 0.039842401 | D51: =(D11-C11)/C11*100 -> -0.61141513 | E51: =(E11-D11)/D11*100 -> -1.2858818 | F51: =(F11-E11)/E11*100 -> 4.2479804 | G51: =(G11-F11)/F11*100 -> 4.1937798 | H51: =(H11-G11)/G11*100 -> 6.0245968 | I51: =(I11-H11)/H11*100 -> 4.9238523 | J51: =(J11-I11)/I11*100 -> -2.1205021 | ... BY51: =(BY11-BX11)/BX11*100 -> -1.4346631
A52: Construction | C52: =(C12-B12)/B12*100 -> 0.10200471 | D52: =(D12-C12)/C12*100 -> 0.72586095 | E52: =(E12-D12)/D12*100 -> 0.40458762 | F52: =(F12-E12)/E12*100 -> 0.16995505 | G52: =(G12-F12)/F12*100 -> 1.0434093 | H52: =(H12-G12)/G12*100 -> 0.59095037 | I52: =(I12-H12)/H12*100 -> 0.2473534 | J52: =(J12-I12)/I12*100 -> 1.1288562 | ... BY52: =(BY12-BX12)/BX12*100 -> 0.75722809
A53: Tertiary industries | C53: =(C13-B13)/B13*100 -> 1.0692714 | D53: =(D13-C13)/C13*100 -> 1.0550908 | E53: =(E13-D13)/D13*100 -> 0.79034457 | F53: =(F13-E13)/E13*100 -> 1.1149623 | G53: =(G13-F13)/F13*100 -> 1.0182322 | H53: =(H13-G13)/G13*100 -> 1.1609153 | I53: =(I13-H13)/H13*100 -> 1.1287012 | J53: =(J13-I13)/I13*100 -> 0.53802509 | ... BY53: =(BY13-BX13)/BX13*100 -> 0.3828832
A54: Wholesale & retail trade; hotels & restaurants | C54: =(C14-B14)/B14*100 -> 1.9268976 | D54: =(D14-C14)/C14*100 -> 2.0921715 | E54: =(E14-D14)/D14*100 -> 1.5377237 | F54: =(F14-E14)/E14*100 -> -0.15882711 | G54: =(G14-F14)/F14*100 -> 0.62541145 | H54: =(H14-G14)/G14*100 -> 0.8336085 | I54: =(I14-H14)/H14*100 -> 1.0845182 | J54: =(J14-I14)/I14*100 -> 0.28543735 | ... BY54: =(BY14-BX14)/BX14*100 -> 0.57799246
A55: Transport , storage and communication | C55: =(C15-B15)/B15*100 -> 2.7037174 | D55: =(D15-C15)/C15*100 -> 2.5018397 | E55: =(E15-D15)/D15*100 -> 2.1266966 | F55: =(F15-E15)/E15*100 -> 0.53391194 | G55: =(G15-F15)/F15*100 -> 1.3338392 | H55: =(H15-G15)/G15*100 -> 1.58602 | I55: =(I15-H15)/H15*100 -> 0.62030213 | J55: =(J15-I15)/I15*100 -> 2.5134538 | ... BY55: =(BY15-BX15)/BX15*100 -> 0.38820408
A56: Finance, real estate and business services | C56: =(C16-B16)/B16*100 -> 0.61474652 | D56: =(D16-C16)/C16*100 -> 0.82112799 | E56: =(E16-D16)/D16*100 -> 0.55266819 | F56: =(F16-E16)/E16*100 -> 2.0755823 | G56: =(G16-F16)/F16*100 -> 2.3674895 | H56: =(H16-G16)/G16*100 -> 2.3866699 | I56: =(I16-H16)/H16*100 -> 2.3061885 | J56: =(J16-I16)/I16*100 -> 0.49874162 | ... BY56: =(BY16-BX16)/BX16*100 -> 0.37684194
A57: Personal services | C57: =(C17-B17)/B17*100 -> 1.6715443 | D57: =(D17-C17)/C17*100 -> 0.83615763 | E57: =(E17-D17)/D17*100 -> 0.4514839 | F57: =(F17-E17)/E17*100 -> 2.81026 | G57: =(G17-F17)/F17*100 -> -1.547583 | H57: =(H17-G17)/G17*100 -> -0.53135241 | I57: =(I17-H17)/H17*100 -> 0.49206452 | J57: =(J17-I17)/I17*100 -> -0.16885442 | ... BY57: =(BY17-BX17)/BX17*100 -> 0.32506901
... A61: SA - GDP at constant 2005 prices | C61: =(C21-B21)/B21*100 -> 0.26681394 | D61: =(D21-C21)/C21*100 -> 0.59101499 | E61: =(E21-D21)/D21*100 -> 0.28887816 | F61: =(F21-E21)/E21*100 -> 1.4518551 | G61: =(G21-F21)/F21*100 -> 1.2664801 | H61: =(H21-G21)/G21*100 -> 1.2070739 | I61: =(I21-H21)/H21*100 -> 1.075039 | J61: =(J21-I21)/I21*100 -> 0.27707894 | ... BY61: =(BY21-BX21)/BX21*100 -> 0.9450897
A63: KZN – GDPR by activity
A64: Quarterly Change
A65: Provincial Industry | B65: 1995q1 | C65: 1995q2 | D65: 1995q3 | E65: 1995q4 | F65: 1996q1 | G65: 1996q2 | H65: 1996q3 | I65: 1996q4 | J65: 1997q1 | K65: 1997q2 | L65: 1997q3 | M65: 1997q4 | N65: 1998q1 | O65: 1998q2 | P65: 1998q3 | Q65: 1998q4 | R65: 1999q1 | S65: 1999q2 | T65: 1999q3 | U65: 1999q4 | V65: 2000q1 | W65: 2000q2 | X65: 2000q3 | Y65: 2000q4 | Z65: 2001q1 | AA65: 2001q2 | AB65: 2001q3 | AC65: 2001q4 | AD65: 2002q1 | AE65: 2002q2 | AF65: 2002q3 | AG65: 2002q4 | AH65: 2003q1 | AI65: 2003q2 | AJ65: 2003q3 | AK65: 2003q4 | AL65: 2004q1 | AM65: 2004q2 | AN65: 2004q3 | AO65: 2004q4 | AP65: 2005q1 | AQ65: 2005q2 | AR65: 2005q3 | AS65: 2005q4 | AT65: 2006q1 | AU65: 2006q2 | AV65: 2006q3 | AW65: 2006q4 | AX65: 2007q1 | AY65: 2007q2 | AZ65: 2007q3 | BA65: 2007q4 | BB65: 2008q1 | BC65: 2008q2 | BD65: 2008q3 | BE65: 2008q4 | BF65: 2009q1 | BG65: 2009q2 | BH65: 2009q3 | BI65: 2009q4 | BJ65: =BJ45 -> 2010q1 | BK65: =BK45 -> 2010q2 | BL65: =BL45 -> 2010q3 | BM65: =BM45 -> 2010q4 | BN65: =BN45 -> 2011q1 | BO65: =BO45 -> 2011q2 | BP65: =BP45 -> 2011q3 | BQ65: =BQ45 -> 2011q4 | ... BY65: =BY45 -> 2013q4
A66: Primary Industries | C66: =(C26-B26)/B26*100 -> -11.020601 | D66: =(D26-C26)/C26*100 -> -6.3097724 | E66: =(E26-D26)/D26*100 -> -0.19499052 | F66: =(F26-E26)/E26*100 -> 22.20921 | G66: =(G26-F26)/F26*100 -> 8.6095475 | H66: =(H26-G26)/G26*100 -> 3.6760386 | I66: =(I26-H26)/H26*100 -> 0.81661369 | J66: =(J26-I26)/I26*100 -> -4.5047446 | ... BY66: =(BY26-BX26)/BX26*100 -> 2.0288831
A67: Agriculture, forestry and fishing | C67: =(C27-B27)/B27*100 -> -15.445705 | D67: =(D27-C27)/C27*100 -> -9.5586179 | E67: =(E27-D27)/D27*100 -> 0.059342717 | F67: =(F27-E27)/E27*100 -> 10.771986 | G67: =(G27-F27)/F27*100 -> 16.041033 | H67: =(H27-G27)/G27*100 -> 5.9198654 | I67: =(I27-H27)/H27*100 -> 1.1540631 | J67: =(J27-I27)/I27*100 -> -7.0816468 | ... BY67: =(BY27-BX27)/BX27*100 -> 1.558544
A68: Mining and quarrying | C68: =(C28-B28)/B28*100 -> -1.3274609 | D68: =(D28-C28)/C28*100 -> -0.21146267 | E68: =(E28-D28)/D28*100 -> -0.62767376 | F68: =(F28-E28)/E28*100 -> 41.801255 | G68: =(G28-F28)/F28*100 -> -1.3349909 | H68: =(H28-G28)/G28*100 -> 0.14463993 | I68: =(I28-H28)/H28*100 -> 0.25489894 | J68: =(J28-I28)/I28*100 -> -0.17678901 | ... BY68: =(BY28-BX28)/BX28*100 -> 3.7159301
A69: Secondary Industries | C69: =(C29-B29)/B29*100 -> 1.0521263 | D69: =(D29-C29)/C29*100 -> 0.68404767 | E69: =(E29-D29)/D29*100 -> -0.67023524 | F69: =(F29-E29)/E29*100 -> 1.1007138 | G69: =(G29-F29)/F29*100 -> 0.28224701 | H69: =(H29-G29)/G29*100 -> 1.1191551 | I69: =(I29-H29)/H29*100 -> 1.1041396 | J69: =(J29-I29)/I29*100 -> 0.49824582 | ... BY69: =(BY29-BX29)/BX29*100 -> 2.3871173
A70: Manufacturing | C70: =(C30-B30)/B30*100 -> 1.2712492 | D70: =(D30-C30)/C30*100 -> 0.82151156 | E70: =(E30-D30)/D30*100 -> -0.72287405 | F70: =(F30-E30)/E30*100 -> 1.2516385 | G70: =(G30-F30)/F30*100 -> -0.23321712 | H70: =(H30-G30)/G30*100 -> 0.60778652 | I70: =(I30-H30)/H30*100 -> 0.73033319 | J70: =(J30-I30)/I30*100 -> 0.57849819 | ... BY70: =(BY30-BX30)/BX30*100 -> 2.9535191
A71: Electricity, gas and water | C71: =(C31-B31)/B31*100 -> 0.039842401 | D71: =(D31-C31)/C31*100 -> -0.61141513 | E71: =(E31-D31)/D31*100 -> -1.2858818 | F71: =(F31-E31)/E31*100 -> 4.5058339 | G71: =(G31-F31)/F31*100 -> 4.1937798 | H71: =(H31-G31)/G31*100 -> 6.0245968 | I71: =(I31-H31)/H31*100 -> 4.9238523 | J71: =(J31-I31)/I31*100 -> -2.5508731 | ... BY71: =(BY31-BX31)/BX31*100 -> -1.4346631
A72: Construction | C72: =(C32-B32)/B32*100 -> 0.10200471 | D72: =(D32-C32)/C32*100 -> 0.72586095 | E72: =(E32-D32)/D32*100 -> 0.40458762 | F72: =(F32-E32)/E32*100 -> -3.5087029 | G72: =(G32-F32)/F32*100 -> 1.0434093 | H72: =(H32-G32)/G32*100 -> 0.59095037 | I72: =(I32-H32)/H32*100 -> 0.2473534 | J72: =(J32-I32)/I32*100 -> 3.3542917 | ... BY72: =(BY32-BX32)/BX32*100 -> 0.75722809
A73: Tertiary industries | C73: =(C33-B33)/B33*100 -> 1.222027 | D73: =(D33-C33)/C33*100 -> 1.1890921 | E73: =(E33-D33)/D33*100 -> 0.9060105 | F73: =(F33-E33)/E33*100 -> 0.96457925 | G73: =(G33-F33)/F33*100 -> 0.98946475 | H73: =(H33-G33)/G33*100 -> 1.1562286 | I73: =(I33-H33)/H33*100 -> 1.0837908 | J73: =(J33-I33)/I33*100 -> -0.59745638 | ... BY73: =(BY33-BX33)/BX33*100 -> 0.39163192
A74: Wholesale & retail trade; hotels & restaurants | C74: =(C34-B34)/B34*100 -> 1.9268976 | D74: =(D34-C34)/C34*100 -> 2.0921715 | E74: =(E34-D34)/D34*100 -> 1.5377237 | F74: =(F34-E34)/E34*100 -> -1.5577391 | G74: =(G34-F34)/F34*100 -> 0.62541145 | H74: =(H34-G34)/G34*100 -> 0.8336085 | I74: =(I34-H34)/H34*100 -> 1.0845182 | J74: =(J34-I34)/I34*100 -> 0.43948816 | ... BY74: =(BY34-BX34)/BX34*100 -> 0.57799246
A75: Transport , storage and communication | C75: =(C35-B35)/B35*100 -> 2.7037174 | D75: =(D35-C35)/C35*100 -> 2.5018397 | E75: =(E35-D35)/D35*100 -> 2.1266966 | F75: =(F35-E35)/E35*100 -> -1.0132334 | G75: =(G35-F35)/F35*100 -> 1.3338392 | H75: =(H35-G35)/G35*100 -> 1.58602 | I75: =(I35-H35)/H35*100 -> 0.62030213 | J75: =(J35-I35)/I35*100 -> 0.56977941 | ... BY75: =(BY35-BX35)/BX35*100 -> 0.38820408
A76: Finance, real estate and business services | C76: =(C36-B36)/B36*100 -> 0.61474652 | D76: =(D36-C36)/C36*100 -> 0.82112799 | E76: =(E36-D36)/D36*100 -> 0.55266819 | F76: =(F36-E36)/E36*100 -> 2.1330037 | G76: =(G36-F36)/F36*100 -> 2.3674895 | H76: =(H36-G36)/G36*100 -> 2.3866699 | I76: =(I36-H36)/H36*100 -> 2.3061885 | J76: =(J36-I36)/I36*100 -> 0.05116181 | ... BY76: =(BY36-BX36)/BX36*100 -> 0.37684194
A77: Personal services | C77: =(C37-B37)/B37*100 -> 1.6715443 | D77: =(D37-C37)/C37*100 -> 0.83615763 | E77: =(E37-D37)/D37*100 -> 0.4514839 | F77: =(F37-E37)/E37*100 -> 2.7513481 | G77: =(G37-F37)/F37*100 -> -1.547583 | H77: =(H37-G37)/G37*100 -> -0.53135241 | I77: =(I37-H37)/H37*100 -> 0.49206452 | J77: =(J37-I37)/I37*100 -> -0.23807797 | ... BY77: =(BY37-BX37)/BX37*100 -> 0.32506901
... A80: Taxes less subsidies on products | C80: =(C40-B40)/B40*100 -> 0.0126349 | D80: =(D40-C40)/C40*100 -> 0.8760721 | E80: =(E40-D40)/D40*100 -> 0.40451869 | F80: =(F40-E40)/E40*100 -> 1.3229044 | G80: =(G40-F40)/F40*100 -> 2.98043 | H80: =(H40-G40)/G40*100 -> 1.0861441 | I80: =(I40-H40)/H40*100 -> 1.2209757 | J80: =(J40-I40)/I40*100 -> 0.18480376 | ... BY80: =(BY40-BX40)/BX40*100 -> 0.45607608
A81: KZN - GDPR at constant 2005 prices | C81: =(C41-B41)/B41*100 -> 0.085586135 | D81: =(D41-C41)/C41*100 -> 0.49727492 | E81: =(E41-D41)/D41*100 -> 0.34372528 | F81: =(F41-E41)/E41*100 -> 2.4014054 | G81: =(G41-F41)/F41*100 -> 1.6116128 | H81: =(H41-G41)/G41*100 -> 1.3436241 | I81: =(I41-H41)/H41*100 -> 1.0829529 | J81: =(J41-I41)/I41*100 -> -0.54111269 | ... U81: =(U41-T41)/T41*100 -> 1.256518 | V81: =V79 -> 1.137337 | W81: =(W41-V41)/V41*100 -> 1.0491539 | X81: =(X41-W41)/W41*100 -> 1.1436305 | Y81: =(Y41-X41)/X41*100 -> 0.89308145 | Z81: =(Z41-Y41)/Y41*100 -> 2.1797671 | AA81: =(AA41-Z41)/Z41*100 -> 0.42619389 | AB81: =(AB41-AA41)/AA41*100 -> 0.23261443 | AC81: =(AC41-AB41)/AB41*100 -> 0.84271972 | AD81: =(AD41-AC41)/AC41*100 -> -0.076768457 | ... BY81: =(BY41-BX41)/BX41*100 -> 0.95493408
A83: SA – GDP by activity
A84: Annual Change
A85: National Industry | B85: 1995q1 | C85: 1995q2 | D85: 1995q3 | E85: 1995q4 | F85: 1996q1 | G85: 1996q2 | H85: 1996q3 | I85: 1996q4 | J85: 1997q1 | K85: 1997q2 | L85: 1997q3 | M85: 1997q4 | N85: 1998q1 | O85: 1998q2 | P85: 1998q3 | Q85: 1998q4 | R85: 1999q1 | S85: 1999q2 | T85: 1999q3 | U85: 1999q4 | V85: 2000q1 | W85: 2000q2 | X85: 2000q3 | Y85: 2000q4 | Z85: 2001q1 | AA85: 2001q2 | AB85: 2001q3 | AC85: 2001q4 | AD85: 2002q1 | AE85: 2002q2 | AF85: 2002q3 | AG85: 2002q4 | AH85: 2003q1 | AI85: 2003q2 | AJ85: 2003q3 | AK85: 2003q4 | AL85: 2004q1 | AM85: 2004q2 | AN85: 2004q3 | AO85: 2004q4 | AP85: 2005q1 | AQ85: 2005q2 | AR85: 2005q3 | AS85: 2005q4 | AT85: 2006q1 | AU85: 2006q2 | AV85: 2006q3 | AW85: 2006q4 | AX85: 2007q1 | AY85: 2007q2 | AZ85: 2007q3 | BA85: 2007q4 | BB85: 2008q1 | BC85: 2008q2 | BD85: 2008q3 | BE85: 2008q4 | BF85: 2009q1 | BG85: 2009q2 | BH85: 2009q3 | BI85: 2009q4 | BJ85: =BJ65 -> 2010q1 | BK85: =BK65 -> 2010q2 | BL85: =BL65 -> 2010q3 | BM85: =BM65 -> 2010q4 | BN85: =BN65 -> 2011q1 | BO85: =BO65 -> 2011q2 | BP85: =BP65 -> 2011q3 | BQ85: =BQ65 -> 2011q4 | ... BY85: =BY65 -> 2013q4
A86: Primary Industries | F86: =(F6-B6)/B6*100 -> -3.1741057 | G86: =(G6-C6)/C6*100 -> 4.0437222 | H86: =(H6-D6)/D6*100 -> 8.0124764 | I86: =(I6-E6)/E6*100 -> 9.0794267 | J86: =(J6-F6)/F6*100 -> 3.3011098 | K86: =(K6-G6)/G6*100 -> 1.8378905 | L86: =(L6-H6)/H6*100 -> 0.77604412 | M86: =(M6-I6)/I6*100 -> 0.17785751 | ... BY86: =(BY6-BU6)/BU6*100 -> 5.9389866
A87: Agriculture, forestry and fishing | F87: =(F7-B7)/B7*100 -> -9.6542445 | G87: =(G7-C7)/C7*100 -> 23.989145 | H87: =(H7-D7)/D7*100 -> 45.20912 | I87: =(I7-E7)/E7*100 -> 46.797811 | J87: =(J7-F7)/F7*100 -> 16.982667 | K87: =(K7-G7)/G7*100 -> 1.1348644 | L87: =(L7-H7)/H7*100 -> -4.7710868 | M87: =(M7-I7)/I7*100 -> -6.6484104 | ... BY87: =(BY7-BU7)/BU7*100 -> 0.54546358
A88: Mining and quarrying | F88: =(F8-B8)/B8*100 -> -1.1877695 | G88: =(G8-C8)/C8*100 -> -1.1953101 | H88: =(H8-D8)/D8*100 -> -0.84271843 | I88: =(I8-E8)/E8*100 -> 0.037944357 | J88: =(J8-F8)/F8*100 -> -0.53332223 | K88: =(K8-G8)/G8*100 -> 2.0696221 | L88: =(L8-H8)/H8*100 -> 2.7099354 | M88: =(M8-I8)/I8*100 -> 2.5790374 | ... BY88: =(BY8-BU8)/BU8*100 -> 8.4295987
A89: Secondary Industries | F89: =(F9-B9)/B9*100 -> 2.1964641 | G89: =(G9-C9)/C9*100 -> 1.5342506 | H89: =(H9-D9)/D9*100 -> 2.0782 | I89: =(I9-E9)/E9*100 -> 3.9578718 | J89: =(J9-F9)/F9*100 -> 3.1123197 | K89: =(K9-G9)/G9*100 -> 4.3972431 | L89: =(L9-H9)/H9*100 -> 2.884989 | M89: =(M9-I9)/I9*100 -> 1.2894804 | ... BY89: =(BY9-BU9)/BU9*100 -> 1.8559652
A90: Manufacturing | F90: =(F10-B10)/B10*100 -> 2.2828354 | G90: =(G10-C10)/C10*100 -> 0.76334113 | H90: =(H10-D10)/D10*100 -> 0.54973939 | I90: =(I10-E10)/E10*100 -> 2.021575 | J90: =(J10-F10)/F10*100 -> 1.7396685 | K90: =(K10-G10)/G10*100 -> 3.8806694 | L90: =(L10-H10)/H10*100 -> 3.0912483 | M90: =(M10-I10)/I10*100 -> 2.0963846 | ... BY90: =(BY10-BU10)/BU10*100 -> 1.9308105
A91: Electricity, gas and water | F91: =(F11-B11)/B11*100 -> 2.3190328 | G91: =(G11-C11)/C11*100 -> 6.5676086 | H91: =(H11-D11)/D11*100 -> 13.682952 | I91: =(I11-E11)/E11*100 -> 20.834319 | J91: =(J11-F11)/F11*100 -> 13.452582 | K91: =(K11-G11)/G11*100 -> 9.1722301 | L91: =(L11-H11)/H11*100 -> 0.88537542 | M91: =(M11-I11)/I11*100 -> -6.2074949 | ... BY91: =(BY11-BU11)/BU11*100 -> 0.036199598
A92: Construction | F92: =(F12-B12)/B12*100 -> 1.4086028 | G92: =(G12-C12)/C12*100 -> 2.3622952 | H92: =(H12-D12)/D12*100 -> 2.2251928 | I92: =(I12-E12)/E12*100 -> 2.0651075 | J92: =(J12-F12)/F12*100 -> 3.0421505 | K92: =(K12-G12)/G12*100 -> 3.2532839 | L92: =(L12-H12)/H12*100 -> 3.5557577 | M92: =(M12-I12)/I12*100 -> 3.9109025 | ... BY92: =(BY12-BU12)/BU12*100 -> 2.5194769
A93: Tertiary industries | F93: =(F13-B13)/B13*100 -> 4.0906417 | G93: =(G13-C13)/C13*100 -> 4.0380766 | H93: =(H13-D13)/D13*100 -> 4.1470249 | I93: =(I13-E13)/E13*100 -> 4.4966501 | J93: =(J13-F13)/F13*100 -> 3.9004178 | K93: =(K13-G13)/G13*100 -> 3.1212233 | L93: =(L13-H13)/H13*100 -> 2.1753225 | M93: =(M13-I13)/I13*100 -> 1.0460231 | ... BY93: =(BY13-BU13)/BU13*100 -> 1.7553456
A94: Wholesale & retail trade; hotels & restaurants | F94: =(F14-B14)/B14*100 -> 5.491713 | G94: =(G14-C14)/C14*100 -> 4.1447083 | H94: =(H14-D14)/D14*100 -> 2.8608422 | I94: =(I14-E14)/E14*100 -> 2.4017311 | J94: =(J14-F14)/F14*100 -> 2.8573893 | K94: =(K14-G14)/G14*100 -> 1.5509242 | L94: =(L14-H14)/H14*100 -> 0.10814509 | M94: =(M14-I14)/I14*100 -> -2.8363982 | ... BY94: =(BY14-BU14)/BU14*100 -> 2.197573
A95: Transport , storage and communication | F95: =(F15-B15)/B15*100 -> 8.0860609 | G95: =(G15-C15)/C15*100 -> 6.6443921 | H95: =(H15-D15)/D15*100 -> 5.6915601 | I95: =(I15-E15)/E15*100 -> 4.132583 | J95: =(J15-F15)/F15*100 -> 6.1829837 | K95: =(K15-G15)/G15*100 -> 6.9714205 | L95: =(L15-H15)/H15*100 -> 7.67667 | M95: =(M15-I15)/I15*100 -> 9.5068155 | ... BY95: =(BY15-BU15)/BU15*100 -> 1.9411392
A96: Finance, real estate and business services | F96: =(F16-B16)/B16*100 -> 4.1186802 | G96: =(G16-C16)/C16*100 -> 5.9324629 | H96: =(H16-D16)/D16*100 -> 7.5773733 | I96: =(I16-E16)/E16*100 -> 9.4533962 | J96: =(J16-F16)/F16*100 -> 7.7625847 | K96: =(K16-G16)/G16*100 -> 5.8391207 | L96: =(L16-H16)/H16*100 -> 3.6919148 | M96: =(M16-I16)/I16*100 -> 1.7652481 | ... BY96: =(BY16-BU16)/BU16*100 -> 2.3631053
A97: Personal services | F97: =(F17-B17)/B17*100 -> 5.8786811 | G97: =(G17-C17)/C17*100 -> 2.5263473 | H97: =(H17-D17)/D17*100 -> 1.1359154 | I97: =(I17-E17)/E17*100 -> 1.1767725 | J97: =(J17-F17)/F17*100 -> -1.7550086 | K97: =(K17-G17)/G17*100 -> 0.059424013 | L97: =(L17-H17)/H17*100 -> 0.9993566 | M97: =(M17-I17)/I17*100 -> 0.60632442 | ... BY97: =(BY17-BU17)/BU17*100 -> 1.4195185
... A101: SA - GDP at constant 2005 prices | F101: =(F21-B21)/B21*100 -> 2.6193292 | G101: =(G21-C21)/C21*100 -> 3.6424501 | H101: =(H21-D21)/D21*100 -> 4.2771972 | I101: =(I21-E21)/E21*100 -> 5.0946223 | J101: =(J21-F21)/F21*100 -> 3.8776642 | K101: =(K21-G21)/G21*100 -> 3.2348327 | L101: =(L21-H21)/H21*100 -> 2.158787 | M101: =(M21-I21)/I21*100 -> 0.99688188 | ... BY101: =(BY21-BU21)/BU21*100 -> 2.1317384
A103: KZN – GDPR by activity
A104: Annual Change
A105: Provincial Industry | B105: 1995q1 | C105: 1995q2 | D105: 1995q3 | E105: 1995q4 | F105: 1996q1 | G105: 1996q2 | H105: 1996q3 | I105: 1996q4 | J105: 1997q1 | K105: 1997q2 | L105: 1997q3 | M105: 1997q4 | N105: 1998q1 | O105: 1998q2 | P105: 1998q3 | Q105: 1998q4 | R105: 1999q1 | S105: 1999q2 | T105: 1999q3 | U105: 1999q4 | V105: 2000q1 | W105: 2000q2 | X105: 2000q3 | Y105: 2000q4 | Z105: 2001q1 | AA105: 2001q2 | AB105: 2001q3 | AC105: 2001q4 | AD105: 2002q1 | AE105: 2002q2 | AF105: 2002q3 | AG105: 2002q4 | AH105: 2003q1 | AI105: 2003q2 | AJ105: 2003q3 | AK105: 2003q4 | AL105: 2004q1 | AM105: 2004q2 | AN105: 2004q3 | AO105: 2004q4 | AP105: 2005q1 | AQ105: 2005q2 | AR105: 2005q3 | AS105: 2005q4 | AT105: 2006q1 | AU105: 2006q2 | AV105: 2006q3 | AW105: 2006q4 | AX105: 2007q1 | AY105: 2007q2 | AZ105: 2007q3 | BA105: 2007q4 | BB105: 2008q1 | BC105: 2008q2 | BD105: 2008q3 | BE105: 2008q4 | BF105: 2009q1 | BG105: 2009q2 | BH105: 2009q3 | BI105: 2009q4 | BJ105: =BJ85 -> 2010q1 | BK105: =BK85 -> 2010q2 | BL105: =BL85 -> 2010q3 | BM105: =BM85 -> 2010q4 | BN105: =BN85 -> 2011q1 | BO105: =BO85 -> 2011q2 | BP105: =BP85 -> 2011q3 | BQ105: =BQ85 -> 2011q4 | ... BY105: =BY85 -> 2013q4
A106: Primary Industries | F106: =(F26-B26)/B26*100 -> 1.6810536 | G106: =(G26-C26)/C26*100 -> 24.113372 | H106: =(H26-D26)/D26*100 -> 37.341781 | I106: =(I26-E26)/E26*100 -> 38.733851 | J106: =(J26-F26)/F26*100 -> 8.4077422 | K106: =(K26-G26)/G26*100 -> 0.49503605 | L106: =(L26-H26)/H26*100 -> -2.9307155 | M106: =(M26-I26)/I26*100 -> -4.1581845 | ... BY106: =(BY26-BU26)/BU26*100 -> 2.7164854
A107: Agriculture, forestry and fishing | F107: =(F27-B27)/B27*100 -> -15.240097 | G107: =(G27-C27)/C27*100 -> 16.323206 | H107: =(H27-D27)/D27*100 -> 36.231203 | I107: =(I27-E27)/E27*100 -> 37.721669 | J107: =(J27-F27)/F27*100 -> 15.524432 | K107: =(K27-G27)/G27*100 -> -0.12582156 | L107: =(L27-H27)/H27*100 -> -5.9581528 | M107: =(M27-I27)/I27*100 -> -7.8120748 | ... BY107: =(BY27-BU27)/BU27*100 -> 1.6424668
A108: Mining and quarrying | F108: =(F28-B28)/B28*100 -> 38.746645 | G108: =(G28-C28)/C28*100 -> 38.736057 | H108: =(H28-D28)/D28*100 -> 39.231147 | I108: =(I28-E28)/E28*100 -> 40.467724 | J108: =(J28-F28)/F28*100 -> -1.1155485 | K108: =(K28-G28)/G28*100 -> 1.4721595 | L108: =(L28-H28)/H28*100 -> 2.1087248 | M108: =(M28-I28)/I28*100 -> 1.978593 | ... BY108: =(BY28-BU28)/BU28*100 -> 6.675513
A109: Secondary Industries | F109: =(F29-B29)/B29*100 -> 2.1738484 | G109: =(G29-C29)/C29*100 -> 1.3954232 | H109: =(H29-D29)/D29*100 -> 1.8336048 | I109: =(I29-E29)/E29*100 -> 3.6527069 | J109: =(J29-F29)/F29*100 -> 3.0350314 | K109: =(K29-G29)/G29*100 -> 4.4411857 | L109: =(L29-H29)/H29*100 -> 3.0295977 | M109: =(M29-I29)/I29*100 -> 1.5167141 | ... BY109: =(BY29-BU29)/BU29*100 -> 1.8538281
A110: Manufacturing | F110: =(F30-B30)/B30*100 -> 2.6338517 | G110: =(G30-C30)/C30*100 -> 1.1091427 | H110: =(H30-D30)/D30*100 -> 0.89480796 | I110: =(I30-E30)/E30*100 -> 2.3716946 | J110: =(J30-F30)/F30*100 -> 1.691108 | K110: =(K30-G30)/G30*100 -> 3.831087 | L110: =(L30-H30)/H30*100 -> 3.0420427 | M110: =(M30-I30)/I30*100 -> 2.0476538 | ... BY110: =(BY30-BU30)/BU30*100 -> 1.9241157
A111: Electricity, gas and water | F111: =(F31-B31)/B31*100 -> 2.5721151 | G111: =(G31-C31)/C31*100 -> 6.8311996 | H111: =(H31-D31)/D31*100 -> 13.964143 | I111: =(I31-E31)/E31*100 -> 21.133199 | J111: =(J31-F31)/F31*100 -> 12.953737 | K111: =(K31-G31)/G31*100 -> 8.6922054 | L111: =(L31-H31)/H31*100 -> 0.44178767 | M111: =(M31-I31)/I31*100 -> -6.6198956 | ... BY111: =(BY31-BU31)/BU31*100 -> -0.24946354
A112: Construction | F112: =(F32-B32)/B32*100 -> -2.3155435 | G112: =(G32-C32)/C32*100 -> -1.3968746 | H112: =(H32-D32)/D32*100 -> -1.528942 | I112: =(I32-E32)/E32*100 -> -1.6831483 | J112: =(J32-F32)/F32*100 -> 5.3096898 | K112: =(K32-G32)/G32*100 -> 5.5254694 | L112: =(L32-H32)/H32*100 -> 5.8345994 | M112: =(M32-I32)/I32*100 -> 6.1975595 | ... BY112: =(BY32-BU32)/BU32*100 -> 2.6587006
A113: Tertiary industries | F113: =(F33-B33)/B33*100 -> 4.350565 | G113: =(G33-C33)/C33*100 -> 4.1108148 | H113: =(H33-D33)/D33*100 -> 4.0770024 | I113: =(I33-E33)/E33*100 -> 4.2603695 | J113: =(J33-F33)/F33*100 -> 2.6473443 | K113: =(K33-G33)/G33*100 -> 2.0100647 | L113: =(L33-H33)/H33*100 -> 1.2026834 | M113: =(M33-I33)/I33*100 -> 0.24214085 | ... BY113: =(BY33-BU33)/BU33*100 -> 1.9339187
...

Sheet Growth Rates Annualised
A1: Year-on-Year Growth Rates per Sector
B2: Primary Industries | C2: Agriculture, forestry and fishing | D2: Mining and quarrying | E2: Secondary Industries | F2: Manufacturing | G2: Electricity, gas and water | H2: Construction | I2: Tertiary industries | J2: Wholesale & retail trade; hotels & restaurants | K2: Transport , storage and communication | L2: Finance, real estate and business services | M2: Personal services | N2: General government services | O2: All industries at basic prices | P2: Taxes less subsidies on products | Q2: GDPR at market prices
A3: 1996 | B3: 24.327179 | C3: 16.33339 | D3: 39.291129 | E3: 2.2634245 | F3: 1.7479865 | G3: 11.07406 | H3: -1.7304781 | I3: 4.1991954 | J3: 2.2470205 | K3: 4.4671965 | L3: 6.8454418 | M3: 2.5993757 | N3: 3.7846872 | O3: 5.1652471 | P3: 5.2529069 | Q3: 5.1754906
A4: =A3+1 -> 1997 | B4: 0.21275363 | C4: -0.35775829 | D4: 1.104701 | E4: 2.9974217 | F4: 2.6509811 | G4: 3.4431571 | H4: 5.7190779 | I4: 1.51452 | J4: 0.55422679 | K4: 5.5598838 | L4: 4.2397691 | M4: -0.10203571 | N4: -2.419891 | O4: 1.8406538 | P4: 2.759255 | Q4: 1.948076
A5: =A4+1 -> 1998 | B5: 0.018089306 | C5: 0.90679689 | D5: -1.3512325 | E5: -1.9763677 | F5: -0.45016265 | G5: -6.1115589 | H5: -11.254457 | I5: 2.7470317 | J5: 0.88094179 | K5: 4.5286472 | L5: 2.4268725 | M5: 6.220466 | N5: 1.9185776 | O5: 1.0643415 | P5: -0.56017126 | Q5: 0.87285779
A6: =A5+1 -> 1999 | B6: -12.3014 | C6: -2.6298178 | D6: -27.544488 | E6: 0.86303659 | F6: 1.6032162 | G6: 0.05873819 | H6: -5.6966269 | I6: 3.2050495 | J6: 7.1534381 | K6: 3.5515228 | L6: 6.0813332 | M6: 3.6957968 | N6: -3.4818139 | O6: 1.126937 | P6: -1.9620212 | Q6: 0.76800943
A7: =A6+1 -> 2000 | B7: 1.7227067 | C7: 3.7541219 | D7: -2.5798703 | E7: 7.9829223 | F7: 8.5899493 | G7: 5.8676268 | H7: 3.9410442 | I7: 3.6950185 | J7: 8.2442431 | K7: 6.4544517 | L7: 1.1933288 | M7: 4.707316 | N7: -0.29083884 | O7: 4.6799297 | P7: 2.5481394 | Q7: 4.6799297
A8: =A7+1 -> 2001 | B8: -1.8158587 | C8: -0.35508425 | D8: -5.1109674 | E8: 4.9791564 | F8: 2.9761257 | G8: -0.1554615 | H8: 34.108681 | I8: 4.4785614 | J8: 7.8119454 | K8: 4.3137984 | L8: 5.7000744 | M8: 2.3313695 | N8: 0.93167195 | O8: 4.2326015 | P8: 6.2281327 | Q8: 4.45411
A9: =A8+1 -> 2002 | B9: 0.10661873 | C9: 4.6535995 | D9: -10.664217 | E9: 1.0269937 | F9: 2.6356048 | G9: 9.7037841 | H9: -21.006938 | I9: 4.0041102 | J9: 2.4495688 | K9: 9.3551418 | L9: 5.0548031 | M9: 2.4114593 | N9: 0.4160728 | O9: 2.8635374 | P9: -0.46973395 | Q9: 2.4874919
A10: =A9+1 -> 2003 | B10: 5.3662048 | C10: 5.1810406 | D10: 5.871938 | E10: -1.4938695 | F10: -0.91605472 | G10: -11.509926 | H10: 4.7497429 | I10: 4.6851053 | J10: 3.4685182 | K10: 6.9910453 | L10: 5.5895925 | M10: 5.5714174 | N10: 2.1974951 | O10: 2.8779539 | P10: 1.6514799 | Q10: 2.743264
A11: =A10+1 -> 2004 | B11: 0.75567789 | C11: 0.30146777 | D11: 2.0029645 | E11: 5.2864306 | F11: 4.700176 | G11: 7.3184307 | H11: 9.3854882 | I11: 4.5034154 | J11: 5.436725 | K11: 4.4789047 | L11: 7.2250772 | M11: 1.7682854 | N11: 1.3494582 | O11: 4.4630634 | P11: 4.7734818 | Q11: 4.4967465
A12: =A11+1 -> 2005 | B12: -5.9574074 | C12: -5.8366161 | D12: -6.2574829 | E12: 6.7971079 | F12: 6.1687914 | G12: 6.5109752 | H12: 13.557313 | I12: 6.7740471 | J12: 6.4677556 | K12: 5.9155791 | L12: 10.575791 | M12: 3.3769874 | N12: 4.5039284 | O12: 5.911328 | P12: 4.5150408 | Q12: 5.7593019
A13: =A12+1 -> 2006 | B13: -0.50635611 | C13: 0.52951144 | D13: -3.3422109 | E13: 5.936585 | F13: 6.0361686 | G13: 3.3018254 | H13: 7.597826 | I13: 5.7542002 | J13: 6.4027775 | K13: 5.2002254 | L13: 7.6947753 | M13: 5.3055693 | N13: 2.9800543 | O13: 5.4278525 | P13: 6.4079118 | Q13: 5.5333279
A14: =A13+1 -> 2007 | B14: 3.6647028 | C14: 4.0860735 | D14: 2.4923366 | E14: 5.9345847 | F14: 5.2996246 | G14: 3.3333849 | H14: 14.424717 | I14: 6.2681907 | J14: 5.5921564 | K14: 7.1322798 | L14: 7.7600516 | M14: 5.5076827 | N14: 4.0691697 | O14: 6.0213237 | P14: 4.8528676 | Q14: 5.8948085
A15: =A14+1 -> 2008 | B15: 9.1361298 | C15: 14.542221 | D15: -6.5363135 | E15: 2.6872727 | F15: 2.5596069 | G15: -4.0239551 | H15: 8.5556574 | I15: 4.3522369 | J15: 1.058302 | K15: 4.1887928 | L15: 7.3847387 | M15: 3.7697571 | N15: 4.9247091 | O15: 4.1317427 | P15: 2.6315269 | Q15: 3.9731293
A16: =A15+1 -> 2009 | B16: -1.84247 | C16: -2.8799951 | D16: -6.3954458 | E16: -8.3894489 | F16: -9.9543463 | G16: -3.9174596 | H16: 8.3931078 | I16: 1.3057585 | J16: 0.063531303 | K16: 1.5923054 | L16: 1.6209403 | M16: -0.022682734 | N16: 3.8975244 | O16: -1.6819698 | P16: -2.7842297 | Q16: -1.7814714
A17: 2010 | B17: 1.9285559 | C17: 2.3561205 | D17: 9.419003 | E17: 5.9145179 | F17: 6.0837594 | G17: 1.1912041 | H17: 1.6492341 | I17: 3.2722108 | J17: 4.1695926 | K17: 2.6750308 | L17: 2.445231 | M17: 0.66604118 | N17: 3.5900024 | O17: 3.9053854 | P17: 5.1120795 | Q17: 4.0111946
A18: 2011 | B18: 0.49440364 | C18: 1.0426825 | D18: -1.3813073 | E18: 2.7934197 | F18: 3.2768041 | G18: 1.1951674 | H18: 0.41834048 | I18: 4.1573387 | J18: 5.0860616 | K18: 2.9019164 | L18: 4.813282 | M18: 2.5547119 | N18: 4.1947896 | O18: 3.5724347 | P18: 3.4452675 | Q18: 3.5589624
A19: 2012 | B19: 2.3917534 | C19: 2.5222651 | D19: 1.9342867 | E19: 1.7605599 | F19: 2.1242758 | G19: -3.3031719 | H19: 2.5206936 | I19: 3.0508918 | J19: 3.7381161 | K19: 2.5631789 | L19: 3.343357 | M19: 2.2575201 | N19: 2.6974344 | O19: 2.6624916 | P19: 4.0207593 | Q19: 2.8062301
A20: 2013 | B20: 2.9899082 | C20: 3.4274041 | D20: 1.4475615 | E20: 0.89089646 | F20: 0.74625617 | G20: -0.70049306 | H20: 2.9647373 | I20: 2.1873694 | J20: 2.8308062 | K20: 1.7156018 | L20: 2.4952662 | M20: 1.9919066 | N20: 1.5456405 | O20: 1.8817304 | P20: 0.55289001 | Q20: 1.7394447
A21: Average Year on Year Growth Rate | B21: =AVERAGE(B3:B20) -> 1.7050662 | C21: =AVERAGE(C3:C20) -> 2.6431901 | D21: =AVERAGE(D3:D20) -> -0.42220083 | E21: =AVERAGE(E3:E20) -> 2.5697024 | F21: =AVERAGE(F3:F20) -> 2.5488202 | G21: =AVERAGE(G3:G20) -> 1.2931293 | H21: =AVERAGE(H3:H20) -> 4.3498423 | I21: =AVERAGE(I3:I20) -> 3.8974584 | ... Q21: =AVERAGE(Q3:Q20) -> 3.2844947

Sheet Growth Rates SeaAdj
A1: Seasonally adjusted and annualised quarterly Rates per Sector
B2: Primary Industries | C2: Agriculture, forestry and fishing | D2: Mining and quarrying | E2: Secondary Industries | F2: Manufacturing | G2: Electricity, gas and water | H2: Construction | I2: Tertiary industries | J2: Wholesale & retail trade; hotels & restaurants | K2: Transport , storage and communication | L2: Finance, real estate and business services | M2: Personal services | N2: General government services | O2: All industries at basic prices | P2: Taxes less subsidies on products | Q2: GDPR at market prices
A3: 1996q1 | B3: 1.6810536 | C3: -15.240097 | D3: 38.746645 | E3: 2.1738484 | F3: 2.6338517 | G3: 2.5721151 | H3: -2.3155435 | I3: 4.350565 | J3: 4.0136292 | K3: 6.4226934 | L3: 4.177251 | M3: 5.8180109 | N3: 2.8636188 | O3: 3.4472758 | P3: 2.6369934 | Q3: 3.3527317
A4: 1996q2 | B4: 24.113372 | C4: 16.323206 | D4: 38.736057 | E4: 1.3954232 | F4: 1.1091427 | G4: 6.8311996 | H4: -1.3968746 | I4: 4.1108148 | J4: 2.6854979 | K4: 5.0032108 | L4: 5.9920541 | M4: 2.4675981 | N4: 3.5813615 | O4: 4.8290452 | P4: 5.6826642 | Q4: 4.9285733
A5: 1996q3 | B5: 37.341781 | C5: 36.231203 | D5: 39.231147 | E5: 1.8336048 | F5: 0.89480796 | G5: 13.964143 | H5: -1.528942 | I5: 4.0770024 | J5: 1.4196205 | K5: 4.0650422 | L5: 7.6378897 | M5: 1.0779629 | N5: 4.1518092 | O5: 5.8002449 | P5: 5.9027459 | Q5: 5.8122411
A6: 1996q4 | B6: 38.733851 | C6: 37.721669 | D6: 40.467724 | E6: 3.6527069 | F6: 2.3716946 | G6: 21.133199 | H6: -1.6831483 | I6: 4.2603695 | J6: 0.96694213 | K6: 2.5300567 | L6: 9.514968 | M6: 1.1187966 | N6: 4.5396586 | O6: 6.5689203 | P6: 6.7639127 | Q6: 6.591755
A7: 1997q1 | B7: 8.4077422 | C7: 15.524432 | D7: -1.1155485 | E7: 3.0350314 | F7: 1.691108 | G7: 12.953737 | H7: 5.3096898 | I7: 2.6473443 | J7: 3.0153909 | K7: 4.1697344 | L7: 7.2826547 | M7: -1.8231323 | N7: -1.2026263 | O7: 3.2620087 | P7: 5.5646964 | Q7: 3.5288267
A8: 1997q2 | B8: 0.49503605 | C8: -0.12582156 | D8: 1.4721595 | E8: 4.4411857 | F8: 3.831087 | G8: 8.6922054 | H8: 5.5254694 | I8: 2.0100647 | J8: 1.706919 | K8: 4.9432222 | L8: 5.367757 | M8: -0.0099578267 | N8: -2.1156143 | O8: 2.5997027 | P8: 2.8326742 | Q8: 2.6270613
A9: 1997q3 | B9: -2.9307155 | C9: -5.9581528 | D9: 2.1087248 | E9: 3.0295977 | F9: 3.0420427 | G9: 0.44178767 | H9: 5.8345994 | I9: 1.2026834 | J9: 0.26192356 | K9: 5.6351001 | L9: 3.2301139 | M9: 0.92932301 | N9: -2.9027789 | O9: 1.3590526 | P9: 1.9231481 | Q9: 1.4251279
A10: 1997q4 | B10: -4.1581845 | C10: -7.8120748 | D10: 1.978593 | E10: 1.5167141 | F10: 2.0476538 | G10: -6.6198956 | H10: 6.1975595 | I10: 0.24214085 | J10: -2.6871429 | K10: 7.4305457 | L10: 1.3120278 | M10: 0.53656336 | N10: -3.4353376 | O10: 0.20912306 | P10: 0.85122186 | Q10: 0.28443799
A11: 1998q1 | B11: 1.8178227 | C11: 2.1951161 | D11: 1.2279829 | E11: 0.030959916 | F11: 1.6447863 | G11: -5.8006402 | H11: -8.053409 | I11: 2.3761589 | J11: -1.21274 | K11: 7.3450961 | L11: 1.6438879 | M11: 3.7319283 | N11: 2.091445 | O11: 1.6152702 | P11: 0.71624952 | Q11: 1.50905
A12: 1998q2 | B12: -0.69891839 | C12: -0.52112924 | D12: -0.9743216 | E12: -1.9692829 | F12: -0.29516366 | G12: -7.3076389 | H12: -11.297486 | I12: 2.8643752 | J12: 0.28663842 | K12: 6.0270761 | L12: 2.521947 | M12: 5.6129431 | N12: 1.9802869 | O12: 1.0652965 | P12: -0.50508437 | Q12: 0.88051197
A13: 1998q3 | B13: -1.3581313 | C13: -0.54302441 | D13: -2.6077571 | E13: -2.9703469 | F13: -1.4158352 | G13: -6.775346 | H13: -12.877313 | I13: 2.7958841 | J13: 1.2730979 | K13: 3.199307 | L13: 2.9549893 | M13: 7.1213464 | N13: 1.8396492 | O13: 0.66552399 | P13: -1.1547579 | Q13: 0.45125835
A14: 1998q4 | B14: 0.32670059 | C14: 2.5142321 | D14: -2.9945696 | E14: -2.9729071 | F14: -1.702557 | G14: -4.504051 | H14: -12.714059 | I14: 2.9481481 | J14: 3.2515896 | K14: 1.7591281 | L14: 2.5797288 | M14: 8.3857556 | N14: 1.7611372 | O14: 0.91561596 | P14: -1.2894656 | Q14: 0.65550929
... A74: 2013q4 | B74: 2.7164854 | C74: 1.6424668 | D74: 6.675513 | E74: 1.8538281 | F74: 1.9241157 | G74: -0.24946354 | H74: 2.6587006 | I74: 1.9339187 | J74: 2.8470937 | K74: 1.7274533 | L74: 2.450658 | M74: 1.6549792 | N74: 0.41968475 | O74: 1.9563583 | P74: 0.80229613 | Q74: 1.8331903
A75: Average Year on Year Growth Rate | B75: =AVERAGE(B3:B74) -> 1.8319401 | C75: =AVERAGE(C3:C74) -> 2.8916456 | D75: =AVERAGE(D3:D74) -> -0.39277115 | E75: =AVERAGE(E3:E74) -> 2.5790346 | F75: =AVERAGE(F3:F74) -> 2.5675236 | G75: =AVERAGE(G3:G74) -> 1.3296816 | H75: =AVERAGE(H3:H74) -> 4.36074 | I75: =AVERAGE(I3:I74) -> 3.8988792 | ... Q75: =AVERAGE(Q3:Q74) -> 3.2877592

Sheet Prov Contributions
A1: Yearly Provincial Contribution Rates per Sector
B2: Primary Industries | C2: Agriculture, forestry and fishing | D2: Mining and quarrying | E2: Secondary Industries | F2: Manufacturing | G2: Electricity, gas and water | H2: Construction | I2: Tertiary industries | J2: Wholesale & retail trade; hotels & restaurants | K2: Transport , storage and communication | L2: Finance, real estate and business services | M2: Personal services | N2: General government services
A3: 1996 | B3: 8.1141393 | C3: 4.9487771 | D3: 3.1653621 | E3: 26.544078 | F3: 21.635484 | G3: 2.5765822 | H3: 2.3320118 | I3: 53.647683 | J3: 11.267858 | K3: 9.4161386 | L3: 13.451546 | M3: 5.5390452 | N3: 13.973095
A4: =A3+1 -> 1997 | B4: 7.9760234 | C4: 4.836847 | D4: 3.1391764 | E4: 26.817294 | F4: 21.784655 | G4: 2.6143681 | H4: 2.4182716 | I4: 53.419535 | J4: 11.113802 | K4: 9.7497328 | L4: 13.753923 | M4: 5.4276585 | N4: 13.374417
A5: =A4+1 -> 1998 | B5: 7.9084368 | C5: 4.8384744 | D5: 3.0699624 | E5: 26.059821 | F5: 21.498933 | G5: 2.4333497 | H5: 2.1275379 | I5: 54.412046 | J5: 11.114693 | K5: 10.103078 | L5: 13.965812 | M5: 5.7153968 | N5: 13.513066
A6: =A5+1 -> 1999 | B6: 6.8827283 | C6: 4.6753244 | D6: 2.2074039 | E6: 26.084396 | F6: 21.677125 | G6: 2.4162222 | H6: 1.9910485 | I6: 55.727983 | J6: 11.819005 | K6: 10.382155 | L6: 14.702205 | M6: 5.8814561 | N6: 12.943162
A7: =A6+1 -> 2000 | B7: 6.7037237 | C7: 4.6446681 | D7: 2.0590556 | E7: 26.969533 | F7: 22.538701 | G7: 2.4492754 | H7: 1.9815567 | I7: 55.331035 | J7: 12.249639 | K7: 10.582516 | L7: 14.245311 | M7: 5.8965701 | N7: 12.356999
A8: =A7+1 -> 2001 | B8: 6.3013256 | C8: 4.4308219 | D8: 1.8705037 | E8: 27.105098 | F8: 22.219788 | G8: 2.3411887 | H8: 2.5441216 | I8: 55.343987 | J8: 12.643422 | K8: 10.568301 | L8: 14.415234 | M8: 5.7767386 | N8: 11.940292
A9: =A8+1 -> 2002 | B9: 6.1549403 | C9: 4.5244688 | D9: 1.6304713 | E9: 26.718837 | F9: 22.251899 | G9: 2.5060351 | H9: 1.9609022 | I9: 56.162972 | J9: 12.638744 | K9: 11.276479 | L9: 14.776336 | M9: 5.772453 | N9: 11.698962
A10: =A9+1 -> 2003 | B10: 6.3120703 | C10: 4.6318203 | D10: 1.6801214 | E10: 25.616951 | F10: 21.459372 | G10: 2.1583822 | H10: 1.9991968 | I10: 57.224449 | J10: 12.727959 | K10: 11.742689 | L10: 15.185689 | M10: 5.9313479 | N10: 11.636817
A11: =A10+1 -> 2004 | B11: 6.086093 | C11: 4.4458645 | D11: 1.6400258 | E11: 25.810539 | F11: 21.501148 | G11: 2.2166641 | H11: 2.0927266 | I11: 57.228101 | J11: 12.842451 | K11: 11.740684 | L11: 15.582176 | M11: 5.7764775 | N11: 11.286333
A12: =A11+1 -> 2005 | B12: 5.4118357 | C12: 3.9584003 | D12: 1.4536797 | E12: 26.063816 | F12: 21.584399 | G12: 2.2324188 | H12: 2.2470308 | I12: 57.777196 | J12: 12.928479 | K12: 11.758033 | L12: 16.291819 | M12: 5.6463577 | N12: 11.152363
A13: =A12+1 -> 2006 | B13: 5.1021158 | C13: 3.7707144 | D13: 1.3314226 | E13: 26.163409 | F13: 21.687243 | G13: 2.1852143 | H13: 2.2909884 | I13: 57.898119 | J13: 13.034992 | K13: 11.72092 | L13: 16.625495 | M13: 5.6341719 | N13: 10.882543
A14: =A13+1 -> 2007 | B14: 4.9946671 | C14: 3.7063088 | D14: 1.2886431 | E14: 26.173236 | F14: 21.56535 | G14: 2.1323576 | H14: 2.4755292 | I14: 58.102266 | J14: 12.997737 | K14: 11.857889 | L14: 16.918338 | M14: 5.6135747 | N14: 10.694927
A15: =A14+1 -> 2008 | B15: 5.2426876 | C15: 4.083063 | D15: 1.1583891 | E15: 25.849547 | F15: 21.272167 | G15: 1.9683475 | H15: 2.5846361 | I15: 58.314119 | J15: 12.633353 | K15: 11.882485 | L15: 17.47347 | M15: 5.6025945 | N15: 10.792808
... A17: =A16+1 -> 2010 | B17: 5.1345214 | C17: 3.9731512 | D17: 1.1613702 | E17: 24.551635 | F17: 19.890692 | G17: 1.8733352 | H17: 2.7876079 | I17: 59.719728 | J17: 12.890267 | K17: 12.132755 | L17: 17.806583 | M17: 5.5195053 | N17: 11.370616
A18: 2011 | B18: 4.9825785 | C18: 3.8766114 | D18: 1.1059672 | E18: 24.370141 | F18: 19.836497 | G18: 1.8305752 | H18: 2.7030684 | I18: 60.064795 | J18: 13.08035 | K18: 12.055777 | L18: 18.022259 | M18: 5.4659805 | N18: 11.440429
A19: 2012 | B19: 4.9624906 | C19: 3.8659036 | D19: 1.096587 | E19: 24.122265 | F19: 19.704914 | G19: 1.7217908 | H19: 2.6955608 | I19: 60.20774 | J19: 13.198916 | K19: 12.027275 | L19: 18.116419 | M19: 5.4368068 | N19: 11.428322
A20: 2013 | B20: 5.0234838 | C20: 3.9300429 | D20: 1.0934409 | E20: 23.921076 | F20: 19.512553 | G20: 1.6804984 | H20: 2.7280246 | I20: 60.472814 | J20: 13.340501 | K20: 12.024457 | L20: 18.251006 | M20: 5.450298 | N20: 11.406552
A21: Average Yearly Contributions | B21: =AVERAGE(B3:B20) -> 6.0296274 | C21: =AVERAGE(C3:C20) -> 4.2877032 | D21: =AVERAGE(D3:D20) -> 1.7364197 | E21: =AVERAGE(E3:E20) -> 25.725117 | F21: =AVERAGE(F3:F20) -> 21.1735 | G21: =AVERAGE(G3:G20) -> 2.1812304 | H21: =AVERAGE(H3:H20) -> 2.3784556 | I21: =AVERAGE(I3:I20) -> 57.288979 | ... N21: =AVERAGE(N3:N20) -> 11.850475
I23: \

Sheet National Contributions
A1: Yearly Provincial Sector as a % of National Sector GDP
B2: Primary Industries | C2: Agriculture, forestry and fishing | D2: Mining and quarrying | E2: Secondary Industries | F2: Manufacturing | G2: Electricity, gas and water | H2: Construction | I2: Tertiary industries | J2: Wholesale & retail trade; hotels & restaurants | K2: Transport , storage and communication | L2: Finance, real estate and business services | M2: Personal services | N2: General government services
A3: 1995 | B3: 9.9424284 | C3: 31.219885 | D3: 4.3687653 | E3: 20.258311 | F3: 20.924039 | G3: 17.394424 | H3: 18.021026 | I3: 15.682809 | J3: 16.221638 | K3: 23.298916 | L3: 13.96367 | M3: 16.393128 | N3: 13.657639
A4: =A3+1 -> 1996 | B4: 11.846085 | C4: 29.289638 | D4: 6.1343776 | E4: 20.22306 | F4: 20.995847 | G4: 17.437449 | H4: 17.359219 | I4: 15.683492 | J4: 15.994351 | K4: 22.940362 | L4: 13.971525 | M4: 16.383734 | N4: 13.905927
A5: =A4+1 -> 1997 | B5: 11.695543 | C5: 28.924531 | D5: 6.0984701 | E5: 20.240022 | F5: 20.985825 | G5: 17.360777 | H5: 17.741225 | I5: 15.52552 | J5: 16.01892 | K5: 22.505408 | L5: 13.909302 | M5: 16.372374 | N5: 13.463214
A6: =A5+1 -> 1998 | B6: 11.860752 | C6: 30.820293 | D6: 6.0220877 | E6: 20.137868 | F6: 20.933221 | G6: 17.395692 | H6: 16.730718 | I6: 15.63944 | J6: 15.952653 | K6: 22.298198 | L6: 13.926272 | M6: 16.373799 | N6: 13.824964
A7: =A6+1 -> 1999 | B7: 10.361367 | C7: 28.257792 | D7: 4.4252885 | E7: 20.253183 | F7: 21.141974 | G7: 17.493377 | H7: 15.994737 | I7: 15.546708 | J7: 15.886446 | K7: 21.948787 | L7: 14.054892 | M7: 16.346474 | N7: 13.458472
A8: =A7+1 -> 2000 | B8: 10.503663 | C8: 28.002507 | D8: 4.3590716 | E8: 20.376978 | F8: 21.237798 | G8: 17.962971 | H8: 15.736125 | I8: 15.510131 | J8: 15.907644 | K8: 21.574756 | L8: 13.784243 | M8: 16.329207 | N8: 13.544797
A9: =A8+1 -> 2001 | B9: 10.409914 | C9: 28.855299 | D9: 4.1404213 | E9: 20.83866 | F9: 21.191726 | G9: 18.624138 | H9: 20.112824 | I9: 15.645274 | J9: 16.83056 | K9: 21.251603 | L9: 13.469804 | M9: 16.342479 | N9: 13.799913
A10: =A9+1 -> 2002 | B10: 10.177248 | C10: 28.355032 | D10: 3.6622552 | E10: 20.407725 | F10: 21.157837 | G10: 19.740468 | H10: 15.015439 | I10: 15.634785 | J10: 16.855168 | K10: 21.320844 | L10: 13.314982 | M10: 16.334138 | N10: 13.758766
A11: =A10+1 -> 2003 | B11: 10.443497 | C11: 29.622369 | D11: 3.7499384 | E11: 20.134162 | F11: 21.284184 | G11: 16.967711 | H11: 14.605836 | I11: 15.711259 | J11: 16.98696 | K11: 21.449795 | L11: 13.415399 | M11: 16.336224 | N11: 13.682483
A12: =A11+1 -> 2004 | B12: 10.383123 | C12: 29.458493 | D12: 3.7681573 | E12: 20.086365 | F12: 21.244725 | G12: 17.052466 | H12: 14.642919 | I12: 15.687998 | J12: 16.993237 | K12: 21.366281 | L12: 13.436771 | M12: 16.339684 | N12: 13.606768
A13: =A12+1 -> 2005 | B13: 9.6216352 | C13: 26.981005 | D13: 3.4964845 | E13: 20.094621 | F13: 21.237649 | G13: 17.241025 | H13: 14.856965 | I13: 15.889524 | J13: 16.901343 | K13: 21.492347 | L13: 14.055377 | M13: 16.273577 | N13: 13.632321
A14: =A13+1 -> 2006 | B14: 9.7546038 | C14: 28.69121 | D14: 3.3997567 | E14: 19.968995 | F14: 21.157434 | G14: 17.2214 | H14: 14.475115 | I14: 15.810172 | J14: 16.971881 | K14: 21.509594 | L14: 13.805498 | M14: 16.286643 | N14: 13.621477
A15: =A14+1 -> 2007 | B15: 10.046867 | C15: 29.088604 | D15: 3.4854353 | E15: 19.910984 | F15: 21.168502 | G15: 17.213097 | H15: 14.402204 | I15: 15.841876 | J15: 17.017461 | K15: 21.616175 | L15: 13.791428 | M15: 16.278713 | N15: 13.646462
... A18: =A17+1 -> 2010 | B18: 11.02007 | C18: 28.8929 | D18: 3.5363263 | E18: 19.825717 | F18: 21.306521 | G18: 16.413865 | H18: 14.618352 | I18: 15.971597 | J18: 17.311027 | K18: 21.944372 | L18: 13.917219 | M18: 16.428511 | N18: 13.763034
A19: 2011 | B19: 11.05284 | C19: 29.21315 | D19: 3.4768417 | E19: 19.852441 | F19: 21.305121 | G19: 16.367918 | H19: 14.638272 | I19: 15.981661 | J19: 17.421665 | K19: 21.898404 | L19: 13.929092 | M19: 16.466811 | N19: 13.763433
A20: 2012 | B20: 11.085609 | C20: 29.352449 | D20: 3.6770642 | E20: 19.879165 | F20: 21.317651 | G20: 16.090187 | H20: 14.668387 | I20: 15.991725 | J20: 17.408257 | K20: 21.929748 | L20: 13.881471 | M20: 16.496783 | N20: 13.753493
A21: 2013 | B21: 11.118378 | C21: 29.6727 | D21: 3.6175797 | E21: 19.905889 | F21: 21.316251 | G21: 16.04424 | H21: 14.688307 | I21: 16.001789 | J21: 17.518896 | K21: 21.883779 | L21: 13.893344 | M21: 16.535083 | N21: 13.753892
A22: Average Yearly Contributions | B22: =AVERAGE(B3:B21) -> 10.712904 | C22: =AVERAGE(C3:C21) -> 29.03865 | D22: =AVERAGE(D3:D21) -> 4.1202907 | E22: =AVERAGE(E3:E21) -> 20.096155 | F22: =AVERAGE(F3:F21) -> 21.171238 | G22: =AVERAGE(G3:G21) -> 17.246868 | H22: =AVERAGE(H3:H21) -> 15.642251 | I22: =AVERAGE(I3:I21) -> 15.758581 | ... N22: =AVERAGE(N3:N21) -> 13.685758

Sheet GDP Durban
D1: Ethekwini Municipal Area
C2: SA GDP | D2: SA Quarterly GDP | E2: KZN Quarterly GDP | F2: SA Fuel Consumption | G2: KZN Fuel Consumption | H2: SA KZN GDP Ratio | I2: SA KZN Fuel Ratio | J2: SA Usage | K2: KZN Usage | L2: Durban Fuel Usage | M2: Durban Quarterly GDP | N2: Durban Quarterly Rate | O2: Durban Annual Rate
A3: 2001q1 | B3: 52513.786 | C3: 322910.91 | D3: =C3*1000000 -> 3.2291091e+11 | E3: =B3*1000000 -> 5.2513786e+10
A4: 2001q2 | B4: 55248.344 | C4: 334720.11 | D4: =C4*1000000 -> 3.3472011e+11 | E4: =B4*1000000 -> 5.5248344e+10
A5: 2001q3 | B5: 55639.049 | C5: 338640.98 | D5: =C5*1000000 -> 3.3864098e+11 | E5: =B5*1000000 -> 5.5639049e+10
A6: 2001q4 | B6: 55758.173 | C6: 342446.67 | D6: =C6*1000000 -> 3.4244667e+11 | E6: =B6*1000000 -> 5.5758173e+10
A7: 2002q1 | B7: 53541.924 | C7: 333305.59 | D7: =C7*1000000 -> 3.3330559e+11 | E7: =B7*1000000 -> 5.3541924e+10 | F7: 4118958622 | G7: 674878797 | H7: =E7/D7*100 -> 16.063914 | I7: =G7/F7*100 -> 16.384695 | J7: =D7/F7 -> 80.919869 | K7: =E7/G7 -> 79.335615 | M7: =E7*$L$26 -> 3.0643924e+10
A8: 2002q2 | B8: 56761.422 | C8: 347204.33 | D8: =C8*1000000 -> 3.4720433e+11 | E8: =B8*1000000 -> 5.6761422e+10 | F8: 4128329079 | G8: 697677279 | H8: =E8/D8*100 -> 16.348132 | I8: =G8/F8*100 -> 16.89975 | J8: =D8/F8 -> 84.102871 | K8: =E8/G8 -> 81.357705 | M8: =E8*$L$26 -> 3.2486555e+10 | N8: =(M8-M7)/M7*100 -> 6.0130403
A9: 2002q3 | B9: 56894.032 | C9: 350396.67 | D9: =C9*1000000 -> 3.5039667e+11 | E9: =B9*1000000 -> 5.6894032e+10 | F9: 4479766142 | G9: 748604188 | H9: =E9/D9*100 -> 16.237035 | I9: =G9/F9*100 -> 16.710787 | J9: =D9/F9 -> 78.217625 | K9: =E9/G9 -> 76.000151 | M9: =E9*$L$26 -> 3.2562453e+10 | N9: =(M9-M8)/M8*100 -> 0.23362625
A10: 2002q4 | B10: 57325.635 | C10: 355528.42 | D10: =C10*1000000 -> 3.5552842e+11 | E10: =B10*1000000 -> 5.7325635e+10 | F10: 4393645140 | G10: 741841930 | H10: =E10/D10*100 -> 16.124065 | I10: =G10/F10*100 -> 16.88443 | J10: =D10/F10 -> 80.918784 | K10: =E10/G10 -> 77.274731 | M10: =E10*$L$26 -> 3.2809475e+10 | N10: =(M10-M9)/M9*100 -> 0.75861004
A11: 2003q1 | B11: 55181.295 | C11: 343994.76 | D11: =C11*1000000 -> 3.4399476e+11 | E11: =B11*1000000 -> 5.5181295e+10 | F11: 4.3245102e+09 | G11: 7.3345414e+08 | H11: =E11/D11*100 -> 16.041318 | I11: =G11/F11*100 -> 16.960398 | J11: =D11/F11 -> 79.54537 | K11: =E11/G11 -> 75.234826 | M11: =E11*$L$26 -> 3.1582193e+10 | N11: =(M11-M10)/M10*100 -> -3.7406313 | O11: =(M11-M7)/M7*100 -> 3.0618441 | R11: Yearly Growth Rate %
A12: 2003q2 | B12: 58708.707 | C12: 358345.1 | D12: =C12*1000000 -> 358345100000 | E12: =B12*1000000 -> 5.8708707e+10 | F12: 4.3448327e+09 | G12: 7.3310499e+08 | H12: =E12/D12*100 -> 16.383287 | I12: =G12/F12*100 -> 16.873032 | J12: =D12/F12 -> 82.476157 | K12: =E12/G12 -> 80.082264 | M12: =E12*$L$26 -> 3.3601055e+10 | N12: =(M12-M11)/M11*100 -> 6.3924065 | O12: =(M12-M8)/M8*100 -> 3.4306495 | R12: 2001
A13: 2003q3 | B13: 58465.53 | C13: 360923 | D13: =C13*1000000 -> 360923000000 | E13: =B13*1000000 -> 5.846553e+10 | F13: 4.469508e+09 | G13: 7.5596579e+08 | H13: =E13/D13*100 -> 16.198893 | I13: =G13/F13*100 -> 16.913848 | J13: =D13/F13 -> 80.752289 | K13: =E13/G13 -> 77.338857 | M13: =E13*$L$26 -> 3.3461876e+10 | N13: =(M13-M12)/M12*100 -> -0.41420957 | O13: =(M13-M9)/M9*100 -> 2.7621505 | R13: =R12+1 -> 2002 | S13: =SUM(M7:M10) -> 1.2850241e+11
A14: 2003q4 | B14: 58326.547 | C14: 364059.16 | D14: =C14*1000000 -> 364059160000 | E14: =B14*1000000 -> 5.8326547e+10 | F14: 4.7924549e+09 | G14: 792421454 | H14: =E14/D14*100 -> 16.021173 | I14: =G14/F14*100 -> 16.534771 | J14: =D14/F14 -> 75.965068 | K14: =E14/G14 -> 73.605462 | M14: =E14*$L$26 -> 3.3382332e+10 | N14: =(M14-M13)/M13*100 -> -0.237718 | O14: =(M14-M10)/M10*100 -> 1.7460109 | R14: =R13+1 -> 2003 | S14: =SUM(M11:M14) -> 1.3202746e+11 | T14: =(S14-S13)/S13*100 -> 2.7431782
A15: 2004q1 | B15: 57038.421 | C15: 356887.07 | D15: =C15*1000000 -> 356887070000 | E15: =B15*1000000 -> 5.7038421e+10 | F15: 4.4993406e+09 | G15: 7.3594163e+08 | H15: =E15/D15*100 -> 15.982204 | I15: =G15/F15*100 -> 16.356655 | J15: =D15/F15 -> 79.319862 | K15: =E15/G15 -> 77.504001 | M15: =E15*$L$26 -> 3.2645092e+10 | N15: =(M15-M14)/M14*100 -> -2.2084734 | O15: =(M15-M11)/M11*100 -> 3.3654996 | R15: =R14+1 -> 2004 | S15: =SUM(M15:M18) -> 1.3796423e+11 | T15: =(S15-S14)/S14*100 -> 4.4966214
A16: 2004q2 | B16: 60603.21 | C16: 371714 | D16: =C16*1000000 -> 371714000000 | E16: =B16*1000000 -> 6.060321e+10 | F16: 4.5436772e+09 | G16: 7.6518177e+08 | H16: =E16/D16*100 -> 16.30372 | I16: =G16/F16*100 -> 16.840584 | J16: =D16/F16 -> 81.809069 | K16: =E16/G16 -> 79.201065 | M16: =E16*$L$26 -> 3.4685346e+10 | N16: =(M16-M15)/M15*100 -> 6.249804 | O16: =(M16-M12)/M12*100 -> 3.2269541 | R16: =R15+1 -> 2005 | S16: =SUM(M19:M22) -> 1.4591076e+11 | T16: =(S16-S15)/S15*100 -> 5.7598464
A17: 2004q3 | B17: 61506.21 | C17: 379044 | D17: =C17*1000000 -> 379044000000 | E17: =B17*1000000 -> 6.150621e+10 | F17: 4.7754909e+09 | G17: 7.9366597e+08 | H17: =E17/D17*100 -> 16.226668 | I17: =G17/F17*100 -> 16.619568 | J17: =D17/F17 -> 79.372783 | K17: =E17/G17 -> 77.496343 | M17: =E17*$L$26 -> 3.5202164e+10 | N17: =(M17-M16)/M16*100 -> 1.4900191 | O17: =(M17-M13)/M13*100 -> 5.2008073 | R17: =R16+1 -> 2006 | S17: =SUM(M23:M26) -> 1.5398411e+11 | T17: =(S17-S16)/S16*100 -> 5.5330718
A18: 2004q4 | B18: 61907.138 | C18: 384685.19 | D18: =C18*1000000 -> 384685190000 | E18: =B18*1000000 -> 6.1907138e+10 | F18: 4.830257e+09 | G18: 826240651 | H18: =E18/D18*100 -> 16.092935 | I18: =G18/F18*100 -> 17.105521 | J18: =D18/F18 -> 79.640729 | K18: =E18/G18 -> 74.92628 | L18: =L31/G31 -> 0.58440942 | M18: =E18*$L$26 -> 3.543163e+10 | N18: =(M18-M17)/M17*100 -> 0.65185016 | O18: =(M18-M14)/M14*100 -> 6.1388701 | R18: =R17+1 -> 2007 | S18: =SUM(M27:M30) -> 1.630291e+11 | T18: =(S18-S17)/S17*100 -> 5.8739793
A19: 2005q1 | B19: 60432.298 | C19: 376326.8 | D19: =C19*1000000 -> 3.763268e+11 | E19: =B19*1000000 -> 6.0432298e+10 | F19: 4690209425 | G19: 774740717 | H19: =E19/D19*100 -> 16.058462 | I19: =G19/F19*100 -> 16.518254 | J19: =D19/F19 -> 80.236673 | K19: =E19/G19 -> 78.003255 | L19: =L32/G32 -> 0.58543455 | M19: =E19*$L$26 -> 3.4587527e+10 | N19: =(M19-M18)/M18*100 -> -2.3823427 | O19: =(M19-M15)/M15*100 -> 5.9501596 | R19: =R18+1 -> 2008 | S19: =SUM(M31:M34) -> 1.7140335e+11 | T19: =(S19-S18)/S18*100 -> 5.1366574
A20: 2005q2 | B20: 63723.503 | C20: 391001.65 | D20: =C20*1000000 -> 391001650000 | E20: =B20*1000000 -> 6.3723503e+10 | F20: 4760343407 | G20: 805551748 | H20: =E20/D20*100 -> 16.297502 | I20: =G20/F20*100 -> 16.922135 | J20: =D20/F20 -> 82.137278 | K20: =E20/G20 -> 79.105413 | L20: =L33/G33 -> 0.58087082 | M20: =E20*$L$26 -> 3.6471199e+10 | N20: =(M20-M19)/M19*100 -> 5.4461033 | O20: =(M20-M16)/M16*100 -> 5.1487255 | R20: =R19+1 -> 2009 | S20: =SUM(M35:M38) -> 1.6420787e+11 | T20: =(S20-S19)/S19*100 -> -4.1979772
A21: 2005q3 | B21: 65295.809 | C21: 399721.75 | D21: =C21*1000000 -> 399721750000 | E21: =B21*1000000 -> 6.5295809e+10 | F21: 4824982237 | G21: 802738840 | H21: =E21/D21*100 -> 16.335315 | I21: =G21/F21*100 -> 16.637136 | J21: =D21/F21 -> 82.844191 | K21: =E21/G21 -> 81.341285 | L21: =L34/G34 -> 0.5631147 | M21: =E21*$L$26 -> 3.7371085e+10 | N21: =(M21-M20)/M20*100 -> 2.4673865 | O21: =(M21-M17)/M17*100 -> 6.1613269 | R21: =R20+1 -> 2010 | S21: =SUM(M39:M42) -> 1.7284862e+11 | T21: =(S21-S20)/S20*100 -> 5.2620775
A22: 2005q4 | B22: 65487.766 | C22: 404031.7 | D22: =C22*1000000 -> 404031700000 | E22: =B22*1000000 -> 6.5487766e+10 | F22: 5011501336 | G22: 832010091 | H22: =E22/D22*100 -> 16.208571 | I22: =G22/F22*100 -> 16.602013 | J22: =D22/F22 -> 80.62089 | K22: =E22/G22 -> 78.710303 | L22: =L35/G35 -> 0.56498434 | M22: =E22*$L$26 -> 3.7480949e+10 | N22: =(M22-M21)/M21*100 -> 0.29398147 | O22: =(M22-M18)/M18*100 -> 5.7838692 | R22: =R21+1 -> 2011 | S22: =SUM(M43:M46) -> 1.7887678e+11 | T22: =(S22-S21)/S21*100 -> 3.4875401
A23: 2006q1 | B23: 63682.062 | C23: 395450.15 | D23: =C23*1000000 -> 3.9545015e+11 | E23: =B23*1000000 -> 6.3682062e+10 | F23: 4675546289 | G23: 750919883 | H23: =E23/D23*100 -> 16.103689 | I23: =G23/F23*100 -> 16.060581 | J23: =D23/F23 -> 84.578384 | K23: =E23/G23 -> 84.805401 | L23: =L36/G36 -> 0.56386607 | M23: =E23*$L$26 -> 3.6447481e+10 | N23: =(M23-M22)/M22*100 -> -2.7573152 | O23: =(M23-M19)/M19*100 -> 5.3775284 | R23: =R22+1 -> 2012 | S23: =SUM(M47:M50) -> 1.8309418e+11 | T23: =(S23-S22)/S22*100 -> 2.3577074
A24: 2006q2 | B24: 66827.792 | C24: 410299.05 | D24: =C24*1000000 -> 410299050000 | E24: =B24*1000000 -> 6.6827792e+10 | F24: 4859349229 | G24: 811777848 | H24: =E24/D24*100 -> 16.287582 | I24: =G24/F24*100 -> 16.705485 | J24: =D24/F24 -> 84.434979 | K24: =E24/G24 -> 82.322759 | L24: =L37/G37 -> 0.56366596 | M24: =E24*$L$26 -> 3.8247893e+10 | N24: =(M24-M23)/M23*100 -> 4.9397431 | O24: =(M24-M20)/M20*100 -> 4.8714975 | R24: =R23+1 -> 2013 | S24: =SUM(M51:M54) -> 1.8686986e+11 | T24: =(S24-S23)/S23*100 -> 2.0621563
A25: 2006q3 | B25: 68605.41 | C25: 420695.75 | D25: =C25*1000000 -> 420695750000 | E25: =B25*1000000 -> 6.860541e+10 | F25: 4906222423 | G25: 827883368 | H25: =E25/D25*100 -> 16.307607 | I25: =G25/F25*100 -> 16.874151 | J25: =D25/F25 -> 85.747386 | K25: =E25/G25 -> 82.868448 | M25: =E25*$L$26 -> 3.9265286e+10 | N25: =(M25-M24)/M24*100 -> 2.6599976 | O25: =(M25-M21)/M21*100 -> 5.0686276
A26: 2006q4 | B26: 69930.091 | C26: 432676.71 | D26: =C26*1000000 -> 432676710000 | E26: =B26*1000000 -> 6.9930091e+10 | F26: 5280826192 | G26: 873224453 | H26: =E26/D26*100 -> 16.162204 | I26: =G26/F26*100 -> 16.535754 | J26: =D26/F26 -> 81.933526 | K26: =E26/G26 -> 80.082607 | L26: =AVERAGE(L18:L24) -> 0.57233512 | M26: =E26*$L$26 -> 4.0023447e+10 | N26: =(M26-M25)/M25*100 -> 1.9308691 | O26: =(M26-M22)/M22*100 -> 6.7834417 | Q26: =M26/E26 -> 0.57233512
A27: 2007q1 | B27: 68125.905 | C27: 421784.96 | D27: =C27*1000000 -> 421784960000 | E27: =B27*1000000 -> 6.8125905e+10 | F27: 5154329343 | G27: 833477953 | H27: =E27/D27*100 -> 16.15181 | I27: =G27/F27*100 -> 16.170444 | J27: =D27/F27 -> 81.831201 | K27: =E27/G27 -> 81.736901 | M27: =E27*$L$26 -> 3.8990848e+10 | N27: =(M27-M26)/M26*100 -> -2.5799844 | O27: =(M27-M23)/M23*100 -> 6.978171 | Q27: =M27/E27 -> 0.57233512
A28: 2007q2 | B28: 70787.165 | C28: 433014.5 | D28: =C28*1000000 -> 433014500000 | E28: =B28*1000000 -> 7.0787165e+10 | F28: 5056692012 | G28: 821281896 | H28: =E28/D28*100 -> 16.347528 | I28: =G28/F28*100 -> 16.241485 | J28: =D28/F28 -> 85.63197 | K28: =E28/G28 -> 86.191069 | M28: =E28*$L$26 -> 4.0513981e+10 | N28: =(M28-M27)/M27*100 -> 3.9063843 | O28: =(M28-M24)/M24*100 -> 5.9247395 | Q28: =M28/E28 -> 0.57233512
A29: 2007q3 | B29: 72253.953 | C29: 442196.5 | D29: =C29*1000000 -> 442196500000 | E29: =B29*1000000 -> 7.2253953e+10 | F29: 5400223668 | G29: 898105429 | H29: =E29/D29*100 -> 16.339784 | I29: =G29/F29*100 -> 16.630893 | J29: =D29/F29 -> 81.884849 | K29: =E29/G29 -> 80.451526 | M29: =E29*$L$26 -> 4.1353475e+10 | N29: =(M29-M28)/M28*100 -> 2.0721098 | O29: =(M29-M25)/M25*100 -> 5.3181559 | Q29: =M29/E29 -> 0.57233512
A30: 2007q4 | B30: 73682 | C30: 454168.72 | D30: =C30*1000000 -> 454168720000 | E30: =B30*1000000 -> 7.3682e+10 | F30: 5579296845 | G30: 902642355 | H30: =E30/D30*100 -> 16.223486 | I30: =G30/F30*100 -> 16.178425 | J30: =D30/F30 -> 81.402502 | K30: =E30/G30 -> 81.62923 | M30: =E30*$L$26 -> 4.2170797e+10 | N30: =(M30-M29)/M29*100 -> 1.9764288 | O30: =(M30-M26)/M26*100 -> 5.3652296 | Q30: =M30/E30 -> 0.57233512
A31: 2008q1 | B31: 71161.409 | C31: 437677.31 | D31: =C31*1000000 -> 437677308000 | E31: =B31*1000000 -> 7.1161409e+10 | F31: 5543646776 | G31: 903773016 | H31: =E31/D31*100 -> 16.258876 | I31: =G31/F31*100 -> 16.302861 | J31: =D31/F31 -> 78.951154 | K31: =E31/G31 -> 78.738143 | L31: 528173464 | M31: =L31*K31 -> 4.1587398e+10 | N31: =(M31-M30)/M30*100 -> -1.3834201 | O31: =(M31-M27)/M27*100 -> 6.6593812 | Q31: =M31/E31 -> 0.58440942
A32: 2008q2 | B32: 74756.111 | C32: 454885.92 | D32: =C32*1000000 -> 454885920000 | E32: =B32*1000000 -> 7.4756111e+10 | F32: 5265926862 | G32: 890535459 | H32: =E32/D32*100 -> 16.434035 | I32: =G32/F32*100 -> 16.911277 | J32: =D32/F32 -> 86.382878 | K32: =E32/G32 -> 83.945126 | L32: 521350226 | M32: =L32*K32 -> 4.376481e+10 | N32: =(M32-M31)/M31*100 -> 5.2357513 | O32: =(M32-M28)/M28*100 -> 8.0239697 | Q32: =M32/E32 -> 0.58543455
A33: 2008q3 | B33: 75462.98 | C33: 459649.57 | D33: =C33*1000000 -> 459649572000 | E33: =B33*1000000 -> 7.546298e+10 | F33: 5202135900 | G33: 869534795 | H33: =E33/D33*100 -> 16.417503 | I33: =G33/F33*100 -> 16.714957 | J33: =D33/F33 -> 88.357855 | K33: =E33/G33 -> 86.785463 | L33: 505087388 | M33: =L33*K33 -> 4.3834243e+10 | N33: =(M33-M32)/M32*100 -> 0.15864996 | O33: =(M33-M29)/M29*100 -> 5.9989354 | Q33: =M33/E33 -> 0.58087082
A34: 2008q4 | B34: 74970.333 | C34: 462381.81 | D34: =C34*1000000 -> 462381807000 | E34: =B34*1000000 -> 7.4970333e+10 | F34: 5460259824 | G34: 899511198 | H34: =E34/D34*100 -> 16.213945 | I34: =G34/F34*100 -> 16.47378 | J34: =D34/F34 -> 84.681283 | K34: =E34/G34 -> 83.345636 | L34: 506527974 | M34: =L34*K34 -> 4.2216896e+10 | N34: =(M34-M33)/M33*100 -> -3.689688 | O34: =(M34-M30)/M30*100 -> 0.109316 | Q34: =M34/E34 -> 0.5631147
A35: 2009q1 | B35: 70528.748 | C35: 433798.09 | D35: =C35*1000000 -> 4.3379809e+11 | E35: =B35*1000000 -> 7.0528748e+10 | F35: 5083035776 | G35: 823636857 | H35: =E35/D35*100 -> 16.258427 | I35: =G35/F35*100 -> 16.203641 | J35: =D35/F35 -> 85.342325 | K35: =E35/G35 -> 85.630879 | L35: 465341929 | M35: =L35*K35 -> 3.9847638e+10 | N35: =(M35-M34)/M34*100 -> -5.6121082 | O35: =(M35-M31)/M31*100 -> -4.1833807 | Q35: =M35/E35 -> 0.56498434
A36: 2009q2 | B36: 72534.525 | C36: 442774.06 | D36: =C36*1000000 -> 4.4277406e+11 | E36: =B36*1000000 -> 7.2534525e+10 | F36: 4994646966 | G36: 831381344 | H36: =E36/D36*100 -> 16.381837 | I36: =G36/F36*100 -> 16.645448 | J36: =D36/F36 -> 88.649721 | K36: =E36/G36 -> 87.245794 | L36: 468787734 | M36: =L36*K36 -> 4.0899758e+10 | N36: =(M36-M35)/M35*100 -> 2.640356 | O36: =(M36-M32)/M32*100 -> -6.546475 | Q36: =M36/E36 -> 0.56386607
A37: 2009q3 | B37: 73855.97 | C37: 450502.49 | D37: =C37*1000000 -> 4.5050249e+11 | E37: =B37*1000000 -> 7.385597e+10 | F37: 5002707417 | G37: 835393434 | H37: =E37/D37*100 -> 16.394131 | I37: =G37/F37*100 -> 16.698827 | J37: =D37/F37 -> 90.051736 | K37: =E37/G37 -> 88.408607 | L37: 470882842 | M37: =L37*K37 -> 4.1630096e+10 | N37: =(M37-M36)/M36*100 -> 1.7856787 | O37: =(M37-M33)/M33*100 -> -5.0283678 | Q37: =M37/E37 -> 0.56366596
A38: 2009q4 | B38: 74797.338 | C38: 459824.14 | D38: =C38*1000000 -> 459824142000 | E38: =B38*1000000 -> 7.4797338e+10 | F38: 5074816265 | G38: 901763015 | H38: =E38/D38*100 -> 16.26651 | I38: =G38/F38*100 -> 17.769373 | J38: =D38/F38 -> 90.609023 | K38: =E38/G38 -> 82.945671 | L38: 504310603 | M38: =L38*K38 -> 4.1830381e+10 | N38: =(M38-M37)/M37*100 -> 0.48110659 | O38: =(M38-M34)/M34*100 -> -0.91554575 | Q38: =M38/E38 -> 0.5592496
A39: 2010q1 | B39: 72421.686 | C39: 443937.1 | D39: =C39*1000000 -> 4.439371e+11 | E39: =B39*1000000 -> 7.2421686e+10 | H39: =E39/D39*100 -> 16.313502 | I39: =G39/F39*100 -> #DIV/0! | J39: =D39/F39 -> #DIV/0! | K39: =E39/G39 -> #DIV/0! | M39: =E39*Q39 -> 4.1563503e+10 | N39: =(M39-M38)/M38*100 -> -0.63800079 | O39: =(M39-M35)/M35*100 -> 4.3060638 | Q39: =(Q27+Q31+Q35)/3 -> 0.57390963
A40: 2010q2 | B40: 75739.547 | C40: 457733.27 | D40: =C40*1000000 -> 457733272000 | E40: =B40*1000000 -> 7.5739547e+10 | H40: =E40/D40*100 -> 16.546655 | M40: =E40*Q40 -> 4.3465304e+10 | N40: =(M40-M39)/M39*100 -> 4.5756511 | O40: =(M40-M36)/M36*100 -> 6.272766 | Q40: =(Q28+Q32+Q36)/3 -> 0.57387858
A41: 2010q3 | B41: 76759.951 | C41: 465818.17 | D41: =C41*1000000 -> 4.6581817e+11 | E41: =B41*1000000 -> 7.6759951e+10 | H41: =E41/D41*100 -> 16.478522 | M41: =E41*Q41 -> 4.3929001e+10 | N41: =(M41-M40)/M40*100 -> 1.066821 | O41: =(M41-M37)/M37*100 -> 5.5222185 | Q41: =(Q29+Q33+Q37)/3 -> 0.57229063
A42: 2010q4 | B42: 77696.63 | C42: 475519.78 | D42: =C42*1000000 -> 475519782000 | E42: =B42*1000000 -> 7.769663e+10 | H42: =E42/D42*100 -> 16.339305 | M42: =E42*Q42 -> 4.3890811e+10 | N42: =(M42-M41)/M41*100 -> -0.086935587 | O42: =(M42-M38)/M38*100 -> 4.9256778 | Q42: =(Q30+Q34+Q38)/3 -> 0.56489981
A43: 2011q1 | B43: 75199.993 | C43: 460862.83 | D43: =C43*1000000 -> 460862825000 | E43: =B43*1000000 -> 7.5199993e+10 | H43: =E43/D43*100 -> 16.317218 | M43: =E43*Q43 -> 4.3197468e+10 | N43: =(M43-M42)/M42*100 -> -1.5796999 | O43: =(M43-M39)/M39*100 -> 3.9312491 | Q43: =(Q31+Q35+Q39)/3 -> 0.57443446
A44: 2011q2 | B44: 78146.805 | C44: 474374.35 | D44: =C44*1000000 -> 4.7437435e+11 | E44: =B44*1000000 -> 7.8146805e+10 | H44: =E44/D44*100 -> 16.473657 | M44: =E44*Q44 -> 4.4886983e+10 | N44: =(M44-M43)/M43*100 -> 3.9111439 | O44: =(M44-M40)/M40*100 -> 3.2708366 | Q44: =(Q32+Q36+Q40)/3 -> 0.57439307
A45: 2011q3 | B45: 79336.356 | C45: 481033.34 | D45: =C45*1000000 -> 4.8103334e+11 | E45: =B45*1000000 -> 7.9336356e+10 | H45: =E45/D45*100 -> 16.492902 | M45: =E45*Q45 -> 4.5402277e+10 | N45: =(M45-M44)/M44*100 -> 1.1479808 | O45: =(M45-M41)/M41*100 -> 3.3537663 | Q45: =(Q33+Q37+Q41)/3 -> 0.5722758
A46: 2011q4 | B46: 80704.715 | C46: 493072.84 | D46: =C46*1000000 -> 493072837000 | E46: =B46*1000000 -> 8.0704715e+10 | H46: =E46/D46*100 -> 16.367707 | M46: =E46*Q46 -> 4.5390056e+10 | N46: =(M46-M45)/M45*100 -> -0.026917253 | O46: =(M46-M42)/M42*100 -> 3.4158515 | Q46: =(Q34+Q38+Q42)/3 -> 0.56242137
A47: 2012q1 | B47: 77631.58 | C47: 473284.4 | D47: =C47*1000000 -> 473284397000 | E47: =B47*1000000 -> 7.763158e+10 | H47: =E47/D47*100 -> 16.402734 | M47: =E47*Q47 -> 4.4336131e+10 | N47: =(M47-M46)/M46*100 -> -2.3219294 | O47: =(M47-M43)/M43*100 -> 2.6359484 | Q47: =(Q35+Q39+Q43)/3 -> 0.57110948
A48: 2012q2 | B48: 80708.193 | C48: 488293.72 | D48: =C48*1000000 -> 4.8829372e+11 | E48: =B48*1000000 -> 8.0708193e+10 | H48: =E48/D48*100 -> 16.528616 | M48: =E48*Q48 -> 4.6061181e+10 | N48: =(M48-M47)/M47*100 -> 3.890844 | O48: =(M48-M44)/M44*100 -> 2.6158977 | Q48: =(Q36+Q40+Q44)/3 -> 0.57071257
A49: 2012q3 | B49: 81187.503 | C49: 491517.2 | D49: =C49*1000000 -> 491517195000 | E49: =B49*1000000 -> 8.1187503e+10 | H49: =E49/D49*100 -> 16.517734 | M49: =E49*Q49 -> 4.6229041e+10 | N49: =(M49-M48)/M48*100 -> 0.36442859 | O49: =(M49-M45)/M45*100 -> 1.8209741 | Q49: =(Q37+Q41+Q45)/3 -> 0.5694108
A50: 2012q4 | B50: 82654.977 | C50: 503348.26 | D50: =C50*1000000 -> 5.0334826e+11 | E50: =B50*1000000 -> 8.2654977e+10 | H50: =E50/D50*100 -> 16.421032 | M50: =E50*Q50 -> 4.6467823e+10 | N50: =(M50-M49)/M49*100 -> 0.5165199 | O50: =(M50-M46)/M46*100 -> 2.3744561 | Q50: =(Q38+Q42+Q46)/3 -> 0.56219026
A51: 2013q1 | B51: 78747.632 | C51: 480893.89 | D51: =C51*1000000 -> 4.8089389e+11 | E51: =B51*1000000 -> 7.8747632e+10 | H51: =E51/D51*100 -> 16.375262 | M51: =E51*Q51 -> 4.5134299e+10 | N51: =(M51-M50)/M50*100 -> -2.8697785 | O51: =(M51-M47)/M47*100 -> 1.8002663 | Q51: =(Q39+Q43+Q47)/3 -> 0.57315119
... A54: 2013q4 | B54: 83974.08 | C54: 513279.16 | D54: =C54*1000000 -> 5.1327916e+11 | E54: =B54*1000000 -> 8.397408e+10 | H54: =E54/D54*100 -> 16.360314 | M54: =E54*Q54 -> 4.7291723e+10 | N54: =(M54-M53)/M53*100 -> 0.56389534 | O54: =(M54-M50)/M50*100 -> 1.773054 | Q54: =(Q42+Q46+Q50)/3 -> 0.56317048
B56: 74822.137
B57: 77729.696
B58: 78919.642
B59: 79587.841
B60: 76650.248

Sheet GDP PMB
D1: Msunduzi Municipal Area
C2: SA GDP | D2: SA Quarterly GDP | E2: KZN Quarterly GDP | F2: SA Fuel Consumption | G2: KZN Fuel Consumption | H2: KZN GDP Ratio | I2: KZN Fuel Ratio | J2: SA Usage | K2: KZN Usage | L2: PMB Fuel Usage | M2: Pietermaritzburg Quarterly GDP | N2: PMB Quarterly Rate | O2: PMB Annual Rate
A3: 2001g1 | B3: 37676.736 | C3: 228114.65 | D3: ='GDP Durban'!D3 -> 3.2291091e+11 | E3: ='GDP Durban'!E3 -> 5.2513786e+10
A4: 2001g2 | B4: 39785.999 | C4: 237077.62 | D4: ='GDP Durban'!D4 -> 3.3472011e+11 | E4: ='GDP Durban'!E4 -> 5.5248344e+10
A5: 2001g3 | B5: 40039.788 | C5: 239764.67 | D5: ='GDP Durban'!D5 -> 3.3864098e+11 | E5: ='GDP Durban'!E5 -> 5.5639049e+10
A6: 2001g4 | B6: 40074.592 | C6: 242416.26 | D6: ='GDP Durban'!D6 -> 3.4244667e+11 | E6: ='GDP Durban'!E6 -> 5.5758173e+10
