Workbook

Sheet Cover Sheet
A1: ExampleApp Functional Specification
A3: Author: | B3: Tony Heap
A5: Version: | B5: This is a living document and is not formally version controlled.
B6: Accordingly, there is no formal sign-off of the document as a whole. Rather, each "acceptance criterion" is signed off individually (see the "Agreed" columns on the "Details" worksheet).
A8: Overview: | B8: This document (together with a number of supplementary documents) is the functional specification for the "ExampleApp" project.
B9: This document specifies what the system will do as opposed to how it will do it (i.e. It is not a technical specification).
B10: This document specifies only the changes to the system; it does not specify existing functionality.
A12: Structure: | B12: The functional specification consists of a set of "stories".
B13: Each story describes some aspect of the system's behaviour, either functional or non-functional.
B14: A story is the smallest unit of system delivery - a story is either delivered or it is not.
B15: In practice, stories are grouped together and delivered as (time-boxed) "increments" every 3-4 weeks.
B16: The "Summary" worksheet is an inventory of all the stories, along with various information for each one.
B17: In particular, the "Status" column in the "Summary" worksheet indicates the status of each story, from "being elaborated" right through to "gone live".
B18: The "Details" worksheet contains the detailed specification for each story.
B19: Each story is specified in "use case" format (ref. "Writing Effective Use Cases", Alistair Cockburn, 2001).
B20: See the column heading comments on the "Summary" and "Details" worksheets for further details on the format of the specification.
B21: The "Actors" workheet specifies all actors (users and external systems)
B22: The "Stats" worksheets show development progress for individual increments, in the form of a "burn down chart"

Sheet Summary
A1: Story ID | B1: Story Name | C1: As a... (Actor) | D1: I can... (Goal) | E1: Status | F1: Priority | G1: Dependencies | H1: Story Points | I1: Dev Increment | J1: Dev Owner | K1: Dev Complete Date | L1: Actual Dev Time (man days) | M1: Time Fixing Defects (man days) | N1: Notes | O1: Beta Test Phase | P1: Tester
A3: S001 | B3: Timeout | C3: Logged In User | D3: Have the system log me out if I do not use it for a period | E3: Live | I3: v7.3
A4: S002 | B4: Submission Warning | C4: Assessment Submitter | D4: Receive a warning before I submit my assessment | E4: Live | I4: v7.3
A5: S003 | B5: Submission E-mail | C5: Assessment Submitter | D5: Receive an e-mail confirming my assessment submission | E5: Live | I5: v7.3
A6: S004 | B6: Approval E-mail Log | C6: DIP Team | D6: View a record of the sending of an approval e-mail | E6: Live | I6: v7.3
A7: S005 | B7: Thingy New User E-mail | C7: XYZ ABC User | D7: Send thingy-specific "new user" e-mails when I create user accounts | E7: Live | I7: v7.3
A8: S006 | B8: Thingy "Not Relevant" Extras | C8: Thingy Assessment Completer | D8: Be able to answer "not relevant" for certain requirements | E8: Live | I8: v7.3
A9: S007 | B9: Thingy KB Doc Change | C9: General User | D9: View an amended thingy Knowledge Base document | E9: Live | I9: v7.3
A10: S008 | B10: Thingy Footer Details | C10: Thingy User | D10: View helpdesk details in any page footer | E10: Live | I10: v7.3
A11: S009 | B11: Thingy Request Registration | C11: Thingy User | D11: View helpdesk details when self registering for a Thingy | E11: Live | I11: v7.3
A12: S010 | B12: Add Widget Comments | C12: Assessment Completer | D12: Add and amend general comments for my requirement response | E12: Live | I12: v7.3
A13: S012 | B13: View Widgets List (Enhancements) | C13: General User | D13: Better understand the requirements list | E13: Implement | F13: Must | H13: 2 | I13: v8.0 (i1) | J13: CC | K13: 40213 | O13: Phase 1
A14: S013 | B14: View Widget Header Information (v8+) | C14: General User | D14: View key information about a (v8+) requirement | E14: Implement | F14: Must | H14: 2 | I14: v8.0 (i1) | J14: CC | K14: 40204 | O14: Phase 1
A15: S014 | B15: View Widget Description (v8+) | C15: General User | D15: View the requirement description for a (v8+) requirement | E15: Implement | F15: Must | H15: 0.5 | I15: v8.0 (i1) | J15: CC | K15: 40205 | O15: Phase 1
A16: S015 | B16: View Widget Guidance Text (v8+) | C16: General User | D16: View the guidance text for a (v8+) requirement | E16: Implement | F16: Must | H16: 0.25 | I16: v8.0 (i1) | J16: CC | K16: 40205 | O16: Phase 1
A17: S016 | B17: View Knowledge Base Resources (v8+) | C17: General User | D17: View and access the knowledge base resources that are relevant to a (v8+) requirement | E17: Implement | F17: Must | G17: S075 | H17: 2 | I17: v8.0 (i1) | J17: CC | K17: 40207 | O17: Phase 1
A18: S017 | B18: View Widget Origins (v8+) | C18: General User | D18: View the requirement origins for a (v8+) requirement | E18: Implement | F18: Should | H18: 0.5 | I18: v8.0 (i1) | J18: CC | K18: 40205 | O18: Phase 1
A19: S068 | B19: View Widget Changes (v8+) | C19: General User | D19: View a list of material changes that have been made in this (major) version of the (v8+) requirements | E19: Implement | F19: Should | H19: 0.5 | I19: v8.0 (i1) | J19: CC | K19: 40205 | O19: Phase 1
A20: S018 | B20: View Training Tool Text (v8+) | C20: General User | D20: View the training tool text for a (v8+) requirement | E20: Implement | F20: Should | H20: 0.25 | I20: v8.0 (i1) | J20: CC | K20: 40206
A21: S019 | B21: View Training Tool Custom Text (v8+) | C21: General User | D21: View (v8+) requirement-specific training tool text | E21: Implement | F21: Should | H21: 0.25 | I21: v8.0 (i1) | J21: CC | K21: 40206
A22: S020 | B22: View Attainment Levels (v8+) | C22: General User | D22: View attainment levels and attainment criteria for a (v8+) requirement | E22: Implement | F22: Must | H22: 3 | I22: v8.0 (i2) | J22: CC | K22: 40233 | L22: 3 | O22: Phase 1
A23: S021 | B23: View Evidence Types | C23: General User | D23: View standard evidence types against each attainment criterion | E23: Implement | F23: Must | G23: S020 | H23: 5 | I23: v8.0 (i2) | J23: RJM | K23: 40232 | L23: 5.5 | O23: Phase 1
A24: S049 | B24: Expand and Collapse Widget (v8+) | C24: General User | D24: Expand or collapse the various sections of the (v8+) requirement page | E24: Implement | F24: Must | G24: S014-S020 | H24: 2 | I24: v8.0 (i1) | J24: CC | K24: 40205 | O24: Phase 1
A25: S023 | B25: Indicate Widget As Not Relevant (v8+) | C25: Organisation User | D25: Indicate that a (v8+) requirement is not relevant to my organisation | E25: Implement | F25: Must | H25: 1 | I25: v8.0 (i2) | J25: CC | K25: 40234 | L25: 1 | O25: Phase 2
A26: S024 | B26: Enter Comments for an Attainment Criterion | C26: Organisation User | D26: Enter comments for an attainment criterion | E26: Implement | F26: Must | H26: 1 | I26: v8.0 (i2) | J26: CC | K26: 40242 | L26: 4 | N26: Much more complicated than initially estimated for | O26: Phase 1
A27: S025 | B27: Add Custom Evidence Type | C27: Organisation User | D27: Add a custom evidence type to an assessment criterion (because the standard evidence types are not appropriate for me) | E27: Implement | F27: Must | H27: 4 | I27: v8.0 (i2) | J27: RJM | K27: 40245 | L27: 5 | N27: more complicated than originally thought. Required integration with main page for testing save functionality | O27: Phase 1
A28: S026 | B28: Indicate Evidence Obtained | C28: Organisation User | D28: Indicate that I have obtained a particular evidence type | E28: Implement | F28: Must | H28: 2 | I28: v8.0 (i2) | J28: RJM | K28: 40238 | L28: 3 | O28: Phase 1
A29: S027 | B29: Enter Evidence Comments | C29: Organisation User | D29: Enter comments against a specific evidence type | E29: Implement | F29: Must | H29: 2 | I29: v8.0 (i2) | J29: RJM | K29: 40239 | L29: 2 | O29: Phase 1
A30: S028 | B30: Specify External Evidence Location | C30: Organisation User | D30: Specify an external location for my evidence | E30: Implement | F30: Should | H30: 5 | I30: v8.0 (i3) | J30: RJM | K30: 40256 | L30: 4 | O30: Phase 1
A31: S131 | B31: Specifiy Evidence Location Improvement | C31: Organisation User | D31: Specify an external location for my evidence (improved UI) | E31: Implement | F31: Must | G31: S028, S030 | H31: 2 | I31: v8.0 (i4) | J31: RJM | K31: 40275 | L31: 4 | N31: Was more complex than anticipated, plus all of the associated bubbling of events needed to be changed. | O31: Phase 1
A32: S030 | B32: Upload Evidence | C32: Organisation User | D32: Upload evidence to the PQRT server | E32: Implement | F32: Should | H32: 3 | I32: v8.0 (i4) | J32: RJM | K32: 40282 | L32: 4 | O32: Phase 2
A33: S031 | B33: View Evidence | C33: Organisation User | D33: View evidence files that I have previously specified in my requirement response | E33: Implement | F33: Should | G33: S028, S030 | H33: 2 | I33: v8.0 (i4) | J33: RJM | K33: 40284 | L33: 3 | O33: Phase 2
A34: S029 | B34: Specify Duplicate Evidence | C34: Organisation User | D34: Indicate that an evidence type is a duplicate of another one I've already specified (and cross reference it) | E34: Withdrawn | F34: Must | G34: S029 | H34: 4 | I34: N/A | J34: RJM | O34: N/A
A35: S140 | B35: View Duplicate Evidence | C35: Organisation User | D35: View duplicate evidence files that I have previously specified in my requirement response | E35: Withdrawn | F35: Should | H35: 1 | I35: N/A | J35: RJM | O35: N/A
A36: S139 | B36: Cannot Delete Referenced Custom Evidence | C36: Organisation User | D36: Be prevented from deleting custom evidence which is referenced from elsewhere | E36: Withdrawn | F36: Must | H36: 2 | I36: N/A | J36: RJM | O36: N/A
A37: S149 | B37: Link to Existing Uploaded Evidence | C37: Organisation User | D37: Specify an existing uploaded evidence file against another evidence item | E37: Withdrawn | F37: Must | H37: 4 | I37: v8.0 (i5) | J37: RJM | K37: 40291 | L37: 4 | N37: Superseded by S163 | O37: N/A
A38: S163 | B38: Link to Existing Uploaded Evidence (Mark 2) | C38: Organisation User | D38: Specify an existing uploaded evidence file against another evidence item (enhanced/simplified version) | E38: Implement | F38: Must | H38: 1 | I38: v8.0 (i5) | J38: RJM | K38: 40298 | L38: 1 | O38: Phase 2
A39: S032 | B39: Configure Evidence Provision Status | C39: Sys Admin | D39: Configure whether evidence provision is mandatory or optional for each org type | E39: Implement | F39: Must | H39: 0.5 | I39: v8.0 (i3) | J39: NL | K39: 40255 | L39: 0.5 | O39: N/A
A40: S033 | B40: Indicate Attainment Criterion Achieved | C40: Organisation User | D40: Indicate a given attainment criterion as achieved either directly or indirectly | E40: Implement | F40: Must | H40: 6 | I40: v8.0 (i3) | J40: CC | K40: 40260 | L40: 5 | O40: Phase 1
A41: S034 | B41: Indicate Attainment Level 0 (v8+) | C41: Organisation User | D41: Explicitly indicate that my organisation is at Attainment Level 0 | E41: Implement | F41: Must | H41: 1.5 | I41: v8.0 (i3) | J41: CC | K41: 40255 | L41: 1.5 | O41: Phase 1
A42: S036 | B42: Determine Current Attainment Level (v8+) | C42: Organisation User | D42: Have the system determine my current attainment level for a given requirement | E42: Implement | F42: Must | G42: S033, S034 | H42: 5 | I42: v8.0 (i3) | J42: RJM | K42: 40260 | L42: 4 | O42: Phase 1
A43: S037 | B43: Determine Widget Status | C43: Organisation User | D43: Have the system determine the status of my requirement response | E43: Implement | F43: Must | H43: 1 | I43: v8.0 (i3) | J43: NL | K43: 40255 | L43: 0.25 | O43: Phase 2
A44: S038 | B44: Grant Widget Exemption | C44: XYZ ABC User | D44: Grant an exemption from a requirement to an organisation | E44: Implement | F44: Must | H44: 3 | I44: v8.0 (i4) | J44: RJM | K44: 40287 | L44: 2
A45: S039 | B45: View Widget Exemption | C45: Organisation User | D45: View a requirement exemption granted to my organisation | E45: Implement | F45: Must | G45: S038 | H45: 1 | I45: v8.0 (i4) | J45: RJM | K45: 40268 | L45: 1
A46: S044 | B46: Grant Evidence Exemption | C46: XYZ ABC User | D46: Grant an exemption from a mandatory evidence type to an organisation | E46: Withdrawn | F46: Could | I46: N/A | O46: N/A
A47: S045 | B47: Grant Evidence Exemption to Org Type | C47: XYZ ABC User | D47: Grant an exemption from a mandatory evidence type to all organisations of a specific type | E47: Withdrawn | F47: Could | G47: S044 | I47: N/A | O47: N/A
A48: S046 | B48: View Evidence Exemption | C48: Organisation User | D48: View an evidence exemption granted to my organisation | E48: Withdrawn | F48: Could | G48: S044 | I48: N/A | O48: N/A
A49: S047 | B49: Save Widget | C49: Organisation User | D49: Save changes I have made to my requirement response | E49: Implement | F49: Must | H49: 0.5 | I49: v8.0 (i3) | J49: RJM/CMC | K49: 40262 | L49: 0.5 | N49: 0.5 days. Most of the functionality was already implemented through other stories. | O49: Phase 1
A50: S022 | B50: View Printable/Downloadable Version of Widget | C50: General User | D50: View a printable/downloadable version of a requirement | E50: Implement | F50: Must | H50: 0.5 | I50: v8.0 (i2) | J50: NL | K50: 40231 | L50: 1.5 | N50: nili: Time Taken includes configuration and set-up time | O50: Phase 1
A51: S050 | B51: Download Widgets In Bulk | C51: Logged In User | D51: Download printable versions of requirements in bulk, for viewing off-line or for printing out | E51: Implement | F51: Must | H51: 2 | I51: v8.0 (i2) | J51: NL | K51: 40241 | L51: 2 | O51: Phase 2
A52: S076 | B52: Download Widgets In Bulk (Per-Initiative Booklets) | C52: Logged In User | D52: Download printable versions of requirements in bulk, for viewing off-line or for printing out (specifically, per-initiative booklets) | E52: Implement | F52: Should | G52: S050 | H52: 1 | I52: v8.0 (i2) | J52: NL | K52: 40241 | L52: 3 | O52: Phase 2
A53: S069 | B53: Download Widgets Spreadsheet | C53: General User | D53: Download the requirement set as a spreadsheet for offline working | E53: Implement | F53: Must | H53: 0 | I53: v8.0 (i3) | J53: NL | K53: 40245 | L53: 0 | O53: Phase 2
A54: S056 | B54: Create Bulk Email | C54: XYZ ABC User | D54: Create bulk emails to be sent to users | E54: Implement | F54: Must | H54: 5 | I54: v8.0 (i1) | J54: DES | K54: 40219
A55: S057 | B55: Add Bulk Email Attachments | C55: XYZ ABC User | D55: Attach files to pending bulk emails | E55: Implement | F55: Must | G55: S056 | H55: 3 | I55: v8.0 (i2) | J55: DES | K55: 40242
A56: S058 | B56: Send Bulk Email | C56: XYZ ABC User | D56: Have the system send all due bulk emails | E56: Implement | F56: Must | G56: S056 | H56: 5 | I56: v8.0 (i5) | J56: DES | K56: 40312 | L56: 4.5 | P56: NL
A57: S059 | B57: View Bulk Emails | C57: XYZ ABC User | D57: View bulk emails (both sent and pending) | E57: Implement | F57: Must | G57: S056, S058 | H57: 1 | I57: v8.0 (i1) | J57: DES | K57: 40221
A58: S060 | B58: Amend Bulk Email | C58: XYZ ABC User | D58: Amend a pending bulk email | E58: Implement | F58: Must | G58: S059 | H58: 1.5 | I58: v8.0 (i1) | J58: DES | K58: 40221
A59: S061 | B59: Delete Bulk Email | C59: XYZ ABC User | D59: Delete a pending bulk email | E59: Implement | F59: Must | G59: S059 | H59: 0.5 | I59: v8.0 (i1) | J59: DES | K59: 40221
A60: S080 | B60: View Bulk Email | C60: XYZ ABC User | D60: View a sent email | E60: Implement | F60: Must | G60: S059 | H60: 1 | I60: v8.0 (i1) | J60: DES | K60: 40221
A61: S102 | B61: Bulk Email Look & Feel | C61: XYZ ABC User | D61: Have a nice look & feel for the bulk email function | E61: Implement | F61: Should | G61: S056, S057, S058, S059, S060, S061 | H61: 1 | I61: v8.0 (i5) | J61: DES | K61: 40312
A62: S063 | B62: View Glossary Term Definition | C62: General User | D62: View the definition of a term that is defined in the glossary | E62: Implement | F62: Must | G62: S064 | H62: 3 | I62: v8.0 (i1) | J62: RJM | K62: 40213 | O62: Phase 1
A63: S070 | B63: View Glossary Term (Printable) | C63: General User | D63: Identify glossary terms in the printable version of a requirement | E63: Implement | F63: Must | G63: S022 | H63: 0 | I63: v8.0 (i4) | J63: TM | K63: 40280 | L63: 0 | O63: Phase 2
A64: S064 | B64: View Glossary | C64: General User | D64: View the entire glossary | E64: Implement | F64: Must | H64: 2 | I64: v8.0 (i1) | J64: RJM | K64: 40217 | O64: Phase 1
A65: S071 | B65: View Printable/Downloadable Version of Glossary | C65: General User | D65: View a printable/downloadable version of the glossary | E65: Implement | F65: Must | H65: 0.5 | I65: v8.0 (i2) | J65: RJM | K65: 40226 | L65: 0.5
A66: S082 | B66: Publish Widgets - Printable Version | C66: Sys Admin | D66: Publish or re-publish the printable versions of the requirements | E66: Implement | F66: Could | G66: S065 | H66: 4 | I66: v8.0 (i4) | J66: TM | K66: 40284 | O66: Phase 2
A67: S099 | B67: Publish Widgets - ZIP File Downloads | C67: Sys Admin | D67: Publish or re-publish the ZIP file downloads for the requirements | E67: Implement | F67: Could | G67: S065 | H67: 3 | I67: v8.0 (i4) | J67: TM | K67: 40290 | O67: Phase 2
A68: S100 | B68: Publish Widgets - Booklet Downloads | C68: Sys Admin | D68: Publish or re-publish the booklet downloads for the requirements | E68: Implement | F68: Could | G68: S065 | H68: 4 | I68: v8.0 (i4) | J68: TM | K68: 40284 | O68: Phase 2
A69: S101 | B69: Publish Widgets - Per-Initiative Booklets | C69: Sys Admin | D69: Publish or re-publish the per-initiative booklet downloads for the requirements | E69: Implement | F69: Could | G69: S065, S076 | H69: 2 | I69: v8.0 (i4) | J69: TM | K69: 40284 | O69: Phase 2
A70: S151 | B70: Publish Widgets - Spreadsheet (Technology Spike) | C70: Sys Admin | D70: Publish or re-publish the XL spreadsheet download for the requirements (simple version to prove technology) | E70: Implement | F70: Must | G70: S065 | H70: 2 | I70: v8.0 (i5) | J70: TM | K70: 40297 | O70: Phase 2
A71: S072 | B71: Publish Widgets - Booklets with Glossaries | C71: Sys Admin | D71: Publish or re-publish the booklet downloads for the requirements, including a glossary section | E71: Withdrawn | F71: Could | G71: S100, S101 | I71: N/A | N71: Decided we don't want to include a 30 page glossary at the end of every booklet | O71: N/A
A72: S067 | B72: Publish Glossary | C72: Sys Admin | D72: Publish a new version of the glossary based on the data held in RAT | E72: Implement | F72: Must | H72: 2.5 | I72: v8.0 (i1) | J72: RM | K72: 40220
A73: S073 | B73: View Assessment Summary | C73: Organisation User | D73: View summary data about my assessment | E73: Implement | F73: Should | H73: 6 | I73: v8.0 (i4) | J73: NL | K73: 40289 | L73: 7 | O73: Phase 2
A74: S136 | B74: View Assessment Summary Target Score | C74: Organisation User | D74: View my target score along with my assessment summary | E74: Implement | F74: Should | H74: 1 | I74: v8.0 (i5) | J74: NL | K74: 40296 | L74: 1 | O74: Phase 2
A75: S077 | B75: Look and Feel | C75: General User | D75: Use the application easily and without aesthetic insult to my eye | E75: Implement | F75: Must | H75: 6 | I75: v8.0 (i2) | J75: TM | K75: 40234 | L75: 4 | O75: Phase 1
A76: S104 | B76: Look and Feel v2 | C76: General User | D76: Have an enhanced aesthetic experience, with lovely soft curves caressing my visual senses | E76: Implement | F76: Must | G76: S077 | H76: 5 | I76: v8.0 (i2) | J76: TM | K76: 40241 | L76: 4 | O76: Phase 1
A77: S078 | B77: Improved Navigation | C77: General User | D77: Navigate the site more easily | E77: Implement | F77: Must | H77: 2 | I77: v8.0 (i2) | J77: DES | K77: 40227 | L77: 2 | O77: Phase 1
A78: S096 | B78: Improved Navigation - Information Mapping | C78: Information Mapping User | D78: Be able to navigate to the information mapping functions | E78: Implement | F78: Must | G78: S078 | H78: 1 | I78: v8.0 (i3) | J78: NL | K78: 40256 | L78: 0.5 | O78: Phase 1
A79: S074 | B79: Navigate to Views Maintenance | C79: XYZ ABC User, Organisation Administrator | D79: Be able to access the Views Maintenance function | E79: Withdrawn | F79: Should | I79: N/A | N79: Delay until we agree whether we are getting rid of Views | O79: N/A
A80: S079 | B80: Home Page | C80: General User | D80: View information on the home page | E80: Implement | F80: Must | H80: 2 | I80: v8.0 (i2) | J80: TM | K80: 40233 | L80: 2 | O80: Phase 1
A81: S091 | B81: Next Deadline Info | C81: Logged In User | D81: Find out when my next assessment deadline is | E81: Implement | F81: Should | H81: 3 | I81: v8.0 (i3) | J81: NL | K81: 40263 | L81: 3
A82: S125 | B82: View Submission Deadline on Performance Update | C82: Organisation Admin | D82: Be told the (correct) submission deadline when I do a Performance Update | E82: Implement | F82: Must | H82: 0.5 | I82: v8.0 (i3) | J82: NL | K82: 40260 | L82: 0
A83: S092 | B83: Log In | C83: General User | D83: Log in to the system | E83: Implement | F83: Must | G83: S079 | H83: 2 | I83: v8.0 (i2) | J83: TM | K83: 40234 | L83: 1 | O83: Phase 1
A84: S093 | B84: Log Out | C84: Logged In User | D84: Log out from the system | E84: Implement | F84: Must | G84: S079, S092 | H84: 1 | I84: v8.0 (i2) | J84: TM | K84: 40233 | L84: 0.5
A85: S090 | B85: Register For an Account | C85: General User | D85: Register for an PQRT account | E85: Implement | F85: Should | H85: 2 | I85: v8.0 (i2) | J85: DES | K85: 40242 | L85: 3.5 | N85: Incorporated Full-text search | O85: Phase 1
A86: S089 | B86: Contact Us | C86: General User | D86: Contact XYZ ABC about the PQRT | E86: Implement | F86: Must | G86: S078 | H86: 2 | I86: v8.0 (i2) | J86: DES | K86: 40232 | L86: 2.5 | O86: Phase 1
A87: S083 | B87: View "About" Info | C87: General User | D87: Read general information about PQRT | E87: Implement | F87: Must | G87: S078 | H87: 0 | I87: v8.0 (i5) | J87: NL | K87: 40305 | L87: 0.25
A88: S097 | B88: Improved Navigation - Widgets | C88: General User | D88: Navigate more sensibly to the requirements list page | E88: Implement | F88: Should | H88: 1 | I88: v8.0 (i3) | J88: NL | K88: 40260 | L88: 0.5 | O88: Phase 1
A89: S098 | B89: Home Page - What Next | C89: Logged In User | D89: Once I have logged in, view instructions on what I can do next | E89: Implement | F89: Must | H89: 2 | I89: v8.0 (i3) | J89: NL | K89: 40256 | L89: 0.75 | O89: Phase 1
A90: S075 | B90: Search Knowledge Base | C90: General User | D90: Search for knowledge base documents based on various criteria | E90: Implement | F90: Must | G90: S016 | H90: 5 | I90: v8.0 (i3) | J90: DES | K90: 40260 | L90: 5
A91: S105 | B91: Context Sensitive Help Mechanism | C91: Developer | D91: Implement context sensitive help in a straightforward and flexible manner | E91: Implement | F91: Must | H91: 2 | I91: v8.0 (i3) | J91: RJM | K91: 40261 | L91: 1 | O91: Phase 1
A92: S108 | B92: Look & Feel - Widget Details | C92: General User | D92: Have a nice look & feel for the requirement details page | E92: Implement | F92: Must | H92: 5 | I92: v8.0 (i3) | J92: RJM | K92: 40253 | L92: 6 | O92: Phase 1
A93: S110 | B93: Can't Enter Widget Level Comments | C93: Organisation User | D93: Not enter requirement-level comments for a (v8+) requirement | E93: Implement | F93: Must | H93: 0 | I93: v8.0 (i4) | J93: CC | K93: 40266 | L93: 0 | O93: Phase 1
A94: S111 | B94: Smaller PQR Assurance Statement Pop-up | C94: Organisation User | D94: Be able to view the PQR Assurance Statement Pop-up on an 800x600 screen | E94: Implement | F94: Must | H94: 0.25 | I94: v8.0 (i3) | J94: CC | K94: 40253 | L94: 0.25 | O94: N/A
A95: S112 | B95: Submission Email Log | C95: Organisation User | D95: View a record of the sending of an submission e-mail | E95: Implement | F95: Must | H95: 0.25 | I95: v8.0 (i3) | J95: CC | K95: 40253 | L95: 0.25 | O95: N/A
A96: S117 | B96: Specify A Widget Owner | C96: Organisation Administrator | D96: Specify a user from my organisation as the owner for a given requirement | E96: Implement | F96: Should | H96: 3 | I96: v8.0 (i4) | J96: DES | K96: 40269 | L96: 3.5 | O96: Phase 2
A97: S113 | B97: Add Improvement Action | C97: Organisation User | D97: Add an improvement action against a specific attainment criterion | E97: Implement | F97: Should | H97: 5 | I97: v8.0 (i4) | J97: DES | K97: 40281 | L97: 6.5 | N97: Had some issues with the jQuery Datepicker formatting. | O97: Phase 2
A98: S138 | B98: View Improvement Actions | C98: XYZ ABC User | D98: View improvement actions | E98: Withdrawn | F98: Must | I98: N/A | O98: N/A
A99: S114 | B99: Produce Improvement Plan and Evidence Report | C99: Organisation User | D99: Produce an improvement plan for my organisation | E99: Implement | F99: Should | H99: 6 | I99: v8.0 (i4) | J99: DES | K99: 40288 | L99: 6 | O99: Phase 2 | P99: EP
A100: S116 | B100: Send Ad-hoc Improvement Action Reminders | C100: Organisation Admin | D100: Send ad-hoc email reminders to requirement owners with outstanding improvement actions | E100: Implement | F100: Should | H100: 4 | I100: v8.0 (i5) | J100: DES | K100: 40303 | L100: 4 | O100: Phase 2 | P100: EP
A101: S115 | B101: Send Regular Improvement Action Reminders | C101: Organisation Admin | D101: Send regular email reminders to requirement owners with outstanding improvement actions | E101: Implement | F101: Could | H101: 4 | I101: v8.0 (i5) | J101: DES | K101: 40308 | L101: 4.5 | O101: Phase 2 | P101: EP
...

Sheet Details
A1: Story ID | B1: Story Name | C1: As a... (Actor) | D1: I can... (Goal) | E1: Flow | F1: Step | G1: When I... (Action) | H1: Then... (Acceptance Criterion) | I1: Prototyped | J1: Agreed PW/MG | K1: Agreed TUG | L1: Agreed Dev | M1: Notes | N1: Test Status | O1: Defect | P1: Defect Priority | Q1: Defect Status | R1: Defect Notes
A2: S01 | B2: Ensure form displays to project specifications | C2: General user | D2: Access all of the items, widgets, buttons, ect…within the webpage form. | E2: Main | F2: 1 | G2: Request to view the web form online | H2: Once the page loads, all widgets are displayed | I2: Y | J2: NA | K2: NA | L2: NA | N2: Pass
A3: S011 | B3: Test clear button | C3: General user | D3: remove current form input in text fields | E3: Main | F3: 1 | G3: Click the "clear" button on form page | H3: The text input is removed from the text fields, and the blank/default field inputs are returned to default state | I3: Y | J3: NA | K3: NA | L3: NA | N3: Pass
A4: S0111 | B4: Submit button | C4: General user | D4: submit input to form | E4: Main | F4: 1 | G4: click the "submit" button on the form | H4: The text items are scraped and echoed out to the user | I4: Y | J4: NA | K4: NA | L4: NA | N4: Pending
A9: S012 | B9: View Widgets List (Enhancements) | C9: General User | D9: Better understand the widgets list | E9: Main | F9: 1 | G9: Request to view the widgets list (any org type)
F10: 2 | H10: The column headings indicate what happens when the column content is clicked | I10: Y | J10: 40135 | K10: 40142 | L10: CMC | N10: Pass
F11: 3 | H11: Column 1 header is "Req No" (previously "Seq No") | I11: Y | J11: 40135 | K11: 40142 | L11: CMC | N11: Pass
F12: 4 | H12: The widgets are grouped by initiative (with initiative sub-headers and colour coding) | I12: Y | J12: 40140 | K12: 40142 | L12: CMC | N12: Pass
F13: 5 | H13: A new column "Key Req" indicates whether key widget (including use of icons and/or colour) | I13: Y | J13: 40140 | K13: 40142 | L13: CMC | M13: CMC: Will need to have ALT text for the Icon as well for accessibility | N13: Pass
F14: 6 | H14: For each answered key widget, the Attainment Level column includes a "status" indicator showing whether or not Attainment Level 2 reached | I14: Y | J14: 40140 | K14: 40142 | L14: CMC | M14: CMC: Again also needs ALT text for icon | N14: Pass | O14: 1) Alt text should read "Attainment Level 2 met/not met for Key Widget". | P14: Medium | Q14: Closed | R14: CMC: (1) Currently alt text reads "Key Widget Minimum Level Met/Not met". Think this is a better wording as there is no guarantee that 2 will remain as the min level for key widgets.
N15: Pass | O15: It's showing the cross icon correctly but it's showing the key icon instead of the tick icon | P15: Medium | Q15: Closed | R15: (2)You can test this as have set page to display for V7 assessment sets in order to allow testing. Suggest using V7 assessment for organisation code REM.
A17: S013 | B17: View Widget Header Information (v8+) | C17: General User | D17: View key information about a (v8+) widget | E17: Main | F17: 1 | G17: Request to view a specific (v8+) widget
F18: 2 | H18: The header panel is re-organised to list key data down the RHS (widget no, initiative, whether key widget, org type, widget version number) | I18: Y | J18: 40133 | K18: 40142 | L18: CMC | N18: Pass
F19: 3 | H19: The version number is of the format <major>.<minor> e.g. 8.0. Note that individual widgets in the same set can be at different minor versions. | I19: Y | J19: 40147 | K19: 40254 | L19: CMC | M19: CMC: Needs investigation as to how this will integrate with RATI tool | N19: Pass
F20: 4 | H20: The HORUS categorisation is removed (this only applies for v8+ widgets - it is to be retained for v7- widgets) | I20: Y | J20: 40133 | K20: 40142 | L20: CMC | M20: TBC knock-on effect on TDB. CMC Will definitely have knock on effect on TDB will require at the least some TDB reports being pulled and at worst changes to TDB data structures and associated batch and SP processes as well. | N20: Pass
F21: 5 | H21: The MSPrPe categorisation is removed (this only applies for v8+ widgets - it is to be retained for v7- widgets) | I21: Y | J21: 40133 | K21: 40142 | L21: CMC | N21: Pass
F22: 6 | H22: The Category categorisation is removed (this only applies for v8+ widgets - it is to be retained for v7- widgets) | I22: Y | J22: 40133 | K22: 40142 | L22: CMC | N22: Pass
F23: 7 | H23: The header panel is colour coded to indicate which initiative it belongs to (see PQRT v8 Colour Palette v1) | I23: Y | J23: 40133 | K23: 40142 | L23: CMC | N23: Pass
F24: 8 | H24: The header panel is colour coded to indicate whether it is a key widget (see PQRT v8 Colour Palette v1) | I24: Y | J24: 40133 | K24: 40142 | L24: CMC | N24: Pass
A26: S014 | B26: View Widget Description (v8+) | C26: General User | D26: View the widget description for a (v8+) widget | E26: Main | F26: 1 | G26: Request to view a specific (v8+) widget
F27: 2 | G27: Precondition: the relevant widget text has been converted from RATML into HTML by S065 (Import Widgets Data)
F28: 3 | H28: The widget description for the widget appears below the header panel (heading: "Widget Description"). This is the text that previously appeared with the widget question in the blue box on the Guidance Document. | I28: Y | J28: 40135 | K28: 40142 | L28: CMC | N28: Pass
A30: S015 | B30: View Widget Guidance Text (v8+) | C30: General User | D30: View the guidance text for a (v8+) widget | E30: Main | F30: 1 | G30: Request to view a specific (v8+) widget
F31: 2 | G31: Precondition: the relevant widget text has been converted from RATML into HTML by S065 (Import Widgets Data)
F32: 3 | H32: The guidance text is presented (correctly formatted) | I32: Y | J32: 40135 | K32: 40142 | L32: CMC | N32: Pass | O32: 1) Paragraph indenting is out. The answer here (I think) is to remove the 5 x &nbsp; at the beginning of each para in the HTML. 2) In IE, the first H3 displays fine but the second and subsequent ones are indented and too small. It seems to be because they are embedded within a <ul> (but so is the first one!), because if I close the <ul> before the <h3> and open it again afterwards it's OK. But then the paragraph numbering goes to cock, unless youe explicitly use the "Start" attribute of <ul>. | P32: Medium | Q32: Closed | R32: CMC:I copied the HTML as was given in the prototype at the time of development. The HTML which will get produced is really part of the publish story, as such . not sure there's too much point frigging with the test HTML to get the result we want. Propose leaving this till testing of the publish process. TH 16/3: I will attempt to "fix" these in the prototype and then you can take the latest cut of the prototype HTML TH 22/3: fixed in prototype (see email from me the other day) CMC 06/04 Think this is now fixed looks ok to me with published data from RATTY anyway TH 12/04: the publish function may work OK but the test data itself needs to be valid, both for manual and automated testing purposes CMC 26/04 Guidance text fixed for Acute Test widget 101
F33: 4 | H33: The guidance text has paragraph numbers (for easy reference) | I33: Y | J33: 40133 | K33: 40142 | L33: CMC | N33: Pass
A35: S016 | B35: View Knowledge Base Resources (v8+) | C35: General User | D35: View and access the knowledge base resources that are relevant to a (v8+) widget | E35: Main | F35: 1 | G35: Request to view a specific (v8+) widget
F36: 2 | H36: There is a list of all knowledge base resources relevant to the widget | I36: Y | J36: 40135 | K36: 40142 | L36: CMC | N36: Pass
F37: 3 | H37: The title of section is "Knowledge Base Resources" | I37: Y | J37: 40135 | K37: 40142 | L37: CMC | N37: Pass
F38: 4 | H38: The resources are grouped into "Key Resources", "Exemplars" and "Useful Websites" | I38: Y | J38: 40135 | K38: 40142 | L38: CMC | N38: Pass | O38: 1) Order of tabs should be Key Resources, Exemplar Materials, Useful Web Sites | P38: Medium | Q38: Closed | R38: CMC:Fixed as part of reskin of widgets page
F39: 5 | H39: The resources are tabulated | I39: Y | J39: 40135 | K39: 40142 | L39: CMC | N39: Pass
F40: 6 | H40: Each resource title is a hyperlink through to the resource (be it a document on our server or an external URL) | I40: Y | J40: 40135 | K40: 40142 | L40: CMC | N40: Pass | O40: Visited weblinks are the same colour as not visited links (OK) but with no underline (not OK) | P40: Medium | Q40: Closed | R40: CMC: Are now underlined as per re-skin of widgets page 22/10 TH: Failed retest. Note that some links are not underlined even before I have visited them.
F41: 7 | H41: When a hyperlink is clicked, the resoruce is displayed in a new tab or window | I41: Y | J41: 40189 | K41: N/A | L41: CMC | N41: Pass
F42: 8 | H42: For each resource there is a description of the resource to help users determine the content of the resource and whether it will be useful to them | I42: Y | J42: 40133 | K42: 40142 | L42: CMC | N42: Pass
F43: 9 | H43: For each resource there is an indicator indicating whether the resource is located internally on the PQRT website or whether it is on an external web page (this gives the user a hint that the content they are looking at is not "owned" by XYZ ABC).. | I43: Y | J43: 40147 | K43: 40142 | L43: CMC | N43: Pass | O43: 1) Can you put a tooltip on the external web site link saying "External web site link" (as per prototype) 2) Can you include the external website link within the <a> tag so it is clickable along with the link itself. | P43: Low | Q43: Closed | R43: CMC: Ok have added tooltip to the a href as well as the image and added the space, try again.
F44: 10 | H44: For each internally located resource, the file type and size is displayed | I44: Y | J44: 40147 | K44: 40142 | L44: CMC | M44: CMC: Possible security access implications as will need to access file system to get this information. TH: the fiel type and size will be in the DB (calculated by RATty) | N44: Pass | O44: Can you remove the leading dot e.g. "DOC", not ".DOC" | P44: Low | Q44: Closed | R44: CMC:Data issue only, fixed in test data set up script
A46: S017 | B46: View Widget Origins (v8+) | C46: General User | D46: View the widget origins for a (v8+) widget | E46: Main | F46: 1 | G46: Request to view a specific (v8+) widget
F47: 2 | G47: Precondition: the relevant widget text has been converted from RATML into HTML by S065 (Import Widgets Data)
F48: 3 | H48: There is a section containing the widget origins (after the (optional) Training section) | I48: Y | J48: 40133 | K48: 40142 | L48: CMC | N48: Pass
F49: 4 | H49: The widget origins section is a bullet list of free format text items | I49: Y | J49: 40133 | K49: 40142 | L49: CMC | N49: Pass
E50: 1a | G50: Request to view a specific (v8+) widget which has no widget origins
H51: The widget origins section is empty i.e. this case is treated as a bullet list with zero items in it (on the basis that it is not expected to arise) | I51: N | J51: 40190 | K51: N/A | L51: CMC | M51: CMC:This looks pretty odd if the situation of 0 orgins does arise | N51: Pass
A53: S068 | B53: View Widget Changes (v8+) | C53: General User | D53: View a list of material changes that have been made in this (major) version of the (v8+) widgets | E53: Main | F53: 1 | G53: Request to view a specific (v8+) widget
F54: 2 | G54: Precondition: the relevant widget text has been converted from RATML into HTML by S065 (Import Widgets Data)
F55: 3 | H55: There is a section containing a list of material changes to the current (major) version of the widget | I55: Y | J55: 40154 | K55: 40254 | L55: CMC | N55: Pass | O55: Put a colon at the end of "The following is a list..." instead of a full stop | P55: Low | Q55: Closed
F56: 4 | H56: The section is a bullet list of free format text items | I56: Y | J56: 40154 | K56: 40254 | L56: CMC | N56: Pass
E57: 1a | F57: 1 | G57: Request to view a specific (v8+) widget which has no material changes
F58: 2 | H58: The "changes" section states that there are no material changes in this version of the widget | I58: N | J58: 40154 | K58: 40254 | L58: CMC | N58: Pass | O58: Rather than saying, "The following is a list..." followed by a bulleted "There are no material changes...", just say "There are no material changes" (not bulleted) | P58: Medium | Q58: Closed
A60: S018 | B60: View Training Tool Text (v8+) | C60: General User | D60: View the training tool text for a (v8+) widget | E60: Main | F60: 1 | G60: Request to view a specific (v8+) widget for which the training tool text is relevant
F61: 2 | H61: The training tool text is displayed (after the knowledge base resources) | I61: Y | J61: 40147 | K61: 40254 | L61: CMC | N61: Pass | O61: 1) Make link to training tool open in new window 2) Put full stop after training tool link (as per prototype) | P61: Medium | Q61: Closed
E62: 1a | F62: 1 | G62: Request to view a specific (v8+) widget for which the training tool text is *not* relevant
H63: The training tool text is *not* displayed (after the knowledge base resources) | I63: N | J63: 40147 | K63: 40254 | N63: Pass | O63: Looking at the database table WidgetOrganisationType, I can not see a data field which indicates whether or not the training tool text is required (in RATTY it's called XXX). I'm therefore guessing that this widget has not been implemented | P63: High | Q63: Closed | R63: CMC:Was a misinterpretation of the widget. I thought it was only the custom text which was conditional and thought that IO could simply check whether it was null or not. So to confirm if the Training Text relevant flag is set you display the traing text section and if theres some custom text you also display that. Correct ?
A65: S019 | B65: View Training Tool Custom Text (v8+) | C65: General User | D65: View (v8+) widget-specific training tool text | E65: Main | F65: 1 | G65: Request to view a specific (v8+) widget for which the training tool text is relevant and for which there is widget-specific training tool text
F66: 2 | G66: Precondition: the relevant widget text has been converted from RATML into HTML by S065 (Import Widgets Data)
F67: 3 | H67: The widget-specific training tool text is displayed as a paragraph immediately prior to the training tool link. | I67: Y | J67: 40154 | K67: 40254 | L67: CMC | N67: Pass
A69: S020 | B69: View Attainment Levels (v8+) | C69: General User | D69: View attainment levels and attainment criteria for a (v8+) widget | E69: Main | F69: 1 | G69: Precondition: the relevant widget text has been converted from RATML into HTML by S065 (Publish Widgets Data)
F70: 2 | G70: Request to view a specific (v8+) widget
F71: 3 | H71: The Attainment Levels section is called "Attainment Levels" | I71: Y | J71: 40135 | K71: 40142 | L71: CMC | N71: Pass
F72: 4 | H72: The Attainment Levels section is the last section (so that the user is encouraged to view all the guidance materials first) | I72: Y | J72: 40135 | K72: 40142 | L72: CMC | N72: Pass
F73: 5 | H73: The attainment levels 0-3 are displayed along with the summary description for each. | I73: Y | J73: 40214 | K73: N/A | L73: CMC | N73: Pass
F74: 6 | H74: For each attainment level, its "child" attainment criteria are dispayed with their individual IDs (1a, 1b, 1c etc.) | J74: 40214 | K74: N/A | L74: CMC | N74: Pass
F75: 7 | H75: The attainment level criteria are based on the current improvement plan items - expressed as an outcome instead of an action e.g. "The Trust should document its current arrangements..." has become "The Trust's current arrangements are documented..." | I75: Y | J75: 40133 | K75: 40142 | L75: CMC | M75: CMC:Should be able to keep existing AttainmentItemPlanTask data structure | N75: Pass
F76: 8 | H76: It is not possible for users to alter the criteria (edit, add or remove) | I76: Y | J76: 40133 | K76: 40142 | L76: CMC | N76: Pass
F77: 9 | H77: Attainment Level 0 has standard text: "Insufficient evidence to attain Level 1" | I77: Y | J77: 40135 | K77: 40142 | L77: CMC | N77: Pass | O77: Can you put a full stop at the end of this sentence please? (sorry, my fault) | P77: Low | Q77: Closed | R77: CMC:Data issue as this text held in database. Have changed test data setup script to include full stop
F78: 10 | H78: The screen layout is such that it is clear that the criteria are cumulative (i.e. To get attainment level 2 you need to achieve all attainment level 1 and 2 criteria) | I78: Y | J78: 40135 | K78: 40142 | L78: CMC | M78: CMC:Will need to be enforced through validation i.e. can't click a criteria unless all previous criteria also clicked TH: this point is really just to do with the way that the page looks, The validation is covered off by S036 (Determine Current Attainment Level) | N78: N/A | O78: Superseded by S108
E79: 2a | F79: 1 | G79: Request to view a (v8+) widget which has Level 3 Maintenance criteria
F80: 2 | H80: Level 3 can include "maintenance" criteria (note: these are criteria which only need to be achieved if the organisation was at level 3 in the previous year) | I80: Y | J80: 40147 | K80: 40142 | L80: CMC | N80: Pass
F81: 3 | H81: The maintenance criteria are explicitly identified as being maintenance criteria | I81: Y | J81: 40147 | K81: 40142 | L81: CMC | N81: Pass
H82: The maintenance criteria do not have criteria Ids | I82: Y | J82: 40217 | K82: N/A | L82: CMC | N82: Pass
H83: The maintenance criteria are displayed *after* the main Level 3 criteria, in any order (the business rule is that there should only ever be one maintenance criterion, so irder isn't important) | I83: Y | J83: 40217 | K83: N/A | L83: CMC | N83: Pass
E84: 2b | F84: 1 | G84: Request to view a (v8+) widget for which "not relevant" is a valid response
F85: 2 | H85: "Not Relevant" is included as a valid Attainment Level | I85: Y | J85: 40147 | K85: 40142 | L85: CMC | N85: Pass
F86: 3 | H86: There is some widget-specific text to explain what "not relevant" means. | I86: Y | J86: 40147 | K86: 40142 | L86: CMC | N86: Pass
E87: 2c | F87: 1 | G87: Request to view a (v8+) widget for which "not relevant" is *not* a valid response
F88: 2 | H88: "Not Relevant" is *not* included as a valid Attainment Level | I88: N | J88: 40147 | K88: 40142 | L88: CMC | N88: Pass
A90: S021 | B90: View Evidence Types | C90: General User | D90: View standard evidence types against each attainment criterion | E90: Main | F90: 1 | G90: Request to view a specific (v8+) widget
F91: 2 | H91: Each attainment criterion has zero or more "standard" evidence types associated with it. | I91: Y | J91: 40133 | K91: 40142 | L91: RJM | N91: Pass
F92: 3 | H92: All standard evidence types are mandatory (optional evidence types were considered but rejected) - although see story S081 re. evidence type strengths | I92: Y | J92: 40147 | K92: 40142 | L92: RJM | N92: Pass | O92: Remove "Type" column (and any associated underlying data structures) - we are no longer including "Type" | P92: High | Q92: Closed
A94: S049 | B94: Expand and Collapse Widget (v8+) | C94: General User | D94: Expand or collapse the various sections of the (v8+) widget page | E94: Main | F94: 1 | G94: View a specific (v8+) widget
F95: 2 | H95: All "top-level" sections are expanded by default | I95: Y | J95: 40135 | K95: 40142 | L95: CMC | N95: Pass
F96: 3 | H96: There are options to individually collapse each top-level section | I96: Y | J96: 40135 | K96: 40142 | L96: CMC | N96: Pass
F97: 4 | H97: There is an option to collapse all top-level sections at once | I97: Y | J97: 40147 | K97: 40142 | L97: CMC | N97: Pass
F98: 5 | H98: There is an option to expand all top-level sections at once | I98: Y | J98: 40147 | K98: 40142 | L98: CMC | N98: Pass
H99: All "attainment criterion details" sections are collapsed by default | I99: Y | J99: 40135 | K99: 40142 | L99: CMC | N99: Pass
F100: 6 | H100: There are options to individually expand the each attainment criterion details section | I100: Y | J100: 40135 | K100: 40142 | L100: CMC | N100: Pass
F101: 7 | H101: The collapse button for each attainment criterion details section is to the LHS of the attainment criterion's "Achieved" tick box | I101: Y | J101: 40147 | K101: N/A | L101: CMC | N101: Pass
F102: 8 | G102: Request to collapse a top-level section
F103: 9 | H103: The section is collapsed | I103: Y | J103: 40135 | K103: 40142 | L103: CMC | N103: Pass | O103: Jerky action - needs to be smoother | P103: Medium | Q103: Closed | R103: CMC:Have been changed to Jquery panels as part of reskin
F104: 10 | H104: There is an option to expand the section, which has replaced the option to collapse the section | I104: Y | J104: 40135 | K104: 40142 | L104: CMC | N104: Pass
F105: 11 | G105: Request to expand the collapsed section
F106: 12 | H106: The section is expanded | I106: Y | J106: 40135 | K106: 40142 | L106: CMC | N106: Pass | O106: Jerky action - needs to be smoother | P106: Medium | Q106: Closed | R106: CMC:Has been changd as part of reskin
F107: 13 | H107: There is an option to collapse the section, which has replaced the option to expand the section | I107: Y | J107: 40135 | K107: 40142 | L107: CMC | N107: Pass
E108: 8a | F108: 1 | G108: Request to collapse all top-level sections
F109: 2 | H109: All top-level sections are collapsed | I109: Y | J109: 40147 | K109: 40142 | L109: CMC | N109: Pass
F110: 3 | H110: There are options to individually expand each section, which have replaced the options to collapse each section | I110: Y | J110: 40147 | K110: 40142 | L110: CMC | N110: Pass
F111: 4 | G111: Request to expand all top-level sections
F112: 5 | H112: All top-level sections are expanded | I112: Y | J112: 40147 | K112: 40142 | L112: CMC | N112: Pass
F113: 6 | H113: There are options to individually collapse each section, which have replaced the options to collapse each section | I113: Y | J113: 40147 | K113: 40142 | L113: CMC | N113: Pass
E114: 8b | F114: 1 | G114: Request to expand an attainment criterion details section
F115: 2 | H115: The section is expanded | I115: Y | J115: 40135 | K115: 40142 | L115: CMC | N115: Pass | O115: Works OK at first. Then if I expand one of the top level sections and then try to expand an attainment level, it expands then collapses again! Each time I expand or collapse a top level section, it adds another iteration fo expanding or collapsing to the attainment level. Weird, huh? | P115: High | Q115: Closed | R115: CMC:Fixed as part of re-skin
...

Sheet Actors
A1: Actor Name | B1: Description
A2: General User | B2: Any user, whether logged in or not
A3: Anonymous User | B3: Any user who is not logged in
A4: Logged In User | B4: Any user who is logged in
A5: Organisation User | B5: User responsible for basic operations within their organisation e.g. entering widget responses
A6: Organisation Reviewer | B6: User responsible for reviewing widget responses for their organisation
A7: Organisation Administrator | B7: User responsible for performing admin tasks for their organisation
A8: Organisation Auditor | B8: User responsible to auditing assessments for a specific organisation
A9: XYZ ABC User | B9: User within XYZ ABC responsible for performing various cross-organisation admin tasks
A10: Sys Admin | B10: System administrator

Sheet Stats (Summary)
A1: Story Point Count Summary
A3: Increment | B3: Story Points | C3: Man Days | D3: Velocity
A5: ='Stats (i1)'!$A$2 -> v8.0 (i1) | B5: ='Stats (i1)'!$E$2 -> 30.75 | C5: ='Stats (i1)'!$C$2 -> 29 | D5: =B5/C5 -> 1.0603448
A6: ='Stats (i2)'!$A$2 -> v8.0 (i2) | B6: ='Stats (i2)'!$E$2 -> 47 | C6: ='Stats (i2)'!$C$2 -> 60 | D6: =B6/C6 -> 0.78333333
A7: ='Stats (i3)'!$A$2 -> v8.0 (i3) | B7: ='Stats (i3)'!$E$2 -> 58 | C7: ='Stats (i3)'!$C$2 -> 59 | D7: =B7/C7 -> 0.98305085
A8: ='Stats (i4)'!$A$2 -> v8.0 (i4) | B8: ='Stats (i4)'!$E$2 -> 48 | C8: ='Stats (i4)'!$C$2 -> 70 | D8: =B8/C8 -> 0.68571429
A9: ='Stats (i5)'!$A$2 -> v8.0 (i5) | B9: ='Stats (i5)'!$E$2 -> 50.5 | C9: ='Stats (i5)'!$C$2 -> 59.5 | D9: =B9/C9 -> 0.8487395
A10: ='Stats (i6)'!$A$2 -> v8.0 (i6) | B10: ='Stats (i6)'!$E$2 -> 37 | C10: ='Stats (i6)'!$C$2 -> 37 | D10: =B10/C10 -> 1
A11: ='Stats (i7)'!$A$2 -> v8.0 (i7) | B11: ='Stats (i7)'!$E$2 -> 22.5 | C11: ='Stats (i7)'!$C$2 -> 69.5 | D11: =B11/C11 -> 0.32374101
A12: ='Stats (i8)'!$A$2 -> v8.0 (i8) | B12: ='Stats (i8)'!$E$2 -> 13 | C12: ='Stats (i8)'!$C$2 -> 37 | D12: =B12/C12 -> 0.35135135
A14: Total | B14: =SUM(B5:B13) -> 306.75 | C14: =SUM(C5:C13) -> 421 | D14: =B14/C14 -> 0.72862233

Sheet Stats (i1)
A1: Increment Name | B1: Total Story Points In Scope | C1: Total Man Days | D1: Estimated Velocity | E1: Total Story Points Delivered | F1: Actual Velocity | I1: Date | J1: Man Days (Today) | K1: Man Days (Cumulative) | L1: Story Points (Est Cumulative) | M1: Story Points (Actual Today) | N1: Story Points (Actual Cumulative)
A2: v8.0 (i1) | B2: {=SUM(Summary!H3:H204*IF(Summary!I3:I204=A2,1,0))} -> 30.75 | C2: =SUM(J2:J16) -> 29 | D2: =B2/C2 -> 1.0603448 | E2: =N16 -> 30.75 | F2: =E2/C2 -> 1.0603448 | H2: Week 1 | I2: 40203 | J2: 1 | K2: =J2 -> 1 | L2: =K2*$D$2 -> 1.0603448 | M2: {=SUM(Summary!$H$3:$H$204*IF(Summary!I$3:I$204=A$2,1,0)*IF(Summary!K$3:K$204=I2,1,0))} -> 0 | N2: =M2 -> 0 | P2: =IF(Summary!I3='Stats (i1)'!$A$2,Summary!H3,0) -> 0
I3: =I2+1 -> 40204 | J3: 1 | K3: =J3+K2 -> 2 | L3: =K3*$D$2 -> 2.1206897 | M3: {=SUM(Summary!$H$3:$H$204*IF(Summary!I$3:I$204=A$2,1,0)*IF(Summary!K$3:K$204=I3,1,0))} -> 2 | N3: =N2+M3 -> 2 | P3: =IF(Summary!I4='Stats (i1)'!$A$2,Summary!H4,0) -> 0
I4: =I3+1 -> 40205 | J4: 1 | K4: =J4+K3 -> 3 | L4: =K4*$D$2 -> 3.1810345 | M4: {=SUM(Summary!$H$3:$H$204*IF(Summary!I$3:I$204=A$2,1,0)*IF(Summary!K$3:K$204=I4,1,0))} -> 3.75 | N4: =N3+M4 -> 5.75 | P4: =IF(Summary!I5='Stats (i1)'!$A$2,Summary!H5,0) -> 0
I5: =I4+1 -> 40206 | J5: 1 | K5: =J5+K4 -> 4 | L5: =K5*$D$2 -> 4.2413793 | M5: {=SUM(Summary!$H$3:$H$204*IF(Summary!I$3:I$204=A$2,1,0)*IF(Summary!K$3:K$204=I5,1,0))} -> 0.5 | N5: =N4+M5 -> 6.25 | P5: =IF(Summary!I6='Stats (i1)'!$A$2,Summary!H6,0) -> 0
I6: =I5+1 -> 40207 | J6: 1 | K6: =J6+K5 -> 5 | L6: =K6*$D$2 -> 5.3017241 | M6: {=SUM(Summary!$H$3:$H$204*IF(Summary!I$3:I$204=A$2,1,0)*IF(Summary!K$3:K$204=I6,1,0))} -> 2 | N6: =N5+M6 -> 8.25 | P6: =IF(Summary!I7='Stats (i1)'!$A$2,Summary!H7,0) -> 0
H7: Week 2 | I7: =I6+3 -> 40210 | J7: 0 | K7: =J7+K6 -> 5 | L7: =K7*$D$2 -> 5.3017241 | M7: {=SUM(Summary!$H$3:$H$204*IF(Summary!I$3:I$204=A$2,1,0)*IF(Summary!K$3:K$204=I7,1,0))} -> 0 | N7: =N6+M7 -> 8.25 | P7: =IF(Summary!I8='Stats (i1)'!$A$2,Summary!H8,0) -> 0
I8: =I7+1 -> 40211 | J8: 0 | K8: =J8+K7 -> 5 | L8: =K8*$D$2 -> 5.3017241 | M8: {=SUM(Summary!$H$3:$H$204*IF(Summary!I$3:I$204=A$2,1,0)*IF(Summary!K$3:K$204=I8,1,0))} -> 0 | N8: =N7+M8 -> 8.25 | P8: =IF(Summary!I9='Stats (i1)'!$A$2,Summary!H9,0) -> 0
I9: =I8+1 -> 40212 | J9: 3 | K9: =J9+K8 -> 8 | L9: =K9*$D$2 -> 8.4827586 | M9: {=SUM(Summary!$H$3:$H$204*IF(Summary!I$3:I$204=A$2,1,0)*IF(Summary!K$3:K$204=I9,1,0))} -> 0 | N9: =N8+M9 -> 8.25 | P9: =IF(Summary!I10='Stats (i1)'!$A$2,Summary!H10,0) -> 0
I10: =I9+1 -> 40213 | J10: 3 | K10: =J10+K9 -> 11 | L10: =K10*$D$2 -> 11.663793 | M10: {=SUM(Summary!$H$3:$H$204*IF(Summary!I$3:I$204=A$2,1,0)*IF(Summary!K$3:K$204=I10,1,0))} -> 5 | N10: =N9+M10 -> 13.25 | P10: =IF(Summary!I11='Stats (i1)'!$A$2,Summary!H11,0) -> 0
I11: =I10+1 -> 40214 | J11: 3 | K11: =J11+K10 -> 14 | L11: =K11*$D$2 -> 14.844828 | M11: {=SUM(Summary!$H$3:$H$204*IF(Summary!I$3:I$204=A$2,1,0)*IF(Summary!K$3:K$204=I11,1,0))} -> 0 | N11: =N10+M11 -> 13.25 | P11: =IF(Summary!I12='Stats (i1)'!$A$2,Summary!H12,0) -> 0
H12: Week 3 | I12: =I11+3 -> 40217 | J12: 3 | K12: =J12+K11 -> 17 | L12: =K12*$D$2 -> 18.025862 | M12: {=SUM(Summary!$H$3:$H$204*IF(Summary!I$3:I$204=A$2,1,0)*IF(Summary!K$3:K$204=I12,1,0))} -> 2 | N12: =N11+M12 -> 15.25 | P12: =IF(Summary!I13='Stats (i1)'!$A$2,Summary!H13,0) -> 2
I13: =I12+1 -> 40218 | J13: 3 | K13: =J13+K12 -> 20 | L13: =K13*$D$2 -> 21.206897 | M13: {=SUM(Summary!$H$3:$H$204*IF(Summary!I$3:I$204=A$2,1,0)*IF(Summary!K$3:K$204=I13,1,0))} -> 0 | N13: =N12+M13 -> 15.25 | P13: =IF(Summary!I14='Stats (i1)'!$A$2,Summary!H14,0) -> 2
I14: =I13+1 -> 40219 | J14: 3 | K14: =J14+K13 -> 23 | L14: =K14*$D$2 -> 24.387931 | M14: {=SUM(Summary!$H$3:$H$204*IF(Summary!I$3:I$204=A$2,1,0)*IF(Summary!K$3:K$204=I14,1,0))} -> 5 | N14: =N13+M14 -> 20.25 | P14: =IF(Summary!I15='Stats (i1)'!$A$2,Summary!H15,0) -> 0.5
I15: =I14+1 -> 40220 | J15: 3 | K15: =J15+K14 -> 26 | L15: =K15*$D$2 -> 27.568966 | M15: {=SUM(Summary!$H$3:$H$204*IF(Summary!I$3:I$204=A$2,1,0)*IF(Summary!K$3:K$204=I15,1,0))} -> 2.5 | N15: =N14+M15 -> 22.75 | P15: =IF(Summary!I16='Stats (i1)'!$A$2,Summary!H16,0) -> 0.25
I16: =I15+1 -> 40221 | J16: 3 | K16: =J16+K15 -> 29 | L16: =K16*$D$2 -> 30.75 | M16: {=SUM(Summary!$H$3:$H$204*IF(Summary!I$3:I$204=A$2,1,0)*IF(Summary!K$3:K$204=I16,1,0))} -> 8 | N16: =N15+M16 -> 30.75 | P16: =IF(Summary!I17='Stats (i1)'!$A$2,Summary!H17,0) -> 2
P17: =IF(Summary!I18='Stats (i1)'!$A$2,Summary!H18,0) -> 0.5
P18: =IF(Summary!I19='Stats (i1)'!$A$2,Summary!H19,0) -> 0.5
P19: =IF(Summary!I20='Stats (i1)'!$A$2,Summary!H20,0) -> 0.25
P20: =IF(Summary!I21='Stats (i1)'!$A$2,Summary!H21,0) -> 0.25
P21: =IF(Summary!I22='Stats (i1)'!$A$2,Summary!H22,0) -> 0

Sheet Stats (i2)
A1: Increment Name | B1: Total Story Points In Scope | C1: Total Man Days | D1: Estimated Velocity | E1: Total Story Points Delivered | F1: Actual Velocity | I1: Date | J1: Man Days (Today) | K1: Man Days (Cumulative) | L1: Story Points (Est Cumulative) | M1: Story Points (Actual Today) | N1: Story Points (Actual Cumulative)
A2: v8.0 (i2) | B2: {=SUM(Summary!H3:H204*IF(Summary!I3:I204=A2,1,0))} -> 47 | C2: =SUM(J2:J17) -> 60 | D2: =B2/C2 -> 0.78333333 | E2: =N17 -> 47 | F2: =E2/C2 -> 0.78333333 | H2: Week 1 | I2: 40224 | J2: 0 | K2: =J2 -> 0 | L2: =K2*$D$2 -> 0 | M2: {=SUM(Summary!$H$3:$H$204*IF(Summary!I$3:I$204=A$2,1,0)*IF(Summary!K$3:K$204=I2,1,0))} -> 0 | N2: =M2 -> 0
I3: =I2+1 -> 40225 | J3: 2 | K3: =J3+K2 -> 2 | L3: =K3*$D$2 -> 1.5666667 | M3: {=SUM(Summary!$H$3:$H$204*IF(Summary!I$3:I$204=A$2,1,0)*IF(Summary!K$3:K$204=I3,1,0))} -> 0 | N3: =N2+M3 -> 0
I4: =I3+1 -> 40226 | J4: 4 | K4: =J4+K3 -> 6 | L4: =K4*$D$2 -> 4.7 | M4: {=SUM(Summary!$H$3:$H$204*IF(Summary!I$3:I$204=A$2,1,0)*IF(Summary!K$3:K$204=I4,1,0))} -> 0.5 | N4: =N3+M4 -> 0.5
I5: =I4+1 -> 40227 | J5: 4 | K5: =J5+K4 -> 10 | L5: =K5*$D$2 -> 7.8333333 | M5: {=SUM(Summary!$H$3:$H$204*IF(Summary!I$3:I$204=A$2,1,0)*IF(Summary!K$3:K$204=I5,1,0))} -> 2 | N5: =N4+M5 -> 2.5
I6: =I5+1 -> 40228 | J6: 4 | K6: =J6+K5 -> 14 | L6: =K6*$D$2 -> 10.966667 | M6: {=SUM(Summary!$H$3:$H$204*IF(Summary!I$3:I$204=A$2,1,0)*IF(Summary!K$3:K$204=I6,1,0))} -> 0 | N6: =N5+M6 -> 2.5
H7: Week 2 | I7: =I6+3 -> 40231 | J7: 5 | K7: =J7+K6 -> 19 | L7: =K7*$D$2 -> 14.883333 | M7: {=SUM(Summary!$H$3:$H$204*IF(Summary!I$3:I$204=A$2,1,0)*IF(Summary!K$3:K$204=I7,1,0))} -> 0.5 | N7: =N6+M7 -> 3
I8: =I7+1 -> 40232 | J8: 5 | K8: =J8+K7 -> 24 | L8: =K8*$D$2 -> 18.8 | M8: {=SUM(Summary!$H$3:$H$204*IF(Summary!I$3:I$204=A$2,1,0)*IF(Summary!K$3:K$204=I8,1,0))} -> 7 | N8: =N7+M8 -> 10
I9: =I8+1 -> 40233 | J9: 5 | K9: =J9+K8 -> 29 | L9: =K9*$D$2 -> 22.716667 | M9: {=SUM(Summary!$H$3:$H$204*IF(Summary!I$3:I$204=A$2,1,0)*IF(Summary!K$3:K$204=I9,1,0))} -> 6 | N9: =N8+M9 -> 16
I10: =I9+1 -> 40234 | J10: 5 | K10: =J10+K9 -> 34 | L10: =K10*$D$2 -> 26.633333 | M10: {=SUM(Summary!$H$3:$H$204*IF(Summary!I$3:I$204=A$2,1,0)*IF(Summary!K$3:K$204=I10,1,0))} -> 9 | N10: =N9+M10 -> 25
I11: =I10+1 -> 40235 | J11: 5 | K11: =J11+K10 -> 39 | L11: =K11*$D$2 -> 30.55 | M11: {=SUM(Summary!$H$3:$H$204*IF(Summary!I$3:I$204=A$2,1,0)*IF(Summary!K$3:K$204=I11,1,0))} -> 0 | N11: =N10+M11 -> 25
H12: Week 3 | I12: =I11+3 -> 40238 | J12: 4 | K12: =J12+K11 -> 43 | L12: =K12*$D$2 -> 33.683333 | M12: {=SUM(Summary!$H$3:$H$204*IF(Summary!I$3:I$204=A$2,1,0)*IF(Summary!K$3:K$204=I12,1,0))} -> 2 | N12: =N11+M12 -> 27
I13: =I12+1 -> 40239 | J13: 4 | K13: =J13+K12 -> 47 | L13: =K13*$D$2 -> 36.816667 | M13: {=SUM(Summary!$H$3:$H$204*IF(Summary!I$3:I$204=A$2,1,0)*IF(Summary!K$3:K$204=I13,1,0))} -> 2 | N13: =N12+M13 -> 29
I14: =I13+1 -> 40240 | J14: 4 | K14: =J14+K13 -> 51 | L14: =K14*$D$2 -> 39.95 | M14: {=SUM(Summary!$H$3:$H$204*IF(Summary!I$3:I$204=A$2,1,0)*IF(Summary!K$3:K$204=I14,1,0))} -> 0 | N14: =N13+M14 -> 29
I15: =I14+1 -> 40241 | J15: 4 | K15: =J15+K14 -> 55 | L15: =K15*$D$2 -> 43.083333 | M15: {=SUM(Summary!$H$3:$H$204*IF(Summary!I$3:I$204=A$2,1,0)*IF(Summary!K$3:K$204=I15,1,0))} -> 8 | N15: =N14+M15 -> 37
I16: =I15+1 -> 40242 | J16: 4 | K16: =J16+K15 -> 59 | L16: =K16*$D$2 -> 46.216667 | M16: {=SUM(Summary!$H$3:$H$204*IF(Summary!I$3:I$204=A$2,1,0)*IF(Summary!K$3:K$204=I16,1,0))} -> 6 | N16: =N15+M16 -> 43
H17: Week 4 | I17: =I16+3 -> 40245 | J17: 1 | K17: =J17+K16 -> 60 | L17: =K17*$D$2 -> 47 | M17: {=SUM(Summary!$H$3:$H$204*IF(Summary!I$3:I$204=A$2,1,0)*IF(Summary!K$3:K$204=I17,1,0))} -> 4 | N17: =N16+M17 -> 47

Sheet Stats (i3)
A1: Increment Name | B1: Total Story Points In Scope | C1: Total Man Days | D1: Estimated Velocity | E1: Total Story Points Delivered | F1: Actual Velocity | I1: Date | J1: Man Days (Today) | K1: Man Days (Cumulative) | L1: Story Points (Est Cumulative) | M1: Story Points (Actual Today) | N1: Story Points (Actual Cumulative) | P1: Chris | Q1: Richard | R1: Tom | S1: Des | T1: Niall
A2: v8.0 (i3) | B2: {=SUM(Summary!H3:H204*IF(Summary!I3:I204=A2,1,0))} -> 58 | C2: =SUM(J2:J18) -> 59 | D2: =B2/C2 -> 0.98305085 | E2: =N18 -> 58 | F2: =E2/C2 -> 0.98305085 | H2: Week 1 | I2: 40245 | J2: =SUM(P2:T2) -> 4 | K2: =J2 -> 4 | L2: =K2*$D$2 -> 3.9322034 | M2: {=SUM(Summary!$H$3:$H$204*IF(Summary!I$3:I$204=A$2,1,0)*IF(Summary!K$3:K$204=I2,1,0))} -> 0 | N2: =M2 -> 0 | P2: 1 | Q2: 0 | R2: 1 | S2: 2
C3: aim for | D3: 0.8 | I3: =I2+1 -> 40246 | J3: =SUM(P3:T3) -> 3 | K3: =J3+K2 -> 7 | L3: =K3*$D$2 -> 6.8813559 | M3: {=SUM(Summary!$H$3:$H$204*IF(Summary!I$3:I$204=A$2,1,0)*IF(Summary!K$3:K$204=I3,1,0))} -> 0 | N3: =N2+M3 -> 0 | Q3: 1 | R3: 1 | S3: 1
D4: =C2*D3 -> 47.2 | I4: =I3+1 -> 40247 | J4: =SUM(P4:T4) -> 3 | K4: =J4+K3 -> 10 | L4: =K4*$D$2 -> 9.8305085 | M4: {=SUM(Summary!$H$3:$H$204*IF(Summary!I$3:I$204=A$2,1,0)*IF(Summary!K$3:K$204=I4,1,0))} -> 0 | N4: =N3+M4 -> 0 | Q4: 1 | R4: 1 | S4: 1
I5: =I4+1 -> 40248 | J5: =SUM(P5:T5) -> 3 | K5: =J5+K4 -> 13 | L5: =K5*$D$2 -> 12.779661 | M5: {=SUM(Summary!$H$3:$H$204*IF(Summary!I$3:I$204=A$2,1,0)*IF(Summary!K$3:K$204=I5,1,0))} -> 0 | N5: =N4+M5 -> 0 | Q5: 1 | R5: 1 | S5: 1
I6: =I5+1 -> 40249 | J6: =SUM(P6:T6) -> 3 | K6: =J6+K5 -> 16 | L6: =K6*$D$2 -> 15.728814 | M6: {=SUM(Summary!$H$3:$H$204*IF(Summary!I$3:I$204=A$2,1,0)*IF(Summary!K$3:K$204=I6,1,0))} -> 0 | N6: =N5+M6 -> 0 | Q6: 1 | R6: 1 | S6: 1
H7: Week 2 | I7: =I6+3 -> 40252 | J7: =SUM(P7:T7) -> 6 | K7: =J7+K6 -> 22 | L7: =K7*$D$2 -> 21.627119 | M7: {=SUM(Summary!$H$3:$H$204*IF(Summary!I$3:I$204=A$2,1,0)*IF(Summary!K$3:K$204=I7,1,0))} -> 0 | N7: =N6+M7 -> 0 | P7: 1 | Q7: 1 | R7: 1 | S7: 2 | T7: 1
I8: =I7+1 -> 40253 | J8: =SUM(P8:T8) -> 5 | K8: =J8+K7 -> 27 | L8: =K8*$D$2 -> 26.542373 | M8: {=SUM(Summary!$H$3:$H$204*IF(Summary!I$3:I$204=A$2,1,0)*IF(Summary!K$3:K$204=I8,1,0))} -> 5.5 | N8: =N7+M8 -> 5.5 | P8: 1 | Q8: 1 | R8: 1 | S8: 1 | T8: 1
I9: =I8+1 -> 40254 | J9: =SUM(P9:T9) -> 5 | K9: =J9+K8 -> 32 | L9: =K9*$D$2 -> 31.457627 | M9: {=SUM(Summary!$H$3:$H$204*IF(Summary!I$3:I$204=A$2,1,0)*IF(Summary!K$3:K$204=I9,1,0))} -> 6 | N9: =N8+M9 -> 11.5 | P9: 1 | Q9: 1 | R9: 1 | S9: 1 | T9: 1
I10: =I9+1 -> 40255 | J10: =SUM(P10:T10) -> 5 | K10: =J10+K9 -> 37 | L10: =K10*$D$2 -> 36.372881 | M10: {=SUM(Summary!$H$3:$H$204*IF(Summary!I$3:I$204=A$2,1,0)*IF(Summary!K$3:K$204=I10,1,0))} -> 3 | N10: =N9+M10 -> 14.5 | P10: 1 | Q10: 1 | R10: 1 | S10: 1 | T10: 1
I11: =I10+1 -> 40256 | J11: =SUM(P11:T11) -> 4 | K11: =J11+K10 -> 41 | L11: =K11*$D$2 -> 40.305085 | M11: {=SUM(Summary!$H$3:$H$204*IF(Summary!I$3:I$204=A$2,1,0)*IF(Summary!K$3:K$204=I11,1,0))} -> 8 | N11: =N10+M11 -> 22.5 | P11: 1 | Q11: 1 | R11: 1 | S11: 1
H12: Week 3 | I12: =I11+3 -> 40259 | J12: =SUM(P12:T12) -> 4 | K12: =J12+K11 -> 45 | L12: =K12*$D$2 -> 44.237288 | M12: {=SUM(Summary!$H$3:$H$204*IF(Summary!I$3:I$204=A$2,1,0)*IF(Summary!K$3:K$204=I12,1,0))} -> 0 | N12: =N11+M12 -> 22.5 | P12: 1 | Q12: 1 | R12: 1 | S12: 1
I13: =I12+1 -> 40260 | J13: =SUM(P13:T13) -> 5 | K13: =J13+K12 -> 50 | L13: =K13*$D$2 -> 49.152542 | M13: {=SUM(Summary!$H$3:$H$204*IF(Summary!I$3:I$204=A$2,1,0)*IF(Summary!K$3:K$204=I13,1,0))} -> 17.5 | N13: =N12+M13 -> 40 | P13: 1 | Q13: 1 | R13: 1 | S13: 1 | T13: 1
I14: =I13+1 -> 40261 | J14: =SUM(P14:T14) -> 4 | K14: =J14+K13 -> 54 | L14: =K14*$D$2 -> 53.084746 | M14: {=SUM(Summary!$H$3:$H$204*IF(Summary!I$3:I$204=A$2,1,0)*IF(Summary!K$3:K$204=I14,1,0))} -> 2 | N14: =N13+M14 -> 42 | P14: 1 | Q14: 1 | R14: 1 | T14: 1
I15: =I14+1 -> 40262 | J15: =SUM(P15:T15) -> 4 | K15: =J15+K14 -> 58 | L15: =K15*$D$2 -> 57.016949 | M15: {=SUM(Summary!$H$3:$H$204*IF(Summary!I$3:I$204=A$2,1,0)*IF(Summary!K$3:K$204=I15,1,0))} -> 1 | N15: =N14+M15 -> 43 | P15: 1 | Q15: 1 | R15: 1 | T15: 1
I16: =I15+1 -> 40263 | J16: =SUM(P16:T16) -> 0 | K16: =J16+K15 -> 58 | L16: =K16*$D$2 -> 57.016949 | M16: {=SUM(Summary!$H$3:$H$204*IF(Summary!I$3:I$204=A$2,1,0)*IF(Summary!K$3:K$204=I16,1,0))} -> 3 | N16: =N15+M16 -> 46
H17: Week 4 | I17: =I16+3 -> 40266 | J17: =SUM(P17:T17) -> 0 | K17: =J17+K16 -> 58 | L17: =K17*$D$2 -> 57.016949 | M17: {=SUM(Summary!$H$3:$H$204*IF(Summary!I$3:I$204=A$2,1,0)*IF(Summary!K$3:K$204=I17,1,0))} -> 0 | N17: =N16+M17 -> 46
I18: =I17+1 -> 40267 | J18: =SUM(P18:T18) -> 1 | K18: =J18+K17 -> 59 | L18: =K18*$D$2 -> 58 | M18: {=SUM(Summary!$H$3:$H$204*IF(Summary!I$3:I$204=A$2,1,0)*IF(Summary!K$3:K$204=I18,1,0))} -> 12 | N18: =N17+M18 -> 58 | R18: 1

Sheet Stats (i4)
A1: Increment Name | B1: Total Story Points In Scope | C1: Total Man Days | D1: Estimated Velocity | E1: Total Story Points Delivered | F1: Actual Velocity | I1: Date | J1: Man Days (Today) | K1: Man Days (Cumulative) | L1: Story Points (Est Cumulative) | M1: Story Points (Actual Today) | N1: Story Points (Actual Cumulative) | P1: Chris | Q1: Richard | R1: Tom | S1: Des | T1: Niall
A2: v8.0 (i4) | B2: {=SUM(Summary!H3:H204*IF(Summary!I3:I204=A2,1,0))} -> 48 | C2: =SUM(J2:J20) -> 70 | D2: =B2/C2 -> 0.68571429 | E2: =N20 -> 48 | F2: =E2/C2 -> 0.68571429 | H2: Week 1 | I2: 40266 | J2: =SUM(P2:T2) -> 0 | K2: =J2 -> 0 | L2: =K2*$D$2 -> 0 | M2: {=SUM(Summary!$H$3:$H$204*IF(Summary!I$3:I$204=A$2,1,0)*IF(Summary!K$3:K$204=I2,1,0))} -> 0 | N2: =M2 -> 0 | P2: 0 | Q2: 0 | R2: 0 | S2: 0 | T2: 0
C3: aim for | D3: 0.75 | I3: =I2+1 -> 40267 | J3: =SUM(P3:T3) -> 3 | K3: =J3+K2 -> 3 | L3: =K3*$D$2 -> 2.0571429 | M3: {=SUM(Summary!$H$3:$H$204*IF(Summary!I$3:I$204=A$2,1,0)*IF(Summary!K$3:K$204=I3,1,0))} -> 0.5 | N3: =N2+M3 -> 0.5 | P3: 1 | Q3: 1 | R3: 0 | S3: 1 | T3: 0
D4: =C2*D3 -> 52.5 | I4: =I3+1 -> 40268 | J4: =SUM(P4:T4) -> 4 | K4: =J4+K3 -> 7 | L4: =K4*$D$2 -> 4.8 | M4: {=SUM(Summary!$H$3:$H$204*IF(Summary!I$3:I$204=A$2,1,0)*IF(Summary!K$3:K$204=I4,1,0))} -> 1 | N4: =N3+M4 -> 1.5 | P4: 1 | Q4: 1 | R4: 1 | S4: 1 | T4: 0
I5: =I4+1 -> 40269 | J5: =SUM(P5:T5) -> 4 | K5: =J5+K4 -> 11 | L5: =K5*$D$2 -> 7.5428571 | M5: {=SUM(Summary!$H$3:$H$204*IF(Summary!I$3:I$204=A$2,1,0)*IF(Summary!K$3:K$204=I5,1,0))} -> 3 | N5: =N4+M5 -> 4.5 | P5: 1 | Q5: 1 | R5: 1 | S5: 1 | T5: 0
I6: =I5+1 -> 40270 | J6: =SUM(P6:T6) -> 0 | K6: =J6+K5 -> 11 | L6: =K6*$D$2 -> 7.5428571 | M6: {=SUM(Summary!$H$3:$H$204*IF(Summary!I$3:I$204=A$2,1,0)*IF(Summary!K$3:K$204=I6,1,0))} -> 0 | N6: =N5+M6 -> 4.5 | P6: 0 | Q6: 0 | R6: 0 | S6: 0 | T6: 0
H7: Week 2 | I7: =I6+3 -> 40273 | J7: =SUM(P7:T7) -> 0 | K7: =J7+K6 -> 11 | L7: =K7*$D$2 -> 7.5428571 | M7: {=SUM(Summary!$H$3:$H$204*IF(Summary!I$3:I$204=A$2,1,0)*IF(Summary!K$3:K$204=I7,1,0))} -> 0 | N7: =N6+M7 -> 4.5 | P7: 0 | Q7: 0 | R7: 0 | S7: 0 | T7: 0
I8: =I7+1 -> 40274 | J8: =SUM(P8:T8) -> 5 | K8: =J8+K7 -> 16 | L8: =K8*$D$2 -> 10.971429 | M8: {=SUM(Summary!$H$3:$H$204*IF(Summary!I$3:I$204=A$2,1,0)*IF(Summary!K$3:K$204=I8,1,0))} -> 0 | N8: =N7+M8 -> 4.5 | P8: 1 | Q8: 1 | R8: 1 | S8: 1 | T8: 1
I9: =I8+1 -> 40275 | J9: =SUM(P9:T9) -> 5 | K9: =J9+K8 -> 21 | L9: =K9*$D$2 -> 14.4 | M9: {=SUM(Summary!$H$3:$H$204*IF(Summary!I$3:I$204=A$2,1,0)*IF(Summary!K$3:K$204=I9,1,0))} -> 2 | N9: =N8+M9 -> 6.5 | P9: 1 | Q9: 1 | R9: 1 | S9: 1 | T9: 1
I10: =I9+1 -> 40276 | J10: =SUM(P10:T10) -> 5 | K10: =J10+K9 -> 26 | L10: =K10*$D$2 -> 17.828571 | M10: {=SUM(Summary!$H$3:$H$204*IF(Summary!I$3:I$204=A$2,1,0)*IF(Summary!K$3:K$204=I10,1,0))} -> 0 | N10: =N9+M10 -> 6.5 | P10: 1 | Q10: 1 | R10: 1 | S10: 1 | T10: 1
I11: =I10+1 -> 40277 | J11: =SUM(P11:T11) -> 7 | K11: =J11+K10 -> 33 | L11: =K11*$D$2 -> 22.628571 | M11: {=SUM(Summary!$H$3:$H$204*IF(Summary!I$3:I$204=A$2,1,0)*IF(Summary!K$3:K$204=I11,1,0))} -> 1.5 | N11: =N10+M11 -> 8 | P11: 1 | Q11: 2 | R11: 1 | S11: 2 | T11: 1
H12: Week 3 | I12: =I11+3 -> 40280 | J12: =SUM(P12:T12) -> 5 | K12: =J12+K11 -> 38 | L12: =K12*$D$2 -> 26.057143 | M12: {=SUM(Summary!$H$3:$H$204*IF(Summary!I$3:I$204=A$2,1,0)*IF(Summary!K$3:K$204=I12,1,0))} -> 0 | N12: =N11+M12 -> 8 | P12: 1 | Q12: 1 | R12: 1 | S12: 1 | T12: 1
I13: =I12+1 -> 40281 | J13: =SUM(P13:T13) -> 5 | K13: =J13+K12 -> 43 | L13: =K13*$D$2 -> 29.485714 | M13: {=SUM(Summary!$H$3:$H$204*IF(Summary!I$3:I$204=A$2,1,0)*IF(Summary!K$3:K$204=I13,1,0))} -> 5 | N13: =N12+M13 -> 13 | P13: 1 | Q13: 1 | R13: 1 | S13: 1 | T13: 1
I14: =I13+1 -> 40282 | J14: =SUM(P14:T14) -> 5 | K14: =J14+K13 -> 48 | L14: =K14*$D$2 -> 32.914286 | M14: {=SUM(Summary!$H$3:$H$204*IF(Summary!I$3:I$204=A$2,1,0)*IF(Summary!K$3:K$204=I14,1,0))} -> 3 | N14: =N13+M14 -> 16 | P14: 1 | Q14: 1 | R14: 1 | S14: 1 | T14: 1
I15: =I14+1 -> 40283 | J15: =SUM(P15:T15) -> 5 | K15: =J15+K14 -> 53 | L15: =K15*$D$2 -> 36.342857 | M15: {=SUM(Summary!$H$3:$H$204*IF(Summary!I$3:I$204=A$2,1,0)*IF(Summary!K$3:K$204=I15,1,0))} -> 2 | N15: =N14+M15 -> 18 | P15: 1 | Q15: 1 | R15: 1 | S15: 1 | T15: 1
I16: =I15+1 -> 40284 | J16: =SUM(P16:T16) -> 7 | K16: =J16+K15 -> 60 | L16: =K16*$D$2 -> 41.142857 | M16: {=SUM(Summary!$H$3:$H$204*IF(Summary!I$3:I$204=A$2,1,0)*IF(Summary!K$3:K$204=I16,1,0))} -> 12 | N16: =N15+M16 -> 30 | P16: 1 | Q16: 2 | R16: 1 | S16: 2 | T16: 1
H17: Week 4 | I17: =I16+3 -> 40287 | J17: =SUM(P17:T17) -> 5 | K17: =J17+K16 -> 65 | L17: =K17*$D$2 -> 44.571429 | M17: {=SUM(Summary!$H$3:$H$204*IF(Summary!I$3:I$204=A$2,1,0)*IF(Summary!K$3:K$204=I17,1,0))} -> 3 | N17: =N16+M17 -> 33 | P17: 1 | Q17: 1 | R17: 1 | S17: 1 | T17: 1
I18: =I17+1 -> 40288 | J18: =SUM(P18:T18) -> 3 | K18: =J18+K17 -> 68 | L18: =K18*$D$2 -> 46.628571 | M18: {=SUM(Summary!$H$3:$H$204*IF(Summary!I$3:I$204=A$2,1,0)*IF(Summary!K$3:K$204=I18,1,0))} -> 6 | N18: =N17+M18 -> 39 | P18: 0 | Q18: 0 | R18: 1 | S18: 1 | T18: 1
I19: =I18+1 -> 40289 | J19: =SUM(P19:T19) -> 1.5 | K19: =J19+K18 -> 69.5 | L19: =K19*$D$2 -> 47.657143 | M19: {=SUM(Summary!$H$3:$H$204*IF(Summary!I$3:I$204=A$2,1,0)*IF(Summary!K$3:K$204=I19,1,0))} -> 6 | N19: =N18+M19 -> 45 | P19: 0 | Q19: 0 | R19: 1 | S19: 0 | T19: 0.5
I20: =I19+1 -> 40290 | J20: =SUM(P20:T20) -> 0.5 | K20: =J20+K19 -> 70 | L20: =K20*$D$2 -> 48 | M20: {=SUM(Summary!$H$3:$H$204*IF(Summary!I$3:I$204=A$2,1,0)*IF(Summary!K$3:K$204=I20,1,0))} -> 3 | N20: =N19+M20 -> 48 | P20: 0 | Q20: 0 | R20: 0.5 | S20: 0 | T20: 0

Sheet Stats (i5)
A1: Increment Name | B1: Total Story Points In Scope | C1: Total Man Days | D1: Estimated Velocity | E1: Total Story Points Delivered | F1: Actual Velocity | I1: Date | J1: Man Days (Today) | K1: Man Days (Cumulative) | L1: Story Points (Est Cumulative) | M1: Story Points (Actual Today) | N1: Story Points (Actual Cumulative) | P1: Chris | Q1: Richard | R1: Tom | S1: Des | T1: Niall
A2: v8.0 (i5) | B2: {=SUM(Summary!H3:H204*IF(Summary!I3:I204=A2,1,0))} -> 50.5 | C2: =SUM(J2:J23) -> 59.5 | D2: =B2/C2 -> 0.8487395 | E2: =N23 -> 50.5 | F2: =E2/C2 -> 0.8487395 | H2: Week 1 | I2: 40287 | J2: =SUM(P2:T2) -> 0 | K2: =J2 -> 0 | L2: =K2*$D$2 -> 0 | M2: {=SUM(Summary!$H$3:$H$204*IF(Summary!I$3:I$204=A$2,1,0)*IF(Summary!K$3:K$204=I2,1,0))} -> 0 | N2: =M2 -> 0 | P2: 0 | Q2: 0 | R2: 0 | S2: 0 | T2: 0
C3: aim for | D3: 0.75 | I3: =I2+1 -> 40288 | J3: =SUM(P3:T3) -> 2 | K3: =J3+K2 -> 2 | L3: =K3*$D$2 -> 1.697479 | M3: {=SUM(Summary!$H$3:$H$204*IF(Summary!I$3:I$204=A$2,1,0)*IF(Summary!K$3:K$204=I3,1,0))} -> 0 | N3: =N2+M3 -> 0 | P3: 1 | Q3: 1 | R3: 0 | S3: 0 | T3: 0
D4: =C2*D3 -> 44.625 | I4: =I3+1 -> 40289 | J4: =SUM(P4:T4) -> 3.5 | K4: =J4+K3 -> 5.5 | L4: =K4*$D$2 -> 4.6680672 | M4: {=SUM(Summary!$H$3:$H$204*IF(Summary!I$3:I$204=A$2,1,0)*IF(Summary!K$3:K$204=I4,1,0))} -> 0 | N4: =N3+M4 -> 0 | P4: 1 | Q4: 1 | R4: 0 | S4: 1 | T4: 0.5
I5: =I4+1 -> 40290 | J5: =SUM(P5:T5) -> 4.5 | K5: =J5+K4 -> 10 | L5: =K5*$D$2 -> 8.487395 | M5: {=SUM(Summary!$H$3:$H$204*IF(Summary!I$3:I$204=A$2,1,0)*IF(Summary!K$3:K$204=I5,1,0))} -> 1 | N5: =N4+M5 -> 1 | P5: 1 | Q5: 1 | R5: 0.5 | S5: 1 | T5: 1
I6: =I5+1 -> 40291 | J6: =SUM(P6:T6) -> 4.5 | K6: =J6+K5 -> 14.5 | L6: =K6*$D$2 -> 12.306723 | M6: {=SUM(Summary!$H$3:$H$204*IF(Summary!I$3:I$204=A$2,1,0)*IF(Summary!K$3:K$204=I6,1,0))} -> 4 | N6: =N5+M6 -> 5 | P6: 0.5 | Q6: 1.5 | R6: 0.5 | S6: 1.5 | T6: 0.5
H7: Week 2 | I7: =I6+3 -> 40294 | J7: =SUM(P7:T7) -> 3 | K7: =J7+K6 -> 17.5 | L7: =K7*$D$2 -> 14.852941 | M7: {=SUM(Summary!$H$3:$H$204*IF(Summary!I$3:I$204=A$2,1,0)*IF(Summary!K$3:K$204=I7,1,0))} -> 1 | N7: =N6+M7 -> 6 | P7: 1 | Q7: 1 | R7: 1 | S7: 0 | T7: 0
I8: =I7+1 -> 40295 | J8: =SUM(P8:T8) -> 2.5 | K8: =J8+K7 -> 20 | L8: =K8*$D$2 -> 16.97479 | M8: {=SUM(Summary!$H$3:$H$204*IF(Summary!I$3:I$204=A$2,1,0)*IF(Summary!K$3:K$204=I8,1,0))} -> 5.5 | N8: =N7+M8 -> 11.5 | P8: 0.5 | Q8: 1 | R8: 1 | S8: 0 | T8: 0
I9: =I8+1 -> 40296 | J9: =SUM(P9:T9) -> 3.5 | K9: =J9+K8 -> 23.5 | L9: =K9*$D$2 -> 19.945378 | M9: {=SUM(Summary!$H$3:$H$204*IF(Summary!I$3:I$204=A$2,1,0)*IF(Summary!K$3:K$204=I9,1,0))} -> 1 | N9: =N8+M9 -> 12.5 | P9: 1 | Q9: 1 | R9: 1 | S9: 0 | T9: 0.5
I10: =I9+1 -> 40297 | J10: =SUM(P10:T10) -> 4 | K10: =J10+K9 -> 27.5 | L10: =K10*$D$2 -> 23.340336 | M10: {=SUM(Summary!$H$3:$H$204*IF(Summary!I$3:I$204=A$2,1,0)*IF(Summary!K$3:K$204=I10,1,0))} -> 4 | N10: =N9+M10 -> 16.5 | P10: 1 | Q10: 1 | R10: 1 | S10: 0 | T10: 1
I11: =I10+1 -> 40298 | J11: =SUM(P11:T11) -> 5 | K11: =J11+K10 -> 32.5 | L11: =K11*$D$2 -> 27.584034 | M11: {=SUM(Summary!$H$3:$H$204*IF(Summary!I$3:I$204=A$2,1,0)*IF(Summary!K$3:K$204=I11,1,0))} -> 4.5 | N11: =N10+M11 -> 21 | P11: 1 | Q11: 2 | R11: 1 | S11: 0 | T11: 1
H12: Week 3 | I12: =I11+3 -> 40301 | J12: =SUM(P12:T12) -> 0 | K12: =J12+K11 -> 32.5 | L12: =K12*$D$2 -> 27.584034 | M12: {=SUM(Summary!$H$3:$H$204*IF(Summary!I$3:I$204=A$2,1,0)*IF(Summary!K$3:K$204=I12,1,0))} -> 0 | N12: =N11+M12 -> 21 | P12: 0 | Q12: 0 | R12: 0 | S12: 0 | T12: 0
I13: =I12+1 -> 40302 | J13: =SUM(P13:T13) -> 2 | K13: =J13+K12 -> 34.5 | L13: =K13*$D$2 -> 29.281513 | M13: {=SUM(Summary!$H$3:$H$204*IF(Summary!I$3:I$204=A$2,1,0)*IF(Summary!K$3:K$204=I13,1,0))} -> 0 | N13: =N12+M13 -> 21 | P13: 0 | Q13: 0 | R13: 1 | S13: 1 | T13: 0
I14: =I13+1 -> 40303 | J14: =SUM(P14:T14) -> 2.5 | K14: =J14+K13 -> 37 | L14: =K14*$D$2 -> 31.403361 | M14: {=SUM(Summary!$H$3:$H$204*IF(Summary!I$3:I$204=A$2,1,0)*IF(Summary!K$3:K$204=I14,1,0))} -> 4.5 | N14: =N13+M14 -> 25.5 | P14: 0 | Q14: 0 | R14: 1 | S14: 1 | T14: 0.5
I15: =I14+1 -> 40304 | J15: =SUM(P15:T15) -> 3 | K15: =J15+K14 -> 40 | L15: =K15*$D$2 -> 33.94958 | M15: {=SUM(Summary!$H$3:$H$204*IF(Summary!I$3:I$204=A$2,1,0)*IF(Summary!K$3:K$204=I15,1,0))} -> 0 | N15: =N14+M15 -> 25.5 | P15: 0 | Q15: 0 | R15: 1 | S15: 1 | T15: 1
I16: =I15+1 -> 40305 | J16: =SUM(P16:T16) -> 4 | K16: =J16+K15 -> 44 | L16: =K16*$D$2 -> 37.344538 | M16: {=SUM(Summary!$H$3:$H$204*IF(Summary!I$3:I$204=A$2,1,0)*IF(Summary!K$3:K$204=I16,1,0))} -> 2 | N16: =N15+M16 -> 27.5 | P16: 0 | Q16: 0 | R16: 1 | S16: 2 | T16: 1
H17: Week 4 | I17: =I16+3 -> 40308 | J17: =SUM(P17:T17) -> 3 | K17: =J17+K16 -> 47 | L17: =K17*$D$2 -> 39.890756 | M17: {=SUM(Summary!$H$3:$H$204*IF(Summary!I$3:I$204=A$2,1,0)*IF(Summary!K$3:K$204=I17,1,0))} -> 5 | N17: =N16+M17 -> 32.5 | P17: 1 | Q17: 0 | R17: 0 | S17: 1 | T17: 1
I18: =I17+1 -> 40309 | J18: =SUM(P18:T18) -> 3 | K18: =J18+K17 -> 50 | L18: =K18*$D$2 -> 42.436975 | M18: {=SUM(Summary!$H$3:$H$204*IF(Summary!I$3:I$204=A$2,1,0)*IF(Summary!K$3:K$204=I18,1,0))} -> 0 | N18: =N17+M18 -> 32.5 | P18: 1 | Q18: 0 | R18: 0 | S18: 1 | T18: 1
I19: =I18+1 -> 40310 | J19: =SUM(P19:T19) -> 3 | K19: =J19+K18 -> 53 | L19: =K19*$D$2 -> 44.983193 | M19: {=SUM(Summary!$H$3:$H$204*IF(Summary!I$3:I$204=A$2,1,0)*IF(Summary!K$3:K$204=I19,1,0))} -> 3 | N19: =N18+M19 -> 35.5 | P19: 1 | Q19: 0 | R19: 0 | S19: 1 | T19: 1
I20: =I19+1 -> 40311 | J20: =SUM(P20:T20) -> 3 | K20: =J20+K19 -> 56 | L20: =K20*$D$2 -> 47.529412 | M20: {=SUM(Summary!$H$3:$H$204*IF(Summary!I$3:I$204=A$2,1,0)*IF(Summary!K$3:K$204=I20,1,0))} -> 5 | N20: =N19+M20 -> 40.5 | P20: 1 | Q20: 0 | R20: 0 | S20: 1 | T20: 1
I21: =I20+1 -> 40312 | J21: =SUM(P21:T21) -> 2.5 | K21: =J21+K20 -> 58.5 | L21: =K21*$D$2 -> 49.651261 | M21: {=SUM(Summary!$H$3:$H$204*IF(Summary!I$3:I$204=A$2,1,0)*IF(Summary!K$3:K$204=I21,1,0))} -> 8.5 | N21: =N20+M21 -> 49 | P21: 1 | Q21: 0 | R21: 0 | S21: 1 | T21: 0.5
H22: Week 5 | I22: =I21+3 -> 40315 | J22: =SUM(P22:T22) -> 0 | K22: =J22+K21 -> 58.5 | L22: =K22*$D$2 -> 49.651261 | M22: {=SUM(Summary!$H$3:$H$204*IF(Summary!I$3:I$204=A$2,1,0)*IF(Summary!K$3:K$204=I22,1,0))} -> 0 | N22: =N21+M22 -> 49 | P22: 0 | Q22: 0 | R22: 0 | S22: 0 | T22: 0
I23: =I22+1 -> 40316 | J23: =SUM(P23:T23) -> 1 | K23: =J23+K22 -> 59.5 | L23: =K23*$D$2 -> 50.5 | M23: {=SUM(Summary!$H$3:$H$204*IF(Summary!I$3:I$204=A$2,1,0)*IF(Summary!K$3:K$204=I23,1,0))} -> 1.5 | N23: =N22+M23 -> 50.5 | P23: 1 | Q23: 0 | R23: 0 | S23: 0 | T23: 0

Sheet Stats (i6)
A1: Increment Name | B1: Total Story Points In Scope | C1: Total Man Days | D1: Estimated Velocity | E1: Total Story Points Delivered | F1: Actual Velocity | I1: Date | J1: Man Days (Today) | K1: Man Days (Cumulative) | L1: Story Points (Est Cumulative) | M1: Story Points (Actual Today) | N1: Story Points (Actual Cumulative) | P1: Chris | Q1: Richard | R1: Tom | S1: Des | T1: Niall
A2: v8.0 (i6) | B2: {=SUM(Summary!H3:H204*IF(Summary!I3:I204=A2,1,0))} -> 37 | C2: =SUM(J2:J16) -> 37 | D2: =B2/C2 -> 1 | E2: =N16 -> 37 | F2: =E2/C2 -> 1 | H2: Week 1 | I2: 40315 | J2: =SUM(P2:T2) -> 0 | K2: =J2 -> 0 | L2: =K2*$D$2 -> 0 | M2: {=SUM(Summary!$H$3:$H$204*IF(Summary!I$3:I$204=A$2,1,0)*IF(Summary!K$3:K$204=I2,1,0))} -> 0 | N2: =M2 -> 0 | P2: 0 | Q2: 0 | R2: 0 | S2: 0 | T2: 0
C3: aim for | D3: 0.75 | I3: =I2+1 -> 40316 | J3: =SUM(P3:T3) -> 2 | K3: =J3+K2 -> 2 | L3: =K3*$D$2 -> 2 | M3: {=SUM(Summary!$H$3:$H$204*IF(Summary!I$3:I$204=A$2,1,0)*IF(Summary!K$3:K$204=I3,1,0))} -> 0.5 | N3: =N2+M3 -> 0.5 | P3: 0 | Q3: 1 | R3: 0 | S3: 1 | T3: 0
D4: =C2*D3 -> 27.75 | I4: =I3+1 -> 40317 | J4: =SUM(P4:T4) -> 3 | K4: =J4+K3 -> 5 | L4: =K4*$D$2 -> 5 | M4: {=SUM(Summary!$H$3:$H$204*IF(Summary!I$3:I$204=A$2,1,0)*IF(Summary!K$3:K$204=I4,1,0))} -> 1 | N4: =N3+M4 -> 1.5 | P4: 1 | Q4: 1 | R4: 0 | S4: 1 | T4: 0
I5: =I4+1 -> 40318 | J5: =SUM(P5:T5) -> 3 | K5: =J5+K4 -> 8 | L5: =K5*$D$2 -> 8 | M5: {=SUM(Summary!$H$3:$H$204*IF(Summary!I$3:I$204=A$2,1,0)*IF(Summary!K$3:K$204=I5,1,0))} -> 0 | N5: =N4+M5 -> 1.5 | P5: 1 | Q5: 1 | R5: 0 | S5: 1 | T5: 0
I6: =I5+1 -> 40319 | J6: =SUM(P6:T6) -> 2 | K6: =J6+K5 -> 10 | L6: =K6*$D$2 -> 10 | M6: {=SUM(Summary!$H$3:$H$204*IF(Summary!I$3:I$204=A$2,1,0)*IF(Summary!K$3:K$204=I6,1,0))} -> 2 | N6: =N5+M6 -> 3.5 | P6: 0 | Q6: 1 | R6: 0 | S6: 1 | T6: 0
H7: Week 2 | I7: =I6+3 -> 40322 | J7: =SUM(P7:T7) -> 2 | K7: =J7+K6 -> 12 | L7: =K7*$D$2 -> 12 | M7: {=SUM(Summary!$H$3:$H$204*IF(Summary!I$3:I$204=A$2,1,0)*IF(Summary!K$3:K$204=I7,1,0))} -> 0 | N7: =N6+M7 -> 3.5 | P7: 0 | Q7: 1 | R7: 0 | S7: 1 | T7: 0
I8: =I7+1 -> 40323 | J8: =SUM(P8:T8) -> 3 | K8: =J8+K7 -> 15 | L8: =K8*$D$2 -> 15 | M8: {=SUM(Summary!$H$3:$H$204*IF(Summary!I$3:I$204=A$2,1,0)*IF(Summary!K$3:K$204=I8,1,0))} -> 2 | N8: =N7+M8 -> 5.5 | P8: 1 | Q8: 1 | R8: 0 | S8: 1 | T8: 0
I9: =I8+1 -> 40324 | J9: =SUM(P9:T9) -> 3 | K9: =J9+K8 -> 18 | L9: =K9*$D$2 -> 18 | M9: {=SUM(Summary!$H$3:$H$204*IF(Summary!I$3:I$204=A$2,1,0)*IF(Summary!K$3:K$204=I9,1,0))} -> 2 | N9: =N8+M9 -> 7.5 | P9: 1 | Q9: 1 | R9: 0 | S9: 1 | T9: 0
I10: =I9+1 -> 40325 | J10: =SUM(P10:T10) -> 3 | K10: =J10+K9 -> 21 | L10: =K10*$D$2 -> 21 | M10: {=SUM(Summary!$H$3:$H$204*IF(Summary!I$3:I$204=A$2,1,0)*IF(Summary!K$3:K$204=I10,1,0))} -> 7 | N10: =N9+M10 -> 14.5 | P10: 1 | Q10: 1 | R10: 0 | S10: 1 | T10: 0
I11: =I10+1 -> 40326 | J11: =SUM(P11:T11) -> 4 | K11: =J11+K10 -> 25 | L11: =K11*$D$2 -> 25 | M11: {=SUM(Summary!$H$3:$H$204*IF(Summary!I$3:I$204=A$2,1,0)*IF(Summary!K$3:K$204=I11,1,0))} -> 5 | N11: =N10+M11 -> 19.5 | P11: 1 | Q11: 1 | R11: 0 | S11: 2 | T11: 0
H12: Week 3 | I12: =I11+3 -> 40329 | J12: =SUM(P12:T12) -> 0 | K12: =J12+K11 -> 25 | L12: =K12*$D$2 -> 25 | M12: {=SUM(Summary!$H$3:$H$204*IF(Summary!I$3:I$204=A$2,1,0)*IF(Summary!K$3:K$204=I12,1,0))} -> 0 | N12: =N11+M12 -> 19.5 | P12: 0 | Q12: 0 | R12: 0 | S12: 0 | T12: 0
I13: =I12+1 -> 40330 | J13: =SUM(P13:T13) -> 2 | K13: =J13+K12 -> 27 | L13: =K13*$D$2 -> 27 | M13: {=SUM(Summary!$H$3:$H$204*IF(Summary!I$3:I$204=A$2,1,0)*IF(Summary!K$3:K$204=I13,1,0))} -> 5 | N13: =N12+M13 -> 24.5 | P13: 1 | Q13: 1 | R13: 0 | S13: 0 | T13: 0
I14: =I13+1 -> 40331 | J14: =SUM(P14:T14) -> 4 | K14: =J14+K13 -> 31 | L14: =K14*$D$2 -> 31 | M14: {=SUM(Summary!$H$3:$H$204*IF(Summary!I$3:I$204=A$2,1,0)*IF(Summary!K$3:K$204=I14,1,0))} -> 5 | N14: =N13+M14 -> 29.5 | P14: 1 | Q14: 1 | R14: 1 | S14: 1 | T14: 0
I15: =I14+1 -> 40332 | J15: =SUM(P15:T15) -> 3 | K15: =J15+K14 -> 34 | L15: =K15*$D$2 -> 34 | M15: {=SUM(Summary!$H$3:$H$204*IF(Summary!I$3:I$204=A$2,1,0)*IF(Summary!K$3:K$204=I15,1,0))} -> 0 | N15: =N14+M15 -> 29.5 | P15: 1 | Q15: 1 | R15: 0 | S15: 1 | T15: 0
I16: =I15+1 -> 40333 | J16: =SUM(P16:T16) -> 3 | K16: =J16+K15 -> 37 | L16: =K16*$D$2 -> 37 | M16: {=SUM(Summary!$H$3:$H$204*IF(Summary!I$3:I$204=A$2,1,0)*IF(Summary!K$3:K$204=I16,1,0))} -> 7.5 | N16: =N15+M16 -> 37 | P16: 1 | Q16: 1 | R16: 0 | S16: 1 | T16: 0

Sheet Stats (i7)
A1: Increment Name | B1: Total Story Points In Scope | C1: Total Man Days | D1: Estimated Velocity | E1: Total Story Points Delivered | F1: Actual Velocity | I1: Date | J1: Man Days (Today) | K1: Man Days (Cumulative) | L1: Story Points (Est Cumulative) | M1: Story Points (Actual Today) | N1: Story Points (Actual Cumulative) | P1: Chris | Q1: Richard | R1: Tom | S1: Des | T1: Niall
A2: v8.0 (i7) | B2: {=SUM(Summary!H3:H204*IF(Summary!I3:I204=A2,1,0))} -> 22.5 | C2: =SUM(J2:J16) -> 69.5 | D2: =B2/C2 -> 0.32374101 | E2: =N16 -> 22.5 | F2: =E2/C2 -> 0.32374101 | H2: Week 1 | I2: 40336 | J2: =SUM(P2:T2) -> 2 | K2: =J2 -> 2 | L2: =K2*$D$2 -> 0.64748201 | M2: {=SUM(Summary!$H$3:$H$204*IF(Summary!I$3:I$204=A$2,1,0)*IF(Summary!K$3:K$204=I2,1,0))} -> 0 | N2: =M2 -> 0 | P2: 0 | Q2: 0 | R2: 1 | S2: 1 | T2: 0
C3: aim for | D3: 0.75 | I3: =I2+1 -> 40337 | J3: =SUM(P3:T3) -> 2.5 | K3: =J3+K2 -> 4.5 | L3: =K3*$D$2 -> 1.4568345 | M3: {=SUM(Summary!$H$3:$H$204*IF(Summary!I$3:I$204=A$2,1,0)*IF(Summary!K$3:K$204=I3,1,0))} -> 0 | N3: =N2+M3 -> 0 | P3: 0.5 | Q3: 0.5 | R3: 0.5 | S3: 0.5 | T3: 0.5
D4: =C2*D3 -> 52.125 | I4: =I3+1 -> 40338 | J4: =SUM(P4:T4) -> 5 | K4: =J4+K3 -> 9.5 | L4: =K4*$D$2 -> 3.0755396 | M4: {=SUM(Summary!$H$3:$H$204*IF(Summary!I$3:I$204=A$2,1,0)*IF(Summary!K$3:K$204=I4,1,0))} -> 0 | N4: =N3+M4 -> 0 | P4: 1 | Q4: 1 | R4: 1 | S4: 1 | T4: 1
I5: =I4+1 -> 40339 | J5: =SUM(P5:T5) -> 5 | K5: =J5+K4 -> 14.5 | L5: =K5*$D$2 -> 4.6942446 | M5: {=SUM(Summary!$H$3:$H$204*IF(Summary!I$3:I$204=A$2,1,0)*IF(Summary!K$3:K$204=I5,1,0))} -> 2 | N5: =N4+M5 -> 2 | P5: 1 | Q5: 1 | R5: 1 | S5: 1 | T5: 1
I6: =I5+1 -> 40340 | J6: =SUM(P6:T6) -> 5 | K6: =J6+K5 -> 19.5 | L6: =K6*$D$2 -> 6.3129496 | M6: {=SUM(Summary!$H$3:$H$204*IF(Summary!I$3:I$204=A$2,1,0)*IF(Summary!K$3:K$204=I6,1,0))} -> 1 | N6: =N5+M6 -> 3 | P6: 1 | Q6: 1 | R6: 1 | S6: 1 | T6: 1
H7: Week 2 | I7: =I6+3 -> 40343 | J7: =SUM(P7:T7) -> 5 | K7: =J7+K6 -> 24.5 | L7: =K7*$D$2 -> 7.9316547 | M7: {=SUM(Summary!$H$3:$H$204*IF(Summary!I$3:I$204=A$2,1,0)*IF(Summary!K$3:K$204=I7,1,0))} -> 0 | N7: =N6+M7 -> 3 | P7: 1 | Q7: 1 | R7: 1 | S7: 1 | T7: 1
I8: =I7+1 -> 40344 | J8: =SUM(P8:T8) -> 5 | K8: =J8+K7 -> 29.5 | L8: =K8*$D$2 -> 9.5503597 | M8: {=SUM(Summary!$H$3:$H$204*IF(Summary!I$3:I$204=A$2,1,0)*IF(Summary!K$3:K$204=I8,1,0))} -> 1.5 | N8: =N7+M8 -> 4.5 | P8: 1 | Q8: 1 | R8: 1 | S8: 1 | T8: 1
I9: =I8+1 -> 40345 | J9: =SUM(P9:T9) -> 5 | K9: =J9+K8 -> 34.5 | L9: =K9*$D$2 -> 11.169065 | M9: {=SUM(Summary!$H$3:$H$204*IF(Summary!I$3:I$204=A$2,1,0)*IF(Summary!K$3:K$204=I9,1,0))} -> 0 | N9: =N8+M9 -> 4.5 | P9: 1 | Q9: 1 | R9: 1 | S9: 1 | T9: 1
I10: =I9+1 -> 40346 | J10: =SUM(P10:T10) -> 5 | K10: =J10+K9 -> 39.5 | L10: =K10*$D$2 -> 12.78777 | M10: {=SUM(Summary!$H$3:$H$204*IF(Summary!I$3:I$204=A$2,1,0)*IF(Summary!K$3:K$204=I10,1,0))} -> 2 | N10: =N9+M10 -> 6.5 | P10: 1 | Q10: 1 | R10: 1 | S10: 1 | T10: 1
I11: =I10+1 -> 40347 | J11: =SUM(P11:T11) -> 5 | K11: =J11+K10 -> 44.5 | L11: =K11*$D$2 -> 14.406475 | M11: {=SUM(Summary!$H$3:$H$204*IF(Summary!I$3:I$204=A$2,1,0)*IF(Summary!K$3:K$204=I11,1,0))} -> 1.5 | N11: =N10+M11 -> 8 | P11: 0 | Q11: 2 | R11: 1 | S11: 1 | T11: 1
H12: Week 3 | I12: =I11+3 -> 40350 | J12: =SUM(P12:T12) -> 5 | K12: =J12+K11 -> 49.5 | L12: =K12*$D$2 -> 16.02518 | M12: {=SUM(Summary!$H$3:$H$204*IF(Summary!I$3:I$204=A$2,1,0)*IF(Summary!K$3:K$204=I12,1,0))} -> 0 | N12: =N11+M12 -> 8 | P12: 1 | Q12: 1 | R12: 1 | S12: 1 | T12: 1
I13: =I12+1 -> 40351 | J13: =SUM(P13:T13) -> 5 | K13: =J13+K12 -> 54.5 | L13: =K13*$D$2 -> 17.643885 | M13: {=SUM(Summary!$H$3:$H$204*IF(Summary!I$3:I$204=A$2,1,0)*IF(Summary!K$3:K$204=I13,1,0))} -> 1 | N13: =N12+M13 -> 9 | P13: 1 | Q13: 1 | R13: 1 | S13: 1 | T13: 1
I14: =I13+1 -> 40352 | J14: =SUM(P14:T14) -> 5 | K14: =J14+K13 -> 59.5 | L14: =K14*$D$2 -> 19.26259 | M14: {=SUM(Summary!$H$3:$H$204*IF(Summary!I$3:I$204=A$2,1,0)*IF(Summary!K$3:K$204=I14,1,0))} -> 8 | N14: =N13+M14 -> 17 | P14: 1 | Q14: 1 | R14: 1 | S14: 1 | T14: 1
I15: =I14+1 -> 40353 | J15: =SUM(P15:T15) -> 5 | K15: =J15+K14 -> 64.5 | L15: =K15*$D$2 -> 20.881295 | M15: {=SUM(Summary!$H$3:$H$204*IF(Summary!I$3:I$204=A$2,1,0)*IF(Summary!K$3:K$204=I15,1,0))} -> 0.5 | N15: =N14+M15 -> 17.5 | P15: 1 | Q15: 1 | R15: 1 | S15: 1 | T15: 1
I16: =I15+1 -> 40354 | J16: =SUM(P16:T16) -> 5 | K16: =J16+K15 -> 69.5 | L16: =K16*$D$2 -> 22.5 | M16: {=SUM(Summary!$H$3:$H$204*IF(Summary!I$3:I$204=A$2,1,0)*IF(Summary!K$3:K$204=I16,1,0))} -> 5 | N16: =N15+M16 -> 22.5 | P16: 1 | Q16: 1 | R16: 1 | S16: 1 | T16: 1

Sheet Stats (i8)
A1: Increment Name | B1: Total Story Points In Scope | C1: Total Man Days | D1: Estimated Velocity | E1: Total Story Points Delivered | F1: Actual Velocity | I1: Date | J1: Man Days (Today) | K1: Man Days (Cumulative) | L1: Story Points (Est Cumulative) | M1: Story Points (Actual Today) | N1: Story Points (Actual Cumulative) | P1: Chris | Q1: Richard | R1: Tom | S1: Des | T1: Niall
A2: v8.0 (i8) | B2: {=SUM(Summary!H3:H204*IF(Summary!I3:I204=A2,1,0))} -> 15 | C2: =SUM(J2:J19) -> 37 | D2: =B2/C2 -> 0.40540541 | E2: =N19 -> 13 | F2: =E2/C2 -> 0.35135135 | H2: Week 1 | I2: 40357 | J2: =SUM(P2:T2) -> 1 | K2: =J2 -> 1 | L2: =K2*$D$2 -> 0.40540541 | M2: {=SUM(Summary!$H$3:$H$204*IF(Summary!I$3:I$204=A$2,1,0)*IF(Summary!K$3:K$204=I2,1,0))} -> 0 | N2: =M2 -> 0 | P2: 0 | Q2: 0 | R2: 0 | S2: 1 | T2: 0
C3: aim for | D3: 0.75 | I3: =I2+1 -> 40358 | J3: =SUM(P3:T3) -> 4 | K3: =J3+K2 -> 5 | L3: =K3*$D$2 -> 2.027027 | M3: {=SUM(Summary!$H$3:$H$204*IF(Summary!I$3:I$204=A$2,1,0)*IF(Summary!K$3:K$204=I3,1,0))} -> 0 | N3: =N2+M3 -> 0 | P3: 1 | Q3: 1 | R3: 1 | S3: 1 | T3: 0
D4: =C2*D3 -> 27.75 | I4: =I3+1 -> 40359 | J4: =SUM(P4:T4) -> 4 | K4: =J4+K3 -> 9 | L4: =K4*$D$2 -> 3.6486486 | M4: {=SUM(Summary!$H$3:$H$204*IF(Summary!I$3:I$204=A$2,1,0)*IF(Summary!K$3:K$204=I4,1,0))} -> 1 | N4: =N3+M4 -> 1 | P4: 1 | Q4: 1 | R4: 1 | S4: 1 | T4: 0
I5: =I4+1 -> 40360 | J5: =SUM(P5:T5) -> 3 | K5: =J5+K4 -> 12 | L5: =K5*$D$2 -> 4.8648649 | M5: {=SUM(Summary!$H$3:$H$204*IF(Summary!I$3:I$204=A$2,1,0)*IF(Summary!K$3:K$204=I5,1,0))} -> 1 | N5: =N4+M5 -> 2 | P5: 1 | Q5: 1 | R5: 1 | S5: 0 | T5: 0
I6: =I5+1 -> 40361 | J6: =SUM(P6:T6) -> 2 | K6: =J6+K5 -> 14 | L6: =K6*$D$2 -> 5.6756757 | M6: {=SUM(Summary!$H$3:$H$204*IF(Summary!I$3:I$204=A$2,1,0)*IF(Summary!K$3:K$204=I6,1,0))} -> 0 | N6: =N5+M6 -> 2 | P6: 1 | Q6: 0 | R6: 1 | S6: 0 | T6: 0
H7: Week 2 | I7: =I6+3 -> 40364 | J7: =SUM(P7:T7) -> 2 | K7: =J7+K6 -> 16 | L7: =K7*$D$2 -> 6.4864865 | M7: {=SUM(Summary!$H$3:$H$204*IF(Summary!I$3:I$204=A$2,1,0)*IF(Summary!K$3:K$204=I7,1,0))} -> 5 | N7: =N6+M7 -> 7 | P7: 1 | Q7: 0 | R7: 1 | S7: 0 | T7: 0
I8: =I7+1 -> 40365 | J8: =SUM(P8:T8) -> 2 | K8: =J8+K7 -> 18 | L8: =K8*$D$2 -> 7.2972973 | M8: {=SUM(Summary!$H$3:$H$204*IF(Summary!I$3:I$204=A$2,1,0)*IF(Summary!K$3:K$204=I8,1,0))} -> 0 | N8: =N7+M8 -> 7 | P8: 1 | Q8: 0 | R8: 1 | S8: 0 | T8: 0
I9: =I8+1 -> 40366 | J9: =SUM(P9:T9) -> 2 | K9: =J9+K8 -> 20 | L9: =K9*$D$2 -> 8.1081081 | M9: {=SUM(Summary!$H$3:$H$204*IF(Summary!I$3:I$204=A$2,1,0)*IF(Summary!K$3:K$204=I9,1,0))} -> 0 | N9: =N8+M9 -> 7 | P9: 1 | Q9: 0 | R9: 1 | S9: 0 | T9: 0
I10: =I9+1 -> 40367 | J10: =SUM(P10:T10) -> 2 | K10: =J10+K9 -> 22 | L10: =K10*$D$2 -> 8.9189189 | M10: {=SUM(Summary!$H$3:$H$204*IF(Summary!I$3:I$204=A$2,1,0)*IF(Summary!K$3:K$204=I10,1,0))} -> 0 | N10: =N9+M10 -> 7 | P10: 1 | Q10: 0 | R10: 1 | S10: 0 | T10: 0
I11: =I10+1 -> 40368 | J11: =SUM(P11:T11) -> 0 | K11: =J11+K10 -> 22 | L11: =K11*$D$2 -> 8.9189189 | M11: {=SUM(Summary!$H$3:$H$204*IF(Summary!I$3:I$204=A$2,1,0)*IF(Summary!K$3:K$204=I11,1,0))} -> 0 | N11: =N10+M11 -> 7 | P11: 0 | Q11: 0 | R11: 0 | S11: 0 | T11: 0
H12: Week 3 | I12: =I11+3 -> 40371 | J12: =SUM(P12:T12) -> 2 | K12: =J12+K11 -> 24 | L12: =K12*$D$2 -> 9.7297297 | M12: {=SUM(Summary!$H$3:$H$204*IF(Summary!I$3:I$204=A$2,1,0)*IF(Summary!K$3:K$204=I12,1,0))} -> 0 | N12: =N11+M12 -> 7 | P12: 1 | Q12: 0 | R12: 1 | S12: 0 | T12: 0
I13: =I12+1 -> 40372 | J13: =SUM(P13:T13) -> 2 | K13: =J13+K12 -> 26 | L13: =K13*$D$2 -> 10.540541 | M13: {=SUM(Summary!$H$3:$H$204*IF(Summary!I$3:I$204=A$2,1,0)*IF(Summary!K$3:K$204=I13,1,0))} -> 0 | N13: =N12+M13 -> 7 | P13: 1 | Q13: 0 | R13: 1 | S13: 0 | T13: 0
I14: =I13+1 -> 40373 | J14: =SUM(P14:T14) -> 2 | K14: =J14+K13 -> 28 | L14: =K14*$D$2 -> 11.351351 | M14: {=SUM(Summary!$H$3:$H$204*IF(Summary!I$3:I$204=A$2,1,0)*IF(Summary!K$3:K$204=I14,1,0))} -> 0 | N14: =N13+M14 -> 7 | P14: 1 | Q14: 0 | R14: 1 | S14: 0 | T14: 0
I15: =I14+1 -> 40374 | J15: =SUM(P15:T15) -> 2 | K15: =J15+K14 -> 30 | L15: =K15*$D$2 -> 12.162162 | M15: {=SUM(Summary!$H$3:$H$204*IF(Summary!I$3:I$204=A$2,1,0)*IF(Summary!K$3:K$204=I15,1,0))} -> 0 | N15: =N14+M15 -> 7 | P15: 1 | Q15: 0 | R15: 1 | S15: 0 | T15: 0
I16: =I15+1 -> 40375 | J16: =SUM(P16:T16) -> 2 | K16: =J16+K15 -> 32 | L16: =K16*$D$2 -> 12.972973 | M16: {=SUM(Summary!$H$3:$H$204*IF(Summary!I$3:I$204=A$2,1,0)*IF(Summary!K$3:K$204=I16,1,0))} -> 0 | N16: =N15+M16 -> 7 | P16: 1 | Q16: 0 | R16: 1 | S16: 0 | T16: 0
H17: Week 4 | I17: =I16+3 -> 40378 | J17: =SUM(P17:T17) -> 1 | K17: =J17+K16 -> 33 | L17: =K17*$D$2 -> 13.378378 | M17: {=SUM(Summary!$H$3:$H$204*IF(Summary!I$3:I$204=A$2,1,0)*IF(Summary!K$3:K$204=I17,1,0))} -> 0 | N17: =N16+M17 -> 7 | P17: 1 | Q17: 0 | R17: 0 | S17: 0 | T17: 0
I18: =I17+1 -> 40379 | J18: =SUM(P18:T18) -> 2 | K18: =J18+K17 -> 35 | L18: =K18*$D$2 -> 14.189189 | M18: {=SUM(Summary!$H$3:$H$204*IF(Summary!I$3:I$204=A$2,1,0)*IF(Summary!K$3:K$204=I18,1,0))} -> 0 | N18: =N17+M18 -> 7 | P18: 1 | Q18: 0 | R18: 1 | S18: 0 | T18: 0
I19: =I18+1 -> 40380 | J19: =SUM(P19:T19) -> 2 | K19: =J19+K18 -> 37 | L19: =K19*$D$2 -> 15 | M19: {=SUM(Summary!$H$3:$H$204*IF(Summary!I$3:I$204=A$2,1,0)*IF(Summary!K$3:K$204=I19,1,0))} -> 6 | N19: =N18+M19 -> 13 | P19: 1 | Q19: 0 | R19: 1 | S19: 0 | T19: 0

Sheet Compatibility Report
B1: Compatibility Report for SampleTestDoc (1).xls
B2: Run on 12/8/2014 10:01
B4: The following features in this workbook are not supported by earlier versions of Excel. These features may be lost or degraded when opening this workbook in an earlier version of Excel or if you save this workbook in an earlier file format.
B6: Significant loss of functionality | E6: # of occurrences | F6: Version
B8: Some cells have more conditional formats than are supported by the selected file format. Only the first three conditions will be displayed in earlier versions of Excel. | E8: 19
E9: Details'!N2714 | F9: Excel 97-2003
E10: Details'!P2505
E11: Details'!P2361:P2367
E12: Details'!P1795:P1802
E13: Details'!N1543:N1544
E14: Details'!Q1140:Q1141
E15: Details'!P815
E16: Details'!P670:P671
E17: Details'!P679:P680
E18: Details'!Q1143:Q2108
E19: Details'!Q2110:Q65536
E20: Details'!N524
E21: Details'!Q1:Q1138
B23: Some cells have overlapping conditional formatting ranges. Earlier versions of Excel will not evaluate all of the conditional formatting rules on the overlapping cells. The overlapping cells will show different conditional formatting. | E23: 13
E24: Details'!N524 | F24: Excel 97-2003
E25: Details'!Q14:Q15
E26: Details'!N2714
E27: Details'!N1543:N1544
E28: Details'!Q1033
E29: Details'!Q1265:Q1271
E30: Details'!Q1276
E31: Details'!Q1273
E32: Details'!Q612:Q613
E33: Details'!Q608
E34: Details'!Q647
E35: Details'!Q576:Q604
E36: Details'!Q641:Q645
B38: Some cells contain conditional formatting with the 'Stop if True' option cleared. Earlier versions of Excel do not recognize this option and will stop after the first true condition. | E38: 13
E39: Details'!H:Q | F39: Excel 97-2003
